Workbook
Name africa: 0.01
Name africaCountries: #REF!
Name allRegions: #REF!
Name americaRegion: #REF!
Name americas: 0.16
Name americasStates: #REF!
Name AppVersion: "GEG-1.0"
Name asiaPacific: 0.73
Name asiaPacificExJapan: 0.26
Name asiaPacificExJapanCountries: #REF!
Name asiaPacificRegion: #REF!
Name asiaPacificStates: #REF!
Name australasia: 0.02
Name BRICS: 0.47
Name BSMethod: 2
Name Button_1: "TFT_report_data_share_prices_List"
Name cc_ReportCurrency: "NTD"
Name cc_ReportCurrencyUnit: "NT$"
Name cc_ReportCurrencyUnitFactor: 1
Name centralEasternEurope: 0.02
Name centralEasternEuropeCountries: #REF!
Name china: 0.4
Name Choices_Wrapper: Choices_Wrapper
Name consumerDemandExposure: #REF!
Name consumersExposure: 0
Name Conv_ITL: 1.93627
Name Conv_mark: 0
Name countryList: "Country Mapping"
Name DB: "WIREHKPROD"
Name developedEuropeExUK: 0.05
Name developedEuropeExUKCountries: #REF!
Name domesticAndForeignExposure: #REF!
Name domesticCostExposure: #REF!
Name DummyEstYears: 3
Name EEMEA: 0.04
Name endDemandExposure: #REF!
Name europe: 0.09
Name europeRegion: #REF!
Name europeStates: #REF!
Name EurosFRF: 1
Name EurosITL: 1
Name FINCriteriaType: 1
Name FR_COM_ABBR: "1122.HK"
Name FR_COU_ABBR: "chn"
Name FR_END_DATE: "'31 Dec 2001"
Name FR_START_DATE: "'1 Jan 2001"
Name FR_SYBASE_SERVER: "PTKFBVDF01"
Name FR_TEMPLATE_KEY: "110952|1"
Name ICP: 0
Name ictsymbol: "NT$"
Name icusymbol: "NT$"
Name india: 0.05
Name instructions: #REF!
Name ISMethod: 1
Name italy: 0.01
Name iue: 1
Name iuesymbol: "NT$"
Name iun: 1000000
Name iunsymbol: "NT$m"
Name ius: 1000000

Sheet ImportantDisclosures
A2: 1 Austin Road West
A3: Kowloon
A4: Hong Kong
A5: Tel: +852 2848 5200
A7: Authors: Daniel Yen,Charlie Chan
A8: Date: 16 Jul 2026
A10: Ticker: 688008.SS
A11: Stock Rating: Overweight
A12: Industry: Greater China Technology Semiconductors
A13: Industry View: Attractive
A14: Price as of 16 Jul 2026: 233.50
A15: Target Price: 377.00
... A143: Equal-weight and Not-Rated to hold and Underweight to sell recommendations, respectively.
B145: Coverage Universe | D145: Investment Banking Clients (IBC) | G145: Other Material Investment Services Clients (MISC)
A146: Stock Rating Category | B146: Count | C146: % of Total | D146: Count | E146: % of Total IBC | F146: % of Rating Category | G146: Count | H146: % of Total Other MISC
A147: Overweight/Buy | B147: 1544 | C147: 0.42 | D147: 453 | E147: 0.49 | F147: 0.29 | G147: 757 | H147: 0.44
A148: Equal-weight/Hold | B148: 1577 | C148: 0.43 | D148: 390 | E148: 0.42 | F148: 0.25 | G148: 769 | H148: 0.44
A149: Not-Rated/Hold | B149: 3 | C149: 0 | D149: 1 | E149: 0 | F149: 0.33 | G149: 1 | H149: 0
A150: Underweight/Sell | B150: 544 | C150: 0.15 | D150: 89 | E150: 0.1 | F150: 0.16 | G150: 204 | H150: 0.12
A151: Total | B151: 3668 | D151: 933 | G151: 1731
A153: Data include common stock and ADRs currently assigned ratings. Investment Banking Clients are companies
A154: from whom Morgan Stanley received investment banking compensation in the last 12 months. Due to rounding
A155: off of decimals, the percentages provided in the "% of total" column may not add up to exactly 100
A156: percent.
A158: Analyst Stock Ratings
A160: Overweight (O). The stock's total return is expected to exceed the average total return of the analyst's
A161: industry (or industry team's) coverage universe, on a risk-adjusted basis, over the next 12-18 months.
A163: Equal-weight (E). The stock's total return is expected to be in line with the average total return of
A164: the analyst's industry (or industry team's) coverage universe, on a risk-adjusted basis, over the next
A165: 12-18 months.
A167: Not-Rated (NR). Currently the analyst does not have adequate conviction about the stock's total return
A168: relative to the average total return of the analyst's industry (or industry team's) coverage universe,
... A454: © Copyright 2026 Morgan Stanley

Sheet Earnings Model
A1: Montage Technology (688008.SS, 6809.HK)
C2: Quarterly Earnings Model
C3: FY Ends: Dec
A8: Rmb$ in million | D8: 1Q16 | E8: 2Q16 | F8: 3Q16 | G8: 4Q16 | H8: 1Q17 | I8: 2Q17 | J8: 3Q17 | K8: 4Q17 | L8: 1Q18 | M8: 2Q18 | N8: 3Q18 | O8: 4Q18 | P8: 1Q19 | Q8: 2Q19 | R8: 3Q19 | S8: 4Q19 | T8: 1Q20 | U8: 2Q20 | V8: 3Q20 | W8: 4Q20 | X8: 1Q21 | Y8: 2Q21 | Z8: 3Q21 | AA8: 4Q21 | AB8: 1Q22 | AC8: 2Q22 | AD8: 3Q22 | AE8: 4Q22 | AF8: 1Q23 | AG8: 2Q23 | AH8: 3Q23 | AI8: 4Q23 | AJ8: 1Q24 | AK8: 2Q24 | AL8: 3Q24 | AM8: 4Q24 | AN8: 1Q25 | AO8: 2Q25 | AP8: 3Q25 | AQ8: 4Q25 | AR8: 1Q26 | AS8: 2Q26E | AT8: 3Q26E | AU8: 4Q26E | AV8: 1Q27E | AW8: 2Q27E | AX8: 3Q27E | AY8: 4Q27E | AZ8: 1Q28E | BA8: 2Q28E | BB8: 3Q28E | BC8: 4Q28E | BG8: 2016 | BH8: 2017 | BI8: 2018 | BJ8: 2019 | BK8: 2020 | BL8: 2021 | BM8: 2022 | BN8: 2023 | BO8: 2024 | BP8: 2025 | BQ8: 2026E | BR8: 2027E | BS8: 2028E
A10: Total Revenues | P10: 404.7171 | Q10: 474.46152 | R10: 505.167 | S10: =+BJ10-SUM(P10:R10) -> 353.38938 | T10: 495.75248 | U10: =1089.57666842-T10 -> 593.82419 | V10: 378.87465 | W10: =BK10-SUM(T10:V10) -> 355.21424 | X10: 299.53 | Y10: 424.933 | Z10: 868.233 | AA10: 969.321 | AB10: 900.423 | AC10: 1026.911 | AD10: 953.493 | AE10: 791.431 | AF10: 419.528 | AG10: 508.088 | AH10: 597.55 | AI10: 760.572 | AJ10: 737.263 | AK10: 927.715 | AL10: 905.892 | AM10: 1068.041 | AN10: 1222.209 | AO10: 1411.247 | AP10: =4057.68849-SUM(AN10:AO10) -> 1424.2325 | AQ10: =4057.68849-SUM(AO10:AP10) -> 1222.209 | AR10: 1460.718 | AS10: =AS128 -> 1773.9752 | AT10: =AT128 -> 1981.7557 | AU10: =AU128 -> 2300.23 | AV10: =AV128 -> 2575.9876 | AW10: =AW128 -> 3387.1186 | AX10: =AX128 -> 3766.2363 | AY10: =AY128 -> 4185.7417 | AZ10: =AZ128 -> 4425.0626 | ... BC10: =BC128 -> 5342.0619 | BG10: 844.945 | BH10: 1227.515 | BI10: 1757.665 | BJ10: 1737.735 | BK10: 1823.6656 | BL10: 2562.017 | BM10: 3672.258 | BN10: 2285.738 | BO10: 3638.911 | BP10: =SUM(AN10:AQ10) -> 5279.8975 | BQ10: =SUM(AR10:AU10) -> 7516.6789 | BR10: =SUM(AV10:AY10) -> 13915.084 | BS10: =SUM(AZ10:BC10) -> 19505.882 | BT10: =+(BS10/BP10)^(1/3)-1 -> 0.54589515 | CB10: =SUM(AY10:BF10) -> 23691.624
C11: Sequential Change | Q11: =Q10/P10-1 -> 0.17232884 | R11: =R10/Q10-1 -> 0.064716473 | S11: =S10/R10-1 -> -0.30045039 | T11: =T10/S10-1 -> 0.40285052 | U11: =U10/T10-1 -> 0.19782396 | V11: =V10/U10-1 -> -0.36197506 | W11: =W10/V10-1 -> -0.062449165 | X11: =X10/W10-1 -> -0.15676241 | ... BC11: =BC10/BB10-1 -> 0.063730423
C12: Change vs Year Ago | T12: =(T10/P10)-1 -> 0.22493584 | U12: =(U10/Q10)-1 -> 0.25157502 | V12: =(V10/R10)-1 -> -0.2500012 | W12: =(W10/S10)-1 -> 0.0051638837 | X12: =(X10/T10)-1 -> -0.39580735 | Y12: =(Y10/U10)-1 -> -0.28441278 | Z12: =(Z10/V10)-1 -> 1.2916102 | AA12: =(AA10/W10)-1 -> 1.7288349 | ... BC12: =(BC10/AY10)-1 -> 0.27625217 | BH12: =(BH10/BG10)-1 -> 0.45277503 | BI12: =(BI10/BH10)-1 -> 0.43188882 | BJ12: =(BJ10/BI10)-1 -> -0.011338907 | BK12: =(BK10/BJ10)-1 -> 0.049449747 | BL12: =(BL10/BK10)-1 -> 0.40487218 | BM12: =(BM10/BL10)-1 -> 0.43334646 | BN12: =(BN10/BM10)-1 -> -0.37756606 | BO12: =(BO10/BN10)-1 -> 0.59200705 | ... BS12: =(BS10/BR10)-1 -> 0.40177966
A14: Cost of Sales | P14: =96.2987357+0.0649224 -> 96.363658 | Q14: =232.11660141+0.081407-P14 -> 135.83435 | R14: 124.581 | S14: =+BJ14-SUM(P14:R14) -> 95.720992 | T14: =136.18547499+0.0481512 -> 136.23363 | U14: =286.60896514+0.71466679-T14 -> 151.09001 | V14: =111.43112144+0.34000907 -> 111.77113 | W14: =W10-W17 -> 108.59024 | X14: 106.571 | Y14: 165.872 | Z14: 544.91 | AA14: 522.55 | AB14: 511.572 | AC14: 592.189 | AD14: 518.224 | AE14: 344.762 | AF14: 195.955 | AG14: 209.184 | AH14: 210.361 | AI14: 323.717 | AJ14: 311.832 | AK14: 391.193 | AL14: 373.779 | AM14: 446.81 | AN14: 483.387 | AO14: 558.436 | AP14: =1563.885615-SUM(AN14:AO14) -> 522.06262 | AQ14: =1563.885615-SUM(AO14:AP14) -> 483.387 | AR14: 441.309 | AS14: =AS10-AS17 -> 572.72862 | AT14: =AT10-AT17 -> 626.5307 | AU14: =AU10-AU17 -> 708.35397 | AV14: =AV10-AV17 -> 779.45922 | AW14: =AW10-AW17 -> 985.08661 | AX14: =AX10-AX17 -> 1083.6408 | AY14: =AY10-AY17 -> 1193.5518 | AZ14: =AZ10-AZ17 -> 1254.7284 | ... BC14: =BC10-BC17 -> 1488.4563 | BG14: 412.309 | BH14: 570.952 | BI14: 517.734 | BJ14: 452.5 | BK14: =SUM(T14:W14) -> 507.685 | BL14: 1330.197 | BM14: 1966.747 | BN14: 939.216 | BO14: 1523.615 | BP14: =BP10-BP17 -> 2047.2726 | BQ14: =BQ10-BQ17 -> 2348.9223 | BR14: =BR10-BR17 -> 4041.7384 | BS14: =BS10-BS17 -> 5479.0973
C15: Percent of Revenues | P15: =P14/P10 -> 0.23810128 | Q15: =Q14/Q10 -> 0.2862916 | R15: =R14/R10 -> 0.2466135 | S15: =S14/S10 -> 0.2708655 | T15: =T14/T10 -> 0.27480171 | U15: =U14/U10 -> 0.25443558 | V15: =V14/V10 -> 0.29500821 | W15: =W14/W10 -> 0.3057035 | ... BC15: =BC14/BC10 -> 0.27862954 | BG15: =BG14/BG10 -> 0.48797141 | BH15: =BH14/BH10 -> 0.46512833 | BI15: =BI14/BI10 -> 0.29455784 | BJ15: =BJ14/BJ10 -> 0.26039644 | BK15: =BK14/BK10 -> 0.27838712 | BL15: =BL14/BL10 -> 0.51919913 | BM15: =BM14/BM10 -> 0.53556885 | BN15: =BN14/BN10 -> 0.41090274 | ... BS15: =BS14/BS10 -> 0.28089462
A17: Gross Profit | P17: =P10-P14 -> 308.35344 | Q17: =Q10-Q14 -> 338.62717 | R17: =R10-R14 -> 380.586 | S17: =S10-S14 -> 257.66839 | T17: =+T10-T14 -> 359.51885 | U17: =+U10-U14 -> 442.73419 | V17: =+V10-V14 -> 267.10352 | W17: =1823.665555-505.751-1.934-SUM(T17:V17) -> 246.624 | X17: =+X10-X14 -> 192.959 | Y17: =+Y10-Y14 -> 259.061 | Z17: =+Z10-Z14 -> 323.323 | AA17: =+AA10-AA14 -> 446.771 | AB17: =+AB10-AB14 -> 388.851 | AC17: =+AC10-AC14 -> 434.722 | AD17: =+AD10-AD14 -> 435.269 | AE17: =+AE10-AE14 -> 446.669 | ... AR17: =+AR10-AR14 -> 1019.409 | AS17: =+AS313 -> 1201.2466 | AT17: =+AT313 -> 1355.225 | AU17: =+AU313 -> 1591.876 | AV17: =+AV313 -> 1796.5284 | AW17: =+AW313 -> 2402.032 | AX17: =+AX313 -> 2682.5955 | AY17: =+AY313 -> 2992.1899 | AZ17: =+AZ313 -> 3170.3341 | ... BC17: =+BC313 -> 3853.6056 | BG17: =+BG10-BG14 -> 432.636 | BH17: =+BH10-BH14 -> 656.563 | BI17: =+BI10-BI14 -> 1239.931 | BJ17: =+BJ10-BJ14 -> 1285.235 | BK17: =SUM(T17:W17) -> 1315.9806 | BL17: =+BL10-BL14 -> 1231.82 | BM17: =+BM10-BM14 -> 1705.511 | BN17: =+BN10-BN14 -> 1346.522 | BO17: =+BO10-BO14 -> 2115.296 | BP17: =SUM(AN17:AQ17) -> 3232.6249 | BQ17: =SUM(AR17:AU17) -> 5167.7566 | BR17: =SUM(AV17:AY17) -> 9873.3458 | BS17: =SUM(AZ17:BC17) -> 14026.785
C18: Percent of Revenues | P18: =P17/P10 -> 0.76189872 | Q18: =Q17/Q10 -> 0.7137084 | R18: =R17/R10 -> 0.7533865 | S18: =S17/S10 -> 0.7291345 | T18: =T17/T10 -> 0.72519829 | U18: =U17/U10 -> 0.74556442 | V18: =V17/V10 -> 0.70499179 | W18: =W17/W10 -> 0.6942965 | ... BC18: =BC17/BC10 -> 0.72137046 | BG18: =BG17/BG10 -> 0.51202859 | BH18: =BH17/BH10 -> 0.53487167 | BI18: =BI17/BI10 -> 0.70544216 | BJ18: =BJ17/BJ10 -> 0.73960356 | BK18: =BK17/BK10 -> 0.72161288 | BL18: =BL17/BL10 -> 0.48080087 | BM18: =BM17/BM10 -> 0.46443115 | BN18: =BN17/BN10 -> 0.58909726 | ... BS18: =BS17/BS10 -> 0.71910538
C19: Incremental Margin | P19: =IF(P10-O10<=0," NM",(P17-O17)/(P10-O10)) -> 0.76189872 | Q19: =IF(Q10-P10<=0," NM",(Q17-P17)/(Q10-P10)) -> 0.43406672 | R19: =IF(R10-Q10<=0," NM",(R17-Q17)/(R10-Q10)) -> 1.3664933 | S19: =IF(S10-R10<=0," NM",(S17-R17)/(S10-R10)) -> NM | T19: =IF(T10-S10<=0," NM",(T17-S17)/(T10-S10)) -> 0.71542741 | U19: =IF(U10-T10<=0," NM",(U17-T17)/(U10-T10)) -> 0.84851515 | V19: =IF(V10-U10<=0," NM",(V17-U17)/(V10-U10)) -> NM | W19: =IF(W10-V10<=0," NM",(W17-V17)/(W10-V10)) -> NM | ... BC19: =IF(BC10-BB10<=0," NM",(BC17-BB17)/(BC10-BB10)) -> 0.74504252 | BJ19: =IF(BJ10-BI10<=0," NM",(BJ17-BI17)/(BJ10-BI10)) -> NM | BK19: =IF(BK10-BJ10<=0," NM",(BK17-BJ17)/(BK10-BJ10)) -> 0.35779537 | BL19: =IF(BL10-BK10<=0," NM",(BL17-BK17)/(BL10-BK10)) -> -0.11398441 | BM19: =IF(BM10-BL10<=0," NM",(BM17-BL17)/(BM10-BL10)) -> 0.42665601 | BN19: =IF(BN10-BM10<=0," NM",(BN17-BM17)/(BN10-BM10)) -> NM | BO19: =IF(BO10-BN10<=0," NM",(BO17-BN17)/(BO10-BN10)) -> 0.56812691 | BP19: =IF(BP10-BO10<=0," NM",(BP17-BO17)/(BP10-BO10)) -> 0.68088853 | BQ19: =IF(BQ10-BP10<=0," NM",(BQ17-BP17)/(BQ10-BP10)) -> 0.86514119 | ... BS19: =IF(BS10-BR10<=0," NM",(BS17-BR17)/(BS10-BR10)) -> 0.74290631
A21: Total Opex | P21: =SUM(P24,P27,P30) -> 64.346519 | Q21: =SUM(Q24,Q27,Q30) -> 188.14604 | R21: =SUM(R24,R27,R30) -> 80.331 | S21: =S24+S27+S30 -> 103.67444 | T21: =T24+T27+T30 -> 162.8856 | U21: =U24+U27+U30 -> 133.51274 | V21: =V24+V27+V30 -> 120.98195 | W21: =W24+W27+W30 -> 152.04138 | X21: =X24+X27+X30 -> 124.545 | Y21: =Y24+Y27+Y30 -> 139.587 | Z21: =Z24+Z27+Z30 -> 184.658 | ... BC21: =BC24+BC27+BC30 -> 729.91546 | BG21: =+BG24+BG27+BG30 -> 298.218 | BH21: =+BH24+BH27+BH30 -> 308.986 | BI21: =+BI24+BI27+BI30 -> 516.695 | BJ21: =BJ24+BJ27+BJ30 -> 436.498 | BK21: =BK24+BK27+BK30 -> 569.58594 | BL21: =BL24+BL27+BL30 -> 645.187 | BM21: =BM24+BM27+BM30 -> 852.042 | BN21: =BN24+BN27+BN30 -> 944.906 | BO21: =BO24+BO27+BO30 -> 1055.739 | BP21: =BP24+BP27+BP30 -> 1485.4573 | BQ21: =BQ24+BQ27+BQ30 -> 1520.0822 | ... BS21: =BS24+BS27+BS30 -> 2704.675
C22: Percent of Revenues | P22: =P21/P10 -> 0.15899135 | Q22: =Q21/Q10 -> 0.39654646 | R22: =R21/R10 -> 0.1590187 | S22: =S21/S10 -> 0.29337169 | T22: =T21/T10 -> 0.32856236 | U22: =U21/U10 -> 0.22483547 | V22: =V21/V10 -> 0.31931921 | W22: =W21/W10 -> 0.42802727 | ... BC22: =BC21/BC10 -> 0.13663553 | BG22: =BG21/BG10 -> 0.35294368 | BH22: =BH21/BH10 -> 0.25171668 | BI22: =BI21/BI10 -> 0.29396671 | BJ22: =BJ21/BJ10 -> 0.2511879 | BK22: =BK21/BK10 -> 0.31233026 | BL22: =BL21/BL10 -> 0.25182776 | BM22: =BM21/BM10 -> 0.23202128 | BN22: =BN21/BN10 -> 0.41339209 | ... BS22: =BS21/BS10 -> 0.13865945
C24: R&D | P24: 36.901363 | Q24: =150.11152879-P24 -> 113.21017 | R24: 46.824 | S24: =+BJ24-SUM(P24:R24) -> 69.919471 | T24: 97.089211 | U24: =164.33915917-T24 -> 67.249948 | V24: 54.531076 | W24: =299.881-SUM(T24:V24) -> 81.010765 | X24: 66.116 | Y24: 77.624 | Z24: 98.91 | AA24: 127.2 | AB24: 88.518 | AC24: 117.344 | AD24: 117.905 | AE24: 239.721 | AF24: 134.045 | AG24: 168.634 | AH24: 184.25 | AI24: 194.884 | AJ24: 176.044 | AK24: 190.672 | AL24: 185.566 | AM24: 211.188 | AN24: 153.058 | AO24: 204.014 | AP24: =533.160918-SUM(AN24:AO24) -> 176.08892 | AQ24: =533.160918-SUM(AO24:AP24) -> 153.058 | AR24: 188.139 | AS24: =+AR24+10 -> 198.139 | AT24: =+AS24+10 -> 208.139 | AU24: =+AT24+10 -> 218.139 | AV24: =+AU24+18 -> 236.139 | AW24: =+AV24+18 -> 254.139 | AX24: =+AW24+18 -> 272.139 | AY24: =+AX24+18 -> 290.139 | AZ24: =+AY24+18 -> 308.139 | BA24: =+AZ24+18 -> 326.139 | BB24: =+BA24+18 -> 344.139 | BC24: =+BB24+18 -> 362.139 | BG24: 198.227 | BH24: 188.269 | BI24: 276.695 | BJ24: 266.855 | BK24: =SUM(T24:W24) -> 299.881 | BL24: 369.85 | BM24: 563.487 | BN24: 681.812 | BO24: 763.47 | BP24: =SUM(AN24:AQ24) -> 686.21892 | BQ24: =SUM(AR24:AU24) -> 812.556 | BR24: =SUM(AV24:AY24) -> 1052.556 | BS24: =SUM(AZ24:BC24) -> 1340.556
C25: Percent of Revenues | P25: =P24/P10 -> 0.091178167 | Q25: =Q24/Q10 -> 0.23860768 | R25: =R24/R10 -> 0.09269014 | S25: =S24/S10 -> 0.19785391 | T25: =T24/T10 -> 0.19584211 | U25: =U24/U10 -> 0.11324892 | V25: =V24/V10 -> 0.14392907 | W25: =W24/W10 -> 0.2280617 | ... BC25: =BC24/BC10 -> 0.067790117 | BG25: =BG24/BG10 -> 0.23460344 | BH25: =BH24/BH10 -> 0.15337409 | BI25: =BI24/BI10 -> 0.15742192 | BJ25: =BJ24/BJ10 -> 0.15356484 | BK25: =BK24/BK10 -> 0.16443859 | BL25: =BL24/BL10 -> 0.14435892 | BM25: =BM24/BM10 -> 0.15344428 | BN25: =BN24/BN10 -> 0.29828966 | ... BS25: =BS24/BS10 -> 0.068725731
C27: General & administrative | P27: 14.729894 | Q27: =55.93711588-P27 -> 41.207221 | R27: 17.898 | S27: =+BJ27-SUM(P27:R27) -> 21.295884 | T27: 44.039237 | U27: =91.12973771-T27 -> 47.0905 | V27: 39.674929 | W27: =187.70494-SUM(T27:V27) -> 56.900273 | X27: 43.461 | Y27: 45.752 | Z27: 65.966 | AA27: 43.576 | AB27: 36.742 | AC27: 40.107 | AD27: 41.864 | AE27: 83.693 | AF27: 38.373 | AG27: 48.398 | AH27: 39.667 | AI27: 46.695 | AJ27: 39.768 | AK27: 39.787 | AL27: 42.315 | AM27: 74.393 | AN27: 101.875 | AO27: 119.744 | AP27: =591.436679-SUM(AN27:AO27) -> 369.81768 | AQ27: =591.436679-SUM(AO27:AP27) -> 101.875 | AR27: 127.382 | AS27: =+AS28*AS10 -> 138.99659 | AT27: =+AT28*AT10 -> 150.32246 | AU27: =+AU28*AU10 -> 168.72917 | AV27: =+AV28*AV10 -> 181.2289 | AW27: =+AW28*AW10 -> 228.13319 | AX27: =+AX28*AX10 -> 253.66797 | AY27: =+AY28*AY10 -> 281.92299 | AZ27: =+AZ28*AZ10 -> 284.76682 | ... BC27: =+BC28*BC10 -> 327.75246 | BG27: 47.754 | BH27: 51.79 | BI27: 112.784 | BJ27: 95.131 | BK27: =SUM(T27:W27) -> 187.70494 | BL27: 198.755 | BM27: 202.408 | BN27: 173.133 | BO27: 196.262 | BP27: =SUM(AN27:AQ27) -> 693.31168 | BQ27: =SUM(AR27:AU27) -> 585.43022 | BR27: =SUM(AV27:AY27) -> 944.95306 | BS27: =SUM(AZ27:BC27) -> 1210.023
C28: Percent of Revenues | P28: =P27/P10 -> 0.036395533 | Q28: =Q27/Q10 -> 0.086850502 | R28: =R27/R10 -> 0.035429868 | S28: =S27/S10 -> 0.060261811 | T28: =T27/T10 -> 0.088833116 | U28: =U27/U10 -> 0.079300408 | V28: =V27/V10 -> 0.10471783 | W28: =W27/W10 -> 0.16018579 | ... AQ28: =AQ27/AQ10 -> 0.083353174 | AR28: =+AQ28-0.25% -> 0.080853174 | AS28: =+AR28-0.25% -> 0.078353174 | AT28: =+AS28-0.25% -> 0.075853174 | AU28: =+AT28-0.25% -> 0.073353174 | AV28: =+AU28-0.3% -> 0.070353174 | AW28: =+AV28-0.3% -> 0.067353174 | AX28: =+AW28 -> 0.067353174 | AY28: =+AX28 -> 0.067353174 | AZ28: =+AY28-0.3% -> 0.064353174 | BA28: =+AZ28-0.3% -> 0.061353174 | BB28: =+BA28 -> 0.061353174 | BC28: =+BB28 -> 0.061353174 | BG28: =BG27/BG10 -> 0.056517288 | BH28: =BH27/BH10 -> 0.04219093 | BI28: =BI27/BI10 -> 0.064166949 | BJ28: =BJ27/BJ10 -> 0.05474425 | BK28: =BK27/BK10 -> 0.10292728 | BL28: =BL27/BL10 -> 0.077577549 | BM28: =BM27/BM10 -> 0.055118132 | BN28: =BN27/BN10 -> 0.075744902 | ... BS28: =BS27/BS10 -> 0.062033748
C30: Selling & marketing | P30: 12.715262 | Q30: =46.44391461-P30 -> 33.728653 | R30: 15.609 | S30: =+BJ30-SUM(P30:R30) -> 12.459085 | T30: 21.757154 | U30: =40.92944941-T30 -> 19.172296 | V30: 26.775946 | W30: =81.83573992-SUM(T30:V30) -> 14.130345 | X30: 14.968 | Y30: 16.211 | Z30: 19.782 | AA30: 25.621 | AB30: 15.058 | AC30: 21.272 | AD30: 22.986 | AE30: 26.832 | AF30: 20.645 | AG30: 24.859 | AH30: 20.497 | AI30: 23.96 | AJ30: 21.6 | AK30: 21.833 | AL30: 25.832 | AM30: 26.742 | AN30: 24.057 | AO30: 27.235 | AP30: =81.869692-SUM(AN30:AO30) -> 30.577692 | AQ30: =81.869692-SUM(AO30:AP30) -> 24.057 | AR30: 29.024 | AS30: =+AR30+1 -> 30.024 | AT30: =+AS30+1 -> 31.024 | AU30: =+AT30+1 -> 32.024 | AV30: =+AU30+1 -> 33.024 | AW30: =+AV30+1 -> 34.024 | AX30: =+AW30+1 -> 35.024 | AY30: =+AX30+1 -> 36.024 | AZ30: =+AY30+1 -> 37.024 | ... BC30: =+BB30+1 -> 40.024 | BG30: 52.237 | BH30: 68.927 | BI30: 127.216 | BJ30: 74.512 | BK30: 82 | BL30: 76.582 | BM30: 86.147 | BN30: 89.961 | BO30: 96.007 | BP30: =SUM(AN30:AQ30) -> 105.92669 | BQ30: =SUM(AR30:AU30) -> 122.096 | BR30: =SUM(AV30:AY30) -> 138.096 | BS30: =SUM(AZ30:BC30) -> 154.096
C31: Percent of Revenues | P31: =P30/P10 -> 0.031417654 | Q31: =Q30/Q10 -> 0.071088278 | R31: =R30/R10 -> 0.030898693 | S31: =S30/S10 -> 0.03525597 | T31: =T30/T10 -> 0.043887131 | U31: =U30/U10 -> 0.032286148 | V31: =V30/V10 -> 0.070672309 | W31: =W30/W10 -> 0.039779781 | ... BC31: =BC30/BC10 -> 0.0074922381 | BG31: =BG30/BG10 -> 0.061822959 | BH31: =BH30/BH10 -> 0.056151656 | BI31: =BI30/BI10 -> 0.072377842 | BJ31: =BJ30/BJ10 -> 0.042878805 | BK31: =BK30/BK10 -> 0.044964385 | BL31: =BL30/BL10 -> 0.029891293 | BM31: =BM30/BM10 -> 0.023458864 | BN31: =BN30/BN10 -> 0.039357529 | ... BS31: =BS30/BS10 -> 0.007899976
A33: Operating Income | P33: =P17-P21 -> 244.00692 | Q33: =Q17-Q21 -> 150.48113 | R33: =R17-R21 -> 300.255 | S33: =S17-S21 -> 153.99395 | T33: =T17-T21 -> 196.63325 | U33: =U17-U21 -> 309.22144 | V33: =V17-V21 -> 146.12156 | W33: =W17-W21 -> 94.582621 | ... BC33: =BC17-BC21 -> 3123.6902 | BG33: =BG17-BG21 -> 134.418 | BH33: =BH17-BH21 -> 347.577 | BI33: =BI17-BI21 -> 723.236 | BJ33: =BJ17-BJ21 -> 848.737 | BK33: =BK17-BK21 -> 746.39462 | BL33: =BL17-BL21 -> 586.633 | BM33: =BM17-BM21 -> 853.469 | BN33: =BN17-BN21 -> 401.616 | ... BS33: =BS17-BS21 -> 11322.11
C34: Percent of Revenues | P34: =P33/P10 -> 0.60290737 | Q34: =Q33/Q10 -> 0.31716193 | R34: =R33/R10 -> 0.5943678 | S34: =S33/S10 -> 0.4357628 | T34: =T33/T10 -> 0.39663594 | U34: =U33/U10 -> 0.52072894 | V34: =V33/V10 -> 0.38567259 | W34: =W33/W10 -> 0.26626922 | ... BC34: =BC33/BC10 -> 0.58473493 | BG34: =BG33/BG10 -> 0.15908491 | BH34: =BH33/BH10 -> 0.28315499 | BI34: =BI33/BI10 -> 0.41147545 | BJ34: =BJ33/BJ10 -> 0.48841567 | BK34: =BK33/BK10 -> 0.40928262 | BL34: =BL33/BL10 -> 0.22897311 | BM34: =BM33/BM10 -> 0.23240987 | BN34: =BN33/BN10 -> 0.17570518 | ... BS34: =BS33/BS10 -> 0.58044593
C35: Change vs Year Ago | T35: =IF((T33/P33)-1>0,(T33/P33)-1,"nm") -> nm | U35: =IF((U33/Q33)-1>0,(U33/Q33)-1,"nm") -> 1.0548851 | V35: =IF((V33/R33)-1>0,(V33/R33)-1,"nm") -> nm | W35: =IF((W33/S33)-1>0,(W33/S33)-1,"nm") -> nm | X35: =(X33/T33)-1 -> -0.65207308 | Y35: =(Y33/U33)-1 -> -0.61362964 | Z35: =(Z33/V33)-1 -> -0.05102987 | AA35: =(AA33/W33)-1 -> 1.6471459 | AB35: =(AB33/X33)-1 -> 2.6327798 | AC35: =(AC33/Y33)-1 -> 1.1427172 | AD35: =(AD33/Z33)-1 -> 0.82103631 | AE35: =(AE33/AA33)-1 -> -0.61488413 | ... BC35: =(BC33/AY33)-1 -> 0.31021561 | BJ35: =BJ33/BI33-1 -> 0.17352704 | BK35: =BK33/BJ33-1 -> -0.12058198 | BL35: =BL33/BK33-1 -> -0.21404444 | BM35: =BM33/BL33-1 -> 0.45486019 | BN35: =BN33/BM33-1 -> -0.52943106 | BO35: =BO33/BN33-1 -> 1.638234 | BP35: =BP33/BO33-1 -> 0.64896045 | BQ35: =BQ33/BP33-1 -> 1.0877644 | ... BS35: =BS33/BR33-1 -> 0.463232
A37: Total Non-operating Income(Loss) | P37: =P46-P33 -> -9.4626048 | Q37: =Q46-Q33 -> 73.221531 | R37: =R46-R33 -> 6.458 | S37: =S46-S33 -> 59.793074 | T37: =+T46-T33 -> 79.972019 | U37: =+U46-U33 -> 39.749125 | V37: =+V46-V33 -> 165.77896 | W37: =+W46-W33 -> 172.58451 | X37: =+X46-X33 -> 84.54 | Y37: =+Y46-Y33 -> 79.972 | Z37: =+Z46-Z33 -> 58.954 | AA37: =+AA46-AA33 -> 114.614 | ... AR37: =+AR46-AR33 -> 202.259 | AS37: =SUM(AS38:AS44) -> -24.966 | AT37: =SUM(AT38:AT44) -> -24.966 | AU37: =SUM(AU38:AU44) -> -24.966 | AV37: =SUM(AV38:AV44) -> 45 | AW37: =SUM(AW38:AW44) -> 45 | AX37: =SUM(AX38:AX44) -> 45 | AY37: =SUM(AY38:AY44) -> 45 | AZ37: =SUM(AZ38:AZ44) -> 45 | ... BC37: =SUM(BC38:BC44) -> 45 | BG37: =+BG46-BG33 -> -35.325 | BH37: =+BH46-BH33 -> 14.793 | BI37: =+BI46-BI33 -> 62.996 | BJ37: =+BJ46-BJ33 -> 130.01 | BK37: =+BK46-BK33 -> 458.24888 | BL37: =+BL46-BL33 -> 328.374 | BM37: =+BM46-BM33 -> 560.397 | BN37: =+BN46-BN33 -> 70.603 | BO37: =+BO46-BO33 -> 353.061 | BP37: =SUM(BP38:BP44) -> 476.59689 | BQ37: =SUM(BQ38:BQ44) -> 127.361 | BR37: =SUM(BR38:BR44) -> 180 | BS37: =SUM(BS38:BS44) -> 180
C38: Interest income | P38: 9.7631738 | Q38: =31.95472418-P38 -> 22.19155 | R38: =+Q38 -> 22.19155 | S38: =+BJ38-SUM(P38:R38) -> 25.495866 | T38: 13.756094 | U38: =20.14199021-T38 -> 6.3858962 | V38: 24.504982 | W38: =BK38-SUM(T38:V38) -> 34.938641 | X38: 12.951 | Y38: =22.62-X38 -> 9.669 | Z38: =49.731-X38-Y38 -> 27.111 | AA38: =+BL38-X38-Y38-Z38 -> 23.442 | AB38: 17.609 | AC38: 23.839 | AD38: 23.924 | AE38: 15.908 | AF38: 27.544 | AG38: 45.815 | AH38: 58.107 | AI38: 48.792 | AJ38: 53.984 | AK38: 67.596 | AL38: 73.493 | AM38: 45.431 | AN38: 40.541 | AO38: 85.145 | AP38: 74.565 | AQ38: 28.066 | AR38: -24.966 | AS38: =+AR38 -> -24.966 | AT38: =+AS38 -> -24.966 | AU38: =+AT38 -> -24.966 | AV38: 45 | AW38: =+AV38 -> 45 | AX38: =+AW38 -> 45 | AY38: =+AX38 -> 45 | AZ38: 45 | BA38: =+AZ38 -> 45 | BB38: =+BA38 -> 45 | BC38: =+BB38 -> 45 | BG38: 0 | BH38: 0 | BI38: 21.097004 | BJ38: 79.642141 | BK38: 79.585613 | BL38: 73.173 | BM38: =SUM(AB38:AE38) -> 81.28 | BN38: =SUM(AC38:AF38) -> 91.215 | BO38: =SUM(AD38:AG38) -> 113.191 | BP38: =SUM(AN38:AQ38) -> 228.317 | BQ38: =SUM(AR38:AU38) -> -99.864 | BR38: =SUM(AV38:AY38) -> 180 | BS38: =SUM(AZ38:BC38) -> 180
C39: Interest expense | P39: 0 | Q39: 0 | R39: 0 | S39: =AVERAGE(O39:R39) -> 0 | T39: 0 | U39: =AVERAGE(Q39:T39) -> 0 | V39: =AVERAGE(R39:U39) -> 0 | W39: =BK39-SUM(T39:V39) -> 0 | X39: 0 | Y39: 0 | Z39: 0 | AA39: 0 | AB39: 0 | AC39: 0 | AD39: 0 | AE39: 0 | AF39: 0 | AG39: 0 | AH39: 0 | AI39: 0 | AJ39: 0 | AK39: 0 | AL39: 1 | AM39: 1 | AN39: 1 | AO39: 1 | AP39: 0 | AQ39: 0 | AR39: 0 | AS39: 0 | AT39: 0 | AU39: 0 | AV39: 0 | AW39: 0 | AX39: 0 | AY39: 0 | AZ39: 0 | BA39: 0 | BB39: 0 | BC39: 0 | BG39: 0 | BH39: 0 | BI39: 0 | BJ39: 0 | BK39: 0 | BL39: =SUM(X39:AA39) -> 0 | BM39: =SUM(AB39:AE39) -> 0 | BN39: =SUM(AC39:AF39) -> 0 | BO39: =SUM(AD39:AG39) -> 0 | BP39: =SUM(AN39:AQ39) -> 2 | BQ39: =SUM(AR39:AU39) -> 0 | BR39: =SUM(AV39:AY39) -> 0 | BS39: =SUM(AZ39:BC39) -> 0
C40: Investment Income(loss) | P40: 0 | Q40: 0 | R40: 7.106 | S40: =AVERAGE(O40:R40) -> 2.3686667 | T40: 32.911078 | U40: =60.10369041-T40 -> 27.192613 | V40: 40.193753 | W40: =BK40-SUM(T40:V40) -> 2.1925566 | X40: 15.108 | Y40: 17.695 | Z40: 228.278 | AA40: 17.033 | AB40: 11.708 | AC40: 13.229 | AD40: 16.707 | AE40: 332.974 | AF40: 12.937 | AG40: 13.748 | AH40: 49.898 | AI40: 14.395 | AJ40: 12.126 | AK40: 4.219 | AL40: 19.54 | AM40: 12.714 | AN40: 9.547 | AO40: 10.435 | AP40: 5 | AQ40: 5 | AR40: 0 | AS40: 0 | AT40: 0 | AU40: 0 | AV40: 0 | AW40: 0 | AX40: 0 | AY40: 0 | AZ40: 0 | BA40: 0 | BB40: 0 | BC40: 0 | BG40: 0.473 | BH40: 6.196 | BI40: 17.305 | BJ40: 71.905 | BK40: 102.49 | BL40: 278.114 | BM40: 374.618 | BN40: 90.978 | BO40: 48.599 | BP40: =SUM(AN40:AQ40) -> 29.982 | BQ40: =SUM(AR40:AU40) -> 0 | BR40: =SUM(AV40:AY40) -> 0 | BS40: =SUM(AZ40:BC40) -> 0
C41: Investment disposal gain(loss) | P41: 0 | Q41: 0 | R41: 0 | S41: 0 | T41: 0 | U41: 0 | V41: 0 | W41: =BK41-SUM(T41:V41) -> 0 | X41: 0 | Y41: 0 | Z41: 0 | AA41: 0 | AB41: 0 | AC41: 0 | AD41: 0 | AE41: 0 | AF41: 0 | AG41: 0 | AH41: 0 | AI41: 0 | AJ41: 0 | AK41: 0 | AL41: 0 | AM41: 0 | AN41: 0 | AO41: 0 | AP41: 0 | AQ41: 0 | AR41: 0 | AS41: 0 | AT41: 0 | AU41: 0 | AV41: 0 | AW41: 0 | AX41: 0 | AY41: · | AZ41: 0 | BA41: 0 | BB41: 0 | BC41: · | BG41: 0 | BH41: -193 | BI41: 0 | BJ41: -124 | BK41: 0 | BL41: -3 | BM41: 0 | BN41: -41 | BO41: 0 | BP41: =SUM(AN41:AQ41) -> 0 | BQ41: =SUM(AR41:AU41) -> 0 | BR41: =SUM(AV41:AY41) -> 0 | BS41: =SUM(AZ41:BC41) -> 0
C42: Forex gain(loss) | P42: 0 | Q42: 0 | R42: 0 | S42: 0 | T42: =39.80282436-13.75609404 -> 26.04673 | U42: =27.86259441-T42 -> 1.8158641 | V42: 0 | W42: =BK42-SUM(T42:V42) -> -51.314701 | X42: 0 | Y42: 0 | Z42: 0 | AA42: 0 | AB42: 0 | AC42: 0 | AD42: 0 | AE42: 0 | AF42: 0 | AG42: 0 | AH42: 0 | AI42: 0 | AJ42: 0 | AK42: 0 | AL42: 0 | AM42: 0 | AN42: 0 | AO42: 0 | AP42: 0 | AQ42: 0 | AR42: 0 | AS42: 0 | AT42: 0 | AU42: 0 | AV42: 0 | AW42: 0 | AX42: 0 | AY42: 0 | AZ42: 0 | BA42: 0 | BB42: 0 | BC42: 0 | BG42: 0 | BH42: 0 | BI42: 0 | BJ42: 21.948618 | BK42: -23.452107 | BL42: =SUM(X42:AA42) -> 0 | BM42: =SUM(AB42:AE42) -> 0 | BN42: =SUM(AC42:AF42) -> 0 | BO42: =SUM(AD42:AG42) -> 0 | BP42: =SUM(AN42:AQ42) -> 0 | BQ42: =SUM(AR42:AU42) -> 0 | BR42: =SUM(AV42:AY42) -> 0 | BS42: =SUM(AZ42:BC42) -> 0
C43: Asset impairment gain (loss) | P43: 0 | Q43: 0 | R43: -70.282 | S43: 0 | T43: -9.8115508 | U43: =-17.99192042-T43 -> -8.1803696 | V43: 18.357 | W43: -12.94 | X43: 2.888 | Y43: -13.173 | Z43: 8.792 | AA43: 0.967 | AB43: -0.228 | AC43: 0.109 | AD43: -0.447 | AE43: -26.176 | AF43: -52.765 | AG43: -91.239 | AH43: -36.234 | AI43: -12.146 | AJ43: -1.508 | AK43: -0.28 | AL43: -0.555 | AM43: -42.564 | AN43: 8.976 | AO43: 21.845 | AP43: 0 | AQ43: 0 | AR43: 0 | AS43: 0 | AT43: 0 | AU43: 0 | AV43: 0 | AW43: 0 | AX43: 0 | AY43: 0 | AZ43: 0 | BA43: 0 | BB43: 0 | BC43: 0 | BG43: -55.4 | BH43: -53.743 | BI43: -13.314 | BJ43: -87.978676 | BK43: -12.728942 | BL43: -0.526 | BM43: -26.742 | BN43: -192.385 | BO43: -44.908 | BP43: =SUM(AN43:AQ43) -> 30.821 | BQ43: =SUM(AR43:AU43) -> 0 | BR43: =SUM(AV43:AY43) -> 0 | BS43: =SUM(AZ43:BC43) -> 0
C44: Others | P44: =P37-SUM(P39:P43) -> -9.4626048 | Q44: =Q37-SUM(Q39:Q43) -> 73.221531 | R44: =R37-SUM(R39:R43) -> 69.634 | S44: =S37-SUM(S39:S43) -> 57.424407 | T44: =T37-SUM(T39:T43) -> 30.825762 | U44: =U37-SUM(U39:U43) -> 18.921018 | V44: =V37-SUM(V39:V43) -> 107.2282 | W44: =W37-SUM(W39:W43) -> 234.64666 | ... AA44: =AA37-SUM(AA39:AA43) -> 96.614 | AB44: =AB37-SUM(AB38:AB43) -> 78.329 | AC44: =AC37-SUM(AC38:AC43) -> 133.308 | AD44: =AD37-SUM(AD38:AD43) -> 14.272 | AE44: =AE37-SUM(AE38:AE43) -> -94.669 | AF44: =AF37-SUM(AF38:AF43) -> 5.808 | AG44: =AG37-SUM(AG38:AG43) -> 46.277 | AH44: =AH37-SUM(AH38:AH43) -> -53.464 | AI44: =AI37-SUM(AI38:AI43) -> -6.868 | ... AO44: =AO37-SUM(AO38:AO43) -> 35.163 | AP44: =+AP37-SUM(AP38:AP43) -> 101.54789 | AQ44: =+AQ37-SUM(AQ38:AQ43) -> 37.882 | AR44: =+AR37-SUM(AR38:AR43) -> 227.225 | AS44: 0 | AT44: 0 | AU44: 0 | AV44: 0 | AW44: 0 | AX44: 0 | AY44: 0 | AZ44: 0 | BA44: 0 | BB44: 0 | BC44: 0 | BG44: =+BG37-SUM(BG38:BG43) -> 19.602 | BH44: =+BH37-SUM(BH38:BH43) -> 255.34 | BI44: =+BI37-SUM(BI38:BI43) -> 37.907996 | BJ44: =+BJ37-SUM(BJ38:BJ43) -> 168.49292 | BK44: =BK37-SUM(BK38:BK43) -> 312.35431 | BL44: =BL37-SUM(BL38:BL43) -> -19.387 | BM44: =BM37-SUM(BM38:BM43) -> 131.241 | BN44: =BN37-SUM(BN38:BN43) -> 121.795 | BO44: =BO37-SUM(BO38:BO43) -> 236.179 | BP44: =SUM(AN44:AQ44) -> 185.47689 | BQ44: =SUM(AR44:AU44) -> 227.225 | BR44: =SUM(AV44:AY44) -> 0 | BS44: =SUM(AZ44:BC44) -> 0
A46: Profit Before Taxes | P46: 234.54431 | Q46: =458.24697934-P46 -> 223.70266 | R46: 306.713 | S46: =+BJ46-SUM(P46:R46) -> 213.78702 | T46: 276.60527 | U46: =625.57583443-T46 -> 348.97057 | V46: 311.90052 | W46: =1204.643491-SUM(T46:V46) -> 267.16714 | X46: 152.954 | Y46: 199.446 | Z46: 197.619 | AA46: 364.988 | AB46: 355.951 | AC46: 426.484 | AD46: 306.97 | AE46: 324.46 | AF46: 24.034 | AG46: 71.614 | AH46: 161.082 | AI46: 215.489 | AJ46: 240.507 | AK46: 399.179 | AL46: 402.017 | AM46: 370.916 | AN46: 530.78 | AO46: 655.406 | AP46: =1692.984472-SUM(AN46:AO46) -> 506.79847 | AQ46: =1692.984472-SUM(AO46:AP46) -> 530.78 | AR46: 877.123 | AS46: =AS33+AS37 -> 809.12098 | AT46: =AT33+AT37 -> 940.77353 | AU46: =AU33+AU37 -> 1148.0178 | AV46: =AV33+AV37 -> 1391.1365 | AW46: =AW33+AW37 -> 1930.7358 | AX46: =AX33+AX37 -> 2166.7645 | AY46: =AY33+AY37 -> 2429.1039 | AZ46: =AZ33+AZ37 -> 2585.4043 | ... BC46: =BC33+BC37 -> 3168.6902 | BG46: 99.093 | BH46: 362.37 | BI46: 786.232 | BJ46: 978.747 | BK46: 1204.6435 | BL46: 915.007 | BM46: 1413.866 | BN46: 472.219 | BO46: 1412.618 | BP46: =BP33+BP37 -> 2223.7645 | BQ46: =BQ33+BQ37 -> 3775.0354 | BR46: =BR33+BR37 -> 7917.7407 | BS46: =BS33+BS37 -> 11502.11
C47: Percent of Revenues | P47: =P46/P10 -> 0.57952658 | Q47: =Q46/Q10 -> 0.47148747 | R47: =R46/R10 -> 0.60715169 | S47: =S46/S10 -> 0.60496165 | T47: =T46/T10 -> 0.55795035 | U47: =U46/U10 -> 0.58766647 | V47: =V46/V10 -> 0.8232288 | W47: =W46/W10 -> 0.75212957 | ... BC47: =BC46/BC10 -> 0.59315864 | BG47: =BG46/BG10 -> 0.11727746 | BH47: =BH46/BH10 -> 0.29520617 | BI47: =BI46/BI10 -> 0.44731618 | BJ47: =BJ46/BJ10 -> 0.56323145 | BK47: =BK46/BK10 -> 0.66056163 | BL47: =BL46/BL10 -> 0.35714322 | BM47: =BM46/BM10 -> 0.38501271 | BN47: =BN46/BN10 -> 0.20659367 | ... BS47: =BS46/BS10 -> 0.58967392
A49: Taxes | P49: 8.8038863 | Q49: =7.41977878-P49 -> -1.3841076 | R49: 14.03 | S49: =+BJ49-SUM(P49:R49) -> 24.439221 | T49: 13.616949 | U49: =24.05116747-T49 -> 10.434218 | V49: 35.656776 | W49: =100.92-SUM(T49:V49) -> 41.212056 | X49: 18.837 | Y49: 25.716 | Z49: -6.984 | AA49: 48.301 | AB49: 49.852 | AC49: 51.626 | AD49: -11.039 | AE49: 24.055 | AF49: 4.313 | AG49: 9.386 | AH49: 9.036 | AI49: -1.664 | AJ49: 17.098 | AK49: 29.433 | AL49: 18.792 | AM49: 6.558 | AN49: 27.061 | AO49: 46.749 | AP49: =116.62-SUM(AN49:AO49) -> 42.81 | AQ49: =116.62-SUM(AO49:AP49) -> 27.061 | AR49: 47.398 | AS49: =AS50*AS46 -> 57.713229 | AT49: =AT50*AT46 -> 67.103783 | AU49: =AU50*AU46 -> 81.886168 | AV49: =AV50*AV46 -> 99.227407 | AW49: =AW50*AW46 -> 137.71612 | AX49: =AX50*AX46 -> 154.55164 | AY49: =AY50*AY46 -> 173.26387 | AZ49: =AZ50*AZ46 -> 184.41251 | ... BC49: =BC50*BC46 -> 226.0173 | BG49: 6.288 | BH49: 15.454 | BI49: 49.354 | BJ49: 45.889 | BK49: =SUM(T49:W49) -> 100.92 | BL49: 85.87 | BM49: 114.494 | BN49: 21.071 | BO49: 71.882 | BP49: =SUM(AN49:AQ49) -> 143.681 | BQ49: =SUM(AR49:AU49) -> 254.10118 | BR49: =SUM(AV49:AY49) -> 564.75904 | BS49: =SUM(AZ49:BC49) -> 820.42602
C50: Tax Rate | P50: =P49/P46 -> 0.037536132 | Q50: =Q49/Q46 -> -0.0061872645 | R50: =R49/R46 -> 0.045743089 | S50: =S49/S46 -> 0.11431574 | T50: =T49/T46 -> 0.049228814 | U50: =U49/U46 -> 0.029899995 | V50: =V49/V46 -> 0.11432099 | W50: =W49/W46 -> 0.15425571 | ... AO50: =AO49/AO46 -> 0.071328306 | AP50: =AO50 -> 0.071328306 | AQ50: =AP50 -> 0.071328306 | AR50: =AQ50 -> 0.071328306 | AS50: =AR50 -> 0.071328306 | AT50: =AS50 -> 0.071328306 | AU50: =AT50 -> 0.071328306 | AV50: =AU50 -> 0.071328306 | AW50: =AV50 -> 0.071328306 | ... BC50: =BB50 -> 0.071328306 | BG50: =BG49/BG46 -> 0.063455542 | BH50: =BH49/BH46 -> 0.042647018 | BI50: =BI49/BI46 -> 0.06277282 | BJ50: =BJ49/BJ46 -> 0.046885457 | BK50: =BK49/BK46 -> 0.083775823 | BL50: =BL49/BL46 -> 0.093846277 | BM50: =BM49/BM46 -> 0.080979386 | BN50: =BN49/BN46 -> 0.044621246 | ... BS50: =BS49/BS46 -> 0.071328306
A52: Net Income | P52: =P46-P49 -> 225.74043 | Q52: =Q46-Q49 -> 225.08677 | R52: =R46-R49 -> 292.683 | S52: =S46-S49 -> 189.3478 | T52: =T46-T49 -> 262.98832 | U52: =U46-U49 -> 338.53635 | V52: =V46-V49 -> 276.24374 | W52: =W46-W49 -> 225.95508 | ... BC52: =BC46-BC49 -> 2942.6729 | BG52: =+BG46-BG49 -> 92.805 | BH52: =+BH46-BH49 -> 346.916 | BI52: =+BI46-BI49 -> 736.878 | BJ52: =BJ46-BJ49 -> 932.858 | BK52: =BK46-BK49 -> 1103.7235 | BL52: =BL46-BL49 -> 829.137 | BM52: =BM46-BM49 -> 1299.372 | BN52: =BN46-BN49 -> 451.148 | BO52: =BO46-BO49 -> 1340.736 | BP52: =BP46-BP49 -> 2080.0835 | BQ52: =BQ46-BQ49 -> 3520.9342 | ... BS52: =BS46-BS49 -> 10681.684
C53: Percent of Revenues | P53: =P52/P10 -> 0.55777339 | Q53: =Q52/Q10 -> 0.47440469 | R53: =R52/R10 -> 0.5793787 | S53: =S52/S10 -> 0.53580501 | T53: =T52/T10 -> 0.53048311 | U53: =U52/U10 -> 0.57009525 | V53: =V52/V10 -> 0.72911647 | W53: =W52/W10 -> 0.63610929 | ... BC53: =BC52/BC10 -> 0.55084964 | BJ53: =BJ52/BJ10 -> 0.53682408 | BK53: =BK52/BK10 -> 0.60522254 | BL53: =BL52/BL10 -> 0.32362666 | BM53: =BM52/BM$10 -> 0.35383462 | BN53: =BN52/BN$10 -> 0.1973752 | BO53: =BO52/BO$10 -> 0.3684443 | BP53: =BP52/BP$10 -> 0.39396285 | BQ53: =BQ52/BQ$10 -> 0.4684162 | BR53: =BR52/BR$10 -> 0.52841805 | BS53: =BS52/BS$10 -> 0.54761347
A55: Minority Interests | P55: 0 | Q55: 0 | R55: 0 | S55: =R55 -> 0 | T55: =S55 -> 0 | U55: =T55 -> 0 | V55: 0 | W55: 0 | X55: 0 | Y55: 0 | Z55: 0 | AA55: 0 | AB55: 0 | AC55: 0.001 | AD55: 0.01 | AE55: -0.017 | AF55: 0 | AG55: 0.093 | AH55: 0.144 | AI55: 0 | AJ55: 0 | AK55: 0 | AL55: -1.699 | AM55: -69.344 | AN55: -21.607 | AO55: -25.087 | AP55: =-55.919487-SUM(AN55:AO55) -> -9.225487 | AQ55: =-55.919487-SUM(AO55:AP55) -> -21.607 | AR55: -17.65 | AS55: =AR55 -> -17.65 | AT55: =AS55 -> -17.65 | AU55: =AT55 -> -17.65 | AV55: =AU55 -> -17.65 | AW55: =AV55 -> -17.65 | AX55: =AW55 -> -17.65 | AY55: =AX55 -> -17.65 | AZ55: =AY55 -> -17.65 | ... BC55: =BB55 -> -17.65 | BG55: =+BG57-BG52 -> -0.001 | BH55: =+BH57-BH52 -> 0 | BI55: =+BI57-BI52 -> 0 | BJ55: =SUM(P55:S55) -> 0 | BK55: =SUM(T55:W55) -> 0 | BL55: =SUM(X55:AA55) -> 0 | BM55: =SUM(AB55:AE55) -> -0.006 | BN55: =SUM(AF55:AI55) -> 0.237 | BO55: =SUM(AJ55:AM55) -> -71.043 | BP55: =SUM(AN55:AQ55) -> -77.526487 | BQ55: =SUM(AR55:AU55) -> -70.6 | BR55: =SUM(AV55:AY55) -> -70.6 | BS55: =SUM(AZ55:BC55) -> -70.6
A57: Reported Income (attributable to parent) | P57: =+P52+P55 -> 225.74043 | Q57: =Q52+Q55 -> 225.08677 | R57: 292.683 | S57: =S52+S55 -> 189.3478 | T57: =T52+T55 -> 262.98832 | U57: =U52+U55 -> 338.53635 | V57: =V52+V55 -> 276.24374 | W57: =W52+W55 -> 225.95508 | X57: =X52+X55 -> 134.117 | Y57: =Y52+Y55 -> 173.73 | Z57: =Z52+Z55 -> 204.603 | ... AH57: =AH52+AH55 -> 152.19 | AI57: =AI52-AI55 -> 217.153 | AJ57: =AJ52-AJ55 -> 223.409 | AK57: =AK52-AK55 -> 369.746 | AL57: =AL52-AL55 -> 384.924 | AM57: =AM52-AM55 -> 433.702 | AN57: =AN52-AN55 -> 525.326 | AO57: =AO52-AO55 -> 633.744 | AP57: =AP52-AP55 -> 473.21396 | ... BC57: =BC52-BC55 -> 2960.3229 | BG57: 92.804 | BH57: 346.916 | BI57: 736.878 | BJ57: 932.858 | BK57: =BK52-BK55 -> 1103.7235 | BL57: 829.138 | BM57: 1299.378 | BN57: 450.91 | BO57: 1411.779 | BP57: =BP52-BP55 -> 2157.61 | BQ57: =BQ52-BQ55 -> 3591.5342 | BR57: =BR52-BR55 -> 7423.5817 | BS57: =BS52-BS55 -> 10752.284 | BT57: =+(BS57/BQ57)^(1/2)-1 -> 0.73025598
C58: Percent of Revenues | P58: =P57/P10 -> 0.55777339 | Q58: =Q57/Q10 -> 0.47440469 | R58: =R57/R10 -> 0.5793787 | S58: =S57/S10 -> 0.53580501 | T58: =T57/T10 -> 0.53048311 | U58: =U57/U10 -> 0.57009525 | V58: =V57/V10 -> 0.72911647 | W58: =W57/W10 -> 0.63610929 | ... BC58: =BC57/BC10 -> 0.55415361 | BG58: =BG57/BG10 -> 0.10983437 | BH58: =BH57/BH10 -> 0.28261651 | BI58: =BI57/BI10 -> 0.41923689 | BJ58: =BJ57/BJ10 -> 0.53682408 | BK58: =BK57/BK10 -> 0.60522254 | BL58: =BL57/BL10 -> 0.32362705 | BM58: =BM57/BM10 -> 0.35383625 | BN58: =BN57/BN10 -> 0.19727108 | ... BS58: =BS57/BS10 -> 0.55123289
C59: Change vs Year Ago | BH59: =IF(OR((BG57<=0),(BH57<=0))," NM",((BH57/BG57)-1)) -> 2.7381578 | BI59: =IF(OR((BH57<=0),(BI57<=0))," NM",((BI57/BH57)-1)) -> 1.1240819 | BJ59: =IF(OR((BI57<=0),(BJ57<=0))," NM",((BJ57/BI57)-1)) -> 0.2659599 | BK59: =IF(OR((BJ57<=0),(BK57<=0))," NM",((BK57/BJ57)-1)) -> 0.18316345 | BL59: =IF(OR((BK57<=0),(BL57<=0))," NM",((BL57/BK57)-1)) -> -0.24878105 | BM59: =IF(OR((BL57<=0),(BM57<=0))," NM",((BM57/BL57)-1)) -> 0.56714323 | BN59: =IF(OR((BM57<=0),(BN57<=0))," NM",((BN57/BM57)-1)) -> -0.65298012 | BO59: =IF(OR((BN57<=0),(BO57<=0))," NM",((BO57/BN57)-1)) -> 2.1309552 | ... BS59: =IF(OR((BR57<=0),(BS57<=0))," NM",((BS57/BR57)-1)) -> 0.4483957
A61: SBC (attributable to parent) | P61: =+P56+P59 -> 0 | Q61: =Q56+Q59 -> 0 | AJ61: 12.122 | AK61: =24.59-AJ61 -> 12.468 | AL61: 11 | AN61: 76.255 | AO61: 100 | AP61: 338 | AQ61: 338 | AR61: =+AR62-AR57 -> 94.625 | AS61: 75 | AT61: 75 | AU61: 75 | AV61: =+AU61 -> 75 | AW61: =+AV61 -> 75 | AX61: 0 | AY61: 0 | AZ61: =+AY61 -> 0 | BA61: =+AZ61 -> 0 | BB61: 0 | BC61: 0 | BG61: 0.00012 | BH61: 0.00046 | BI61: 0.00087 | BJ61: 0.00088 | BK61: =BK56-BK59 -> -0.18316345 | BL61: 1e-06 | BM61: 131.491 | BN61: 105.994 | BO61: 50.924 | BP61: =SUM(AN61:AQ61) -> 852.255 | BQ61: =SUM(AR61:AU61) -> 319.625 | BR61: =SUM(AV61:AY61) -> 150 | BS61: =SUM(AZ61:BC61) -> 0
A62: Adj. reported Income (attributable to parent) | P62: =+P57+P60 -> 225.74043 | Q62: =Q57+Q60 -> 225.08677 | AP62: =+AP57+AP61 -> 811.21396 | AQ62: =+AQ57+AQ61 -> 863.326 | AR62: 942 | BG62: 757.032 | BH62: 757.032 | BI62: 847.87584 | BJ62: 1060.066 | BK62: =BK57-BK60 -> 1103.7235 | BL62: 1131.307 | BM62: =+BM61+BM57 -> 1430.869 | BN62: =+BN61+BN57 -> 556.904 | BO62: =+BO61+BO57 -> 1462.703 | BP62: =+BP61+BP57 -> 3009.865 | BQ62: =+BQ61+BQ57 -> 3911.1592 | BR62: =+BR61+BR57 -> 7573.5817 | BS62: =+BS61+BS57 -> 10752.284
BM63: =BM62/BM$10 -> 0.38964283 | BN63: =BN62/BN$10 -> 0.24364297 | BO63: =BO62/BO$10 -> 0.40196174 | BP63: =BP62/BP$10 -> 0.57006125 | BQ63: =BQ62/BQ$10 -> 0.52033075 | BR63: =BR62/BR$10 -> 0.54427135 | BS63: =BS62/BS$10 -> 0.55123289
A65: Reported EPS (Rmb) | P65: =P57/P77 -> 0.21556634 | Q65: =Q57/Q77 -> 0.21494215 | R65: =R57/R77 -> 0.25905415 | S65: =S57/S77 -> 0.16759201 | T65: =T57/T77 -> 0.23277134 | U65: =U57/U77 -> 0.29963901 | V65: =V57/V77 -> 0.24450374 | W65: =W57/W77 -> 0.19999317 | ... AQ65: =AQ57/AQ77 -> 0.46229487 | AR65: 0.73 | AS65: =AS57/AS77 -> 0.66253094 | AT65: =AT57/AT77 -> 0.7678577 | AU65: =AU57/AU77 -> 0.93366056 | AV65: =AV57/AV77 -> 1.1281642 | AW65: =AW57/AW77 -> 1.559863 | AX65: =AX57/AX77 -> 1.7486944 | AY65: =AY57/AY77 -> 1.9585753 | AZ65: =AZ57/AZ77 -> 2.0836212 | ... BC65: =BC57/BC77 -> 2.5502708 | BG65: =BG57/BG82 -> 0.12258927 | BH65: =BH57/BH82 -> 0.45825804 | BI65: =BI57/BI82 -> 0.86908715 | BJ65: =BJ57/BJ82 -> 0.87999992 | BK65: =BK57/BK82 -> 0.97260299 | BL65: =BL57/BL82 -> 0.73303735 | BM65: =BM57/BM77 -> 1.1465 | BN65: =BN57/BN77 -> 0.39638845 | BO65: =BO57/BO77 -> 1.2447981 | BP65: =BP57/BP77 -> 1.8952084 | BQ65: =BQ57/BQ77 -> 3.0940492 | BR65: =BR57/BR77 -> 6.3952968 | BS65: =BS57/BS77 -> 9.2629204
C66: Change vs Year Ago | T66: =T65/P65-1 -> 0.079812994 | U66: =U65/Q65-1 -> 0.39404493 | V66: =V65/R65-1 -> -0.056167441 | W66: =W65/S65-1 -> 0.19333354 | X66: =X65/T65-1 -> -0.49057506 | Y66: =Y65/U65-1 -> -0.48737198 | Z66: =Z65/V65-1 -> -0.26013519 | AA66: =AA65/W65-1 -> 0.39969885 | ... BC66: =BC65/AY65-1 -> 0.30210505 | BH66: =IF(OR((BG65<=0),(BH65<=0))," NM",((BH65/BG65)-1)) -> 2.7381578 | BI66: =IF(OR((BH65<=0),(BI65<=0))," NM",((BI65/BH65)-1)) -> 0.89650171 | BJ66: =IF(OR((BI65<=0),(BJ65<=0))," NM",((BJ65/BI65)-1)) -> 0.01255659 | BK66: =IF(OR((BJ65<=0),(BK65<=0))," NM",((BK65/BJ65)-1)) -> 0.10523077 | BL66: =IF(OR((BK65<=0),(BL65<=0))," NM",((BL65/BK65)-1)) -> -0.2463139 | BM66: =IF(OR((BL65<=0),(BM65<=0))," NM",((BM65/BL65)-1)) -> 0.56404031 | BN66: =IF(OR((BM65<=0),(BN65<=0))," NM",((BN65/BM65)-1)) -> -0.65426213 | BO66: =IF(OR((BN65<=0),(BO65<=0))," NM",((BO65/BN65)-1)) -> 2.1403489 | ... BS66: =IF(OR((BR65<=0),(BS65<=0))," NM",((BS65/BR65)-1)) -> 0.4483957
A68: A-share Reported EPS (Rmb) | P68: =+P65 -> 0.21556634 | T68: =+T65 -> 0.23277134 | U68: =+U65 -> 0.29963901 | V68: =+V65 -> 0.24450374 | W68: =+W65 -> 0.19999317 | X68: =+X65 -> 0.11857952 | Y68: =+Y65 -> 0.15360335 | Z68: =+Z65 -> 0.18089971 | AA68: =+AA65 -> 0.2799302 | ... AQ68: =+AQ65 -> 0.46229487 | AR68: 0.73 | AS68: =+AS65 -> 0.66253094 | AT68: =+AT65 -> 0.7678577 | AU68: =+AU65 -> 0.93366056 | AV68: =+AV65 -> 1.1281642 | AW68: =+AW65 -> 1.559863 | AX68: =+AX65 -> 1.7486944 | AY68: =+AY65 -> 1.9585753 | AZ68: =+AZ65 -> 2.0836212 | ... BC68: =+BC65 -> 2.5502708 | BG68: =BG60/BG85 -> #DIV/0! | BH68: =BH60/BH85 -> #DIV/0! | BI68: =BI60/BI85 -> #DIV/0! | BJ68: =BJ60/BJ85 -> #DIV/0! | BK68: =BK60/BK85 -> #DIV/0! | BL68: =BL60/BL85 -> #DIV/0! | BM68: =+BM65 -> 1.1465 | BN68: =+BN65 -> 0.39638845 | BO68: =+BO65 -> 1.2447981 | BP68: =+BP65 -> 1.8952084 | BQ68: =+BQ65 -> 3.0940492 | BR68: =+BR65 -> 6.3952968 | BS68: =+BS65 -> 9.2629204
C69: Change vs Year Ago | T69: =T68/P68-1 -> 0.079812994 | U69: =U68/Q68-1 -> #DIV/0! | V69: =V68/R68-1 -> #DIV/0! | W69: =W68/S68-1 -> #DIV/0! | X69: =X68/T68-1 -> -0.49057506 | Y69: =Y68/U68-1 -> -0.48737198 | Z69: =Z68/V68-1 -> -0.26013519 | AA69: =AA68/W68-1 -> 0.39969885 | ... BC69: =BC68/AY68-1 -> 0.30210505 | BH69: =IF(OR((BG68<=0),(BH68<=0))," NM",((BH68/BG68)-1)) -> #DIV/0! | BI69: =IF(OR((BH68<=0),(BI68<=0))," NM",((BI68/BH68)-1)) -> #DIV/0! | BJ69: =IF(OR((BI68<=0),(BJ68<=0))," NM",((BJ68/BI68)-1)) -> #DIV/0! | BK69: =IF(OR((BJ68<=0),(BK68<=0))," NM",((BK68/BJ68)-1)) -> #DIV/0! | BL69: =IF(OR((BK68<=0),(BL68<=0))," NM",((BL68/BK68)-1)) -> #DIV/0! | BM69: =IF(OR((BL68<=0),(BM68<=0))," NM",((BM68/BL68)-1)) -> #DIV/0! | BN69: =IF(OR((BM68<=0),(BN68<=0))," NM",((BN68/BM68)-1)) -> -0.65426213 | BO69: =IF(OR((BN68<=0),(BO68<=0))," NM",((BO68/BN68)-1)) -> 2.1403489 | ... BS69: =IF(OR((BR68<=0),(BS68<=0))," NM",((BS68/BR68)-1)) -> 0.4483957
A71: H-share Reported EPS (Rmb) | P71: =+P65 -> 0.21556634 | Q71: =+Q65 -> 0.21494215 | R71: =+R65 -> 0.25905415 | S71: =+S65 -> 0.16759201 | T71: =+T65 -> 0.23277134 | U71: =+U65 -> 0.29963901 | V71: =+V65 -> 0.24450374 | W71: =+W65 -> 0.19999317 | ... AQ71: =+AQ65 -> 0.46229487 | AR71: 0.73 | AS71: =+AS65 -> 0.66253094 | AT71: =+AT65 -> 0.7678577 | AU71: =+AU65 -> 0.93366056 | AV71: =+AV65 -> 1.1281642 | AW71: =+AW65 -> 1.559863 | AX71: =+AX65 -> 1.7486944 | AY71: =+AY65 -> 1.9585753 | AZ71: =+AZ65 -> 2.0836212 | ... BC71: =+BC65 -> 2.5502708 | BG71: =BG63/BG88 -> #DIV/0! | BH71: =BH63/BH88 -> #DIV/0! | BI71: =BI63/BI88 -> #DIV/0! | BJ71: =BJ63/BJ88 -> #DIV/0! | BK71: =BK63/BK88 -> #DIV/0! | BL71: =BL63/BL88 -> #DIV/0! | BM71: =+BM65 -> 1.1465 | BN71: =+BN65 -> 0.39638845 | BO71: =+BO65 -> 1.2447981 | BP71: =+BP65 -> 1.8952084 | BQ71: =+BQ65 -> 3.0940492 | BR71: =+BR65 -> 6.3952968 | BS71: =+BS65 -> 9.2629204
C72: Change vs Year Ago | T72: =T71/P71-1 -> 0.079812994 | U72: =U71/Q71-1 -> 0.39404493 | V72: =V71/R71-1 -> -0.056167441 | W72: =W71/S71-1 -> 0.19333354 | X72: =X71/T71-1 -> -0.49057506 | Y72: =Y71/U71-1 -> -0.48737198 | Z72: =Z71/V71-1 -> -0.26013519 | AA72: =AA71/W71-1 -> 0.39969885 | ... BC72: =BC71/AY71-1 -> 0.30210505 | BH72: =IF(OR((BG71<=0),(BH71<=0))," NM",((BH71/BG71)-1)) -> #DIV/0! | BI72: =IF(OR((BH71<=0),(BI71<=0))," NM",((BI71/BH71)-1)) -> #DIV/0! | BJ72: =IF(OR((BI71<=0),(BJ71<=0))," NM",((BJ71/BI71)-1)) -> #DIV/0! | BK72: =IF(OR((BJ71<=0),(BK71<=0))," NM",((BK71/BJ71)-1)) -> #DIV/0! | BL72: =IF(OR((BK71<=0),(BL71<=0))," NM",((BL71/BK71)-1)) -> #DIV/0! | BM72: =IF(OR((BL71<=0),(BM71<=0))," NM",((BM71/BL71)-1)) -> #DIV/0! | BN72: =IF(OR((BM71<=0),(BN71<=0))," NM",((BN71/BM71)-1)) -> -0.65426213 | BO72: =IF(OR((BN71<=0),(BO71<=0))," NM",((BO71/BN71)-1)) -> 2.1403489 | ... BS72: =IF(OR((BR71<=0),(BS71<=0))," NM",((BS71/BR71)-1)) -> 0.4483957
A76: Basic shares (mn units) | P76: =+P81 -> 1047.197 | Q76: =+Q81 -> 1047.197 | R76: =+R81 -> 1047.197 | S76: =+S81 -> 1060.066 | T76: =+T81 -> 1129.814 | U76: =+U81 -> 1129.814 | V76: =+V81 -> 1129.814 | W76: =+W81 -> 1129.814 | ... AQ76: =+AQ81 -> 1136.344 | AR76: =+AR77 -> 1160.7877 | AS76: =+AR76 -> 1160.7877 | AT76: =+AS76 -> 1160.7877 | AU76: =+AT76 -> 1160.7877 | AV76: =+AU76 -> 1160.7877 | AW76: =+AV76 -> 1160.7877 | AX76: =+AW76 -> 1160.7877 | AY76: =+AX76 -> 1160.7877 | AZ76: =+AY76 -> 1160.7877 | ... BC76: =+BB76 -> 1160.7877 | BG76: 0 | BH76: 0 | BI76: 0 | BJ76: 0 | BK76: 1129.814 | BL76: =AVERAGE(X76:AA76) -> 1131.0992 | BM76: =+BM81+BM89 -> 1133.3432 | BN76: =+BN81+BN89 -> 1137.5457 | BO76: =+BO81+BO89 -> 1134.143 | BP76: =+BP81+BP89 -> 1138.4552 | BQ76: =+BQ81+BQ89 -> 1160.7877 | BR76: =+BR81+BR89 -> 1160.7877 | BS76: =+BS81+BS89 -> 1160.7877
A77: Diluted | P77: =+P82 -> 1047.197 | Q77: =+Q82 -> 1047.197 | R77: =+R82 -> 1129.814 | S77: =+S82 -> 1129.814 | T77: =+T82 -> 1129.814 | U77: =+U82 -> 1129.814 | V77: =+V82 -> 1129.814 | W77: =+W82 -> 1129.814 | ... AQ77: =+AQ82 -> 1136.344 | AR77: =+AR57/AR65 -> 1160.7877 | AS77: =+AR77 -> 1160.7877 | AT77: =+AS77 -> 1160.7877 | AU77: =+AT77 -> 1160.7877 | AV77: =+AU77 -> 1160.7877 | AW77: =+AV77 -> 1160.7877 | AX77: =+AW77 -> 1160.7877 | AY77: =+AX77 -> 1160.7877 | AZ77: =+AY77 -> 1160.7877 | ... BC77: =+BB77 -> 1160.7877 | BG77: =+BG76 -> 0 | BH77: =+BH76 -> 0 | BI77: =+BI76 -> 0 | BJ77: =+BJ76 -> 0 | BK77: =1129.814+5 -> 1134.814 | BL77: =AVERAGE(X77:AA77) -> 1131.0992 | BM77: =+BM82+BM90 -> 1133.3432 | BN77: =+BN82+BN90 -> 1137.5457 | BO77: =+BO82+BO90 -> 1134.143 | BP77: =+BP82+BP90 -> 1138.4552 | BQ77: =+BQ82+BQ90 -> 1160.7877 | BR77: =+BR82+BR90 -> 1160.7877 | BS77: =+BS82+BS90 -> 1160.7877
A78: Period End share | P78: =+P83 -> 1047.197 | Q78: =+Q83 -> 1047.197 | R78: =+R83 -> 1047.197 | S78: =+S83 -> 1060.066 | T78: =+T83 -> 1129.814 | U78: =+U83 -> 1129.814 | V78: =+V83 -> 1129.814 | W78: =+W83 -> 1129.814 | ... AQ78: =+AQ83 -> 1136.344 | AR78: =+AR77 -> 1160.7877 | AS78: =+AR78 -> 1160.7877 | AT78: =+AS78 -> 1160.7877 | AU78: =+AT78 -> 1160.7877 | AV78: =+AU78 -> 1160.7877 | AW78: =+AV78 -> 1160.7877 | AX78: =+AW78 -> 1160.7877 | AY78: =+AX78 -> 1160.7877 | AZ78: =+AY78 -> 1160.7877 | ... BC78: =+BB78 -> 1160.7877 | BG78: =+'Balance Sheet'!AO56 -> 0 | BH78: =+'Balance Sheet'!AP56 -> 0 | BI78: =+'Balance Sheet'!AQ56 -> 0 | BJ78: =+'Balance Sheet'!AR56 -> 0 | BK78: =+'Balance Sheet'!AS56 -> 0 | BL78: =+'Balance Sheet'!AT56 -> 0 | BM78: =+BM83+BM91 -> 1134.068 | BN78: =+BN83+BN91 -> 1138.74 | BO78: =+BO83+BO91 -> 1144.789 | BP78: =+BP83+BP91 -> 1136.344 | BQ78: =+BQ83+BQ91 -> 1160.7877 | BR78: =+BR83+BR91 -> 1160.7877 | BS78: =+BS83+BS91 -> 1160.7877
A79: Statutory Tax | P79: 0.25 | Q79: 0.25 | R79: 0.25 | S79: 0.25 | T79: 0.25 | U79: 0.25 | V79: 0.25 | W79: 0.25 | X79: 0.25 | Y79: 0.25 | Z79: 0.25 | AA79: 0.25 | AB79: 0.25 | AC79: 0.25 | AD79: 0.25 | AE79: 0.25 | AF79: 0.25 | AG79: 0.25 | AH79: 0.25 | AI79: 0.25 | AJ79: 0.25 | AK79: 0.25 | AL79: 0.25 | AM79: 0.25 | AN79: 0.25 | AO79: 0.25 | AP79: 0.25 | AQ79: 0.25 | AR79: 0.25 | AS79: 0.25 | AT79: 0.25 | AU79: 0.25 | AV79: 0.25 | AW79: 0.25 | AX79: 0.25 | AY79: 0.25 | AZ79: 0.25 | BA79: 0.25 | BB79: 0.25 | BC79: 0.25 | BG79: 0.25 | BH79: 0.25 | BI79: 0.25 | BJ79: 0.25 | BK79: 0.25 | BL79: 0.25 | BM79: 0.25 | BN79: 0.25 | BO79: 0.25 | BP79: 0.25 | BQ79: 0.25 | BR79: 0.25 | BS79: 0.25
A81: A-share Basic shares (mn units) | P81: =+Q81 -> 1047.197 | Q81: =+R81 -> 1047.197 | R81: 1047.197 | S81: 1060.066 | T81: 1129.814 | U81: 1129.814 | V81: 1129.814 | W81: 1129.814 | X81: 1131.03 | Y81: 1131.03 | Z81: 1131.03 | AA81: 1131.307 | AB81: 1132.824 | AC81: 1132.824 | AD81: 1133.657 | AE81: 1134.068 | AF81: 1136.078 | AG81: 1137.357 | AH81: 1138.008 | AI81: 1138.74 | AJ81: 1141.461 | AK81: 1141.461 | AL81: 1124.227 | AM81: 1129.423 | AN81: 1144.789 | AO81: 1136.344 | AP81: =AO81 -> 1136.344 | AQ81: =AP81 -> 1136.344 | AR81: =+AQ81 -> 1136.344 | AS81: =+AR81 -> 1136.344 | AT81: =+AS81 -> 1136.344 | AU81: =+AT81 -> 1136.344 | AV81: =+AU81 -> 1136.344 | AW81: =+AV81 -> 1136.344 | AX81: =+AW81 -> 1136.344 | AY81: =+AX81 -> 1136.344 | ... BC81: =+BB81 -> 1136.344 | BG81: 757.032 | BH81: 757.032 | BI81: 847.87584 | BJ81: 1060.066 | BK81: 1129.814 | BL81: =AVERAGE(X81:AA81) -> 1131.0992 | BM81: =AVERAGE(AB81:AE81) -> 1133.3432 | BN81: =AVERAGE(AF81:AI81) -> 1137.5457 | BO81: =AVERAGE(AJ81:AM81) -> 1134.143 | BP81: =AVERAGE(AN81:AQ81) -> 1138.4552 | BQ81: =AVERAGE(AR81:AU81) -> 1136.344 | BR81: =AVERAGE(AV81:AY81) -> 1136.344 | BS81: =AVERAGE(AZ81:BC81) -> 1136.344
A82: A-share Diluted | P82: =P81 -> 1047.197 | Q82: =Q81 -> 1047.197 | R82: 1129.814 | S82: 1129.814 | T82: 1129.814 | U82: 1129.814 | V82: 1129.814 | W82: 1129.814 | X82: 1131.03 | Y82: 1131.03 | Z82: 1131.03 | AA82: =AA81 -> 1131.307 | AB82: =AB81 -> 1132.824 | AC82: =AC81 -> 1132.824 | AD82: =AD81 -> 1133.657 | AE82: =AE81 -> 1134.068 | AF82: =AF81 -> 1136.078 | AG82: =AG81 -> 1137.357 | AH82: =AH81 -> 1138.008 | ... AQ82: =AQ81 -> 1136.344 | AR82: =+AQ82 -> 1136.344 | AS82: =+AR82 -> 1136.344 | AT82: =+AS82 -> 1136.344 | AU82: =+AT82 -> 1136.344 | AV82: =+AU82 -> 1136.344 | AW82: =+AV82 -> 1136.344 | AX82: =+AW82 -> 1136.344 | AY82: =+AX82 -> 1136.344 | ... BC82: =+BB82 -> 1136.344 | BG82: =+BG81 -> 757.032 | BH82: =+BH81 -> 757.032 | BI82: =+BI81 -> 847.87584 | BJ82: =+BJ81 -> 1060.066 | BK82: =1129.814+5 -> 1134.814 | BL82: =AVERAGE(X82:AA82) -> 1131.0992 | BM82: =AVERAGE(AB82:AE82) -> 1133.3432 | BN82: =AVERAGE(AF82:AI82) -> 1137.5457 | BO82: =AVERAGE(AJ82:AM82) -> 1134.143 | BP82: =AVERAGE(AN82:AQ82) -> 1138.4552 | BQ82: =AVERAGE(AR82:AU82) -> 1136.344 | BR82: =AVERAGE(AV82:AY82) -> 1136.344 | BS82: =AVERAGE(AZ82:BC82) -> 1136.344
A83: A-share Period End share | P83: =P81 -> 1047.197 | Q83: =Q81 -> 1047.197 | R83: =R81 -> 1047.197 | S83: =S81 -> 1060.066 | T83: =T81 -> 1129.814 | U83: =U81 -> 1129.814 | V83: =V81 -> 1129.814 | W83: =W81 -> 1129.814 | ... AQ83: =AQ81 -> 1136.344 | AR83: =+AQ83 -> 1136.344 | AS83: =+AR83 -> 1136.344 | AT83: =+AS83 -> 1136.344 | AU83: =+AT83 -> 1136.344 | AV83: =+AU83 -> 1136.344 | AW83: =+AV83 -> 1136.344 | AX83: =+AW83 -> 1136.344 | AY83: =+AX83 -> 1136.344 | ... BC83: =+BB83 -> 1136.344 | BG83: =+'Balance Sheet'!AO35 -> 757.032 | BH83: =+'Balance Sheet'!AP35 -> 757.032 | BI83: =+'Balance Sheet'!AQ35 -> 1016.833 | BJ83: =+'Balance Sheet'!AR35 -> 1129.814 | BK83: =+'Balance Sheet'!AS35 -> 1129.814 | BL83: =+'Balance Sheet'!AT35 -> 1131.307 | BM83: =+'Balance Sheet'!AU35 -> 1134.068 | BN83: =+'Balance Sheet'!AV35 -> 1138.74 | BO83: =+'Balance Sheet'!AW35 -> 1144.789 | BP83: =+AQ83 -> 1136.344 | BQ83: =+AU83 -> 1136.344 | BR83: =+AY83 -> 1136.344 | BS83: =+BC83 -> 1136.344
A86: A-share ownership ratio | AR86: 1 | AS86: 1 | AT86: 1 | AU86: 1 | AV86: 1 | AW86: 1 | AX86: 1 | AY86: 1 | AZ86: 1 | BA86: 1 | BB86: 1 | BC86: 1 | BM86: 1 | BN86: 1 | BO86: 1 | BP86: 1 | BQ86: 1 | BR86: 1 | BS86: 1
A89: H-share Basic shares (mn units) | AR89: =+AR76-AR81 -> 24.443671 | AS89: =+AS76-AS81 -> 24.443671 | AT89: =+AT76-AT81 -> 24.443671 | AU89: =+AU76-AU81 -> 24.443671 | AV89: =+AV76-AV81 -> 24.443671 | AW89: =+AW76-AW81 -> 24.443671 | AX89: =+AX76-AX81 -> 24.443671 | AY89: =+AY76-AY81 -> 24.443671 | ... BC89: =+BC76-BC81 -> 24.443671 | BG89: 0 | BH89: 0 | BI89: 0 | BJ89: 0 | BK89: 1129.814 | BL89: =AVERAGE(X89:AA89) -> #DIV/0! | BQ89: =AVERAGE(AR89:AU89) -> 24.443671 | BR89: =AVERAGE(AV89:AY89) -> 24.443671 | BS89: =AVERAGE(AZ89:BC89) -> 24.443671
A90: H-share Diluted | AR90: =+AR77-AR82 -> 24.443671 | AS90: =+AS77-AS82 -> 24.443671 | AT90: =+AT77-AT82 -> 24.443671 | AU90: =+AU77-AU82 -> 24.443671 | AV90: =+AV77-AV82 -> 24.443671 | AW90: =+AW77-AW82 -> 24.443671 | AX90: =+AX77-AX82 -> 24.443671 | AY90: =+AY77-AY82 -> 24.443671 | ... BC90: =+BC77-BC82 -> 24.443671 | BG90: =+BG89 -> 0 | BH90: =+BH89 -> 0 | BI90: =+BI89 -> 0 | BJ90: =+BJ89 -> 0 | BK90: =1129.814+5 -> 1134.814 | BL90: =AVERAGE(X90:AA90) -> #DIV/0! | BQ90: =AVERAGE(AR90:AU90) -> 24.443671 | BR90: =AVERAGE(AV90:AY90) -> 24.443671 | BS90: =AVERAGE(AZ90:BC90) -> 24.443671
A91: H-share Period End share | AR91: =+AR78-AR83 -> 24.443671 | AS91: =+AS78-AS83 -> 24.443671 | AT91: =+AT78-AT83 -> 24.443671 | AU91: =+AU78-AU83 -> 24.443671 | AV91: =+AV78-AV83 -> 24.443671 | AW91: =+AW78-AW83 -> 24.443671 | AX91: =+AX78-AX83 -> 24.443671 | AY91: =+AY78-AY83 -> 24.443671 | ... BC91: =+BC78-BC83 -> 24.443671 | BG91: =+'Balance Sheet'!AO49 -> 1.1427205 | BH91: =+'Balance Sheet'!AP49 -> 1.5405148 | BI91: =+'Balance Sheet'!AQ49 -> 4.2338487 | BJ91: =+'Balance Sheet'!AR49 -> 6.8991006 | BK91: =+'Balance Sheet'!AS49 -> 7.102489 | BL91: =+'Balance Sheet'!AT49 -> 7.3080183 | BQ91: =+AU91 -> 24.443671 | BR91: =+AY91 -> 24.443671 | BS91: =+BC91 -> 24.443671
A94: H-share ownership ratio | AR94: 1 | AS94: 1 | AT94: 1 | AU94: 1 | AV94: 1 | AW94: 1 | AX94: 1 | AY94: 1 | AZ94: 1 | BA94: 1 | BB94: 1 | BC94: 1 | BM94: 1 | BN94: 1 | BO94: 1 | BP94: 1 | BQ94: 1 | BR94: 1 | BS94: 1
A99: Unrecorded Goodwill | P99: 0 | Q99: 0 | R99: 0 | S99: 0 | T99: 0 | U99: 0 | V99: 0 | W99: 0 | X99: 0 | Y99: 0 | Z99: 0 | AA99: 0 | AB99: 0 | AC99: 0 | AD99: 0 | AE99: 0 | AF99: 0 | AG99: 0 | AH99: 0 | AI99: 0 | AJ99: 0 | AK99: 0 | AL99: 0 | AM99: 0 | AN99: 0 | AO99: 0 | AP99: 0 | AQ99: 0 | AR99: 0 | AS99: 0 | AT99: 0 | AU99: 0 | AV99: 0 | AW99: 0 | AX99: 0 | AY99: 0 | AZ99: 0 | BA99: 0 | BB99: 0 | BC99: 0 | BG99: 0 | BH99: 0 | BI99: 0 | BJ99: 0 | BK99: 0 | BL99: 0 | BM99: 0 | BN99: 0 | BO99: 0 | BP99: 0 | BQ99: 0 | BR99: 0 | BS99: 0
A100: Cash bonus to Directors/employees
A101: Employee Stock Bonus
C106: Exchange rate | P106: 7 | Q106: 7 | R106: 7 | S106: =+R106 -> 7 | T106: =+S106 -> 7 | U106: =+T106 -> 7 | V106: 6.8 | W106: 6.6 | X106: 6.5 | Y106: =+X106 -> 6.5 | Z106: =+Y106 -> 6.5 | AA106: =+Z106 -> 6.5 | AB106: =+AA106+0.1 -> 6.6 | AC106: =+AB106 -> 6.6 | AD106: =+AC106 -> 6.6 | AE106: =+AD106 -> 6.6 | AF106: =+AE106 -> 6.6 | AG106: =+AF106 -> 6.6 | AH106: =+AG106 -> 6.6 | AI106: =+AH106 -> 6.6 | AJ106: =+AI106 -> 6.6 | AK106: 7 | AL106: =+AK106 -> 7 | AM106: =+AL106 -> 7 | AN106: 7 | AO106: 7 | AP106: 7 | AQ106: 7 | AR106: 6.9 | AS106: 6.9 | AT106: 6.9 | AU106: 6.9 | AV106: 6.9 | AW106: 6.9 | AX106: 6.9 | AY106: 6.9 | AZ106: 6.9 | BA106: 6.9 | BB106: 6.9 | BC106: 6.9 | BG106: 6.805 | BH106: 6.91 | BI106: 6.79 | BJ106: =AVERAGE(P106:S106) -> 7 | BK106: =AVERAGE(T106:W106) -> 6.85 | BL106: =AVERAGE(X106:AA106) -> 6.5 | BM106: =AVERAGE(AB106:AE106) -> 6.6 | BN106: =AVERAGE(AF106:AI106) -> 6.6 | BO106: =AVERAGE(AJ106:AM106) -> 6.9 | BP106: =AVERAGE(AN106:AQ106) -> 7 | BQ106: =AVERAGE(AR106:AU106) -> 6.9 | BR106: =AVERAGE(AV106:AY106) -> 6.9 | BS106: =AVERAGE(AZ106:BC106) -> 6.9
A108: Sales
A109: Revenue (Rmb mn) | BP109: =+BP110/(347.8*7) -> 1.7209328
B110: Memory Interconnect | R110: =+R111+R114+R118 -> 501.84278 | S110: =+S111+S114+S118 -> 347.424 | T110: =+T111+T114+T118 -> 490.39055 | U110: =+U111+U114+U118 -> 587.81361 | V110: =+V111+V114+V118 -> 370.98559 | W110: =+W111+W114+W118 -> 346.31832 | X110: =+X111+X114+X118 -> 250.81723 | Y110: =+Y111+Y114+Y118 -> 309.41519 | ... AH110: =+AH111+AH114+AH118 -> 535.358 | AI110: =+AI111+AI114+AI118+AI121 -> 628.06092 | AJ110: =+AJ111+AJ114+AJ118+AJ121 -> 879.85738 | AK110: =+AK111+AK114+AK118+AK121 -> 1002.2155 | AL110: =+AL111+AL114+AL118+AL121 -> 954.63976 | AM110: =+AM111+AM114+AM118+AM121 -> 865.29897 | AN110: =+AN111+AN114+AN118+AN121 -> 1007.1851 | AO110: =+AO111+AO114+AO118+AO121 -> 1025.9108 | AP110: =+AP111+AP114+AP118+AP121 -> 1063.7197 | ... BC110: =+BC111+BC114+BC118+BC121 -> 2878.1716 | BG110: =+BG111+BG114+BG118 -> 558.3267 | BH110: =+BH111+BH114+BH118 -> 934.668 | BI110: =+BI111+BI114+BI118 -> 1748.6526 | BJ110: =+BJ111+BJ114+BJ118 -> 1721.4585 | BK110: =+BK111+BK114+BK118 -> 1795.5081 | BL110: =+BL111+BL114+BL118 -> 1727.3524 | BM110: =+BM111+BM114+BM118+BM121 -> 2684.4566 | BN110: =+BN111+BN114+BN118+BN121 -> 1985.2474 | BO110: =+BO111+BO114+BO118+BO121 -> 3702.0116 | BP110: =+BP111+BP114+BP118+BP121 -> 4189.7831 | BQ110: =+BQ111+BQ114+BQ118+BQ121 -> 5468.4289 | BR110: =+BR111+BR114+BR118+BR121 -> 7773.4938 | BS110: =+BS111+BS114+BS118+BS121 -> 10467.94 | BT110: =+(BS110/BP110)^(1/3)-1 -> 0.35692725
C111: Memory interface | R111: =+SUM(R112:R113) -> 501.84278 | S111: =+SUM(S112:S113) -> 347.424 | T111: =+SUM(T112:T113) -> 490.39055 | U111: =+SUM(U112:U113) -> 587.81361 | V111: =+SUM(V112:V113) -> 370.98559 | W111: =+SUM(W112:W113) -> 346.31832 | X111: =+SUM(X112:X113) -> 250.81723 | Y111: =+SUM(Y112:Y113) -> 309.41519 | ... BC111: =+SUM(BC112:BC113) -> 1779.1729 | BG111: 558.3267 | BH111: 934.668 | BI111: 1748.6526 | BJ111: 1721.4585 | BK111: 1795.5081 | BL111: =+SUM(BL112:BL113) -> 1726.1524 | BM111: =+SUM(BM112:BM113) -> 2603.0066 | BN111: =+SUM(BN112:BN113) -> 1783.2211 | BO111: =+SUM(BO112:BO113) -> 3264.2048 | BP111: =+SUM(BP112:BP113) -> 3408.3947 | BQ111: =+SUM(BQ112:BQ113) -> 4313.7083 | BR111: =+SUM(BR112:BR113) -> 5432.9236 | BS111: =+SUM(BS112:BS113) -> 6618.8598 | BT111: =+(BS111/BP111)^(1/3)-1 -> 0.2476069
C112: RCD | R112: =R175*R221 -> 378.87545 | S112: =S175*S221 -> 259.424 | T112: =T175*T221 -> 375.8549 | U112: =U175*U221 -> 446.64372 | V112: =V175*V221 -> 282.89558 | W112: =W175*W221 -> 262.5271 | X112: =X175*X221 -> 193.58292 | Y112: =Y175*Y221 -> 252.86768 | ... AE112: =AE175*AE221 -> 591.54771 | AF112: 285.68892 | AG112: 344.28372 | AH112: 391.50223 | AI112: 439.2655 | AJ112: =AJ175*AJ221 -> 687.80758 | AK112: =AK175*AK221 -> 751.18217 | AL112: =AL175*AL221 -> 687.72981 | AM112: =AM175*AM221 -> 701.53599 | AN112: =AN175*AN221 -> 715.61932 | AO112: =AO175*AO221 -> 729.98538 | AP112: =AP175*AP221 -> 744.63984 | AQ112: =AQ175*AQ221 -> 759.58848 | ... BC112: =BC175*BC221 -> 1539.8049 | BG112: 457.18905 | BH112: 748.99931 | BI112: 1330.5794 | BJ112: 1308.7045 | BK112: 1367.9213 | BL112: =SUM(X112:AA112) -> 1410.1358 | BM112: =SUM(AB112:AE112) -> 2136.5116 | BN112: =SUM(AF112:AI112) -> 1460.7404 | BO112: =SUM(AJ112:AM112) -> 2828.2555 | BP112: =SUM(AN112:AQ112) -> 2949.833 | BQ112: =SUM(AR112:AU112) -> 3733.3468 | BR112: =SUM(AV112:AY112) -> 4701.9841 | BS112: =SUM(AZ112:BC112) -> 5728.3657
C113: DB | R113: =R176*R222 -> 122.96733 | S113: =S176*S222 -> 88 | T113: =T176*T222 -> 114.53565 | U113: =U176*U222 -> 141.16989 | V113: =V176*V222 -> 88.09001 | W113: =W176*W222 -> 83.791218 | X113: =X176*X222 -> 57.234318 | Y113: =Y176*Y222 -> 56.547507 | ... AE113: =AE176*AE222 -> 131.66406 | AF113: 70.428483 | AG113: 83.422538 | AH113: 78.834298 | AI113: 89.795419 | AJ113: =AJ176*AJ222 -> 102.9498 | AK113: =AK176*AK222 -> 117.03334 | AL113: =AL176*AL222 -> 106.90995 | AM113: =AM176*AM222 -> 109.05617 | AN113: =AN176*AN222 -> 111.24547 | AO113: =AO176*AO222 -> 113.47873 | AP113: =AP176*AP222 -> 115.75681 | AQ113: =AQ176*AQ222 -> 118.08063 | ... BC113: =BC176*BC222 -> 239.36795 | BG113: 101.13765 | BH113: 185.66869 | BI113: 418.07316 | BJ113: 412.75396 | BK113: 427.58677 | BL113: =SUM(X113:AA113) -> 316.01659 | BM113: =SUM(AB113:AE113) -> 466.49498 | BN113: =SUM(AF113:AI113) -> 322.48074 | BO113: =SUM(AJ113:AM113) -> 435.94926 | BP113: =SUM(AN113:AQ113) -> 458.56164 | BQ113: =SUM(AR113:AU113) -> 580.36153 | BR113: =SUM(AV113:AY113) -> 730.93951 | BS113: =SUM(AZ113:BC113) -> 890.49405
C114: Supporting chips | AA114: =+SUM(AA115:AA117) -> 1.2 | AB114: =+SUM(AB115:AB117) -> 11.75 | AC114: =+SUM(AC115:AC117) -> 15.75 | AD114: =+SUM(AD115:AD117) -> 21.85 | AE114: =+SUM(AE115:AE117) -> 32.1 | AF114: =+SUM(AF115:AF117) -> 18.871406 | AG114: =+SUM(AG115:AG117) -> 19.133467 | AH114: =+SUM(AH115:AH117) -> 65.02147 | ... BC114: =+SUM(BC115:BC117) -> 60.824262 | BG114: =+SUM(BG115:BG117) -> 0 | BH114: =+SUM(BH115:BH117) -> 0 | BI114: =+SUM(BI115:BI117) -> 0 | BJ114: =+SUM(BJ115:BJ117) -> 0 | BK114: =+SUM(BK115:BK117) -> 0 | BL114: =+SUM(BL115:BL117) -> 1.2 | BM114: =+SUM(BM115:BM117) -> 81.45 | BN114: =+SUM(BN115:BN117) -> 162.02634 | ... BS114: =+SUM(BS115:BS117) -> 238.70253 | BT114: =+(BS114/BP114)^(1/3)-1 -> 0.062494877
C115: PMIC | AA115: 0.4 | AB115: =AB178*AB224 -> 6.5 | AC115: =AC178*AC224 -> 9.1 | AD115: =AD178*AD224 -> 7.8 | AE115: =AE178*AE224 -> 10.4 | AF115: 6.239376 | AG115: 6.3017698 | AH115: 32.884735 | AI115: 30 | AJ115: 40 | AK115: 50 | AL115: 80 | AM115: =AM178*AM224 -> 15.917253 | AN115: =AN178*AN224 -> 16.121949 | AO115: =AO178*AO224 -> 16.329277 | AP115: =AP178*AP224 -> 16.539271 | AQ115: =AQ178*AQ224 -> 17.408906 | AR115: =AR178*AR224 -> 17.632785 | AS115: =AS178*AS224 -> 17.859543 | AT115: =AT178*AT224 -> 18.089216 | ... BC115: =BC178*BC224 -> 20.293854 | BG115: =SUM(D115:G115) -> 0 | BH115: =SUM(H115:K115) -> 0 | BI115: =SUM(L115:O115) -> 0 | BJ115: =SUM(P115:S115) -> 0 | BK115: =SUM(T115:W115) -> 0 | BL115: =SUM(X115:AA115) -> 0.4 | BM115: =SUM(AB115:AE115) -> 33.8 | BN115: =SUM(AF115:AI115) -> 75.425881 | BO115: =SUM(AJ115:AM115) -> 185.91725 | BP115: =SUM(AN115:AQ115) -> 66.399404 | BQ115: =SUM(AR115:AU115) -> 71.903387 | BR115: =SUM(AV115:AY115) -> 75.674059 | BS115: =SUM(AZ115:BC115) -> 79.642468
C116: SPD | AA116: 0.4 | AB116: =AB179*AB225 -> 3.25 | AC116: =AC179*AC225 -> 3.9 | AD116: =AD179*AD225 -> 11.05 | AE116: =AE179*AE225 -> 18.2 | AF116: 10.594606 | AG116: 10.753525 | AH116: 23.790893 | AI116: 20 | AJ116: 25.5 | AK116: 39 | AL116: 40 | AM116: =AM179*AM225 -> 20.2043 | AN116: =AN179*AN225 -> 20.464127 | AO116: =AO179*AO225 -> 20.727296 | AP116: =AP179*AP225 -> 20.993849 | AQ116: =AQ179*AQ225 -> 22.097705 | AR116: =AR179*AR225 -> 22.381882 | AS116: =AS179*AS225 -> 22.669713 | AT116: =AT179*AT225 -> 22.961245 | ... BC116: =BC179*BC225 -> 25.759665 | BG116: =SUM(D116:G116) -> 0 | BH116: =SUM(H116:K116) -> 0 | BI116: =SUM(L116:O116) -> 0 | BJ116: =SUM(P116:S116) -> 0 | BK116: =SUM(T116:W116) -> 0 | BL116: =SUM(X116:AA116) -> 0.4 | BM116: =SUM(AB116:AE116) -> 36.4 | BN116: =SUM(AF116:AI116) -> 65.139023 | BO116: =SUM(AJ116:AM116) -> 124.7043 | BP116: =SUM(AN116:AQ116) -> 84.282976 | BQ116: =SUM(AR116:AU116) -> 91.269366 | BR116: =SUM(AV116:AY116) -> 96.055606 | BS116: =SUM(AZ116:BC116) -> 101.09284
C117: TS | AA117: 0.4 | AB117: 2 | AC117: =AC180*AC226 -> 2.75 | AD117: =AD180*AD226 -> 3 | AE117: =AE180*AE226 -> 3.5 | AF117: 2.0374241 | AG117: 2.0781726 | AH117: 8.3458423 | AI117: 9 | AJ117: =AJ180*AJ226 -> 13.6 | AK117: 30 | AL117: 20 | AM117: =AM180*AM226 -> 11.585263 | AN117: =AN180*AN226 -> 11.73425 | AO117: =AO180*AO226 -> 11.885152 | AP117: =AP180*AP226 -> 12.037995 | AQ117: =AQ180*AQ226 -> 12.670953 | AR117: =AR180*AR226 -> 12.833901 | AS117: =AS180*AS226 -> 12.998945 | AT117: =AT180*AT226 -> 13.166112 | ... BC117: =BC180*BC226 -> 14.770742 | BG117: =SUM(D117:G117) -> 0 | BH117: =SUM(H117:K117) -> 0 | BI117: =SUM(L117:O117) -> 0 | BJ117: =SUM(P117:S117) -> 0 | BK117: =SUM(T117:W117) -> 0 | BL117: =SUM(X117:AA117) -> 0.4 | BM117: =SUM(AB117:AE117) -> 11.25 | BN117: =SUM(AF117:AI117) -> 21.461439 | BO117: =SUM(AJ117:AM117) -> 75.185263 | BP117: =SUM(AN117:AQ117) -> 48.32835 | BQ117: =SUM(AR117:AU117) -> 52.334387 | BR117: =SUM(AV117:AY117) -> 55.078845 | BS117: =SUM(AZ117:BC117) -> 57.967224
C118: MRCD/MDB | AI118: =+SUM(AI119:AI120) -> 0 | AJ118: =+SUM(AJ119:AJ120) -> 0 | AK118: =+SUM(AK119:AK120) -> 0 | AL118: =+SUM(AL119:AL120) -> 0 | AM118: =+SUM(AM119:AM120) -> 0 | AN118: =+SUM(AN119:AN120) -> 0 | AO118: =+SUM(AO119:AO120) -> 0 | AP118: =+SUM(AP119:AP120) -> 61.08795 | ... BC118: =+SUM(BC119:BC120) -> 926.43012 | BG118: =SUM(D118:G118) -> 0 | BH118: =SUM(H118:K118) -> 0 | BI118: =SUM(L118:O118) -> 0 | BJ118: =SUM(P118:S118) -> 0 | BK118: =SUM(T118:W118) -> 0 | BL118: =SUM(X118:AA118) -> 0 | BM118: =SUM(AB118:AE118) -> 0 | BN118: =SUM(AF118:AI118) -> 0 | BO118: =SUM(AJ118:AM118) -> 0 | BP118: =SUM(AN118:AQ118) -> 130.63658 | BQ118: =SUM(AR118:AU118) -> 550.77343 | BR118: =SUM(AV118:AY118) -> 1701.6482 | BS118: =SUM(AZ118:BC118) -> 3173.1478 | BT118: =+(BS118/BP118)^(1/3)-1 -> 1.8960663
C119: MRCD | AI119: =AI182*AI228 -> 0 | AJ119: =AJ182*AJ228 -> 0 | AK119: =AK182*AK228 -> 0 | AL119: =AL182*AL228 -> 0 | AM119: =AM182*AM228 -> 0 | AN119: =AN182*AN228 -> 0 | AO119: =AO182*AO228 -> 0 | AP119: =AP182*AP228 -> 25.5717 | ... BC119: =BC182*BC228 -> 387.80796 | BG119: =SUM(D119:G119) -> 0 | BH119: =SUM(H119:K119) -> 0 | BI119: =SUM(L119:O119) -> 0 | BJ119: =SUM(P119:S119) -> 0 | BK119: =SUM(T119:W119) -> 0 | BL119: =SUM(X119:AA119) -> 0 | BM119: =SUM(AB119:AE119) -> 0 | BN119: =SUM(AF119:AI119) -> 0 | BO119: =SUM(AJ119:AM119) -> 0 | BP119: =SUM(AN119:AQ119) -> 54.68508 | BQ119: =SUM(AR119:AU119) -> 230.55632 | BR119: =SUM(AV119:AY119) -> 712.31784 | BS119: =SUM(AZ119:BC119) -> 1328.2944
C120: MDB | AI120: =AI183*AI229 -> 0 | AJ120: =AJ183*AJ229 -> 0 | AK120: =AK183*AK229 -> 0 | AL120: =AL183*AL229 -> 0 | AM120: =AM183*AM229 -> 0 | AN120: =AN183*AN229 -> 0 | AO120: =AO183*AO229 -> 0 | AP120: =AP183*AP229 -> 35.51625 | ... BC120: =BC183*BC229 -> 538.62216 | BG120: =SUM(D120:G120) -> 0 | BH120: =SUM(H120:K120) -> 0 | BI120: =SUM(L120:O120) -> 0 | BJ120: =SUM(P120:S120) -> 0 | BK120: =SUM(T120:W120) -> 0 | BL120: =SUM(X120:AA120) -> 0 | BM120: =SUM(AB120:AE120) -> 0 | BN120: =SUM(AF120:AI120) -> 0 | BO120: =SUM(AJ120:AM120) -> 0 | BP120: =SUM(AN120:AQ120) -> 75.951501 | BQ120: =SUM(AR120:AU120) -> 320.21711 | BR120: =SUM(AV120:AY120) -> 989.33033 | BS120: =SUM(AZ120:BC120) -> 1844.8533
C121: CKD | AI121: 40 | AJ121: 10 | AK121: 15 | AL121: 20 | AM121: 7 | AN121: 132 | AO121: 133.505 | AP121: =+AP184*AP230 -> 92.664 | AQ121: =+AQ184*AQ230 -> 93.572107 | AR121: =+AR184*AR230 -> 94.966332 | AS121: =+AS184*AS230 -> 96.38133 | AT121: =+AT184*AT230 -> 97.817412 | AU121: =+AU184*AU230 -> 99.274891 | AV121: =+AV184*AV230 -> 100.75409 | AW121: =+AW184*AW230 -> 102.25532 | ... BC121: =+BC184*BC230 -> 111.74432 | BG121: =SUM(D121:G121) -> 0 | BH121: =SUM(H121:K121) -> 0 | BI121: =SUM(L121:O121) -> 0 | BJ121: =SUM(P121:S121) -> 0 | BK121: =SUM(T121:W121) -> 0 | BL121: =SUM(X121:AA121) -> 0 | BM121: =SUM(AB121:AE121) -> 0 | BN121: =SUM(AF121:AI121) -> 40 | BO121: =SUM(AJ121:AM121) -> 52 | BP121: =SUM(AN121:AQ121) -> 451.74111 | BQ121: =SUM(AR121:AU121) -> 388.43996 | BR121: =SUM(AV121:AY121) -> 412.11357 | BS121: =SUM(AZ121:BC121) -> 437.22997
B122: PCIe/CXL Interconnect | AI122: =SUM(AI123:AI125) -> 13.125 | AJ122: =SUM(AJ123:AJ125) -> 36.015 | AK122: =SUM(AK123:AK125) -> 70 | AL122: =SUM(AL123:AL125) -> 138.58614 | AM122: =SUM(AM123:AM125) -> 153.66431 | AN122: =SUM(AN123:AN125) -> 170.38299 | AO122: =SUM(AO123:AO125) -> 210.84895 | AP122: =SUM(AP123:AP125) -> 240.05153 | ... BC122: =SUM(BC123:BC125) -> 2403.1972 | BG122: =SUM(D122:G122) -> 0 | BH122: =SUM(H122:K122) -> 0 | BI122: =SUM(L122:O122) -> 0 | BJ122: =SUM(P122:S122) -> 0 | BK122: =SUM(T122:W122) -> 0 | BL122: =SUM(X122:AA122) -> 0 | BM122: =SUM(AB122:AE122) -> 0 | BN122: =SUM(AF122:AI122) -> 13.125 | BO122: =SUM(AJ122:AM122) -> 398.26545 | BP122: =SUM(AN122:AQ122) -> 870.81703 | BQ122: =SUM(AR122:AU122) -> 1847.2669 | BR122: =SUM(AV122:AY122) -> 5917.9353 | BS122: =SUM(AZ122:BC122) -> 8800.5159 | BT122: =+(BS122/BP122)^(1/3)-1 -> 1.1620235
C123: PCIe Retimer | AI123: =+AI186*AI232 -> 13.125 | AJ123: =+AJ186*AJ232 -> 36.015 | AK123: 70 | AL123: =+AL186*AL232 -> 138.58614 | AM123: =+AM186*AM232 -> 153.66431 | AN123: =+AN186*AN232 -> 170.38299 | AO123: =+AO186*AO232 -> 210.84895 | AP123: =+AP186*AP232 -> 240.05153 | AQ123: =+AQ186*AQ232 -> 249.53356 | AR123: =+AR186*AR232 -> 259.39014 | AS123: =+AS186*AS232 -> 410.87398 | ... BC123: =+BC186*BC232 -> 820.31001 | BG123: =SUM(D123:G123) -> 0 | BH123: =SUM(H123:K123) -> 0 | BI123: =SUM(L123:O123) -> 0 | BJ123: =SUM(P123:S123) -> 0 | BK123: =SUM(T123:W123) -> 0 | BL123: =SUM(X123:AA123) -> 0 | BM123: =SUM(AB123:AE123) -> 0 | BN123: =SUM(AF123:AI123) -> 13.125 | BO123: =SUM(AJ123:AM123) -> 398.26545 | BP123: =SUM(AN123:AQ123) -> 870.81703 | BQ123: =SUM(AR123:AU123) -> 1738.2669 | BR123: =SUM(AV123:AY123) -> 2749.5609 | BS123: =SUM(AZ123:BC123) -> 3233.7822
C124: PCIe switch | AI124: =+AI187*AI233 -> 0 | AJ124: =+AJ187*AJ233 -> 0 | AK124: =+AK187*AK233 -> 0 | AL124: =+AL187*AL233 -> 0 | AM124: =+AM187*AM233 -> 0 | AN124: =+AN187*AN233 -> 0 | AO124: =+AO187*AO233 -> 0 | AP124: =+AP187*AP233 -> 0 | ... BC124: =+BC187*BC233 -> 665.88724 | BG124: =SUM(D124:G124) -> 0 | BH124: =SUM(H124:K124) -> 0 | BI124: =SUM(L124:O124) -> 0 | BJ124: =SUM(P124:S124) -> 0 | BK124: =SUM(T124:W124) -> 0 | BL124: =SUM(X124:AA124) -> 0 | BM124: =SUM(AB124:AE124) -> 0 | BN124: =SUM(AF124:AI124) -> 0 | BO124: =SUM(AJ124:AM124) -> 0 | BP124: =SUM(AN124:AQ124) -> 0 | BQ124: =SUM(AR124:AU124) -> 0 | BR124: =SUM(AV124:AY124) -> 1616.3744 | BS124: =SUM(AZ124:BC124) -> 2528.7337
C125: CXL MXC | AI125: =+AI188*AI234 -> 0 | AJ125: =+AJ188*AJ234 -> 0 | AK125: =+AK188*AK234 -> 0 | AL125: =+AL188*AL234 -> 0 | AM125: =+AM188*AM234 -> 0 | AN125: =+AN188*AN234 -> 0 | AO125: =+AO188*AO234 -> 0 | AP125: =+AP188*AP234 -> 0 | ... BC125: =+BC188*BC234 -> 917 | BG125: =SUM(D125:G125) -> 0 | BH125: =SUM(H125:K125) -> 0 | BI125: =SUM(L125:O125) -> 0 | BJ125: =SUM(P125:S125) -> 0 | BK125: =SUM(T125:W125) -> 0 | BL125: =SUM(X125:AA125) -> 0 | BM125: =SUM(AB125:AE125) -> 0 | BN125: =SUM(AF125:AI125) -> 0 | BO125: =SUM(AJ125:AM125) -> 0 | BP125: =SUM(AN125:AQ125) -> 0 | BQ125: =SUM(AR125:AU125) -> 109 | BR125: =SUM(AV125:AY125) -> 1552 | BS125: =SUM(AZ125:BC125) -> 3038
B126: CPU | R126: =R189*R235 -> 3.185 | S126: =S189*S235 -> 6.0515 | T126: =T189*T235 -> 5.44635 | U126: =U189*U235 -> 6.1108047 | V126: =V189*V235 -> 7.2303041 | W126: =W189*W235 -> 8.8498922 | X126: =X189*X235 -> 48.549566 | Y126: =Y189*Y235 -> 115.7098 | ... AB126: =AB189*AB235 -> 324.52871 | AC126: =690-AB126 -> 365.47129 | AD126: =928-AB126-AC126 -> 238 | AE126: =936.5612-AB126-AC126-AD126 -> 8.5612 | AF126: 5 | AG126: 9 | AH126: 14.4 | AI126: 65.1473 | AJ126: 39 | AK126: =130-AJ126 -> 91 | AL126: =185-AJ126-AK126 -> 55 | AM126: =290-SUM(AJ126:AL126) -> 105 | AN126: =AN189*AN235 -> 48.150309 | AO126: =AO189*AO235 -> 49.842793 | AP126: =AP189*AP235 -> 51.594767 | AQ126: =AQ189*AQ235 -> 53.408323 | AR126: =AR189*AR235 -> 50.991596 | AS126: =AS189*AS235 -> 52.271485 | AT126: =AT189*AT235 -> 53.058171 | AU126: =AU189*AU235 -> 53.856697 | ... BC126: =BC189*BC235 -> 60.693083 | BG126: =SUM(D126:G126) -> 0 | BH126: =SUM(H126:K126) -> 0 | BI126: =SUM(L126:O126) -> 0 | BJ126: =SUM(P126:S126) -> 9.2365 | BK126: =SUM(T126:W126) -> 27.637351 | BL126: =SUM(X126:AA126) -> 834.13012 | BM126: =SUM(AB126:AE126) -> 936.5612 | BN126: =SUM(AF126:AI126) -> 93.5473 | BO126: =SUM(AJ126:AM126) -> 290 | BP126: =SUM(AN126:AQ126) -> 202.99619 | BQ126: =SUM(AR126:AU126) -> 210.17795 | BR126: =SUM(AV126:AY126) -> 223.65513 | BS126: =SUM(AZ126:BC126) -> 237.42618
B127: Other | R127: =+R10-SUM(R110,R122,R126) -> 0.1392208 | S127: =+S10-SUM(S110,S122,S126) -> -0.08612077 | T127: =+T10-SUM(T110,T122,T126) -> -0.08442631 | U127: =+U10-SUM(U110,U122,U126) -> -0.10022081 | V127: =+V10-SUM(V110,V122,V126) -> 0.65874798 | W127: =+W10-SUM(W110,W122,W126) -> 0.046029156 | X127: =+X10-SUM(X110,X122,X126) -> 0.16319948 | Y127: =+Y10-SUM(Y110,Y122,Y126) -> -0.19198932 | ... AP127: =+AP10-SUM(AP110,AP122,AP126) -> 68.866481 | AQ127: 0 | AR127: 0 | AS127: 0 | AT127: 0 | AU127: 0 | AV127: 0 | AW127: 0 | AX127: 0 | AY127: 0 | AZ127: 0 | BA127: 0 | BB127: 0 | BC127: 0 | BG127: =SUM(D127:G127) -> 0 | BH127: =SUM(H127:K127) -> 0 | BI127: =SUM(L127:O127) -> 0 | BJ127: =SUM(P127:S127) -> 0.05310003 | BK127: =SUM(T127:W127) -> 0.52013002 | BL127: =SUM(X127:AA127) -> 0.53450701 | BM127: =SUM(AB127:AE127) -> 51.240184 | BN127: =SUM(AF127:AI127) -> 193.81825 | BO127: =SUM(AJ127:AM127) -> -751.36608 | BP127: =SUM(AN127:AQ127) -> 190.00149 | BQ127: =SUM(AR127:AU127) -> 0 | BR127: =SUM(AV127:AY127) -> 0 | BS127: =SUM(AZ127:BC127) -> 0
A128: Total | R128: =+R110+R122+R126+R127 -> 505.167 | S128: =+S110+S122+S126+S127 -> 353.38938 | T128: =+T110+T122+T126+T127 -> 495.75248 | U128: =+U110+U122+U126+U127 -> 593.82419 | V128: =+V110+V122+V126+V127 -> 378.87465 | W128: =+W110+W122+W126+W127 -> 355.21424 | X128: =+X110+X122+X126+X127 -> 299.53 | Y128: =+Y110+Y122+Y126+Y127 -> 424.933 | ... BC128: =+BC110+BC122+BC126+BC127 -> 5342.0619 | BG128: =+BG10 -> 844.945 | BH128: =+BH10 -> 1227.515 | BI128: =+BI10 -> 1757.665 | BJ128: =+BJ10 -> 1737.735 | BK128: =+BK10 -> 1823.6656 | BL128: =+BL10 -> 2562.017 | BM128: =+BM10 -> 3672.258 | BN128: =+BN10 -> 2285.738 | BO128: =+BO10 -> 3638.911 | BP128: =+BP110+BP122+BP126+BP127 -> 5453.5978 | BQ128: =+BQ110+BQ122+BQ126+BQ127 -> 7525.8737 | BR128: =+BR110+BR122+BR126+BR127 -> 13915.084 | BS128: =+BS110+BS122+BS126+BS127 -> 19505.882
A129: Check | R129: =R128-R10 -> 0 | S129: =S128-S10 -> 0 | T129: =T128-T10 -> 0 | U129: =U128-U10 -> 0 | V129: =V128-V10 -> 0 | W129: =W128-W10 -> 0 | X129: =X128-X10 -> 0 | Y129: =Y128-Y10 -> 0 | ... BC129: =BC128-BC10 -> 0 | BG129: =BG128-BG10 -> 0 | BH129: =BH128-BH10 -> 0 | BI129: =BI128-BI10 -> 0 | BJ129: =BJ128-BJ10 -> 0 | BK129: =BK128-BK10 -> 0 | BL129: =BL128-BL10 -> 0 | BM129: =BM128-BM10 -> 0 | BN129: =BN128-BN10 -> 0 | ... BS129: =BS128-BS10 -> 0
A132: Sales Breakdown
B133: Memory Interconnect | R133: =R110/R$128 -> 0.99341956 | S133: =S110/S$128 -> 0.98311953 | T133: =T110/T$128 -> 0.98918427 | U133: =U110/U$128 -> 0.98987818 | V133: =V110/V$128 -> 0.97917767 | W133: =W110/W$128 -> 0.97495618 | X133: =X110/X$128 -> 0.83736933 | Y133: =Y110/Y$128 -> 0.72815054 | ... BC133: =BC110/BC$128 -> 0.53877541 | BG133: =BG110/BG$128 -> 0.66078467 | BH133: =BH110/BH$128 -> 0.76143102 | BI133: =BI110/BI$128 -> 0.99487252 | BJ133: =BJ110/BJ$128 -> 0.9906335 | BK133: =BK110/BK$128 -> 0.98455995 | BL133: =BL110/BL$128 -> 0.67421581 | BM133: =BM110/BM$128 -> 0.73100981 | BN133: =BN110/BN$128 -> 0.86853675 | ... BS133: =BS110/BS$128 -> 0.53665556
C134: Memory interface | R134: =R111/R$128 -> 0.99341956 | S134: =S111/S$128 -> 0.98311953 | T134: =T111/T$128 -> 0.98918427 | U134: =U111/U$128 -> 0.98987818 | V134: =V111/V$128 -> 0.97917767 | W134: =W111/W$128 -> 0.97495618 | X134: =X111/X$128 -> 0.83736933 | Y134: =Y111/Y$128 -> 0.72815054 | ... BC134: =BC111/BC$128 -> 0.33304984 | BG134: =BG111/BG$128 -> 0.66078467 | BH134: =BH111/BH$128 -> 0.76143102 | BI134: =BI111/BI$128 -> 0.99487252 | BJ134: =BJ111/BJ$128 -> 0.9906335 | BK134: =BK111/BK$128 -> 0.98455995 | BL134: =BL111/BL$128 -> 0.67374743 | BM134: =BM111/BM$128 -> 0.70882999 | BN134: =BN111/BN$128 -> 0.78015114 | ... BS134: =BS111/BS$128 -> 0.33932635
C135: RCD | R135: =R112/R$128 -> 0.75000039 | S135: =S112/S$128 -> 0.73410242 | T135: =T112/T$128 -> 0.75815033 | U135: =U112/U$128 -> 0.75214807 | V135: =V112/V$128 -> 0.7466733 | W135: =W112/W$128 -> 0.73906694 | X135: =X112/X$128 -> 0.64628891 | Y135: =Y112/Y$128 -> 0.5950766 | ... BC135: =BC112/BC$128 -> 0.28824169 | BG135: =BG112/BG$128 -> 0.54108735 | BH135: =BH112/BH$128 -> 0.61017528 | BI135: =BI112/BI$128 -> 0.75701538 | BJ135: =BJ112/BJ$128 -> 0.75310939 | BK135: =BK112/BK$128 -> 0.75009439 | BL135: =BL112/BL$128 -> 0.55040064 | BM135: =BM112/BM$128 -> 0.5817978 | BN135: =BN112/BN$128 -> 0.63906728 | ... BS135: =BS112/BS$128 -> 0.29367376
C136: DB | R136: =R113/R$128 -> 0.24341917 | S136: =S113/S$128 -> 0.2490171 | T136: =T113/T$128 -> 0.23103394 | U136: =U113/U$128 -> 0.23773011 | V136: =V113/V$128 -> 0.23250437 | W136: =W113/W$128 -> 0.23588924 | X136: =X113/X$128 -> 0.19108042 | Y136: =Y113/Y$128 -> 0.13307394 | ... BC136: =BC113/BC$128 -> 0.044808157 | BG136: =BG113/BG$128 -> 0.11969732 | BH136: =BH113/BH$128 -> 0.15125574 | BI136: =BI113/BI$128 -> 0.23785713 | BJ136: =BJ113/BJ$128 -> 0.23752411 | BK136: =BK113/BK$128 -> 0.23446556 | BL136: =BL113/BL$128 -> 0.1233468 | BM136: =BM113/BM$128 -> 0.12703219 | BN136: =BN113/BN$128 -> 0.14108386 | ... BS136: =BS113/BS$128 -> 0.045652591
C137: Supporting chips | R137: =R114/R$128 -> 0 | S137: =S114/S$128 -> 0 | T137: =T114/T$128 -> 0 | U137: =U114/U$128 -> 0 | V137: =V114/V$128 -> 0 | W137: =W114/W$128 -> 0 | X137: =X114/X$128 -> 0 | Y137: =Y114/Y$128 -> 0 | ... BC137: =BC114/BC$128 -> 0.011385915 | BG137: =BG114/BG$128 -> 0 | BH137: =BH114/BH$128 -> 0 | BI137: =BI114/BI$128 -> 0 | BJ137: =BJ114/BJ$128 -> 0 | BK137: =BK114/BK$128 -> 0 | BL137: =BL114/BL$128 -> 0.00046838097 | BM137: =BM114/BM$128 -> 0.022179814 | BN137: =BN114/BN$128 -> 0.07088579 | ... BS137: =BS114/BS$128 -> 0.012237464
C138: PMIC | R138: =R115/R$128 -> 0 | S138: =S115/S$128 -> 0 | T138: =T115/T$128 -> 0 | U138: =U115/U$128 -> 0 | V138: =V115/V$128 -> 0 | W138: =W115/W$128 -> 0 | X138: =X115/X$128 -> 0 | Y138: =Y115/Y$128 -> 0 | ... BC138: =BC115/BC$128 -> 0.0037988804 | BG138: =BG115/BG$128 -> 0 | BH138: =BH115/BH$128 -> 0 | BI138: =BI115/BI$128 -> 0 | BJ138: =BJ115/BJ$128 -> 0 | BK138: =BK115/BK$128 -> 0 | BL138: =BL115/BL$128 -> 0.00015612699 | BM138: =BM115/BM$128 -> 0.0092041463 | BN138: =BN115/BN$128 -> 0.032998481 | ... BS138: =BS115/BS$128 -> 0.0040829975
C139: SPD | R139: =R116/R$128 -> 0 | S139: =S116/S$128 -> 0 | T139: =T116/T$128 -> 0 | U139: =U116/U$128 -> 0 | V139: =V116/V$128 -> 0 | W139: =W116/W$128 -> 0 | X139: =X116/X$128 -> 0 | Y139: =Y116/Y$128 -> 0 | ... BC139: =BC116/BC$128 -> 0.0048220455 | BG139: =BG116/BG$128 -> 0 | BH139: =BH116/BH$128 -> 0 | BI139: =BI116/BI$128 -> 0 | BJ139: =BJ116/BJ$128 -> 0 | BK139: =BK116/BK$128 -> 0 | BL139: =BL116/BL$128 -> 0.00015612699 | BM139: =BM116/BM$128 -> 0.0099121576 | BN139: =BN116/BN$128 -> 0.028498027 | ... BS139: =BS116/BS$128 -> 0.0051826849
C140: TS | R140: =R117/R$128 -> 0 | S140: =S117/S$128 -> 0 | T140: =T117/T$128 -> 0 | U140: =U117/U$128 -> 0 | V140: =V117/V$128 -> 0 | W140: =W117/W$128 -> 0 | X140: =X117/X$128 -> 0 | Y140: =Y117/Y$128 -> 0 | ... BC140: =BC117/BC$128 -> 0.002764989 | BG140: =BG117/BG$128 -> 0 | BH140: =BH117/BH$128 -> 0 | BI140: =BI117/BI$128 -> 0 | BJ140: =BJ117/BJ$128 -> 0 | BK140: =BK117/BK$128 -> 0 | BL140: =BL117/BL$128 -> 0.00015612699 | BM140: =BM117/BM$128 -> 0.0030635102 | BN140: =BN117/BN$128 -> 0.0093892822 | ... BS140: =BS117/BS$128 -> 0.0029717817
C141: MRCD/MDB, CKD | R141: =R118/R$128 -> 0 | S141: =S118/S$128 -> 0 | T141: =T118/T$128 -> 0 | U141: =U118/U$128 -> 0 | V141: =V118/V$128 -> 0 | W141: =W118/W$128 -> 0 | X141: =X118/X$128 -> 0 | Y141: =Y118/Y$128 -> 0 | ... BC141: =BC118/BC$128 -> 0.17342182 | BG141: =BG118/BG$128 -> 0 | BH141: =BH118/BH$128 -> 0 | BI141: =BI118/BI$128 -> 0 | BJ141: =BJ118/BJ$128 -> 0 | BK141: =BK118/BK$128 -> 0 | BL141: =BL118/BL$128 -> 0 | BM141: =BM118/BM$128 -> 0 | BN141: =BN118/BN$128 -> 0 | ... BS141: =BS118/BS$128 -> 0.16267646
C142: MRCD | R142: =R119/R$128 -> 0 | S142: =S119/S$128 -> 0 | T142: =T119/T$128 -> 0 | U142: =U119/U$128 -> 0 | V142: =V119/V$128 -> 0 | W142: =W119/W$128 -> 0 | X142: =X119/X$128 -> 0 | Y142: =Y119/Y$128 -> 0 | ... BC142: =BC119/BC$128 -> 0.072595182 | BG142: =BG119/BG$128 -> 0 | BH142: =BH119/BH$128 -> 0 | BI142: =BI119/BI$128 -> 0 | BJ142: =BJ119/BJ$128 -> 0 | BK142: =BK119/BK$128 -> 0 | BL142: =BL119/BL$128 -> 0 | BM142: =BM119/BM$128 -> 0 | BN142: =BN119/BN$128 -> 0 | ... BS142: =BS119/BS$128 -> 0.068097121
C143: MDB | R143: =R120/R$128 -> 0 | S143: =S120/S$128 -> 0 | T143: =T120/T$128 -> 0 | U143: =U120/U$128 -> 0 | V143: =V120/V$128 -> 0 | W143: =W120/W$128 -> 0 | X143: =X120/X$128 -> 0 | Y143: =Y120/Y$128 -> 0 | ... BC143: =BC120/BC$128 -> 0.10082664 | BG143: =BG120/BG$128 -> 0 | BH143: =BH120/BH$128 -> 0 | BI143: =BI120/BI$128 -> 0 | BJ143: =BJ120/BJ$128 -> 0 | BK143: =BK120/BK$128 -> 0 | BL143: =BL120/BL$128 -> 0 | BM143: =BM120/BM$128 -> 0 | BN143: =BN120/BN$128 -> 0 | ... BS143: =BS120/BS$128 -> 0.094579335
...

Sheet Balance Sheet
A1: ='Earnings Model'!A1 -> Montage Technology (688008.SS, 6809.HK)
B2: Bottom-Up Model ($ in million)
B3: FY Ends: Dec
A5: ='Earnings Model'!A8 -> Rmb$ in million | C5: 4Q16 | D5: 1Q17 | E5: 2Q17 | F5: 3Q17 | G5: 4Q17 | H5: 1Q18 | I5: 2Q18 | J5: 3Q18 | K5: 4Q18 | L5: 1Q19 | M5: 2Q19 | N5: 3Q19 | O5: 4Q19 | P5: 1Q20 | Q5: 2Q20 | R5: 3Q20 | S5: 4Q20 | T5: 1Q21 | U5: 2Q21 | V5: 3Q21 | W5: 4Q21 | X5: 1Q22 | Y5: 2Q22 | Z5: 3Q22 | AA5: 4Q22 | AB5: 1Q23 | AC5: 2Q23 | AD5: 3Q23 | AE5: 4Q23 | AF5: 1Q24 | AG5: 2Q24 | AH5: 3Q24 | AI5: 4Q24 | AJ5: 1Q25 | AK5: 2Q25 | AL5: 3Q25 | AM5: 4Q25 | AO5: 2016 | AP5: 2017 | AQ5: 2018 | AR5: 2019 | AS5: 2020 | AT5: 2021 | AU5: 2022 | AV5: 2023 | AW5: 2024 | AX5: 2025 | AY5: 2026E | AZ5: 2027E | BA5: 2028E
A8: Assets
B9: Cash & Securities | C9: =SUM(C10:C11) -> 0 | D9: =SUM(D10:D11) -> 0 | E9: =SUM(E10:E11) -> 0 | F9: =SUM(F10:F11) -> 0 | G9: =SUM(G10:G11) -> 0 | H9: =SUM(H10:H11) -> 0 | I9: =SUM(I10:I11) -> 0 | J9: =SUM(J10:J11) -> 0 | ... AM9: =SUM(AM10:AM11) -> 9302.288 | AO9: 454.351 | AP9: 687.786 | AQ9: 3679.991 | AR9: =+AR10+AR11 -> 7357.8446 | AS9: =SUM(AS10:AS12) -> 6345.992 | AT9: =+AT10+AT11 -> 6666.491 | AU9: =+AU10+AU11 -> 7480.528 | AV9: =+AV10+AV11 -> 7446.842 | AW9: =+AW10+AW11 -> 7400.152 | AX9: =+AX10+AX11 -> 7364.08 | AY9: =SUM(AY10:AY12) -> 17407.123 | AZ9: =SUM(AZ10:AZ12) -> 23937.581 | BA9: =SUM(BA10:BA12) -> 33913.698
B10: Cash & Cash Equivalents | C10: 0 | D10: 0 | E10: 0 | F10: 0 | G10: 0 | H10: 0 | I10: 0 | J10: 0 | K10: 3679.9913 | L10: 0 | M10: 4030.3676 | N10: 7133.001 | O10: 7257.0637 | P10: 7582.2988 | Q10: 7320.8061 | R10: 6806.7686 | S10: 5474.592 | T10: 5668.54 | U10: 5842.794 | V10: 5722.253 | W10: 5104.338 | X10: 4879.758 | Y10: 5476.76 | Z10: 5119.689 | AA10: 5870.438 | AB10: 5388.085 | AC10: 5861.541 | AD10: 5726.784 | AE10: 5743.575 | AF10: 5723.346 | AG10: 5851.634 | AH10: 6242.95 | AI10: 6843.297 | AJ10: 7174.73 | AK10: 8353.452 | AL10: 8898.71 | AM10: 8478.984 | AO10: =+AO9-AO11-AO12 -> 454.351 | AP10: =+AP9-AP11-AP12 -> 687.786 | AQ10: =+AQ9-AQ11-AQ12 -> 3679.991 | AR10: =+O10 -> 7257.0637 | AS10: =S10 -> 5474.592 | AT10: =W10 -> 5104.338 | AU10: =+AA10 -> 5870.438 | AV10: =+AE10 -> 5743.575 | AW10: =+AF10 -> 5723.346 | AX10: =+AG10 -> 5851.634 | AY10: ='Cash Flow'!O46 -> 15894.677 | AZ10: ='Cash Flow'!P46 -> 22425.135 | BA10: ='Cash Flow'!Q46 -> 32401.252
B11: Marketable securities | C11: 0 | D11: 0 | E11: 0 | F11: 0 | G11: 0 | H11: 0 | I11: 0 | J11: 0 | K11: 0 | L11: 0 | M11: 0 | N11: 0 | O11: 100.78082 | P11: 114.72822 | Q11: 388.40642 | R11: 65.168767 | S11: 871.4 | T11: 799.737 | U11: 412.86 | V11: 1012.425 | W11: 1562.153 | X11: 2070.325 | Y11: 2280.461 | Z11: 2139.308 | AA11: 1610.09 | AB11: 1563.525 | AC11: 1784.75 | AD11: 1630.029 | AE11: 1703.267 | AF11: 1676.806 | AG11: 1512.446 | AH11: 1493.089 | AI11: 1783.495 | AJ11: 1573.106 | AK11: 666.888 | AL11: 545.849 | AM11: 823.304 | AO11: 0 | AP11: 0 | AQ11: 0 | AR11: =+O11 -> 100.78082 | AS11: =S11 -> 871.4 | AT11: =+W11 -> 1562.153 | AU11: =+AA11 -> 1610.09 | AV11: =+AE11 -> 1703.267 | AW11: =+AF11 -> 1676.806 | AX11: =+AG11 -> 1512.446 | AY11: =AX11-'Cash Flow'!O26 -> 1512.446 | AZ11: =AY11-'Cash Flow'!P26 -> 1512.446 | BA11: =AZ11-'Cash Flow'!Q26 -> 1512.446
B12: Restricted Cash and Cash Equivalents | AY12: =AX12 -> 0 | AZ12: =AY12 -> 0 | BA12: =AZ12 -> 0
B13: Accounts and Notes Receivable | C13: 0 | D13: 0 | E13: 0 | F13: 0 | G13: 0 | H13: 0 | I13: 0 | J13: 0 | K13: =241.14922121 -> 241.14922 | L13: 0 | M13: =191.9930483 -> 191.99305 | N13: 238.942 | O13: 131.86482 | P13: =177.25627846 -> 177.25628 | Q13: =122.0480395 -> 122.04804 | R13: 120.37637 | S13: 87.453 | T13: 104.934 | U13: 163.68 | V13: 414.739 | W13: 172.433 | X13: 212.29 | Y13: 196.307 | Z13: 280.93 | AA13: 322.379 | AB13: 169.069 | AC13: 185.44 | AD13: 256.438 | AE13: 294.254 | AF13: 218.392 | AG13: 248.611 | AH13: 260.825 | AI13: 387.792 | AJ13: 463.919 | AK13: 391.064 | AL13: 568.204 | AM13: 567.532 | AO13: 58.796 | AP13: 119.258 | AQ13: 241.149 | AR13: =+O13 -> 131.86482 | AS13: =S13 -> 87.453 | AT13: 172.433 | AU13: 322.379 | AV13: 294.254 | AW13: 387.792 | AX13: 567.532 | AY13: =AY62*'Earnings Model'!BQ10/365 -> 704.43063 | AZ13: =AZ62*'Earnings Model'!BR10/365 -> 1304.0615 | BA13: =BA62*'Earnings Model'!BS10/365 -> 1828.0069
B14: Inventories | C14: 0 | D14: 0 | E14: 0 | F14: 0 | G14: 0 | H14: 0 | I14: 0 | J14: 0 | K14: 120.67354 | L14: 0 | M14: 132.83984 | N14: 82.425 | O14: 156.80486 | P14: 142.66072 | Q14: 176.92772 | R14: 198.72442 | S14: 186.542 | T14: 195.267 | U14: 281.206 | V14: 293.633 | W14: 375.292 | X14: 405.564 | Y14: 670.709 | Z14: 662.437 | AA14: 738.433 | AB14: 819.031 | AC14: 736.426 | AD14: 632.683 | AE14: 482.386 | AF14: 476.777 | AG14: 400.825 | AH14: 393.622 | AI14: 352.196 | AJ14: 310.734 | AK14: 400.616 | AL14: 795.747 | AM14: 896.135 | AO14: 256.069 | AP14: 132.513 | AQ14: 120.674 | AR14: 156.805 | AS14: =S14 -> 186.542 | AT14: 375.292 | AU14: 738.433 | AV14: 482.386 | AW14: 352.196 | AX14: 896.135 | AY14: =AY63*'Earnings Model'!BQ14/365 -> 643.32796 | AZ14: =AZ63*'Earnings Model'!BR14/365 -> 1106.9601 | BA14: =BA63*'Earnings Model'!BS14/365 -> 1500.6271
B15: Others | C15: =C16-C9-C13-C14 -> 0 | D15: =D16-D9-D13-D14 -> 0 | E15: =E16-E9-E13-E14 -> 0 | F15: =F16-F9-F13-F14 -> 0 | G15: =G16-G9-G13-G14 -> 0 | H15: =H16-H9-H13-H14 -> 0 | I15: =I16-I9-I13-I14 -> 0 | J15: =J16-J9-J13-J14 -> 0 | ... AM15: =AM16-AM9-AM13-AM14 -> 268.12 | AO15: =AO16-AO9-AO13-AO14 -> 309.26 | AP15: =AP16-AP9-AP13-AP14 -> 486.647 | AQ15: =AQ16-AQ9-AQ13-AQ14 -> 44.718 | AR15: =AR16-AR9-AR13-AR14 -> 32.231634 | AS15: =S15 -> 39.76 | AT15: =W15 -> 208.84 | AU15: =AU16-AU9-AU13-AU14 -> 95.138 | AV15: =AV16-AV9-AV13-AV14 -> 72.645 | AW15: =AW16-AW9-AW13-AW14 -> 1321.164 | AX15: =AX16-AX9-AX13-AX14 -> 2206.328 | AY15: =AX15 -> 2206.328 | AZ15: =AY15 -> 2206.328 | BA15: =AZ15 -> 2206.328
B16: Total Current Assets | C16: 0 | D16: 0 | E16: 0 | F16: 0 | G16: 0 | H16: 0 | I16: 0 | J16: 0 | K16: 4086.5323 | L16: 0 | M16: 4382.9412 | N16: 7475.609 | O16: 7678.7462 | P16: 8045.3918 | Q16: 8043.0098 | R16: 7741.658 | S16: 6659.747 | T16: 6814.135 | U16: 6743.272 | V16: 7512.269 | W16: 7423.056 | X16: 7789.609 | Y16: 8714.779 | Z16: 8367.635 | AA16: 8636.478 | AB16: 8239.979 | AC16: 8625.566 | AD16: 8324.469 | AE16: 8296.127 | AF16: 8183.803 | AG16: 8105.686 | AH16: 8496.421 | AI16: 9461.304 | AJ16: 9882.72 | AK16: 10119.816 | AL16: 10961.154 | AM16: 11034.075 | AO16: 1078.476 | AP16: 1426.204 | AQ16: 4086.532 | AR16: 7678.746 | AS16: =S16 -> 6659.747 | AT16: 7423.056 | AU16: 8636.478 | AV16: 8296.127 | AW16: 9461.304 | AX16: 11034.075 | AY16: =AY9+SUM(AY13:AY15) -> 20961.209 | AZ16: =AZ9+SUM(AZ13:AZ15) -> 28554.93 | BA16: =BA9+SUM(BA13:BA15) -> 39448.66
B17: Long-term investments | C17: 0 | D17: 0 | E17: 0 | F17: 0 | G17: 0 | H17: 0 | I17: 0 | J17: 0 | K17: 0 | L17: 0 | M17: 0 | N17: 0 | O17: 0 | P17: 0 | Q17: 0 | R17: 0.8502165 | S17: 72.737 | T17: 72.487 | U17: 69.546 | V17: 67.969 | W17: 67.91 | X17: 66.335 | Y17: 64.71 | Z17: 64.083 | AA17: 64.349 | AB17: 63.568 | AC17: 62.081 | AD17: 70.89 | AE17: 70.714 | AF17: 69.723 | AG17: 74.956 | AH17: 107.863 | AI17: 109.225 | AJ17: 105.168 | AK17: 99.319 | AL17: 95.614 | AM17: 91.96 | AO17: 0 | AP17: 0 | AQ17: 0 | AR17: 0 | AS17: =S17 -> 72.737 | AT17: 67.91 | AU17: 64.349 | AV17: 70.714 | AW17: 109.225 | AX17: 91.96 | AY17: =AX17 -> 91.96 | AZ17: =AY17 -> 91.96 | BA17: =AZ17 -> 91.96
B18: Gross PPE | C18: 0 | D18: =C18 -> 0 | E18: 0 | F18: =E18 -> 0 | G18: 0 | H18: =G18 -> 0 | I18: 0 | J18: =I18 -> 0 | K18: 0 | L18: =K18 -> 0 | M18: =L18 -> 0 | N18: =M18 -> 0 | O18: 0 | P18: 0 | Q18: 0 | AO18: 42.496 | AP18: 21.936 | AQ18: 43.877 | AR18: 57.785 | AS18: 1034.281 | AT18: 105.872 | AU18: 609.928 | AV18: 752.45 | AW18: 790.301 | AX18: 1005.8 | AY18: nd | AZ18: nd | BA18: nd
B19: Accumulated Depreciation | C19: =C20-C18 -> 0 | D19: =D20-D18 -> 0 | E19: =E20-E18 -> 0 | F19: =F20-F18 -> 0 | G19: =G20-G18 -> 0 | H19: =H20-H18 -> 0 | I19: =I20-I18 -> 0 | J19: =J20-J18 -> 0 | K19: =+K20-K18 -> 23.150272 | L19: =+L20-L18 -> 0 | M19: =+M20-M18 -> 25.877296 | N19: =+N20-N18 -> 29.876 | O19: =+O20-O18 -> 27.669965 | P19: =+P20-P18 -> 27.386551 | Q19: =+Q20-Q18 -> 32.796069 | AO19: =+AO20-AO18 -> -30.332 | AP19: =+AP20-AP18 -> -14.612 | AQ19: =+AQ20-AQ18 -> -20.727 | AR19: =+AR20-AR18 -> -30.115 | AS19: =+AS20-AS18 -> -48.778 | AT19: =+AT20-AT18 -> -67.224 | AU19: =+AU20-AU18 -> -89.428 | AV19: =+AV20-AV18 -> -140.643 | ... AX19: =+AX20-AX18 -> -289.733 | AY19: nd | AZ19: nd | BA19: nd
B20: Net PP&E | C20: 0 | D20: 0 | E20: 0 | F20: 0 | G20: 0 | H20: 0 | I20: 0 | J20: 0 | K20: =23.15027153 -> 23.150272 | L20: 0 | M20: 25.877296 | N20: 29.876 | O20: =27.6699652 -> 27.669965 | P20: =27.38655086 -> 27.386551 | Q20: =32.79606893 -> 32.796069 | R20: 30.356324 | S20: 985.503 | T20: 978.833 | U20: 982.349 | V20: 972.782 | W20: 38.648 | X20: 37.32 | Y20: 39.311 | Z20: 38.279 | AA20: 520.5 | AB20: 536.353 | AC20: 582.344 | AD20: 584.767 | AE20: 611.807 | AF20: 602.734 | AG20: 591.572 | AH20: 579.069 | AI20: 582.259 | AJ20: 566.366 | AK20: 685.302 | AL20: 720.955 | AM20: 716.067 | AO20: 12.164 | AP20: 7.324 | AQ20: 23.15 | AR20: 27.67 | AS20: =S20 -> 985.503 | AT20: 38.648 | AU20: 520.5 | AV20: 611.807 | AW20: 582.259 | AX20: 716.067 | AY20: =+AX20+20 -> 736.067 | AZ20: =+AY20+20 -> 756.067 | BA20: =+AZ20+20 -> 776.067
B21: Intangible Assets | C21: 0 | D21: 0 | E21: 0 | F21: 0 | G21: 0 | H21: 0 | I21: 0 | J21: 0 | K21: 25.970719 | L21: 0 | M21: 24.916662 | N21: 20.465 | O21: 16.22184 | P21: 12.54741 | Q21: 8.8281565 | R21: 6.8403509 | S21: 10.247 | T21: 9.859 | U21: 8.177 | V21: 22.77 | W21: 124.605 | X21: 123.525 | Y21: 121.183 | Z21: 120.689 | AA21: 131.081 | AB21: 128.666 | AC21: 147.719 | AD21: 142.791 | AE21: 137.486 | AF21: 131.436 | AG21: 125.784 | AH21: 123.195 | AI21: 133.755 | AJ21: 127.459 | AK21: 120.969 | AL21: 119.693 | AM21: 113.433 | AO21: 17.948 | AP21: 20.788 | AQ21: 25.971 | AR21: 16.222 | AS21: =S21 -> 10.247 | AT21: 124.605 | AU21: 131.081 | AV21: 137.486 | AW21: 133.755 | AX21: 113.433 | AY21: =AX21 -> 113.433 | AZ21: =AY21 -> 113.433 | BA21: =AZ21 -> 113.433
B22: Deffered Tax Assets | C22: 0 | D22: 0 | E22: 0 | F22: 0 | G22: 0 | H22: 0 | I22: 0 | J22: 0 | K22: 39.946689 | L22: 0 | M22: 47.403383 | N22: 59.338 | O22: 54.513501 | P22: 64.571283 | Q22: 71.674498 | R22: 70.087985 | S22: 43.075 | T22: 49.811 | U22: 57.355 | V22: 64.773 | W22: 64.532 | X22: 59.296 | Y22: 70.883 | Z22: 82.707 | AA22: 92.404 | AB22: 86.385 | AC22: 78.431 | AD22: 80.03 | AE22: 90.578 | AF22: 89.209 | AG22: 87.432 | AH22: 81.353 | AI22: 83.097 | AJ22: 94.115 | AK22: 79.582 | AL22: 90.532 | AM22: 43.299 | AO22: 10.753 | AP22: 17.032 | AQ22: 39.947 | AR22: 54.514 | AS22: =S22 -> 43.075 | AT22: 64.532 | AU22: 92.404 | AV22: 90.578 | AW22: 83.097 | AX22: 43.299 | AY22: =AX22 -> 43.299 | AZ22: =AY22 -> 43.299 | BA22: =AZ22 -> 43.299
B23: Other Assets | C23: =C24-C16-C17-C20-C21-C22 -> 0 | D23: =D24-D16-D17-D20-D21-D22 -> 0 | E23: =E24-E16-E17-E20-E21-E22 -> 0 | F23: =F24-F16-F17-F20-F21-F22 -> 0 | G23: =G24-G16-G17-G20-G21-G22 -> 0 | H23: =H24-H16-H17-H20-H21-H22 -> 0 | I23: =I24-I16-I17-I20-I21-I22 -> 0 | J23: =J24-J16-J17-J20-J21-J22 -> 0 | ... AM23: =AM24-AM16-AM17-AM20-AM21-AM22 -> 1749.313 | AO23: =AO24-AO16-AO17-AO20-AO21-AO22 -> 2.003 | AP23: =AP24-AP16-AP17-AP20-AP21-AP22 -> 3.345 | AQ23: =AQ24-AQ16-AQ17-AQ20-AQ21-AQ22 -> 5.057 | AR23: =AR24-AR16-AR17-AR20-AR21-AR22 -> 3.601 | AS23: =S23 -> 648.133 | AT23: =AT24-AT16-AT17-AT20-AT21-AT22 -> 1239.811 | AU23: =AU24-AU16-AU17-AU20-AU21-AU22 -> 1241.234 | AV23: =AV24-AV16-AV17-AV20-AV21-AV22 -> 1490.829 | AW23: =AW24-AW16-AW17-AW20-AW21-AW22 -> 1849.271 | AX23: =AX24-AX16-AX17-AX20-AX21-AX22 -> 1749.313 | AY23: =AX23 -> 1749.313 | AZ23: =AY23 -> 1749.313 | BA23: =AZ23 -> 1749.313
A24: Total Assets | C24: 0 | D24: 0 | E24: 0 | F24: 0 | G24: 0 | H24: 0 | I24: 0 | J24: 0 | K24: 4180.6574 | L24: 0 | M24: 4484.8242 | N24: 7589.091 | O24: 7780.7535 | P24: 8174.8453 | Q24: 8540.9198 | R24: 8378.5118 | S24: 8419.442 | T24: 8685.978 | U24: 8620.2 | V24: 9009.717 | W24: 8958.562 | X24: 9391.582 | Y24: 10354.43 | Z24: 10264.186 | AA24: 10686.046 | AB24: 10519.681 | AC24: 10943.151 | AD24: 10619.712 | AE24: 10697.541 | AF24: 10707.524 | AG24: 10660.783 | AH24: 11181.976 | AI24: 12218.911 | AJ24: 12665.661 | AK24: 12878.881 | AL24: 13751.629 | AM24: 13748.147 | AO24: 1121.344 | AP24: 1474.693 | AQ24: 4180.657 | AR24: 7780.753 | AS24: =S24 -> 8419.442 | AT24: 8958.562 | AU24: 10686.046 | AV24: 10697.541 | AW24: 12218.911 | AX24: 13748.147 | AY24: =AY16+AY17+SUM(AY20:AY23) -> 23695.281 | AZ24: =AZ16+AZ17+SUM(AZ20:AZ23) -> 31309.002 | BA24: =BA16+BA17+SUM(BA20:BA23) -> 42222.732
A26: Liabilities & Shareholders' Equity
B27: Short-Term Debt | C27: 0 | D27: 0 | E27: 0 | F27: 0 | G27: 0 | H27: 0 | I27: 0 | J27: 0 | K27: 0 | L27: 0 | M27: 0 | N27: 0 | O27: 0 | P27: 0 | Q27: 0 | R27: 0 | S27: 0 | T27: 0 | U27: 0 | V27: 0 | W27: 0 | X27: 0 | Y27: 0 | Z27: 0 | AA27: 0 | AB27: 0 | AC27: 0 | AD27: 0 | AE27: 0 | AF27: 0 | AG27: 0 | AH27: 0 | AI27: 0 | AJ27: 0 | AK27: 0 | AL27: 0 | AM27: 0 | AO27: 0 | AP27: 0 | AQ27: 0 | AR27: 0 | AS27: =S27 -> 0 | AT27: 0 | AU27: 0 | AV27: 0 | AW27: 0 | AX27: 0 | AY27: =AX27+'Cash Flow'!O33 -> 0 | AZ27: =AY27+'Cash Flow'!P33 -> 0 | BA27: =AZ27+'Cash Flow'!Q33 -> 0
B28: Accounts Payable | C28: 0 | D28: 0 | E28: 0 | F28: 0 | G28: 0 | H28: 0 | I28: 0 | J28: 0 | K28: =74.3775691 -> 74.377569 | L28: 0 | M28: =113.25534615 -> 113.25535 | N28: 72.038 | O28: =91.29405784 -> 91.294058 | P28: =118.59080495 -> 118.5908 | Q28: =120.01846117 -> 120.01846 | R28: 78.692974 | S28: 85.844 | T28: 108.305 | U28: 208.124 | V28: 312.074 | W28: 206.707 | X28: 259.157 | Y28: 478.604 | Z28: 167.261 | AA28: 197.166 | AB28: 126.626 | AC28: 79.187 | AD28: 103.185 | AE28: 131.115 | AF28: 171.013 | AG28: 115.143 | AH28: 158.523 | AI28: 211.154 | AJ28: 204.301 | AK28: 145.093 | AL28: 304.965 | AM28: 208.234 | AO28: 112.21 | AP28: 107.313 | AQ28: 74.378 | AR28: 91.294 | AS28: =S28 -> 85.844 | AT28: 206.707 | AU28: 197.166 | AV28: 131.115 | AW28: 211.154 | AX28: 208.234 | AY28: =AY64*'Earnings Model'!BQ14/365 -> 263.83413 | AZ28: =AZ64*'Earnings Model'!BR14/365 -> 453.97353 | BA28: =BA64*'Earnings Model'!BS14/365 -> 615.41962
B29: Others | C29: =C30-C27-C28 -> 0 | D29: =D30-D27-D28 -> 0 | E29: =E30-E27-E28 -> 0 | F29: =F30-F27-F28 -> 0 | G29: =G30-G27-G28 -> 0 | H29: =H30-H27-H28 -> 0 | I29: =I30-I27-I28 -> 0 | J29: =J30-J27-J28 -> 0 | ... AM29: =AM30-AM27-AM28 -> 561.409 | AO29: =AO30-AO27-AO28 -> 108.022 | AP29: =AP30-AP27-AP28 -> 160.545 | AQ29: =AQ30-AQ27-AQ28 -> 352.646 | AR29: =AR30-AR27-AR28 -> 188.419 | AS29: =S29 -> 150.588 | AT29: =AT30-AT27-AT28 -> 230.59 | AU29: =AU30-AU27-AU28 -> 442.263 | AV29: =AV30-AV27-AV28 -> 260.058 | AW29: =AW30-AW27-AW28 -> 468.724 | AX29: =AX30-AX27-AX28 -> 561.409 | AY29: =AX29 -> 561.409 | AZ29: =AY29 -> 561.409 | BA29: =AZ29 -> 561.409
B30: Current Liabilities | C30: 0 | D30: 0 | E30: 0 | F30: 0 | G30: 0 | H30: 0 | I30: 0 | J30: 0 | K30: 427.02387 | L30: 0 | M30: 268.46659 | N30: 259.907 | O30: 279.71266 | P30: 317.30442 | Q30: 630.23546 | R30: 236.55965 | S30: 236.432 | T30: 246.414 | U30: 338.419 | V30: 526.037 | W30: 437.297 | X30: 478.959 | Y30: 1105.617 | Z30: 459.916 | AA30: 639.429 | AB30: 423.31 | AC30: 706.981 | AD30: 386.273 | AE30: 391.173 | AF30: 369.801 | AG30: 377.776 | AH30: 520.687 | AI30: 679.878 | AJ30: 527.27 | AK30: 591.945 | AL30: 961.35 | AM30: 769.643 | AO30: 220.232 | AP30: 267.858 | AQ30: 427.024 | AR30: 279.713 | AS30: =S30 -> 236.432 | AT30: 437.297 | AU30: 639.429 | AV30: 391.173 | AW30: 679.878 | AX30: 769.643 | AY30: =SUM(AY27:AY29) -> 825.24313 | AZ30: =SUM(AZ27:AZ29) -> 1015.3825 | BA30: =SUM(BA27:BA29) -> 1176.8286
B31: Long-Term Debt | C31: 0 | D31: 0 | E31: 0 | F31: 0 | G31: 0 | H31: 0 | I31: 0 | J31: 0 | K31: 0 | L31: 0 | M31: 0 | N31: 0 | O31: 0 | P31: 0 | Q31: 0 | R31: 0 | S31: 0 | T31: 0 | U31: 0 | V31: 0 | W31: 0 | X31: 0 | Y31: 0 | Z31: 0 | AA31: 0 | AB31: 0 | AC31: 0 | AD31: 0 | AE31: 0 | AF31: 0 | AG31: 0 | AH31: 0 | AI31: 0 | AJ31: 0 | AK31: 0 | AL31: 0 | AM31: 0 | AO31: 0 | AP31: 0 | AQ31: 0 | AR31: 0 | AS31: =S31 -> 0 | AT31: 0 | AU31: 0 | AV31: 0 | AW31: 0 | AX31: 0 | AY31: =AX31+'Cash Flow'!O34 -> 0 | AZ31: =AY31+'Cash Flow'!P34 -> 0 | BA31: =AZ31+'Cash Flow'!Q34 -> 0
B32: Other Liabilities | C32: =C33-C30-C31 -> 0 | D32: =D33-D30-D31 -> 0 | E32: =E33-E30-E31 -> 0 | F32: =F33-F30-F31 -> 0 | G32: =G33-G30-G31 -> 0 | H32: =H33-H30-H31 -> 0 | I32: =I33-I30-I31 -> 0 | J32: =J33-J30-J31 -> 0 | ... Q32: =Q33-Q30-Q31 -> 174.35968 | R32: 172.65484 | S32: 172.65484 | T32: 173.65484 | U32: 174.65484 | V32: 174.65484 | W32: 174.65484 | X32: 174.65484 | Y32: 175.65484 | Z32: 176.65484 | AA32: 177.65484 | AB32: 178.65484 | AC32: 179.65484 | AD32: 180.65484 | AE32: 181.65484 | AF32: 182.65484 | AG32: 183.65484 | AH32: 184.65484 | AI32: 184.65484 | AJ32: 184.65484 | AK32: 184.65484 | AL32: 184.65484 | AM32: 184.65484 | AO32: =AO33-AO30-AO31 -> 18.088 | AP32: =AP33-AP30-AP31 -> 19.828 | AQ32: =AQ33-AQ30-AQ31 -> 137.884 | AR32: =AR33-AR30-AR31 -> 171.316 | AS32: =AS33-AS30-AS31 -> 112.759 | AT32: =AT33-AT30-AT31 -> 130.566 | AU32: =AU33-AU30-AU31 -> 119.362 | AV32: =AV33-AV30-AV31 -> 99.749 | ... AX32: =AX33-AX30-AX31 -> 107.349 | AY32: =AX32 -> 107.349 | AZ32: =AY32 -> 107.349 | BA32: =AZ32 -> 107.349
B33: Total Liabilities | C33: 0 | D33: 0 | E33: 0 | F33: 0 | G33: 0 | H33: 0 | I33: 0 | J33: 0 | K33: 564.90763 | L33: 0 | M33: 407.95641 | N33: 426.29 | O33: 451.02911 | P33: 493.17666 | Q33: 804.59514 | R33: 435.24491 | S33: 349.191 | T33: 378.378 | U33: 492.414 | V33: 629.901 | W33: 567.863 | X33: 624.798 | Y33: 1307.371 | Z33: 611.548 | AA33: 758.791 | AB33: 538.151 | AC33: 813.221 | AD33: 484.821 | AE33: 490.922 | AF33: 493.057 | AG33: 490.774 | AH33: 634.945 | AI33: 822.406 | AJ33: 723.952 | AK33: 818.532 | AL33: 1494.538 | AM33: 876.992 | AO33: 238.32 | AP33: 287.686 | AQ33: 564.908 | AR33: 451.029 | AS33: =S33 -> 349.191 | AT33: 567.863 | AU33: 758.791 | AV33: 490.922 | AW33: 822.406 | AX33: 876.992 | AY33: =SUM(AY30:AY32) -> 932.59213 | AZ33: =SUM(AZ30:AZ32) -> 1122.7315 | BA33: =SUM(BA30:BA32) -> 1284.1776
B35: Issued Capital | C35: 0 | D35: 0 | E35: 0 | F35: 0 | G35: 0 | H35: 0 | I35: 0 | J35: 0 | K35: 1016.8325 | L35: 0 | M35: 1016.8325 | N35: 1129.814 | O35: 1129.8139 | P35: 1129.8139 | Q35: 1129.8139 | R35: 1129.8139 | S35: 1129.814 | T35: 1131.03 | U35: 1131.03 | V35: 1131.03 | W35: 1131.307 | X35: 1132.824 | Y35: 1132.824 | Z35: 1133.657 | AA35: 1134.068 | AB35: 1136.078 | AC35: 1137.357 | AD35: 1138.008 | AE35: 1138.74 | AF35: 1141.461 | AG35: 1141.461 | AH35: 1142.538 | AI35: 1144.789 | AJ35: 1144.789 | AK35: 1144.789 | AL35: 1145.151 | AM35: 1146.427 | AO35: 757.032 | AP35: 757.032 | AQ35: 1016.833 | AR35: 1129.814 | AS35: =S35 -> 1129.814 | AT35: 1131.307 | AU35: 1134.068 | AV35: 1138.74 | AW35: 1144.789 | AX35: 1146.427 | AY35: =AX35 -> 1146.427 | AZ35: =AY35 -> 1146.427 | BA35: =AZ35 -> 1146.427
B36: Additional Capital | C36: 0 | D36: 0 | E36: 0 | F36: 0 | G36: 0 | H36: 0 | I36: 0 | J36: 0 | K36: 1831.0733 | L36: 0 | M36: 2065.9065 | N36: 4699.483 | O36: 4699.4832 | P36: 4754.0833 | Q36: 4811.7697 | R36: 4866.7057 | S36: 4901.652 | T36: 4978.936 | U36: 5025.642 | V36: 5068.586 | W36: 5113.492 | X36: 5179.278 | Y36: 5215.371 | Z36: 5279.672 | AA36: 5329.258 | AB36: 5412.181 | AC36: 5342.457 | AD36: 5393.062 | AE36: 5432.387 | AF36: 5508.174 | AG36: 5519.012 | AH36: 5556.229 | AI36: 5625.97 | AJ36: 5673.134 | AK36: 5717.509 | AL36: 5777.616 | AM36: 6114.018 | AO36: 66.185 | AP36: 66.185 | AQ36: 1831.073 | AR36: 4699.483 | AS36: =S36 -> 4901.652 | AT36: 5113.492 | AU36: 5329.258 | AV36: 5432.387 | AW36: 5625.97 | AX36: 6114.018 | AY36: =AX36+'Cash Flow'!O35 -> 12414.018 | AZ36: =AY36+'Cash Flow'!P35 -> 12414.018 | BA36: =AZ36+'Cash Flow'!Q35 -> 12414.018
B37: Treasury Stocks | C37: 0 | D37: 0 | E37: 0 | F37: 0 | G37: 0 | H37: 0 | I37: 0 | J37: 0 | K37: 0 | L37: 0 | M37: 0 | N37: 0 | O37: 0 | P37: 0 | Q37: 0 | R37: 0 | S37: 0 | T37: 0 | U37: 0 | V37: 0 | W37: -300.083 | X37: -300.083 | Y37: -300.083 | Z37: -300.083 | AA37: -300.083 | AB37: -300.083 | AC37: 0 | AD37: -173.871 | AE37: -300.031 | AF37: -602.478 | AG37: -709.089 | AH37: -709.089 | AI37: -427.558 | AJ37: -427.558 | AK37: -506.621 | AL37: -628.081 | AM37: -848.359 | AO37: 0 | AP37: 0 | AQ37: 0 | AR37: 0 | AS37: =S37 -> 0 | AT37: -300.083 | AU37: -300.083 | AV37: -300.031 | AW37: -427.558 | AX37: -848.359 | AY37: =AX37 -> -848.359 | AZ37: =AY37 -> -848.359 | BA37: =AZ37 -> -848.359
B38: Retained earnings | C38: 0 | D38: 0 | E38: 0 | F38: 0 | G38: 0 | H38: 0 | I38: 0 | J38: 0 | K38: 664.0965 | L38: 0 | M38: 881.05222 | N38: 1173.735 | O38: 1306.6763 | P38: 1569.6646 | Q38: 1569.2568 | R38: 1845.5006 | S38: 2021.29 | T38: 2154.385 | U38: 1988.82 | V38: 2193.423 | W38: 2461.879 | X38: 2767.846 | Y38: 2803.43 | Z38: 3137.781 | AA38: 3386.154 | AB38: 3405.875 | AC38: 3126.802 | AD38: 3278.751 | AE38: 3478.054 | AF38: 3701.462 | AG38: 3733.014 | AH38: 4117.938 | AI38: 4518.383 | AJ38: 5043.709 | AK38: 5234.313 | AL38: 5480.671 | AM38: 6018.558 | AO38: -17.148 | AP38: 312.375 | AQ38: 664.096 | AR38: 1306.676 | AS38: =S38 -> 2021.29 | AT38: 2461.879 | AU38: 3386.154 | AV38: 3478.054 | AW38: 4518.383 | AX38: 6018.558 | AY38: =AX38+'Earnings Model'!BQ57+'Cash Flow'!O36 -> 9610.0922 | AZ38: =AY38+'Earnings Model'!BR57+'Cash Flow'!P36 -> 17033.674 | BA38: =AZ38+'Earnings Model'!BS57+'Cash Flow'!Q36 -> 27785.958
B39: Others | C39: =C40-SUM(C35:C38) -> 1121.344 | D39: =D40-SUM(D35:D38) -> -2146826265 | E39: =E40-SUM(E35:E38) -> -2146826265 | F39: =F40-SUM(F35:F38) -> -2146826265 | G39: =G40-SUM(G35:G38) -> 1474.693 | H39: =H40-SUM(H35:H38) -> -2146826265 | I39: =I40-SUM(I35:I38) -> -2146826265 | J39: =J40-SUM(J35:J38) -> -2146826265 | ... AM39: =AM40-SUM(AM35:AM38) -> 440.512 | AO39: =AO40-SUM(AO35:AO38) -> 76.955 | AP39: =AP40-SUM(AP35:AP38) -> 51.415 | AQ39: =AQ40-SUM(AQ35:AQ38) -> 103.747 | AR39: =AR40-SUM(AR35:AR38) -> 193.751 | AS39: =AS40-SUM(AS35:AS38) -> 17.495 | AT39: =AT40-SUM(AT35:AT38) -> -15.896 | AU39: =AU40-SUM(AU35:AU38) -> 377.858 | AV39: =AV40-SUM(AV35:AV38) -> 457.469 | ... AX39: =AX40-SUM(AX35:AX38) -> 440.511 | AY39: =AX39 -> 440.511 | AZ39: =AY39 -> 440.511 | BA39: =AZ39 -> 440.511
B40: Total Shareholders' Equity | C40: =C42-C33 -> 1121.344 | D40: =D42-D33 -> -2146826265 | E40: =E42-E33 -> -2146826265 | F40: =F42-F33 -> -2146826265 | G40: =G42-G33 -> 1474.693 | H40: =H42-H33 -> -2146826265 | I40: =I42-I33 -> -2146826265 | J40: =J42-J33 -> -2146826265 | ... N40: =N42-N33 -> 7162.801 | O40: 7329.7244 | P40: 7681.6686 | Q40: 7736.3246 | R40: 7943.2669 | S40: 8070.251 | T40: 8307.6 | U40: 8127.786 | V40: 8379.816 | W40: 8390.699 | X40: 8766.784 | Y40: 9047.059 | Z40: 9652.638 | AA40: 9927.255 | AB40: 9981.53 | AC40: 10129.93 | AD40: 10134.892 | AE40: 10206.619 | AF40: 10214.466 | AG40: 10170.009 | AH40: 10547.031 | AI40: 11396.506 | AJ40: 11941.709 | AK40: 12060.349 | AL40: 12257.091 | AM40: 12871.156 | AO40: =AO42-AO33 -> 883.024 | AP40: =AP42-AP33 -> 1187.007 | AQ40: =AQ42-AQ33 -> 3615.749 | AR40: =AR42-AR33 -> 7329.724 | AS40: =S40 -> 8070.251 | AT40: =AT42-AT33 -> 8390.699 | AU40: =AU42-AU33 -> 9927.255 | AV40: =AV42-AV33 -> 10206.619 | AW40: =AW42-AW33 -> 11396.505 | AX40: =AX42-AX33 -> 12871.155 | AY40: =+SUM(AY35:AY39) -> 22762.689 | AZ40: =+SUM(AZ35:AZ39) -> 30186.271 | BA40: =+SUM(BA35:BA39) -> 40938.555
A42: Total Liabilities & Equity | C42: 1121.344 | D42: -2146826265 | E42: -2146826265 | F42: -2146826265 | G42: 1474.693 | H42: -2146826265 | I42: -2146826265 | J42: -2146826265 | K42: 4180.657 | L42: 7780.753 | M42: 4484.8242 | N42: 7589.091 | O42: 7780.7535 | P42: 8174.8453 | Q42: 8540.9198 | R42: 8378.5118 | S42: 8419.442 | T42: =T40+T33 -> 8685.978 | U42: =U40+U33 -> 8620.2 | V42: =V40+V33 -> 9009.717 | W42: =W40+W33 -> 8958.562 | X42: =X40+X33 -> 9391.582 | Y42: =Y40+Y33 -> 10354.43 | Z42: =Z40+Z33 -> 10264.186 | AA42: =AA40+AA33 -> 10686.046 | ... AM42: =AM40+AM33 -> 13748.148 | AO42: 1121.344 | AP42: 1474.693 | AQ42: 4180.657 | AR42: 7780.753 | AS42: =S42 -> 8419.442 | AT42: 8958.562 | AU42: 10686.046 | AV42: 10697.541 | AW42: 12218.911 | AX42: 13748.147 | AY42: =AY33+AY40 -> 23695.281 | AZ42: =AZ33+AZ40 -> 31309.002 | BA42: =BA33+BA40 -> 42222.732
A44: Check | C44: =+C42-C24 -> 1121.344 | D44: =+D42-D24 -> -2146826265 | E44: =+E42-E24 -> -2146826265 | F44: =+F42-F24 -> -2146826265 | G44: =+G42-G24 -> 1474.693 | H44: =+H42-H24 -> -2146826265 | I44: =+I42-I24 -> -2146826265 | J44: =+J42-J24 -> -2146826265 | ... AM44: =+AM42-AM24 -> 0.001 | AO44: =+AO42-AO24 -> 0 | AP44: =+AP42-AP24 -> 0 | AQ44: =+AQ42-AQ24 -> 0 | AR44: =+AR42-AR24 -> 0 | AS44: =+AS42-AS24 -> 0 | AT44: =+AT42-AT24 -> 0 | AU44: =+AU42-AU24 -> 0 | AV44: =+AV42-AV24 -> 0 | ... BA44: =+BA42-BA24 -> 0
A46: Balance Sheet Ratios
B48: Book Value Per Share (Reported) | C48: 0 | D48: 0 | E48: 0 | F48: 0 | G48: 0 | H48: 0 | I48: 0 | J48: 0 | K48: =K40/'Earnings Model'!#REF! -> #REF! | L48: =L40/'Earnings Model'!P$81 -> 7.4300757 | M48: =M40/'Earnings Model'!Q$81 -> 3.893124 | N48: =N40/'Earnings Model'!R$81 -> 6.8399747 | O48: =O40/'Earnings Model'!S$81 -> 6.9144038 | P48: =P40/'Earnings Model'!T$81 -> 6.7990559 | Q48: =Q40/'Earnings Model'!U$81 -> 6.8474321 | R48: =R40/'Earnings Model'!V$81 -> 7.030597 | S48: =S40/'Earnings Model'!W$81 -> 7.1429908 | ... AM48: =AM40/'Earnings Model'!AQ$81 -> 11.326813 | AO48: =AO40/'Earnings Model'!BG82 -> 1.1664289 | AP48: =AP40/'Earnings Model'!BH82 -> 1.5679747 | AQ48: =AQ40/'Earnings Model'!BI82 -> 4.2644793 | AR48: =AR40/'Earnings Model'!BJ82 -> 6.9144034 | AS48: =AS40/'Earnings Model'!BK82 -> 7.1115187 | AT48: =AT40/'Earnings Model'!BL82 -> 7.418181 | AU48: =AU40/'Earnings Model'!BM82 -> 8.759266 | AV48: =AV40/'Earnings Model'!BN82 -> 8.972491 | ... BA48: =BA40/'Earnings Model'!BS82 -> 36.026551
B49: Book Value Per Share (Tangible) | C49: =(+C40-C21)/'Earnings Model'!#REF! -> #REF! | D49: =(+D40-D21)/'Earnings Model'!#REF! -> #REF! | E49: =(+E40-E21)/'Earnings Model'!#REF! -> #REF! | F49: =(+F40-F21)/'Earnings Model'!#REF! -> #REF! | G49: =(+G40-G21)/'Earnings Model'!#REF! -> #REF! | H49: =(+H40-H21)/'Earnings Model'!#REF! -> #REF! | I49: =(+I40-I21)/'Earnings Model'!#REF! -> #REF! | J49: =(+J40-J21)/'Earnings Model'!#REF! -> #REF! | K49: =(+K40-K21)/'Earnings Model'!#REF! -> #REF! | L49: =(+L40-L21)/'Earnings Model'!P82 -> 7.4300757 | M49: =(+M40-M21)/'Earnings Model'!Q82 -> 3.8693303 | N49: =(+N40-N21)/'Earnings Model'!R82 -> 6.3216919 | O49: =(+O40-O21)/'Earnings Model'!S82 -> 6.4731916 | P49: =(+P40-P21)/'Earnings Model'!T82 -> 6.7879502 | Q49: =(+Q40-Q21)/'Earnings Model'!U82 -> 6.8396183 | R49: =(+R40-R21)/'Earnings Model'!V82 -> 7.0245426 | S49: =(+S40-S21)/'Earnings Model'!W82 -> 7.1339212 | ... AM49: =(+AM40-AM21)/'Earnings Model'!AQ82 -> 11.22699 | AO49: =(AO40-AO21)/'Earnings Model'!BG82 -> 1.1427205 | AP49: =(AP40-AP21)/'Earnings Model'!BH82 -> 1.5405148 | AQ49: =(AQ40-AQ21)/'Earnings Model'!BI82 -> 4.2338487 | AR49: =(AR40-AR21)/'Earnings Model'!BJ82 -> 6.8991006 | AS49: =(AS40-AS21)/'Earnings Model'!BK82 -> 7.102489 | AT49: =(AT40-AT21)/'Earnings Model'!BL82 -> 7.3080183 | AU49: =(AU40-AU21)/'Earnings Model'!BM82 -> 8.6436073 | AV49: =(AV40-AV21)/'Earnings Model'!BN82 -> 8.851629 | ... BA49: =(BA40-BA21)/'Earnings Model'!BS82 -> 35.926728
B50: Cash Per Share | C50: =C9/'Earnings Model'!#REF! -> #REF! | D50: =D9/'Earnings Model'!#REF! -> #REF! | E50: =E9/'Earnings Model'!#REF! -> #REF! | F50: =F9/'Earnings Model'!#REF! -> #REF! | G50: =G9/'Earnings Model'!#REF! -> #REF! | H50: =H9/'Earnings Model'!#REF! -> #REF! | I50: =I9/'Earnings Model'!#REF! -> #REF! | J50: =J9/'Earnings Model'!#REF! -> #REF! | K50: =K9/'Earnings Model'!#REF! -> #REF! | L50: =L9/'Earnings Model'!P82 -> 0 | M50: =M9/'Earnings Model'!Q82 -> 3.8487196 | N50: =N9/'Earnings Model'!R82 -> 6.3134295 | O50: =O9/'Earnings Model'!S82 -> 6.5124388 | P50: =P9/'Earnings Model'!T82 -> 6.8126497 | Q50: =Q9/'Earnings Model'!U82 -> 6.8234351 | R50: =R9/'Earnings Model'!V82 -> 6.0823617 | S50: =S9/'Earnings Model'!W82 -> 5.6168467 | ... AM50: =AM9/'Earnings Model'!AQ82 -> 8.1861549 | AO50: =AO9/'Earnings Model'!BG82 -> 0.6001741 | AP50: =AP9/'Earnings Model'!BH82 -> 0.90852963 | AQ50: =AQ9/'Earnings Model'!BI82 -> 4.3402475 | AR50: =AR9/'Earnings Model'!BJ82 -> 6.9409306 | AS50: =AS9/'Earnings Model'!BK82 -> 5.5920988 | AT50: =AT9/'Earnings Model'!BL82 -> 5.8938161 | AU50: =AU9/'Earnings Model'!BM82 -> 6.6004081 | AV50: =AV9/'Earnings Model'!BN82 -> 6.546411 | ... BA50: =BA9/'Earnings Model'!BS82 -> 29.84457
B52: Long-Term Debt/Equity | C52: =(C31)/C40 -> 0 | D52: =(D31)/D40 -> 0 | E52: =(E31)/E40 -> 0 | F52: =(F31)/F40 -> 0 | G52: =(G31)/G40 -> 0 | H52: =(H31)/H40 -> 0 | I52: =(I31)/I40 -> 0 | J52: =(J31)/J40 -> 0 | ... AM52: =(AM31)/AM40 -> 0 | AO52: =(AO31)/AO40 -> 0 | AP52: =(AP31)/AP40 -> 0 | AQ52: =(AQ31)/AQ40 -> 0 | AR52: =(AR31)/AR40 -> 0 | AS52: =(AS31)/AS40 -> 0 | AT52: =(AT31)/AT40 -> 0 | AU52: =(AU31)/AU40 -> 0 | AV52: =(AV31)/AV40 -> 0 | ... BA52: =(BA31)/BA40 -> 0
B53: Total Debt/Equity | C53: =(C27+C31)/C40 -> 0 | D53: =(D27+D31)/D40 -> 0 | E53: =(E27+E31)/E40 -> 0 | F53: =(F27+F31)/F40 -> 0 | G53: =(G27+G31)/G40 -> 0 | H53: =(H27+H31)/H40 -> 0 | I53: =(I27+I31)/I40 -> 0 | J53: =(J27+J31)/J40 -> 0 | ... AM53: =(AM27+AM31)/AM40 -> 0 | AO53: =(AO27+AO31)/AO40 -> 0 | AP53: =(AP27+AP31)/AP40 -> 0 | AQ53: =(AQ27+AQ31)/AQ40 -> 0 | AR53: =(AR27+AR31)/AR40 -> 0 | AS53: =(AS27+AS31)/AS40 -> 0 | AT53: =(AT27+AT31)/AT40 -> 0 | AU53: =(AU27+AU31)/AU40 -> 0 | AV53: =(AV27+AV31)/AV40 -> 0 | ... BA53: =(BA27+BA31)/BA40 -> 0
B54: Net Working Capital | C54: =C16-C30 -> 0 | D54: =D16-D30 -> 0 | E54: =E16-E30 -> 0 | F54: =F16-F30 -> 0 | G54: =G16-G30 -> 0 | H54: =H16-H30 -> 0 | I54: =I16-I30 -> 0 | J54: =J16-J30 -> 0 | ... AM54: =AM16-AM30 -> 10264.432 | AO54: =AO16-AO30 -> 858.244 | AP54: =AP16-AP30 -> 1158.346 | AQ54: =AQ16-AQ30 -> 3659.508 | AR54: =AR16-AR30 -> 7399.033 | AS54: =AS16-AS30 -> 6423.315 | AT54: =AT16-AT30 -> 6985.759 | AU54: =AU16-AU30 -> 7997.049 | AV54: =AV16-AV30 -> 7904.954 | ... BA54: =BA16-BA30 -> 38271.832
B55: Current Ratio | C55: =C16/C30 -> #DIV/0! | D55: =D16/D30 -> #DIV/0! | E55: =E16/E30 -> #DIV/0! | F55: =F16/F30 -> #DIV/0! | G55: =G16/G30 -> #DIV/0! | H55: =H16/H30 -> #DIV/0! | I55: =I16/I30 -> #DIV/0! | J55: =J16/J30 -> #DIV/0! | K55: =K16/K30 -> 9.5697983 | M55: =M16/M30 -> 16.325835 | N55: =N16/N30 -> 28.76263 | O55: =O16/O30 -> 27.452265 | P55: =P16/P30 -> 25.355436 | Q55: =Q16/Q30 -> 12.761913 | R55: =R16/R30 -> 32.726029 | S55: =S16/S30 -> 28.167706 | T55: =T16/T30 -> 27.653197 | ... AM55: =AM16/AM30 -> 14.336615 | AO55: =AO16/AO30 -> 4.8969995 | AP55: =AP16/AP30 -> 5.3244779 | AQ55: =AQ16/AQ30 -> 9.5697947 | AR55: =AR16/AR30 -> 27.452231 | AS55: =AS16/AS30 -> 28.167706 | AT55: =AT16/AT30 -> 16.974861 | AU55: =AU16/AU30 -> 13.506547 | AV55: =AV16/AV30 -> 21.208332 | ... BA55: =BA16/BA30 -> 33.52116
B57: Return on Ave Equity | C57: =(+'Earnings Model'!G52*4)/AVERAGE(B40:C40) -> 0 | D57: =(+'Earnings Model'!H52*4)/AVERAGE(C40:D40) -> 0 | E57: =(+'Earnings Model'!I52*4)/AVERAGE(D40:E40) -> 0 | F57: =(+'Earnings Model'!J52*4)/AVERAGE(E40:F40) -> 0 | G57: =(+'Earnings Model'!K52*4)/AVERAGE(F40:G40) -> 0 | H57: =(+'Earnings Model'!L52*4)/AVERAGE(G40:H40) -> 0 | I57: =(+'Earnings Model'!M52*4)/AVERAGE(H40:I40) -> 0 | J57: =(+'Earnings Model'!N52*4)/AVERAGE(I40:J40) -> 0 | ... AM57: =(+'Earnings Model'!AQ52*4)/AVERAGE(AL40:AM40) -> 0.16036741 | AO57: =(+'Earnings Model'!BG52)/AVERAGE(AO40:AO40) -> 0.10509907 | AP57: =(+'Earnings Model'!BH52)/AVERAGE(AP40:AP40) -> 0.29226112 | AQ57: =(+'Earnings Model'!BI52)/AVERAGE(AQ40:AQ40) -> 0.20379678 | AR57: =(+'Earnings Model'!BJ52)/AVERAGE(AQ40:AR40) -> 0.17045549 | AS57: =(+'Earnings Model'!BK52)/AVERAGE(AR40:AS40) -> 0.14334095 | AT57: =(+'Earnings Model'!BL52)/AVERAGE(AS40:AT40) -> 0.10073987 | AU57: =(+'Earnings Model'!BM52)/AVERAGE(AT40:AU40) -> 0.14186868 | AV57: =(+'Earnings Model'!BN52)/AVERAGE(AU40:AV40) -> 0.044814823 | AW57: =(+'Earnings Model'!BO52)/AVERAGE(AV40:AW40) -> 0.12412427 | AX57: =(+'Earnings Model'!BP52)/AVERAGE(AW40:AX40) -> 0.17142843 | AY57: =(+'Earnings Model'!BQ52)/AVERAGE(AX40:AY40) -> 0.19761742 | ... BA57: =(+'Earnings Model'!BS52)/AVERAGE(AZ40:BA40) -> 0.30036443
B58: Return on Ave Assets | C58: =(+'Earnings Model'!G52*4)/AVERAGE(B24:C24) -> #DIV/0! | D58: =(+'Earnings Model'!H52*4)/AVERAGE(C24:D24) -> #DIV/0! | E58: =(+'Earnings Model'!I52*4)/AVERAGE(D24:E24) -> #DIV/0! | F58: =(+'Earnings Model'!J52*4)/AVERAGE(E24:F24) -> #DIV/0! | G58: =(+'Earnings Model'!K52*4)/AVERAGE(F24:G24) -> #DIV/0! | H58: =(+'Earnings Model'!L52*4)/AVERAGE(G24:H24) -> #DIV/0! | I58: =(+'Earnings Model'!M52*4)/AVERAGE(H24:I24) -> #DIV/0! | J58: =(+'Earnings Model'!N52*4)/AVERAGE(I24:J24) -> #DIV/0! | ... AM58: =(+'Earnings Model'!AQ52*4)/AVERAGE(AL24:AM24) -> 0.14653763 | AO58: =(+'Earnings Model'!BG52)/AVERAGE(AO24:AO24) -> 0.082762292 | AP58: =(+'Earnings Model'!BH52)/AVERAGE(AP24:AP24) -> 0.23524625 | AQ58: =(+'Earnings Model'!BI52)/AVERAGE(AQ24:AQ24) -> 0.1762589 | AR58: =(+'Earnings Model'!BJ52)/AVERAGE(AQ24:AR24) -> 0.15597793 | AS58: =(+'Earnings Model'!BK52)/AVERAGE(AR24:AS24) -> 0.13626052 | AT58: =(+'Earnings Model'!BL52)/AVERAGE(AS24:AT24) -> 0.095423732 | AU58: =(+'Earnings Model'!BM52)/AVERAGE(AT24:AU24) -> 0.1322879 | AV58: =(+'Earnings Model'!BN52)/AVERAGE(AU24:AV24) -> 0.042195727 | AW58: =(+'Earnings Model'!BO52)/AVERAGE(AV24:AW24) -> 0.11701078 | AX58: =(+'Earnings Model'!BP52)/AVERAGE(AW24:AX24) -> 0.16020941 | AY58: =(+'Earnings Model'!BQ52)/AVERAGE(AX24:AY24) -> 0.18806687 | ... BA58: =(+'Earnings Model'!BS52)/AVERAGE(AZ24:BA24) -> 0.29053262
B59: Return on Sales | C59: =+'Earnings Model'!G52/'Earnings Model'!G10 -> #DIV/0! | D59: =+'Earnings Model'!H52/'Earnings Model'!H10 -> #DIV/0! | E59: =+'Earnings Model'!I52/'Earnings Model'!I10 -> #DIV/0! | F59: =+'Earnings Model'!J52/'Earnings Model'!J10 -> #DIV/0! | G59: =+'Earnings Model'!K52/'Earnings Model'!K10 -> #DIV/0! | H59: =+'Earnings Model'!L52/'Earnings Model'!L10 -> #DIV/0! | I59: =+'Earnings Model'!M52/'Earnings Model'!M10 -> #DIV/0! | J59: =+'Earnings Model'!N52/'Earnings Model'!N10 -> #DIV/0! | ... AM59: =+'Earnings Model'!AQ52/'Earnings Model'!AQ10 -> 0.41213819 | AO59: =+'Earnings Model'!BG52/'Earnings Model'!BG10 -> 0.10983555 | AP59: =+'Earnings Model'!BH52/'Earnings Model'!BH10 -> 0.28261651 | AQ59: =+'Earnings Model'!BI52/'Earnings Model'!BI10 -> 0.41923689 | AR59: =+'Earnings Model'!BJ52/'Earnings Model'!BJ10 -> 0.53682408 | AS59: =+'Earnings Model'!BK52/'Earnings Model'!BK10 -> 0.60522254 | AT59: =+'Earnings Model'!BL52/'Earnings Model'!BL10 -> 0.32362666 | AU59: =+'Earnings Model'!BM52/'Earnings Model'!BM10 -> 0.35383462 | AV59: =+'Earnings Model'!BN52/'Earnings Model'!BN10 -> 0.1973752 | ... BA59: =+'Earnings Model'!BS52/'Earnings Model'!BS10 -> 0.54761347
B60: Return on Ave Invested Capital
B61: Ave Inventory Turns | C61: =365/C63 -> #DIV/0! | D61: =365/D63 -> #DIV/0! | E61: =365/E63 -> #DIV/0! | F61: =365/F63 -> #DIV/0! | G61: =365/G63 -> #DIV/0! | H61: =365/H63 -> #DIV/0! | I61: =365/I63 -> #DIV/0! | J61: =365/J63 -> #DIV/0! | ... L61: =365/L63 -> 6.4059375 | N61: =365/N63 -> 4.6425884 | O61: =365/O63 -> 3.2097652 | P61: =365/P63 -> 3.6493781 | Q61: =365/Q63 -> 3.7925048 | R61: =365/R63 -> 2.3868506 | S61: =365/S63 -> 2.2610549 | T61: =365/T63 -> 2.2391044 | U61: =365/U63 -> 2.7926484 | ... AM61: =365/AM63 -> 2.2919565 | AP61: =365/AP63 -> 2.9386436 | AQ61: =365/AQ63 -> 4.089736 | AR61: =365/AR63 -> 3.2615081 | AS61: =365/AS63 -> 2.9572706 | AT61: =365/AT63 -> 4.7351958 | AU61: =365/AU63 -> 3.531836 | AV61: =365/AV63 -> 1.5386654 | AW61: =365/AW63 -> 3.651205 | ... BA61: =365/BA63 -> 3.651205
B62: Ave Days Receivable | C62: =AVERAGE(B13,C13)/(+'Earnings Model'!G10)*91 -> #DIV/0! | D62: =AVERAGE(C13,D13)/(+'Earnings Model'!H10)*91 -> #DIV/0! | E62: =AVERAGE(D13,E13)/(+'Earnings Model'!I10)*91 -> #DIV/0! | F62: =AVERAGE(E13,F13)/(+'Earnings Model'!J10)*91 -> #DIV/0! | G62: =AVERAGE(F13,G13)/(+'Earnings Model'!K10)*91 -> #DIV/0! | H62: =AVERAGE(G13,H13)/(+'Earnings Model'!L10)*91 -> #DIV/0! | I62: =AVERAGE(H13,I13)/(+'Earnings Model'!M10)*91 -> #DIV/0! | J62: =AVERAGE(I13,J13)/(+'Earnings Model'!N10)*91 -> #DIV/0! | ... L62: =AVERAGE(K13,L13)/(+'Earnings Model'!P10)*91 -> 27.111011 | N62: =AVERAGE(M13,N13)/(+'Earnings Model'!R10)*91 -> 38.813986 | O62: =AVERAGE(N13,O13)/(+'Earnings Model'!S10)*91 -> 47.74255 | P62: =AVERAGE(O13,P13)/(+'Earnings Model'!T10)*91 -> 28.371033 | Q62: =AVERAGE(P13,Q13)/(+'Earnings Model'!U10)*91 -> 22.933297 | R62: =AVERAGE(Q13,R13)/(+'Earnings Model'!V10)*91 -> 29.113351 | S62: =AVERAGE(R13,S13)/(+'Earnings Model'!W10)*91 -> 26.621219 | T62: =AVERAGE(S13,T13)/(+'Earnings Model'!X10)*91 -> 29.22448 | U62: =AVERAGE(T13,U13)/(+'Earnings Model'!Y10)*91 -> 28.762033 | ... AM62: =AVERAGE(AL13,AM13)/(+'Earnings Model'!AQ10)*91 -> 42.280811 | AP62: =AVERAGE(AO13,AP13)/(+'Earnings Model'!BH10)*365 -> 26.472063 | AQ62: =AVERAGE(AP13,AQ13)/(+'Earnings Model'!BI10)*365 -> 37.421396 | AR62: =AVERAGE(AQ13,AR13)/(+'Earnings Model'!BJ10)*365 -> 39.17457 | AS62: =AVERAGE(AR13,AS13)/(+'Earnings Model'!BK10)*365 -> 21.94783 | AT62: =AVERAGE(AS13,AT13)/(+'Earnings Model'!BL10)*365 -> 18.512444 | AU62: =AVERAGE(AT13,AU13)/(+'Earnings Model'!BM10)*365 -> 24.590644 | AV62: =AVERAGE(AU13,AV13)/(+'Earnings Model'!BN10)*365 -> 49.23378 | AW62: =AVERAGE(AV13,AW13)/(+'Earnings Model'!BO10)*365 -> 34.206221 | AX62: =+AW62 -> 34.206221 | AY62: =+AX62 -> 34.206221 | AZ62: =+AY62 -> 34.206221 | BA62: =+AZ62 -> 34.206221
B63: Ave Days of Inventory | C63: =AVERAGE(B14,C14)/+'Earnings Model'!G14*91 -> #DIV/0! | D63: =AVERAGE(C14,D14)/+'Earnings Model'!H14*91 -> #DIV/0! | E63: =AVERAGE(D14,E14)/+'Earnings Model'!I14*91 -> #DIV/0! | F63: =AVERAGE(E14,F14)/+'Earnings Model'!J14*91 -> #DIV/0! | G63: =AVERAGE(F14,G14)/+'Earnings Model'!K14*91 -> #DIV/0! | H63: =AVERAGE(G14,H14)/+'Earnings Model'!L14*91 -> #DIV/0! | I63: =AVERAGE(H14,I14)/+'Earnings Model'!M14*91 -> #DIV/0! | J63: =AVERAGE(I14,J14)/+'Earnings Model'!N14*91 -> #DIV/0! | ... L63: =AVERAGE(K14,L14)/+'Earnings Model'!P14*91 -> 56.978389 | N63: =AVERAGE(M14,N14)/+'Earnings Model'!R14*91 -> 78.619935 | O63: =AVERAGE(N14,O14)/+'Earnings Model'!S14*91 -> 113.71548 | P63: =AVERAGE(O14,P14)/+'Earnings Model'!T14*91 -> 100.01704 | Q63: =AVERAGE(P14,Q14)/+'Earnings Model'!U14*91 -> 96.242463 | R63: =AVERAGE(Q14,R14)/+'Earnings Model'!V14*91 -> 152.92117 | S63: =AVERAGE(R14,S14)/+'Earnings Model'!W14*91 -> 161.42908 | T63: =AVERAGE(S14,T14)/+'Earnings Model'!X14*91 -> 163.0116 | U63: =AVERAGE(T14,U14)/+'Earnings Model'!Y14*91 -> 130.70031 | ... AM63: =AVERAGE(AL14,AM14)/+'Earnings Model'!AQ14*91 -> 159.25259 | AP63: =AVERAGE(AO14,AP14)/+'Earnings Model'!BH14*365 -> 124.20696 | AQ63: =AVERAGE(AP14,AQ14)/+'Earnings Model'!BI14*365 -> 89.247814 | AR63: =AVERAGE(AQ14,AR14)/+'Earnings Model'!BJ14*365 -> 111.91142 | AS63: =AVERAGE(AR14,AS14)/+'Earnings Model'!BK14*365 -> 123.42462 | AT63: =AVERAGE(AS14,AT14)/+'Earnings Model'!BL14*365 -> 77.082346 | AU63: =AVERAGE(AT14,AU14)/+'Earnings Model'!BM14*365 -> 103.34568 | AV63: =AVERAGE(AU14,AV14)/+'Earnings Model'!BN14*365 -> 237.21856 | AW63: =AVERAGE(AV14,AW14)/+'Earnings Model'!BO14*365 -> 99.966996 | AX63: =+AW63 -> 99.966996 | AY63: =+AX63 -> 99.966996 | AZ63: =+AY63 -> 99.966996 | BA63: =+AZ63 -> 99.966996
B64: Ave Days Accounts Payable | C64: =AVERAGE(C28,B28)/'Earnings Model'!G14*91 -> #DIV/0! | D64: =AVERAGE(D28,C28)/'Earnings Model'!H14*91 -> #DIV/0! | E64: =AVERAGE(E28,D28)/'Earnings Model'!I14*91 -> #DIV/0! | F64: =AVERAGE(F28,E28)/'Earnings Model'!J14*91 -> #DIV/0! | G64: =AVERAGE(G28,F28)/'Earnings Model'!K14*91 -> #DIV/0! | H64: =AVERAGE(H28,G28)/'Earnings Model'!L14*91 -> #DIV/0! | I64: =AVERAGE(I28,H28)/'Earnings Model'!M14*91 -> #DIV/0! | J64: =AVERAGE(J28,I28)/'Earnings Model'!N14*91 -> #DIV/0! | ... L64: =AVERAGE(L28,K28)/'Earnings Model'!P14*91 -> 35.118835 | N64: =AVERAGE(N28,M28)/'Earnings Model'!R14*91 -> 67.67362 | O64: =AVERAGE(O28,N28)/'Earnings Model'!S14*91 -> 77.638233 | P64: =AVERAGE(P28,O28)/'Earnings Model'!T14*91 -> 70.098415 | Q64: =AVERAGE(Q28,P28)/'Earnings Model'!U14*91 -> 71.855988 | R64: =AVERAGE(R28,Q28)/'Earnings Model'!V14*91 -> 80.891821 | S64: =AVERAGE(S28,R28)/'Earnings Model'!W14*91 -> 68.942038 | T64: =AVERAGE(T28,S28)/'Earnings Model'!X14*91 -> 82.891026 | U64: =AVERAGE(U28,T28)/'Earnings Model'!Y14*91 -> 86.798975 | ... AM64: =AVERAGE(AM28,AL28)/'Earnings Model'!AQ14*91 -> 48.306128 | AP64: =AVERAGE(AP28,AO28)/'Earnings Model'!BH14*365 -> 70.168679 | AQ64: =AVERAGE(AQ28,AP28)/'Earnings Model'!BI14*365 -> 64.045644 | AR64: =AVERAGE(AR28,AQ28)/'Earnings Model'!BJ14*365 -> 66.817989 | AS64: =AVERAGE(AS28,AR28)/'Earnings Model'!BK14*365 -> 63.67666 | AT64: =AVERAGE(AT28,AS28)/'Earnings Model'!BL14*365 -> 40.137331 | AU64: =AVERAGE(AU28,AT28)/'Earnings Model'!BM14*365 -> 37.476515 | AV64: =AVERAGE(AV28,AU28)/'Earnings Model'!BN14*365 -> 63.788609 | AW64: =AVERAGE(AW28,AV28)/'Earnings Model'!BO14*365 -> 40.997294 | AX64: =+AW64 -> 40.997294 | AY64: =+AX64 -> 40.997294 | AZ64: =+AY64 -> 40.997294 | BA64: =+AZ64 -> 40.997294
B66: Revenues Per Employee (000)
A68: Source: Company reports.
A72: Number of Employees
B79: Shareholders Equity statement
B80: opening Balance | AP80: =AO87 -> 883.024 | AQ80: =AP87 -> 1187.007 | AR80: =AQ87 -> 3615.749 | AS80: =AR87 -> 7329.724 | AT80: =AS87 -> 8070.251 | AU80: =AT87 -> 8390.699 | AV80: =AU87 -> 9927.255 | AW80: =AV87 -> 10206.619 | ... BA80: =AZ87 -> 30186.271
B81: Issuance of Capital | AO81: =+'Cash Flow'!E35 -> 4524.383 | AP81: =AP35-AO35 -> 0 | AQ81: =AQ35-AP35 -> 259.801 | AR81: =AR35-AQ35 -> 112.981 | AS81: =AS35-AR35 -> 0 | AT81: =AT35-AS35 -> 1.493 | AU81: =AU35-AT35 -> 2.761 | AV81: =AV35-AU35 -> 4.672 | AW81: =AW35-AV35 -> 6.049 | ... BA81: =BA35-AZ35 -> 0
B82: Net Income | AO82: =+'Earnings Model'!BG57 -> 92.804 | AP82: =+'Earnings Model'!BH57 -> 346.916 | AQ82: =+'Earnings Model'!BI57 -> 736.878 | AR82: =+'Earnings Model'!BJ57 -> 932.858 | AS82: =+'Earnings Model'!BK57 -> 1103.7235 | AT82: =+'Earnings Model'!BL57 -> 829.138 | AU82: =+'Earnings Model'!BM57 -> 1299.378 | AV82: =+'Earnings Model'!BN57 -> 450.91 | ... BA82: =+'Earnings Model'!BS57 -> 10752.284
B83: Dividend | AO83: ='Cash Flow'!E36 -> 0 | AP83: ='Cash Flow'!F36 -> 0 | AQ83: ='Cash Flow'!G36 -> -298.271 | AR83: ='Cash Flow'!H36 -> -233.871 | AS83: ='Cash Flow'!I36 -> 0 | AT83: ='Cash Flow'!J36 -> -339.309 | AU83: ='Cash Flow'!K36 -> 0 | AV83: ='Cash Flow'!L36 -> -341.402 | ... BA83: ='Cash Flow'!Q36 -> 0 | BI83: 284.8217 | BJ83: 212.9101 | BK83: 0
B84: Bonus to Directors/employees | BI84: =+SUM(BI85,BI93) -> 558.3267 | BJ84: =+SUM(BJ85,BJ93) -> 934.668 | BK84: =+SUM(BK85,BK93) -> 1748.6526
B85: changes in Reserves | C85: Memory interface | AO85: =AO87-SUM(AO80:AO84) -> -3734.163 | AP85: =AP87-SUM(AP80:AP84) -> -42.933 | AQ85: =AQ87-SUM(AQ80:AQ84) -> 1730.334 | AR85: =AR87-SUM(AR80:AR84) -> 2902.007 | AS85: =AS87-SUM(AS80:AS84) -> -363.19649 | AT85: =AT87-SUM(AT80:AT84) -> -170.874 | AU85: =AU87-SUM(AU80:AU84) -> 234.417 | AV85: =AV87-SUM(AV80:AV84) -> 165.184 | ... BA85: =BA87-SUM(BA80:BA84) -> 0 | BI85: 558.3267 | BJ85: 934.668 | BK85: 1748.6526
B87: Closing Balance | AO87: =AO40 -> 883.024 | AP87: =AP40 -> 1187.007 | AQ87: =AQ40 -> 3615.749 | AR87: =AR40 -> 7329.724 | AS87: =AS40 -> 8070.251 | AT87: =AT40 -> 8390.699 | AU87: =AU40 -> 9927.255 | AV87: =AV40 -> 10206.619 | ... BA87: =BA40 -> 40938.555
B89: Check | AO89: =AO87-AO80 -> 883.024 | AP89: =AP87-AP80 -> 303.983 | AQ89: =AQ87-AQ80 -> 2428.742 | AR89: =AR87-AR80 -> 3713.975 | AS89: =AS87-AS80 -> 740.527 | AT89: =AT87-AT80 -> 320.448 | AU89: =AU87-AU80 -> 1536.556 | AV89: =AV87-AV80 -> 279.364 | ... BA89: =BA87-BA80 -> 10752.284
B92: Change in Accumulated Other Comprehensive Income
C93: Others high speed interface | BI93: 0 | BJ93: 0 | BK93: 0
BI94: 0 | BJ94: 7.5964 | BK94: 9.012
BI95: =+BI96-SUM(BI83,BI84,BI94) -> -843.1484 | BJ95: =+BJ96-SUM(BJ83,BJ84,BJ94) -> -1155.1745 | BK95: =+BK96-SUM(BK83,BK84,BK94) -> -1757.6646
BI96: =+BI10 -> 0 | BJ96: =+BJ10 -> 0 | BK96: =+BK10 -> 0
B337: English

Sheet Cash Flow
A2: ='Earnings Model'!A1 -> Montage Technology (688008.SS, 6809.HK)
A3: Cash Flow Statement
A5: ($ Millions, Except Per-Share Data; Fiscal Year Ends December)
A9: Rmb$ in million | E9: 2016 | F9: 2017 | G9: 2018 | H9: 2019 | I9: 2020 | J9: 2021 | K9: 2022 | L9: 2023 | M9: 2024 | N9: 2025 | O9: 2026E | P9: 2027E | Q9: 2028E
A11: Cash flows from Operating Activities:
B12: Net Income | E12: ='Earnings Model'!BG57 -> 92.804 | F12: ='Earnings Model'!BH57 -> 346.916 | G12: ='Earnings Model'!BI57 -> 736.878 | H12: ='Earnings Model'!BJ57 -> 932.858 | I12: ='Earnings Model'!BK57 -> 1103.7235 | J12: ='Earnings Model'!BL57 -> 829.138 | K12: ='Earnings Model'!BM57 -> 1299.378 | L12: ='Earnings Model'!BN57 -> 450.91 | ... Q12: ='Earnings Model'!BS57 -> 10752.284
B13: Depreciation | E13: =-'Balance Sheet'!AO19+'Balance Sheet'!AH19 -> 30.332 | F13: =-'Balance Sheet'!AP19+'Balance Sheet'!AO19 -> -15.72 | G13: =-'Balance Sheet'!AQ19+'Balance Sheet'!AP19 -> 6.115 | H13: =-'Balance Sheet'!AR19+'Balance Sheet'!AQ19 -> 9.388 | I13: =-'Balance Sheet'!AS19+'Balance Sheet'!AR19 -> 18.663 | J13: =-'Balance Sheet'!AT19+'Balance Sheet'!AS19 -> 18.446 | K13: =-'Balance Sheet'!AU19+'Balance Sheet'!AT19 -> 22.204 | L13: =-'Balance Sheet'!AV19+'Balance Sheet'!AU19 -> 51.215 | M13: =-'Balance Sheet'!AW19+'Balance Sheet'!AV19 -> 67.399 | N13: =-'Balance Sheet'!AX19+'Balance Sheet'!AW19 -> 81.691 | O13: =+N13+5 -> 86.691 | P13: =+O13+5 -> 91.691 | Q13: =+P13+5 -> 96.691
B14: Amortization | F14: -1.215 | G14: 14.042 | H14: 17.847 | I14: 11.804225 | J14: 9.287 | K14: 12.476 | L14: 22.83 | M14: 22.83 | N14: 22.83 | O14: =N14+5 -> 27.83 | P14: =O14+5 -> 32.83 | Q14: =P14+5 -> 37.83
B15: Gain on disposal of PPE | E15: 0 | F15: -56.81 | G15: 0 | H15: 0
B16: Change in working capital | E16: =SUM(E17:E21) -> 0 | F16: =SUM(F17:F21) -> -66.667 | G16: =SUM(G17:G21) -> 491.043 | H16: =SUM(H17:H21) -> -61.671449 | I16: =SUM(I17:I21) -> -36.134551 | J16: =SUM(J17:J21) -> -241.945 | K16: =SUM(K17:K21) -> -197.253 | L16: =SUM(L17:L21) -> 58.409 | ... Q16: =SUM(Q17:Q21) -> -756.16628
B17: (Increase)/Decrease in Accounts Receivable | F17: ='Balance Sheet'!AO13-'Balance Sheet'!AP13 -> -60.462 | G17: ='Balance Sheet'!AP13-'Balance Sheet'!AQ13 -> -121.891 | H17: ='Balance Sheet'!AQ13-'Balance Sheet'!AR13 -> 109.28418 | I17: ='Balance Sheet'!AR13-'Balance Sheet'!AS13 -> 44.411815 | J17: ='Balance Sheet'!AS13-'Balance Sheet'!AT13 -> -84.98 | K17: ='Balance Sheet'!AT13-'Balance Sheet'!AU13 -> -149.946 | L17: ='Balance Sheet'!AU13-'Balance Sheet'!AV13 -> 28.125 | M17: ='Balance Sheet'!AV13-'Balance Sheet'!AW13 -> -93.538 | ... Q17: ='Balance Sheet'!AZ13-'Balance Sheet'!BA13 -> -523.9454
B18: (Increase)/Decrease in Inventories | F18: ='Balance Sheet'!AO14-'Balance Sheet'!AP14 -> 123.556 | G18: ='Balance Sheet'!AP14-'Balance Sheet'!AQ14 -> 11.839 | H18: ='Balance Sheet'!AQ14-'Balance Sheet'!AR14 -> -36.131 | I18: ='Balance Sheet'!AR14-'Balance Sheet'!AS14 -> -29.737 | J18: ='Balance Sheet'!AS14-'Balance Sheet'!AT14 -> -188.75 | K18: ='Balance Sheet'!AT14-'Balance Sheet'!AU14 -> -363.141 | L18: ='Balance Sheet'!AU14-'Balance Sheet'!AV14 -> 256.047 | M18: ='Balance Sheet'!AV14-'Balance Sheet'!AW14 -> 130.19 | ... Q18: ='Balance Sheet'!AZ14-'Balance Sheet'!BA14 -> -393.66697
B19: (Increase)/Decrease in Other Current Assets | F19: ='Balance Sheet'!AO15-'Balance Sheet'!AP15 -> -177.387 | G19: ='Balance Sheet'!AP15-'Balance Sheet'!AQ15 -> 441.929 | H19: ='Balance Sheet'!AQ15-'Balance Sheet'!AR15 -> 12.486366 | I19: ='Balance Sheet'!AR15-'Balance Sheet'!AS15 -> -7.5283658 | J19: ='Balance Sheet'!AS15-'Balance Sheet'!AT15 -> -169.08 | K19: ='Balance Sheet'!AT15-'Balance Sheet'!AU15 -> 113.702 | L19: ='Balance Sheet'!AU15-'Balance Sheet'!AV15 -> 22.493 | M19: ='Balance Sheet'!AV15-'Balance Sheet'!AW15 -> -1248.519 | ... Q19: ='Balance Sheet'!AZ15-'Balance Sheet'!BA15 -> 0
B20: Increase/(Decrease) in Accounts Payable | F20: ='Balance Sheet'!AP28-'Balance Sheet'!AO28 -> -4.897 | G20: ='Balance Sheet'!AQ28-'Balance Sheet'!AP28 -> -32.935 | H20: ='Balance Sheet'!AR28-'Balance Sheet'!AQ28 -> 16.916 | I20: ='Balance Sheet'!AS28-'Balance Sheet'!AR28 -> -5.45 | J20: ='Balance Sheet'!AT28-'Balance Sheet'!AS28 -> 120.863 | K20: ='Balance Sheet'!AU28-'Balance Sheet'!AT28 -> -9.541 | L20: ='Balance Sheet'!AV28-'Balance Sheet'!AU28 -> -66.051 | M20: ='Balance Sheet'!AW28-'Balance Sheet'!AV28 -> 80.039 | ... Q20: ='Balance Sheet'!BA28-'Balance Sheet'!AZ28 -> 161.44609
B21: Increase/(Decrease) in Other Current Liabilities | F21: ='Balance Sheet'!AP29-'Balance Sheet'!AO29 -> 52.523 | G21: ='Balance Sheet'!AQ29-'Balance Sheet'!AP29 -> 192.101 | H21: ='Balance Sheet'!AR29-'Balance Sheet'!AQ29 -> -164.227 | I21: ='Balance Sheet'!AS29-'Balance Sheet'!AR29 -> -37.831 | J21: ='Balance Sheet'!AT29-'Balance Sheet'!AS29 -> 80.002 | K21: ='Balance Sheet'!AU29-'Balance Sheet'!AT29 -> 211.673 | L21: ='Balance Sheet'!AV29-'Balance Sheet'!AU29 -> -182.205 | M21: ='Balance Sheet'!AW29-'Balance Sheet'!AV29 -> 208.666 | ... Q21: ='Balance Sheet'!BA29-'Balance Sheet'!AZ29 -> 0
B22: Others | E22: =E23-SUM(E12:E16) -> 263.949 | F22: =F23-SUM(F12:F16) -> 20.327 | G22: =G23-SUM(G12:G16) -> -278.931 | H22: =H23-SUM(H12:H16) -> -29.458551 | I22: =I23-SUM(I12:I16) -> -97.944596 | J22: =J23-SUM(J12:J16) -> 65.488535 | K22: =K23-SUM(K12:K16) -> -447.97 | L22: =L23-SUM(L12:L16) -> 147.886 | ... N22: =N23-SUM(N12:N16) -> 1278.968
D23: Net Cash Provided by Operating Activities | E23: 387.085 | F23: 226.831 | G23: 969.147 | H23: 868.963 | I23: 1000.1116 | J23: 680.41453 | K23: 688.835 | L23: 731.25 | M23: 1691.322 | N23: 2022.021 | O23: =SUM(O12:O16,O22) -> 3877.5637 | P23: =SUM(P12:P16,P22) -> 6674.9791 | Q23: =SUM(Q12:Q16,Q22) -> 10130.639
A25: Cash Flows from Investing Activities:
B26: Increase in marketable securities | F26: ='Balance Sheet'!AP11-'Balance Sheet'!AO11 -> 0 | G26: ='Balance Sheet'!AQ11-'Balance Sheet'!AP11 -> 0 | H26: ='Balance Sheet'!AR11-'Balance Sheet'!AQ11 -> 100.78082 | I26: ='Balance Sheet'!AS11-'Balance Sheet'!AR11 -> 770.61918 | J26: ='Balance Sheet'!AT11-'Balance Sheet'!AS11 -> 690.753 | K26: ='Balance Sheet'!AU11-'Balance Sheet'!AT11 -> 47.937 | L26: ='Balance Sheet'!AV11-'Balance Sheet'!AU11 -> 93.177 | M26: ='Balance Sheet'!AW11-'Balance Sheet'!AV11 -> -26.461 | N26: ='Balance Sheet'!AX11-'Balance Sheet'!AW11 -> -164.36
B27: Purchase of long-term investment | F27: =-('Balance Sheet'!AP17-'Balance Sheet'!AO17) -> 0 | G27: ='Balance Sheet'!AP17-'Balance Sheet'!AQ17 -> 0 | H27: ='Balance Sheet'!AQ17-'Balance Sheet'!AR17 -> 0 | I27: ='Balance Sheet'!AR17-'Balance Sheet'!AS17 -> -72.737 | J27: ='Balance Sheet'!AS17-'Balance Sheet'!AT17 -> 4.827 | K27: ='Balance Sheet'!AT17-'Balance Sheet'!AU17 -> 3.561 | L27: ='Balance Sheet'!AU17-'Balance Sheet'!AV17 -> -6.365 | M27: ='Balance Sheet'!AV17-'Balance Sheet'!AW17 -> -38.511 | N27: ='Balance Sheet'!AW17-'Balance Sheet'!AX17 -> 17.265
B28: Purchase of Property, plant & Equipment | E28: -4.613 | F28: -57.635 | G28: -17.894 | H28: -21.57 | I28: -439.33 | J28: -153.468 | K28: -226.86 | L28: -423.987 | M28: -379.122 | N28: -265.829 | O28: =-O13+'Balance Sheet'!AX20-'Balance Sheet'!AY20-O14 -> -134.521 | P28: =-P13+'Balance Sheet'!AY20-'Balance Sheet'!AZ20-P14 -> -144.521 | Q28: =-Q13+'Balance Sheet'!AZ20-'Balance Sheet'!BA20-Q14 -> -154.521
B29: Others | E29: =E30-E26-E27-E28 -> -218.059 | F29: =F30-F26-F27-F28 -> 95.351 | G29: =G30-G26-G27-G28 -> -82.031 | H29: =H30-H26-H27-H28 -> -2088.0598 | I29: =I30-I26-I27-I28 -> -602.3207 | J29: =J30-J26-J27-J28 -> -473.204 | K29: =K30-K26-K27-K28 -> 238.807 | L29: =L30-L26-L27-L28 -> -237.066 | ... N29: =N30-N26-N27-N28 -> 1263.236 | O29: ='Balance Sheet'!AX21-'Balance Sheet'!AY21 -> 0 | P29: ='Balance Sheet'!AY21-'Balance Sheet'!AZ21 -> 0 | Q29: ='Balance Sheet'!AZ21-'Balance Sheet'!BA21 -> 0
D30: Net Cash Used by Investing Activities | E30: -222.672 | F30: 37.716 | G30: -99.925 | H30: -2008.849 | I30: -343.76852 | J30: 68.908 | K30: 63.445 | L30: -574.241 | M30: -443.474 | N30: 850.312 | O30: =SUM(O26:O29) -> -134.521 | P30: =SUM(P26:P29) -> -144.521 | Q30: =SUM(Q26:Q29) -> -154.521
A32: Cash Flows from Financing Activities:
B33: Increase in S/T debt | F33: ='Balance Sheet'!AP27-'Balance Sheet'!AO27 -> 0 | G33: ='Balance Sheet'!AQ27-'Balance Sheet'!AP27 -> 0 | H33: ='Balance Sheet'!AR27-'Balance Sheet'!AQ27 -> 0 | I33: ='Balance Sheet'!AS27-'Balance Sheet'!AR27 -> 0 | J33: ='Balance Sheet'!AT27-'Balance Sheet'!AS27 -> 0 | K33: ='Balance Sheet'!AU27-'Balance Sheet'!AT27 -> 0 | L33: ='Balance Sheet'!AV27-'Balance Sheet'!AU27 -> 0 | M33: ='Balance Sheet'!AW27-'Balance Sheet'!AV27 -> 0 | N33: ='Balance Sheet'!AX27-'Balance Sheet'!AW27 -> 0 | O33: 0 | P33: 0 | Q33: 0
B34: Increase in L/T debt | F34: ='Balance Sheet'!AP31-'Balance Sheet'!AO31 -> 0 | G34: ='Balance Sheet'!AQ31-'Balance Sheet'!AP31 -> 0 | H34: ='Balance Sheet'!AR31-'Balance Sheet'!AQ31 -> 0 | I34: ='Balance Sheet'!AS31-'Balance Sheet'!AR31 -> 0 | J34: ='Balance Sheet'!AT31-'Balance Sheet'!AS31 -> 0 | K34: ='Balance Sheet'!AU31-'Balance Sheet'!AT31 -> 0 | L34: ='Balance Sheet'!AV31-'Balance Sheet'!AU31 -> 0 | M34: ='Balance Sheet'!AW31-'Balance Sheet'!AV31 -> 0 | N34: ='Balance Sheet'!AX31-'Balance Sheet'!AW31 -> 0 | O34: 0 | P34: 0 | Q34: 0
B35: Equity Financing | E35: 4524.383 | F35: 0 | G35: 1932.069 | H35: 3020.58 | I35: 0 | J35: 36.791 | K35: 82.331 | L35: 116.673 | M35: 194.345 | N35: 99.595 | O35: 6300
B36: Dividend Paid | E36: 0 | F36: 0 | G36: -298.271 | H36: -233.871 | I36: 0 | J36: -339.309 | K36: 0 | L36: -341.402 | M36: -338.193 | N36: -669.996 | O36: =-N53*N58 -> 0 | P36: =-O53*O58 -> 0 | Q36: =-P53*P58 -> 0
B37: Others | E37: =E38-SUM(E33:E36) -> -4553.91 | F37: =F38-SUM(F33:F36) -> 0 | G37: =G38-SUM(G33:G36) -> 58.441 | H37: =H38-SUM(H33:H36) -> -97.18 | I37: =I38-SUM(I33:I36) -> -339.094 | J37: =J38-SUM(J33:J36) -> -306.62 | K37: =K38-SUM(K33:K36) -> -352.421 | L37: =L38-SUM(L33:L36) -> -147.381 | ... N37: =N38-SUM(N33:N36) -> -458.663
D38: Net Cash Used by Financing Activities | E38: -29.527 | F38: 0 | G38: 1692.239 | H38: 2689.529 | I38: -339.094 | J38: -609.138 | K38: -270.09 | L38: -372.11 | M38: -276.938 | N38: -1029.064 | O38: =SUM(O33:O37) -> 6300 | P38: =SUM(P33:P37) -> 0 | Q38: =SUM(Q33:Q37) -> 0
D40: Effect of Exchange Rate Change | E40: 25.101 | F40: -31.765 | G40: 76.11 | H40: 48.112 | I40: -234.499 | J40: -60.904 | K40: 267.619 | L40: 47.23 | M40: 62.142 | N40: -126.127
D41: Other changes in cash equivalents | E41: =+E46-E40-E38-E30-E23-E42 -> 25.101 | F41: =+F46-F40-F38-F30-F23-F42 -> 0.653 | G41: =+G46-G40-G38-G30-G23-G42 -> 354.634 | H41: =+H46-H40-H38-H30-H23-H42 -> 1979.3177 | I41: =+I46-I40-I38-I30-I23-I42 -> -1865.2218 | J41: =+'Balance Sheet'!AT10-(I46+J43) -> -449.53453 | K41: ='Balance Sheet'!AU10-(K42+K43) -> 16.291 | L41: ='Balance Sheet'!AV10-(L42+L43) -> 41.008 | M41: ='Balance Sheet'!AW10-(M42+M43) -> -1053.281 | N41: ='Balance Sheet'!AX10-(N42+N43) -> -1588.854
C42: Cash and Cash Equiv. at Beginning of Period | E42: =E46-E44-E40-E43 -> 269.263 | F42: =E46 -> 454.351 | G42: =F46 -> 687.786 | H42: =G46 -> 3679.991 | I42: =+H46 -> 7257.0637 | J42: 5004.6612 | K42: =+J46 -> 5104.338 | L42: =+K46 -> 5870.438 | M42: =+L46 -> 5743.575 | N42: =+M46 -> 5723.346 | O42: =+N46 -> 5851.634 | P42: =+O46 -> 15894.677 | Q42: =+P46 -> 22425.135
C43: Increase/Decrease in Cash and Cash Equiv. | E43: =SUM(E38,E30,E23,E40) -> 159.987 | F43: =SUM(F38,F30,F23,F40) -> 232.782 | G43: =SUM(G38,G30,G23,G40) -> 2637.571 | H43: =SUM(H38,H30,H23,H40) -> 1597.755 | I43: =SUM(I38,I30,I23,I40) -> 82.750051 | J43: =SUM(J38,J30,J23,J40) -> 79.280535 | K43: =SUM(K38,K30,K23,K40) -> 749.809 | L43: =SUM(L38,L30,L23,L40) -> -167.871 | ... Q43: =SUM(Q38,Q30,Q23,Q40) -> 9976.1176
D44: Change in restricted Cash | F44: ='Balance Sheet'!AP12-'Balance Sheet'!AO12 -> 0 | G44: ='Balance Sheet'!AQ12-'Balance Sheet'!AP12 -> 0 | H44: ='Balance Sheet'!AR12-'Balance Sheet'!AQ12 -> 0 | I44: ='Balance Sheet'!AS12-'Balance Sheet'!AR12 -> 0 | J44: ='Balance Sheet'!AT12-'Balance Sheet'!AS12 -> 0 | K44: ='Balance Sheet'!AU12-'Balance Sheet'!AT12 -> 0 | L44: ='Balance Sheet'!AV12-'Balance Sheet'!AU12 -> 0 | M44: ='Balance Sheet'!AW12-'Balance Sheet'!AV12 -> 0 | ... Q44: ='Balance Sheet'!BA12-'Balance Sheet'!AZ12 -> 0
C45: Total Change in Cash and Cash Equiv. | E45: =E44+E43 -> 159.987 | F45: =F44+F43 -> 232.782 | G45: =G44+G43 -> 2637.571 | H45: =H44+H43 -> 1597.755 | I45: =I44+I43 -> 82.750051 | J45: =J44+J43 -> 79.280535 | K45: =K44+K43 -> 749.809 | L45: =L44+L43 -> -167.871 | ... Q45: =Q44+Q43 -> 9976.1176
C46: Cash and Cash Equiv. at End of Period | E46: ='Balance Sheet'!AO10 -> 454.351 | F46: ='Balance Sheet'!AP10 -> 687.786 | G46: ='Balance Sheet'!AQ10 -> 3679.991 | H46: ='Balance Sheet'!AR10 -> 7257.0637 | I46: ='Balance Sheet'!AS10 -> 5474.592 | J46: ='Balance Sheet'!AT10 -> 5104.338 | K46: =K42+K43+K44+K41 -> 5870.438 | L46: =L42+L43+L44+L41 -> 5743.575 | M46: =M42+M43+M44+M41 -> 5723.346 | N46: =N42+N43+N44+N41 -> 5851.634 | O46: =O42+O43+O44 -> 15894.677 | P46: =P42+P43+P44 -> 22425.135 | Q46: =Q42+Q43+Q44 -> 32401.252
E48: =+E46-'Balance Sheet'!AO10 -> 0 | F48: =+F46-'Balance Sheet'!AP10 -> 0 | G48: =+G46-'Balance Sheet'!AQ10 -> 0 | H48: =+H46-'Balance Sheet'!AR10 -> 0 | I48: =+I46-'Balance Sheet'!AS10 -> 0 | J48: =+J46-'Balance Sheet'!AT10 -> 0 | K48: =+K46-'Balance Sheet'!AU10 -> 0 | L48: =+L46-'Balance Sheet'!AV10 -> 0 | ... Q48: =+Q46-'Balance Sheet'!BA10 -> 0
I50: =+I36/I12 -> 0 | J50: =+J36/J12 -> -0.40923103 | K50: =+K36/K12 -> 0 | L50: =+L36/L12 -> -0.75714001
B53: Cash dividend per share
B54: Cash dividend per share
AK84: 284.8217 | AL84: 212.9101 | AM84: 0
AK85: =+SUM(AK86,AK94) -> 558.3267 | AL85: =+SUM(AL86,AL94) -> 934.668 | AM85: =+SUM(AM86,AM94) -> 1748.6526
C86: Memory interface | AK86: 558.3267 | AL86: 934.668 | AM86: 1748.6526
C94: Others high speed interface | AK94: 0 | AL94: 0 | AM94: 0
AK95: 0 | AL95: 7.5964 | AM95: 9.012
AK96: =+AK97-SUM(AK84,AK85,AK95) -> -843.1484 | AL96: =+AL97-SUM(AL84,AL85,AL95) -> -1155.1745 | AM96: =+AM97-SUM(AM84,AM85,AM95) -> -1757.6646
AK97: =+AK10 -> 0 | AL97: =+AL10 -> 0 | AM97: =+AM10 -> 0

Sheet IndexInformation
A1: MacroVersion | B1: 6.10
A2: PublishDate | B2: 07/16/26 09:42
A3: Discipline | B3: Research
A4: ResearchTopic | B4: Company
A5: DocType | B5: Model
A6: SubjectCode
A7: Description | B7: Montage Technology Co Ltd
A8: KeepVersions | B8: All
A9: Rating | B9: Overweight / Attractive
A10: CurrYearTotalRevenue*
A11: CurrYearEPS*
A12: NextYearTotalRevenue*
A13: NextYearEPS*
A14: FollowingYearTotalRevenue*
A15: FollowingYearEPS*
A16: 5YearGrowthRate
A17: UpdateReason | B17: Regular Update
A18: Authors | B18: MSA02MCM, MSA12108
A19: Tickers | B19: 688008.SS
A20: CUSIP
A21: RIC | B21: 688008.SS
A22: SEDOL | B22: BK7F3F3
A23: Current Stock Price | B23: 233.50
A24: Currency | B24: CNY
A25: PathName | B25: \\Msad\root\AP\APBO\TP\lib\er\data\Charlie Chan New\3. IC design\Montage Tech\Model\Montage Tech_Model_20260617 (publish).xlsm
A26: Distribution | B26: 0
A27: Deleted | B27: NO
A28: EmailAlert | B28: YES
A29: CurrQtrEPS
A30: CYEnd
A31: CQEnd
A32: CurrYearTotalRevenueActual*
A33: NextYearTotalRevenueActual*
A34: FollowingYearTotalRevenueActual*
A35: Multiplier | B35: 1000000
A36: TemplateRegion | B36: AsiaPacific
A37: ObjectType | B37: excel
A38: LanguageCode | B38: en-US
A39: SubmitterUserId | B39: ethjia
A40: IndustryId | B40: 1900000837
A41: TickerRegion | B41: 5
A42: AdditionalInstructions
A43: *Estimated
A44: OwnerTeam | B44: I888888929

Sheet ModPubIndex
A1: [BRO MSA]
A2: [DOCDAT 2026-07-16]
A3: [DOCTIME 09:42]
A4: [PSYM 688008.SS(Reuters) (None)]
A5: [COU China]
A6: [PRODUCT MODEL]
A7: [ANA MSA12108]
A8: [HL 688008.SS Model]
A9: [IND Technology]
A10: [EMAIL_ALERT YES]
A11: [PANA MSA02MCM]
A12: [DISCIPLINE Company]
A13: [SUPPRESSED NO]
