Workbook
Name A_ALL_000050.SZ: #REF!
Name A_ALL_000413.SZ: #REF!
Name A_ALL_000725.SZ: #REF!
Name A_ALL_002371.SZ: #REF!
Name A_ALL_002415.SZ: #REF!
Name A_ALL_002415.SZ_: #REF!
Name A_ALL_002456.SZ: #REF!
Name A_ALL_002876.SZ: #REF!
Name A_ALL_2018.HK: #REF!
Name A_ALL_2303.TW: '[1]2303.TW_Annotation_Sheet'!$A$1:$CD$384
Name A_ALL_2303.TW: #REF!
Name A_ALL_2324.TW: #REF!
Name A_ALL_300502.SZ: #REF!
Name A_ALL_4966.TWO: #REF!
Name A_ALL_600584.SS: #REF!
Name A_ALL_600699.SS: #REF!
Name A_ALL_603986.SS: #REF!
Name A_ALL_6415.TW: '[2]6415.TW_Annotation_Sheet'!$A$1:$BZ$286
Name A_ALL_6415.TW: #REF!
Name A_ALL_KEYWORDS_TYPE_Breakdown_EQTY_200004222: #REF!,#REF!
Name A_ALL_KEYWORDS_TYPE_Breakdown_EQTY_200004679: #REF!,#REF!
Name A_ALL_KEYWORDS_TYPE_Breakdown_EQTY_200008919: #REF!
Name A_ALL_KEYWORDS_TYPE_ScalarContributed_EQTY_200004222: #REF!,#REF!
Name A_ALL_KEYWORDS_TYPE_ScalarContributed_EQTY_200004679: #REF!,#REF!,#REF!,#REF!
Name A_ALL_KEYWORDS_TYPE_ScalarContributed_EQTY_200006786: #REF!,#REF!,#REF!,#REF!
Name A_ALL_KEYWORDS_TYPE_ScalarContributed_EQTY_200007666: #REF!,#REF!
Name A_ALL_KEYWORDS_TYPE_ScalarContributed_EQTY_200008919: #REF!,#REF!
Name A_ALL_KEYWORDS_TYPE_ScalarContributed_EQTY_200011172: #REF!,#REF!
Name A_ALL_KEYWORDS_TYPE_ScalarContributed_EQTY_200012735: #REF!,#REF!
Name A_ALL_KEYWORDS_TYPE_ScalarContributed_EQTY_200012909: #REF!,#REF!
Name A_ALL_KEYWORDS_TYPE_ScalarContributed_EQTY_200012913: #REF!,#REF!
Name A_ALL_KEYWORDS_TYPE_ScalarContributed_EQTY_200016087: #REF!,#REF!
Name A_ALL_KEYWORDS_TYPE_ScalarContributed_EQTY_200019451: #REF!,#REF!,#REF!
Name A_ALL_KEYWORDS_TYPE_ScalarContributed_EQTY_200019558: #REF!,#REF!
Name A_ALL_KEYWORDS_TYPE_ScalarContributed_EQTY_200019559: #REF!,#REF!
Name A_ALL_KEYWORDS_TYPE_ScalarContributed_ISSR_208001202: #REF!,#REF!
Name A_ALL_KEYWORDS_TYPE_ScalarContributed_ISSR_208001316: #REF!,#REF!
Name A_ALL_KEYWORDS_TYPE_ScalarContributed_ISSR_208002015: #REF!,#REF!
Name A_ALL_KEYWORDS_TYPE_ScalarContributed_ISSR_208003261: #REF!,#REF!
Name A_ALL_KEYWORDS_TYPE_ScalarContributed_ISSR_208007067: #REF!,#REF!
Name A_ALL_KEYWORDS_TYPE_ScalarContributed_ISSR_208010212: #REF!,#REF!
Name A_ALL_KEYWORDS_TYPE_ScalarContributed_ISSR_208015000: #REF!,#REF!
Name A_ALL_KEYWORDS_TYPE_ScalarContributed_ISSR_208019081: #REF!,#REF!
Name A_ALL_KEYWORDS_TYPE_ScalarContributed_ISSR_208019322: #REF!,#REF!
Name A_ALL_KEYWORDS_TYPE_ScalarContributed_ISSR_208021173: #REF!,#REF!
Name A_ALL_KEYWORDS_TYPE_ScalarContributed_ISSR_208021175: #REF!,#REF!
Name A_ALL_KEYWORDS_TYPE_Vector_EQTY_200004222: #REF!,#REF!,#REF!,#REF!,#REF!
Name A_ALL_KEYWORDS_TYPE_Vector_EQTY_200004679: #REF!,#REF!,#REF!,#REF!,#REF!
Name A_ALL_KEYWORDS_TYPE_Vector_EQTY_200006785: #REF!,#REF!,#REF!,#REF!,#REF!
Name A_ALL_KEYWORDS_TYPE_Vector_EQTY_200006786: #REF!,#REF!,#REF!,#REF!,#REF!,#REF!
Name A_ALL_KEYWORDS_TYPE_Vector_EQTY_200007666: #REF!,#REF!,#REF!,#REF!,#REF!
Name A_ALL_KEYWORDS_TYPE_Vector_EQTY_200008918: #REF!,#REF!,#REF!,#REF!,#REF!
Name A_ALL_KEYWORDS_TYPE_Vector_EQTY_200011172: #REF!,#REF!,#REF!,#REF!,#REF!
Name A_ALL_KEYWORDS_TYPE_Vector_EQTY_200012735: #REF!,#REF!,#REF!,#REF!,#REF!
Name A_ALL_KEYWORDS_TYPE_Vector_EQTY_200012909: #REF!,#REF!,#REF!,#REF!,#REF!
Name A_ALL_KEYWORDS_TYPE_Vector_EQTY_200012913: #REF!,#REF!,#REF!,#REF!,#REF!
Name A_ALL_KEYWORDS_TYPE_Vector_EQTY_200013283: #REF!,#REF!,#REF!,#REF!,#REF!
Name A_ALL_KEYWORDS_TYPE_Vector_EQTY_200016087: #REF!,#REF!,#REF!,#REF!,#REF!
Name A_ALL_KEYWORDS_TYPE_Vector_EQTY_200017468: #REF!,#REF!,#REF!,#REF!,#REF!
Name A_ALL_KEYWORDS_TYPE_Vector_EQTY_200018245: #REF!,#REF!,#REF!,#REF!,#REF!

Sheet Cover Page 
B4: Greater China Technology Team
B6: Eoptolink (300502.SZ)
B7: Rating | C7: Buy
B8: Target Price/ Target price period/ Upside/downside to target price | C8: 633/ 12 Month/ 24.1%
B9: M&A probability (1 = high, 3 = low) | C9: 3
B10: Market Cap (US$ mn) (price as of Jul 20, 2026): | C10: 105054.36
B11: Current shares outstanding (mn): | C11: =Model!BT56 -> 1391.5613
B12: Currency: | C12: CNY
B13: Current Publication Date: | C13: 46223
B14: Previous Publication Date: | C14: 46210
B16: Team Contacts:
B17: Primary Analyst
B18: Ting Song, ting.song@gs.com, +852 2978 6466 Goldman Sachs (Asia) L.L.C.
B19: Allen Chang, allen.k.chang@gs.com, +852 2978 2930 Goldman Sachs (Asia) L.L.C.
B20: Verena Jeng, verena.jeng@gs.com, +852 2978 1681 Goldman Sachs (Asia) L.L.C.

Sheet 300502.SZ_Exchange_Sheet 
A1: Issuer: Eoptolink | F1: 2011 | G1: 2012 | H1: 2013 | I1: 2014 | J1: 2015 | K1: 2016 | L1: 2017 | M1: 2018 | N1: 2019 | O1: 2020 | P1: 2021 | Q1: 2022 | R1: 2023 | S1: 2024 | T1: 2025 | U1: 2026 | V1: 2027 | W1: 2028 | Y1: 2015 Q1 | Z1: 2015 Q2 | AA1: 2015 Q3 | AB1: 2015 Q4 | AC1: 2016 Q1 | AD1: 2016 Q2 | AE1: 2016 Q3 | AF1: 2016 Q4 | AG1: 2017 Q1 | AH1: 2017 Q2 | AI1: 2017 Q3 | AJ1: 2017 Q4 | AK1: 2018 Q1 | AL1: 2018 Q2 | AM1: 2018 Q3 | AN1: 2018 Q4 | AO1: 2019 Q1 | AP1: 2019 Q2 | AQ1: 2019 Q3 | AR1: 2019 Q4 | AS1: 2020 Q1 | AT1: 2020 Q2 | AU1: 2020 Q3 | AV1: 2020 Q4 | AW1: 2021 Q1 | AX1: 2021 Q2 | AY1: 2021 Q3 | AZ1: 2021 Q4 | BA1: 2022 Q1 | BB1: 2022 Q2 | BC1: 2022 Q3 | BD1: 2022 Q4 | BE1: 2023 Q1 | BF1: 2023 Q2 | BG1: 2023 Q3 | BH1: 2023 Q4 | BI1: 2024 Q1 | BJ1: 2024 Q2 | BK1: 2024 Q3 | BL1: 2024 Q4 | BM1: 2025 Q1 | BN1: 2025 Q2 | BO1: 2025 Q3 | BP1: 2025 Q4 | BQ1: 2026 Q1 | BR1: 2026 Q2 | BS1: 2026 Q3 | BT1: 2026 Q4 | BU1: 2027 Q1 | BV1: 2027 Q2 | BW1: 2027 Q3 | BX1: 2027 Q4
A2: ISSUER ID: 208021942 | F2: Actual | G2: Actual | H2: Actual | I2: Actual | J2: Actual | K2: Actual | L2: Actual | M2: Actual | N2: Actual | O2: Actual | P2: Actual | Q2: Actual | R2: Actual | S2: Actual | T2: Actual | U2: Estimate | V2: Estimate | W2: Estimate | Y2: Actual | Z2: Actual | AA2: Actual | AB2: Actual | AC2: Actual | AD2: Actual | AE2: Actual | AF2: Actual | AG2: Actual | AH2: Actual | AI2: Actual | AJ2: Actual | AK2: Actual | AL2: Actual | AM2: Actual | AN2: Actual | AO2: Actual | AP2: Actual | AQ2: Actual | AR2: Actual | AS2: Actual | AT2: Actual | AU2: Actual | AV2: Actual | AW2: Actual | AX2: Actual | AY2: Actual | AZ2: Actual | BA2: Actual | BB2: Actual | BC2: Actual | BD2: Actual | BE2: Actual | BF2: Actual | BG2: Actual | BH2: Actual | BI2: Actual | BJ2: Actual | BK2: Actual | BL2: Actual | BM2: Actual | BN2: Actual | BO2: Actual | BP2: Actual | BQ2: Actual | BR2: Estimate | BS2: Estimate | BT2: Estimate | BU2: Estimate | BV2: Estimate | BW2: Estimate | BX2: Estimate
F3: 40908 | G3: 41274 | H3: 41639 | I3: 42004 | J3: 42369 | K3: 42735 | L3: 43100 | M3: 43465 | N3: 43830 | O3: 44196 | P3: 44561 | Q3: 44926 | R3: 45291 | S3: 45657 | T3: 46022 | U3: 46387 | V3: 46752 | W3: 47118 | Y3: 42094 | Z3: 42185 | AA3: 42277 | AB3: 42369 | AC3: 42460 | AD3: 42551 | AE3: 42643 | AF3: 42735 | AG3: 42825 | AH3: 42916 | AI3: 43008 | AJ3: 43100 | AK3: 43190 | AL3: 43281 | AM3: 43373 | AN3: 43465 | AO3: 43555 | AP3: 43646 | AQ3: 43738 | AR3: 43830 | AS3: 43921 | AT3: 44012 | AU3: 44104 | AV3: 44196 | AW3: 44286 | AX3: 44377 | AY3: 44469 | AZ3: 44561 | BA3: 44651 | BB3: 44742 | BC3: 44834 | BD3: 44926 | BE3: 45016 | BF3: 45107 | BG3: 45199 | BH3: 45291 | BI3: 45382 | BJ3: 45473 | BK3: 45565 | BL3: 45657 | BM3: 45747 | BN3: 45838 | BO3: 45930 | BP3: 46022 | BQ3: 46112 | BR3: 46203 | BS3: 46295 | BT3: 46387 | BU3: 46477 | BV3: 46568 | BW3: 46660 | BX3: 46752
A4: Issuer: Eoptolink
A5: Reference Data
B6: Issuer Name | C6: Issuer Name | E6: Eoptolink
B7: Reporting Currency | C7: CURRENCY_ISO | E7: CNY
A8: General Information
B9: M&A probability (1 = high, 3 = low) | C9: MA_PROB | E9: 3
A10: Income Statement
B11: Sales, net revenue | C11: SALES | D11: =E_CURRENCY_ISSR_208021942_REP -> CNY | F11: =[5]Model!E7 -> 304.92843 | G11: =[5]Model!F7 -> 347.56807 | H11: =[5]Model!G7 -> 461.049 | I11: =[5]Model!H7 -> 522.63427 | J11: =[5]Model!I7 -> 615.11958 | K11: =[5]Model!J7 -> 713.93165 | L11: =[5]Model!K7 -> 877.36536 | M11: =[5]Model!L7 -> 759.95028 | ... W11: =[5]Model!V7 -> 84975.376 | Y11: =[5]Model!AB7 -> 141.26116 | Z11: =[5]Model!AC7 -> 166.47504 | AA11: =[5]Model!AD7 -> 142.20005 | AB11: =[5]Model!AE7 -> 165.18332 | AC11: =[5]Model!AF7 -> 146.321 | AD11: =[5]Model!AG7 -> 192.79163 | AE11: =[5]Model!AH7 -> 170.51717 | AF11: =[5]Model!AI7 -> 204.30185 | ... BX11: =[5]Model!CA7 -> 20276.903
B12: Compensation & benfits expense | C12: PERSONNEL | D12: =E_CURRENCY_ISSR_208021942_REP -> CNY
B13: Cost of goods sold, COGS | C13: COST_GD_SD | D13: =E_CURRENCY_ISSR_208021942_REP -> CNY | F13: =-[5]Model!E10 -> -213.53676 | G13: =-[5]Model!F10 -> -234.62009 | H13: =-[5]Model!G10 -> -330.78362 | I13: =-[5]Model!H10 -> -363.06989 | J13: =-[5]Model!I10 -> -446.55322 | K13: =-[5]Model!J10 -> -525.653 | L13: =-[5]Model!K10 -> -666.78476 | M13: =-[5]Model!L10 -> -611.69329 | ... W13: =-[5]Model!V10 -> -43619.538 | Y13: =-[5]Model!AB10 -> -101.0667 | Z13: =-[5]Model!AC10 -> -121.38813 | AA13: =-[5]Model!AD10 -> -103.18521 | AB13: =-[5]Model!AE10 -> -120.91319 | AC13: =-[5]Model!AF10 -> -110.12175 | AD13: =-[5]Model!AG10 -> -143.06903 | AE13: =-[5]Model!AH10 -> -117.13324 | AF13: =-[5]Model!AI10 -> -155.32899 | ... BX13: =-[5]Model!CA10 -> -10233.746
B14: SG&A, selling, general and admin. expense | C14: SEL_GL_AD | D14: =E_CURRENCY_ISSR_208021942_REP -> CNY | F14: =-[5]Model!E16-[5]Model!E17-[5]Model!E18 -> -13.704189 | G14: =-[5]Model!F16-[5]Model!F17-[5]Model!F18 -> -19.558636 | H14: =-[5]Model!G16-[5]Model!G17-[5]Model!G18 -> -19.32508 | I14: =-[5]Model!H16-[5]Model!H17-[5]Model!H18 -> -30.516253 | J14: =-[5]Model!I16-[5]Model!I17-[5]Model!I18 -> -31.549274 | K14: =-[5]Model!J16-[5]Model!J17-[5]Model!J18 -> -35.348699 | L14: =-[5]Model!K16-[5]Model!K17-[5]Model!K18 -> -37.046046 | M14: =-[5]Model!L16-[5]Model!L17-[5]Model!L18 -> -52.506831 | ... W14: =-[5]Model!V16-[5]Model!V17-[5]Model!V18 -> -888.51887 | Y14: =-[5]Model!AB16-[5]Model!AB17-[5]Model!AB18 -> -5.6643154 | Z14: =-[5]Model!AC16-[5]Model!AC17-[5]Model!AC18 -> -8.0558268 | AA14: =-[5]Model!AD16-[5]Model!AD17-[5]Model!AD18 -> -7.9521598 | AB14: =-[5]Model!AE16-[5]Model!AE17-[5]Model!AE18 -> -9.8611696 | AC14: =-[5]Model!AF16-[5]Model!AF17-[5]Model!AF18 -> -5.7882392 | AD14: =-[5]Model!AG16-[5]Model!AG17-[5]Model!AG18 -> -7.7444157 | AE14: =-[5]Model!AH16-[5]Model!AH17-[5]Model!AH18 -> -10.190174 | AF14: =-[5]Model!AI16-[5]Model!AI17-[5]Model!AI18 -> -11.610822 | ... BX14: =-[5]Model!CA16-[5]Model!CA17-[5]Model!CA18 -> -182.94597
B15: Total operating expense | C15: OP_COST | D15: =E_CURRENCY_ISSR_208021942_REP -> CNY | F15: =F13+F14 -> -227.24095 | G15: =G13+G14 -> -254.17873 | H15: =H13+H14 -> -350.1087 | I15: =I13+I14 -> -393.58614 | J15: =J13+J14 -> -478.10249 | K15: =K13+K14 -> -561.0017 | L15: =L13+L14 -> -703.83081 | M15: =M13+M14 -> -664.20012 | ... W15: =W13+W14 -> -44508.057 | Y15: =Y13+Y14 -> -106.73101 | Z15: =Z13+Z14 -> -129.44395 | AA15: =AA13+AA14 -> -111.13737 | AB15: =AB13+AB14 -> -130.77436 | AC15: =AC13+AC14 -> -115.90998 | AD15: =AD13+AD14 -> -150.81344 | AE15: =AE13+AE14 -> -127.32341 | AF15: =AF13+AF14 -> -166.93981 | ... BX15: =BX13+BX14 -> -10416.692
B16: R&D expense | C16: RD_EXP | D16: =E_CURRENCY_ISSR_208021942_REP -> CNY | F16: =-[5]Model!E19 -> -10.77461 | G16: =-[5]Model!F19 -> -14.292519 | H16: =-[5]Model!G19 -> -16.201662 | I16: =-[5]Model!H19 -> -18.188965 | J16: =-[5]Model!I19 -> -23.420253 | K16: =-[5]Model!J19 -> -29.256149 | L16: =-[5]Model!K19 -> -44.921107 | M16: =-[5]Model!L19 -> -52.66467 | ... W16: =-[5]Model!V19 -> -984.4 | Y16: =-[5]Model!AB19 -> -5.38205 | Z16: =-[5]Model!AC19 -> -6.3426992 | AA16: =-[5]Model!AD19 -> -5.4178219 | AB16: =-[5]Model!AE19 -> -6.2934847 | AC16: =-[5]Model!AF19 -> -5.9991611 | AD16: =-[5]Model!AG19 -> -7.9044569 | AE16: =-[5]Model!AH19 -> -6.991204 | AF16: =-[5]Model!AI19 -> -8.3763757 | ... BX16: =-[5]Model!CA19 -> -332.5
B17: Other operating income/(expense) (incl. leases) | C17: OTH_OP_INC_EXP | D17: =E_CURRENCY_ISSR_208021942_REP -> CNY
B18: Total operating expense (incl. D&A) | C18: TOT_OPS_EXP_DDA | D18: =E_CURRENCY_ISSR_208021942_REP -> CNY | F18: =F15+F16 -> -238.01556 | G18: =G15+G16 -> -268.47125 | H18: =H15+H16 -> -366.31036 | I18: =I15+I16 -> -411.7751 | J18: =J15+J16 -> -501.52274 | K18: =K15+K16 -> -590.25785 | L18: =L15+L16 -> -748.75191 | M18: =M15+M16 -> -716.86479 | ... W18: =W15+W16 -> -45492.457 | Y18: =Y15+Y16 -> -112.11306 | Z18: =Z15+Z16 -> -135.78665 | AA18: =AA15+AA16 -> -116.55519 | AB18: =AB15+AB16 -> -137.06784 | AC18: =AC15+AC16 -> -121.90915 | AD18: =AD15+AD16 -> -158.7179 | AE18: =AE15+AE16 -> -134.31462 | AF18: =AF15+AF16 -> -175.31619 | ... BX18: =BX15+BX16 -> -10749.192
B19: Total operating expense (excl. D&A) | C19: TOT_OPS_EXP | D19: =E_CURRENCY_ISSR_208021942_REP -> CNY | F19: =F18-F21-F22 -> -235.09806 | G19: =G18-G21-G22 -> -265.56485 | H19: =H18-H21-H22 -> -360.81015 | I19: =I18-I21-I22 -> -399.38829 | J19: =J18-J21-J22 -> -485.87516 | K19: =K18-K21-K22 -> -565.94531 | L19: =L18-L21-L22 -> -701.46852 | M19: =M18-M21-M22 -> -662.95614 | ... W19: =W18-W21-W22 -> -44458.69 | Y19: =Y18-Y21-Y22 -> -108.46433 | Z19: =Z18-Z21-Z22 -> -132.13792 | AA19: =AA18-AA21-AA22 -> -112.90645 | AB19: =AB18-AB21-AB22 -> -133.41911 | AC19: =AC18-AC21-AC22 -> -118.26041 | AD19: =AD18-AD21-AD22 -> -155.06917 | AE19: =AE18-AE21-AE22 -> -125.81847 | AF19: =AF18-AF21-AF22 -> -166.82004 | ... BX19: =BX18-BX21-BX22 -> -10537.294
B20: EBITDA | C20: EBITDA_CALC | D20: =E_CURRENCY_ISSR_208021942_REP -> CNY | F20: =[5]Model!E46 -> 69.83037 | G20: =[5]Model!F46 -> 82.00322 | H20: =[5]Model!G46 -> 100.23885 | I20: =[5]Model!H46 -> 123.24598 | J20: =[5]Model!I46 -> 129.24441 | K20: =[5]Model!J46 -> 147.98634 | L20: =[5]Model!K46 -> 175.89684 | M20: =[5]Model!L46 -> 96.994142 | ... W20: =[5]Model!V46 -> 40516.685 | Y20: =[5]Model!AB46 -> 32.79683 | Z20: =[5]Model!AC46 -> 34.337127 | AA20: =[5]Model!AD46 -> 29.293594 | AB20: =[5]Model!AE46 -> 31.764219 | AC20: =[5]Model!AF46 -> 28.060592 | AD20: =[5]Model!AG46 -> 37.722466 | AE20: =[5]Model!AH46 -> 44.698701 | AF20: =[5]Model!AI46 -> 37.481809 | ... BX20: =[5]Model!CA46 -> 9739.609
B21: Depreciation | C21: DEPREC | D21: =E_CURRENCY_ISSR_208021942_REP -> CNY | F21: =-[5]Model!E44 -> -2.7811 | G21: =-[5]Model!F44 -> -2.8049 | H21: =-[5]Model!G44 -> -5.2721238 | I21: =-[5]Model!H44 -> -12.068054 | J21: =-[5]Model!I44 -> -15.214017 | K21: =-[5]Model!J44 -> -23.896633 | L21: =-[5]Model!K44 -> -46.862284 | M21: =-[5]Model!L44 -> -53.2327 | ... W21: =-[5]Model!V44 -> -1018.9813 | Y21: =-[5]Model!AB44 -> -3.5434411 | Z21: =-[5]Model!AC44 -> -3.5434411 | AA21: =-[5]Model!AD44 -> -3.5434411 | AB21: =-[5]Model!AE44 -> -3.5434411 | AC21: =-[5]Model!AF44 -> -3.5434411 | AD21: =-[5]Model!AG44 -> -3.5434411 | AE21: =-[5]Model!AH44 -> -8.3934916 | AF21: =-[5]Model!AI44 -> -8.3934916 | ... BX21: =-[5]Model!CA44 -> -207.5998
B22: Amortization | C22: GOODWILL_AMORT | D22: =E_CURRENCY_ISSR_208021942_REP -> CNY | F22: =-[5]Model!E45 -> -0.1364 | G22: =-[5]Model!F45 -> -0.1015 | H22: =-[5]Model!G45 -> -0.22808715 | I22: =-[5]Model!H45 -> -0.31876193 | J22: =-[5]Model!I45 -> -0.43356578 | K22: =-[5]Model!J45 -> -0.41590236 | L22: =-[5]Model!K45 -> -0.42110674 | M22: =-[5]Model!L45 -> -0.67595024 | ... W22: =-[5]Model!V45 -> -14.785555 | Y22: =-[5]Model!AB45 -> -0.105294 | Z22: =-[5]Model!AC45 -> -0.105294 | AA22: =-[5]Model!AD45 -> -0.105294 | AB22: =-[5]Model!AE45 -> -0.105294 | AC22: =-[5]Model!AF45 -> -0.105294 | AD22: =-[5]Model!AG45 -> -0.105294 | AE22: =-[5]Model!AH45 -> -0.10265718 | AF22: =-[5]Model!AI45 -> -0.10265718 | ... BX22: =-[5]Model!CA45 -> -4.2981265
B23: EBIT, operating profit | C23: EBIT | D23: =E_CURRENCY_ISSR_208021942_REP -> CNY | F23: =[5]Model!E43 -> 66.91287 | G23: =[5]Model!F43 -> 79.09682 | H23: =[5]Model!G43 -> 94.738635 | I23: =[5]Model!H43 -> 110.85916 | J23: =[5]Model!I43 -> 113.59683 | K23: =[5]Model!J43 -> 123.6738 | L23: =[5]Model!K43 -> 128.61345 | M23: =[5]Model!L43 -> 43.085493 | ... W23: =[5]Model!V43 -> 39482.918 | Y23: =[5]Model!AB43 -> 29.148095 | Z23: =[5]Model!AC43 -> 30.688392 | AA23: =[5]Model!AD43 -> 25.644859 | AB23: =[5]Model!AE43 -> 28.115484 | AC23: =[5]Model!AF43 -> 24.411857 | AD23: =[5]Model!AG43 -> 34.073731 | AE23: =[5]Model!AH43 -> 36.202552 | AF23: =[5]Model!AI43 -> 28.985661 | ... BX23: =[5]Model!CA43 -> 9527.711
B24: Interest income | C24: INT_INC_IND | D24: =E_CURRENCY_ISSR_208021942_REP -> CNY | F24: =[5]Model!E24 -> 0 | G24: =[5]Model!F24 -> 0 | H24: =[5]Model!G24 -> 0 | I24: =[5]Model!H24 -> 0 | J24: =[5]Model!I24 -> 0 | K24: =[5]Model!J24 -> 0 | L24: =[5]Model!K24 -> 0 | M24: =[5]Model!L24 -> 1.6758867 | ... W24: =[5]Model!V24 -> 32 | Y24: =[5]Model!AB24 -> 0 | Z24: =[5]Model!AC24 -> 0 | AA24: =[5]Model!AD24 -> 0 | AB24: =[5]Model!AE24 -> 0 | AC24: =[5]Model!AF24 -> 0 | AD24: =[5]Model!AG24 -> 0 | AE24: =[5]Model!AH24 -> 0 | AF24: =[5]Model!AI24 -> 0 | ... BX24: =[5]Model!CA24 -> 8
B25: Interest expense | C25: INT_EXP_IND | D25: =E_CURRENCY_ISSR_208021942_REP -> CNY | F25: =[5]Model!E25 -> 0 | G25: =[5]Model!F25 -> 0 | H25: =[5]Model!G25 -> 0 | I25: =[5]Model!H25 -> 0 | J25: =[5]Model!I25 -> 0 | K25: =[5]Model!J25 -> 0 | L25: =[5]Model!K25 -> 0 | M25: =[5]Model!L25 -> -0.16884679 | ... W25: =[5]Model!V25 -> 0 | Y25: =[5]Model!AB25 -> 0 | Z25: =[5]Model!AC25 -> 0 | AA25: =[5]Model!AD25 -> 0 | AB25: =[5]Model!AE25 -> 0 | AC25: =[5]Model!AF25 -> 0 | AD25: =[5]Model!AG25 -> 0 | AE25: =[5]Model!AH25 -> 0 | AF25: =[5]Model!AI25 -> 0 | ... BX25: =[5]Model!CA25 -> 0
B26: Net interest income/(expense) | C26: NET_INT_EXP | D26: =E_CURRENCY_ISSR_208021942_REP -> CNY | F26: =[5]Model!E23 -> 0 | G26: =[5]Model!F23 -> 0 | H26: =[5]Model!G23 -> 0 | I26: =[5]Model!H23 -> 0 | J26: =[5]Model!I23 -> 0 | K26: =[5]Model!J23 -> 0 | L26: =[5]Model!K23 -> 0 | M26: =[5]Model!L23 -> 1.5070399 | ... W26: =[5]Model!V23 -> 32 | Y26: =[5]Model!AB23 -> 0 | Z26: =[5]Model!AC23 -> 0 | AA26: =[5]Model!AD23 -> 0 | AB26: =[5]Model!AE23 -> 0 | AC26: =[5]Model!AF23 -> 0 | AD26: =[5]Model!AG23 -> 0 | AE26: =[5]Model!AH23 -> 0 | AF26: =[5]Model!AI23 -> 0 | ... BX26: =[5]Model!CA23 -> 8
B27: Income/(loss) from unconsolidated subs & associates | C27: ASSOCIATE | D27: =E_CURRENCY_ISSR_208021942_REP -> CNY | F27: =[5]Model!E29+[5]Model!E30 -> 0 | G27: =[5]Model!F29+[5]Model!F30 -> 0 | H27: =[5]Model!G29+[5]Model!G30 -> 0 | I27: =[5]Model!H29+[5]Model!H30 -> 0 | J27: =[5]Model!I29+[5]Model!I30 -> 0 | K27: =[5]Model!J29+[5]Model!J30 -> 0 | L27: =[5]Model!K29+[5]Model!K30 -> 0 | M27: =[5]Model!L29+[5]Model!L30 -> -3.1526989 | ... W27: =[5]Model!V29+[5]Model!V30 -> 0 | Y27: =[5]Model!AB29+[5]Model!AB30 -> 0 | Z27: =[5]Model!AC29+[5]Model!AC30 -> 0 | AA27: =[5]Model!AD29+[5]Model!AD30 -> 0 | AB27: =[5]Model!AE29+[5]Model!AE30 -> 0 | AC27: =[5]Model!AF29+[5]Model!AF30 -> 0 | AD27: =[5]Model!AG29+[5]Model!AG30 -> 0 | AE27: =[5]Model!AH29+[5]Model!AH30 -> 0 | AF27: =[5]Model!AI29+[5]Model!AI30 -> 0 | ... BX27: =[5]Model!CA29+[5]Model!CA30 -> 0
B28: Profit/(loss) on disposals of assets, pre-tax | C28: PROFIT_ON_DISP | D28: =E_CURRENCY_ISSR_208021942_REP -> CNY | F28: =[5]Model!E27 -> 0 | G28: =[5]Model!F27 -> 0 | H28: =[5]Model!G27 -> 0 | I28: =[5]Model!H27 -> 0 | J28: =[5]Model!I27 -> 0 | K28: =[5]Model!J27 -> 0 | L28: =[5]Model!K27 -> 0.0014594 | M28: =[5]Model!L27 -> -0.00519486 | ... W28: =[5]Model!V27 -> 0 | Y28: =[5]Model!AB27 -> 0 | Z28: =[5]Model!AC27 -> 0 | AA28: =[5]Model!AD27 -> 0 | AB28: =[5]Model!AE27 -> 0 | AC28: =[5]Model!AF27 -> 0 | AD28: =[5]Model!AG27 -> 0 | AE28: =[5]Model!AH27 -> 0 | AF28: =[5]Model!AI27 -> 0 | ... BX28: =[5]Model!CA27 -> 0
B29: Other non-ops income/(expense) | C29: OTH_COST_INC | D29: =E_CURRENCY_ISSR_208021942_REP -> CNY | F29: =[5]Model!E31+[5]Model!E26+[5]Model!E28 -> -4.2849725 | G29: =[5]Model!F31+[5]Model!F26+[5]Model!F28 -> -1.5198879 | H29: =[5]Model!G31+[5]Model!G26+[5]Model!G28 -> -1.379428 | I29: =[5]Model!H31+[5]Model!H26+[5]Model!H28 -> -2.6637495 | J29: =[5]Model!I31+[5]Model!I26+[5]Model!I28 -> -3.1236165 | K29: =[5]Model!J31+[5]Model!J26+[5]Model!J28 -> 4.3547783 | L29: =[5]Model!K31+[5]Model!K26+[5]Model!K28 -> -1.0775177 | M29: =[5]Model!L31+[5]Model!L26+[5]Model!L28 -> -5.9242649 | ... T29: =[5]Model!S31+[5]Model!S26+[5]Model!S28 -> 70.50304 | U29: =[5]Model!T31+[5]Model!T26 -> 153.11671 | V29: =[5]Model!U31+[5]Model!U26 -> 0 | W29: =[5]Model!V31+[5]Model!V26 -> 0 | Y29: =[5]Model!AB31+[5]Model!AB26 -> -0.0005322 | Z29: =[5]Model!AC31+[5]Model!AC26 -> 0.77051535 | AA29: =[5]Model!AD31+[5]Model!AD26 -> -1.0370546 | AB29: =[5]Model!AE31+[5]Model!AE26 -> -1.6070271 | AC29: =[5]Model!AF31+[5]Model!AF26 -> 0.71100772 | AD29: =[5]Model!AG31+[5]Model!AG26 -> -1.9259063 | AE29: =[5]Model!AH31+[5]Model!AH26 -> 3.7583548 | AF29: =[5]Model!AI31+[5]Model!AI26 -> -0.43464277 | ... BX29: =[5]Model!CA31+[5]Model!CA26 -> 0
B30: Pre-tax profit | C30: PT_PROF | D30: =E_CURRENCY_ISSR_208021942_REP -> CNY | F30: =[5]Model!E33 -> 62.627898 | G30: =[5]Model!F33 -> 77.576932 | H30: =[5]Model!G33 -> 93.359207 | I30: =[5]Model!H33 -> 108.19541 | J30: =[5]Model!I33 -> 110.47321 | K30: =[5]Model!J33 -> 128.02858 | L30: =[5]Model!K33 -> 127.53739 | M30: =[5]Model!L33 -> 35.510374 | ... W30: =[5]Model!V33 -> 39514.918 | Y30: =[5]Model!AB33 -> 29.114392 | Z30: =[5]Model!AC33 -> 31.227481 | AA30: =[5]Model!AD33 -> 23.399505 | AB30: =[5]Model!AE33 -> 26.731837 | AC30: =[5]Model!AF33 -> 25.347175 | AD30: =[5]Model!AG33 -> 32.56913 | AE30: =[5]Model!AH33 -> 40.459621 | AF30: =[5]Model!AI33 -> 29.652653 | ... BX30: =[5]Model!CA33 -> 9535.711
A31: Additional Income Statement Items
B32: Contribution margin ratio | C32: CONTRIB_MARGIN_RATIO | D32: =E_CURRENCY_ISSR_208021942_REP -> CNY
B33: Operating lease cost | C33: LEASE_PAY | D33: =E_CURRENCY_ISSR_208021942_REP -> CNY
B34: Lease payments (deemed interest portion) | C34: LEASE_DEEM_INT | D34: =E_CURRENCY_ISSR_208021942_REP -> CNY
B35: Lease payments (deemed depreciation portion) | C35: LEASE_DEEM_DEPR | D35: =E_CURRENCY_ISSR_208021942_REP -> CNY
B36: Gross interest charge | C36: NET_INT_CH | D36: =E_CURRENCY_ISSR_208021942_REP -> CNY
B37: Income from associates (operating) | C37: ASSOCIATE_OP | D37: =E_CURRENCY_ISSR_208021942_REP -> CNY
B38: Depreciation ROU assets (applicable to IFRS cos.) | C38: DEPR_ROU_ASSETS | D38: =E_CURRENCY_ISSR_208021942_REP -> CNY
B39: Lease interest charge (applicable to IFRS cos.) | C39: LEASE_INT_CHG | D39: =E_CURRENCY_ISSR_208021942_REP -> CNY
B40: Lease standard adopted (US GAAP ASC 842/ IFRS 16) | C40: LEASE_ADOPT | E40: Y
A41: Balance Sheet
B42: Cash & cash equivalents | C42: CASH_EQ | D42: =E_CURRENCY_ISSR_208021942_REP -> CNY | F42: =[5]Model!E121 -> 106.83876 | G42: =[5]Model!F121 -> 98.539043 | H42: =[5]Model!G121 -> 62.524122 | I42: =[5]Model!H121 -> 89.896097 | J42: =[5]Model!I121 -> 79.318084 | K42: =[5]Model!J121 -> 135.6074 | L42: =[5]Model!K121 -> 108.06688 | M42: =[5]Model!L121 -> 237.00027 | ... W42: =[5]Model!V121 -> 57966.209
B43: Accounts receivable | C43: DEBTORS | D43: =E_CURRENCY_ISSR_208021942_REP -> CNY | F43: =[5]Model!E122 -> 85.102423 | G43: =[5]Model!F122 -> 86.140899 | H43: =[5]Model!G122 -> 146.06797 | I43: =[5]Model!H122 -> 197.93571 | J43: =[5]Model!I122 -> 222.84344 | K43: =[5]Model!J122 -> 292.11327 | L43: =[5]Model!K122 -> 424.13408 | M43: =[5]Model!L122 -> 330.83004 | ... W43: =[5]Model!V122 -> 17498.723
B44: Inventory | C44: STOCKS | D44: =E_CURRENCY_ISSR_208021942_REP -> CNY | F44: =[5]Model!E123 -> 72.280689 | G44: =[5]Model!F123 -> 80.490802 | H44: =[5]Model!G123 -> 115.46273 | I44: =[5]Model!H123 -> 124.84104 | J44: =[5]Model!I123 -> 207.71725 | K44: =[5]Model!J123 -> 283.69802 | L44: =[5]Model!K123 -> 433.53856 | M44: =[5]Model!L123 -> 291.23773 | ... W44: =[5]Model!V123 -> 21026.46
B45: Other current assets | C45: OTH_CUR_ASS | D45: =E_CURRENCY_ISSR_208021942_REP -> CNY | F45: =[5]Model!E124 -> 7.2910473 | G45: =[5]Model!F124 -> 12.590333 | H45: =[5]Model!G124 -> 11.723954 | I45: =[5]Model!H124 -> 9.8690225 | J45: =[5]Model!I124 -> 14.123435 | K45: =[5]Model!J124 -> 196.69455 | L45: =[5]Model!K124 -> 51.211822 | M45: =[5]Model!L124 -> 105.35122 | ... W45: =[5]Model!V124 -> 36.542861
B46: Total current assets | C46: CUR_ASS | D46: =E_CURRENCY_ISSR_208021942_REP -> CNY | F46: =[5]Model!E125 -> 271.51292 | G46: =[5]Model!F125 -> 277.76108 | H46: =[5]Model!G125 -> 335.77877 | I46: =[5]Model!H125 -> 422.54186 | J46: =[5]Model!I125 -> 524.00221 | K46: =[5]Model!J125 -> 908.11323 | L46: =[5]Model!K125 -> 1016.9513 | M46: =[5]Model!L125 -> 964.41925 | ... W46: =[5]Model!V125 -> 96527.935
B47: Gross fixed assets, PP&E | C47: GR_FIX_ASS | D47: =E_CURRENCY_ISSR_208021942_REP -> CNY | F47: =[5]Model!E127 -> 27.712329 | G47: =[5]Model!F127 -> 33.345201 | H47: =[5]Model!G127 -> 128.77975 | I47: =[5]Model!H127 -> 139.8054 | J47: =[5]Model!I127 -> 179.35463 | K47: =[5]Model!J127 -> 285.84733 | L47: =[5]Model!K127 -> 425.31414 | M47: =[5]Model!L127 -> 472.77134 | ... W47: =[5]Model!V127 -> 11802.999
B48: Accumulated depreciation | C48: ACC_DDA | D48: =E_CURRENCY_ISSR_208021942_REP -> CNY | F48: =[5]Model!E128 -> -17.669141 | G48: =[5]Model!F128 -> -20.450241 | H48: =[5]Model!G128 -> -23.255141 | I48: =[5]Model!H128 -> -28.527265 | J48: =[5]Model!I128 -> -40.595319 | K48: =[5]Model!J128 -> -64.469184 | L48: =[5]Model!K128 -> -111.17553 | M48: =[5]Model!L128 -> -164.30953 | ... W48: =[5]Model!V128 -> -3474.9991
B49: Net PP&E | C49: NET_FIX_ASS | D49: =E_CURRENCY_ISSR_208021942_REP -> CNY | F49: =[5]Model!E129 -> 10.043188 | G49: =[5]Model!F129 -> 12.89496 | H49: =[5]Model!G129 -> 105.52461 | I49: =[5]Model!H129 -> 111.27814 | J49: =[5]Model!I129 -> 138.75931 | K49: =[5]Model!J129 -> 221.37815 | L49: =[5]Model!K129 -> 314.13861 | M49: =[5]Model!L129 -> 308.46181 | ... W49: =[5]Model!V129 -> 8327.9998
B50: Gross intangibles | C50: GR_INTANG | D50: =E_CURRENCY_ISSR_208021942_REP -> CNY | F50: =[5]Model!E130 -> 0.38778088 | G50: =[5]Model!F130 -> 0.28629652 | H50: =[5]Model!G130 -> 5.7639664 | I50: =[5]Model!H130 -> 6.2936403 | J50: =[5]Model!I130 -> 7.5779689 | K50: =[5]Model!J130 -> 7.6308792 | L50: =[5]Model!K130 -> 7.7333852 | M50: =[5]Model!L130 -> 10.095152 | ... W50: =[5]Model!V130 -> 207.79133
B51: Accumulated amortization | C51: ACC_AMORT | D51: =E_CURRENCY_ISSR_208021942_REP -> CNY | F51: =[5]Model!E131 -> 0 | G51: =[5]Model!F131 -> 0 | H51: =[5]Model!G131 -> 0 | I51: =[5]Model!H131 -> 0 | J51: =[5]Model!I131 -> -1.4217406 | K51: =[5]Model!J131 -> -1.8376429 | L51: =[5]Model!K131 -> -2.2587497 | M51: =[5]Model!L131 -> -2.9346999 | ... W51: =[5]Model!V131 -> -116.96577
B52: Net intangible assets | C52: NET_INTANG | D52: =E_CURRENCY_ISSR_208021942_REP -> CNY | F52: =[5]Model!E132 -> 0.38778088 | G52: =[5]Model!F132 -> 0.28629652 | H52: =[5]Model!G132 -> 5.7639664 | I52: =[5]Model!H132 -> 6.2936403 | J52: =[5]Model!I132 -> 6.1562284 | K52: =[5]Model!J132 -> 5.7932363 | L52: =[5]Model!K132 -> 5.4746356 | M52: =[5]Model!L132 -> 7.1604522 | ... W52: =[5]Model!V132 -> 90.825553
B53: Equity method investments | C53: FIX_ASS_INV | D53: =E_CURRENCY_ISSR_208021942_REP -> CNY
B54: Investments in securities | C54: INV_SECUR | D54: =E_CURRENCY_ISSR_208021942_REP -> CNY | F54: =[5]Model!E133 -> 0 | G54: =[5]Model!F133 -> 0 | H54: =[5]Model!G133 -> 0 | I54: =[5]Model!H133 -> 0 | J54: =[5]Model!I133 -> 0 | K54: =[5]Model!J133 -> 30 | L54: =[5]Model!K133 -> 49.6026 | M54: =[5]Model!L133 -> 74.162701 | ... W54: =[5]Model!V133 -> 0
B55: Other long-term assets | C55: OTH_LT_ASS | D55: =E_CURRENCY_ISSR_208021942_REP -> CNY | F55: =[5]Model!E134 -> 1.6789946 | G55: =[5]Model!F134 -> 35.104783 | H55: =[5]Model!G134 -> 9.5035134 | I55: =[5]Model!H134 -> 18.227247 | J55: =[5]Model!I134 -> 19.085089 | K55: =[5]Model!J134 -> 32.049451 | L55: =[5]Model!K134 -> 16.191293 | M55: =[5]Model!L134 -> 25.33051 | ... W55: =[5]Model!V134 -> 1818.0524
B56: Total assets | C56: TOT_ASSET | D56: =E_CURRENCY_ISSR_208021942_REP -> CNY | F56: =[5]Model!E136 -> 283.62288 | G56: =[5]Model!F136 -> 326.04712 | H56: =[5]Model!G136 -> 456.57086 | I56: =[5]Model!H136 -> 558.34089 | J56: =[5]Model!I136 -> 688.00284 | K56: =[5]Model!J136 -> 1197.3341 | L56: =[5]Model!K136 -> 1402.3585 | M56: =[5]Model!L136 -> 1379.5347 | ... W56: =[5]Model!V136 -> 106764.81
B57: Accounts payable | C57: ACC_PAY_GQ | D57: =E_CURRENCY_ISSR_208021942_REP -> CNY | F57: =[5]Model!E138 -> 54.296813 | G57: =[5]Model!F138 -> 46.50863 | H57: =[5]Model!G138 -> 75.88395 | I57: =[5]Model!H138 -> 81.652737 | J57: =[5]Model!I138 -> 122.17952 | K57: =[5]Model!J138 -> 143.87787 | L57: =[5]Model!K138 -> 179.24891 | M57: =[5]Model!L138 -> 159.52688 | ... W57: =[5]Model!V138 -> 9108.2902
B58: Short-term debt | C58: SHORT_T_DEBT | D58: =E_CURRENCY_ISSR_208021942_REP -> CNY | F58: =[5]Model!E139 -> 17 | G58: =[5]Model!F139 -> 0 | H58: =[5]Model!G139 -> 10 | I58: =[5]Model!H139 -> 5 | J58: =[5]Model!I139 -> 0 | K58: =[5]Model!J139 -> 0 | L58: =[5]Model!K139 -> 21.238513 | M58: =[5]Model!L139 -> 0 | ... W58: =[5]Model!V139 -> 3.6224246
B59: Current lease liabilities (op lease: US GAAP) | C59: ST_LEASE_LIAB | D59: =E_CURRENCY_ISSR_208021942_REP -> CNY
B60: Other current liabilities | C60: OTH_CUR_LIABS | D60: =E_CURRENCY_ISSR_208021942_REP -> CNY | F60: =[5]Model!E140 -> 32.2836 | G60: =[5]Model!F140 -> 18.33636 | H60: =[5]Model!G140 -> 23.254144 | I60: =[5]Model!H140 -> 31.210486 | J60: =[5]Model!I140 -> 32.292606 | K60: =[5]Model!J140 -> 51.641753 | L60: =[5]Model!K140 -> 110.16957 | M60: =[5]Model!L140 -> 78.494349 | ... W60: =[5]Model!V140 -> 1617.3002
B61: Total current liabilities | C61: SHORT_TERM_LIABS | D61: =E_CURRENCY_ISSR_208021942_REP -> CNY | F61: =[5]Model!E141 -> 103.58041 | G61: =[5]Model!F141 -> 64.84499 | H61: =[5]Model!G141 -> 109.13809 | I61: =[5]Model!H141 -> 117.86322 | J61: =[5]Model!I141 -> 154.47213 | K61: =[5]Model!J141 -> 195.51962 | L61: =[5]Model!K141 -> 310.657 | M61: =[5]Model!L141 -> 238.02123 | ... W61: =[5]Model!V141 -> 10729.213
B62: Long-term debt | C62: LT_DEBT | D62: =E_CURRENCY_ISSR_208021942_REP -> CNY | F62: =[5]Model!E143 -> 0 | G62: =[5]Model!F143 -> 0 | H62: =[5]Model!G143 -> 0 | I62: =[5]Model!H143 -> 0 | J62: =[5]Model!I143 -> 0 | K62: =[5]Model!J143 -> 0 | L62: =[5]Model!K143 -> 0 | M62: =[5]Model!L143 -> 0 | ... W62: =[5]Model!V143 -> 0
B63: Non-current lease liabilities (op lease: US GAAP) | C63: LT_LEASE_LIAB | D63: =E_CURRENCY_ISSR_208021942_REP -> CNY
B64: Other long-term liabilities | C64: OTH_LT_CRED_GQ | D64: =E_CURRENCY_ISSR_208021942_REP -> CNY | F64: =[5]Model!E144 -> 0 | G64: =[5]Model!F144 -> 1.7 | H64: =[5]Model!G144 -> 8.5718718 | I64: =[5]Model!H144 -> 9.2182385 | J64: =[5]Model!I144 -> 7.8209549 | K64: =[5]Model!J144 -> 6.2656942 | L64: =[5]Model!K144 -> 3.9895053 | M64: =[5]Model!L144 -> 5.7360385 | ... W64: =[5]Model!V144 -> 1220.5646
B65: Total long-term liabilities | C65: TOT_LT_LIAB | D65: =E_CURRENCY_ISSR_208021942_REP -> CNY | F65: =[5]Model!E145 -> 0 | G65: =[5]Model!F145 -> 1.7 | H65: =[5]Model!G145 -> 8.5718718 | I65: =[5]Model!H145 -> 9.2182385 | J65: =[5]Model!I145 -> 7.8209549 | K65: =[5]Model!J145 -> 6.2656942 | L65: =[5]Model!K145 -> 3.9895053 | M65: =[5]Model!L145 -> 5.7360385 | ... W65: =[5]Model!V145 -> 1220.5646
B66: Total liabilities | C66: TOT_LIAB | D66: =E_CURRENCY_ISSR_208021942_REP -> CNY | F66: =[5]Model!E146 -> 103.58041 | G66: =[5]Model!F146 -> 66.54499 | H66: =[5]Model!G146 -> 117.70997 | I66: =[5]Model!H146 -> 127.08146 | J66: =[5]Model!I146 -> 162.29309 | K66: =[5]Model!J146 -> 201.78531 | L66: =[5]Model!K146 -> 314.6465 | M66: =[5]Model!L146 -> 243.75726 | ... W66: =[5]Model!V146 -> 11949.777
B67: Preferred shares | C67: PREF_SH | D67: =E_CURRENCY_ISSR_208021942_REP -> CNY
B68: Total common equity | C68: ORD_SH_FUND | D68: =E_CURRENCY_ISSR_208021942_REP -> CNY | F68: =[5]Model!E153 -> 180.04247 | G68: =[5]Model!F153 -> 259.50213 | H68: =[5]Model!G153 -> 338.86089 | I68: =[5]Model!H153 -> 431.25943 | J68: =[5]Model!I153 -> 525.70976 | K68: =[5]Model!J153 -> 995.54875 | L68: =[5]Model!K153 -> 1087.712 | M68: =[5]Model!L153 -> 1135.7775 | ... W68: =[5]Model!V153 -> 94727.117
B69: Minority interest | C69: MINORITIES | D69: =E_CURRENCY_ISSR_208021942_REP -> CNY | F69: =[5]Model!E154 -> 0 | G69: =[5]Model!F154 -> 0 | H69: =[5]Model!G154 -> 0 | I69: =[5]Model!H154 -> 0 | J69: =[5]Model!I154 -> 0 | K69: =[5]Model!J154 -> 0 | L69: =[5]Model!K154 -> 0 | M69: =[5]Model!L154 -> 0 | ... W69: =[5]Model!V154 -> 87.91857
B70: Total shareholders' equity | C70: EQ | D70: =E_CURRENCY_ISSR_208021942_REP -> CNY | F70: =[5]Model!E155 -> 180.04247 | G70: =[5]Model!F155 -> 259.50213 | H70: =[5]Model!G155 -> 338.86089 | I70: =[5]Model!H155 -> 431.25943 | J70: =[5]Model!I155 -> 525.70976 | K70: =[5]Model!J155 -> 995.54875 | L70: =[5]Model!K155 -> 1087.712 | M70: =[5]Model!L155 -> 1135.7775 | ... W70: =[5]Model!V155 -> 94815.035
B71: Total liabilities and equity | C71: TOT_LIAB_EQ | D71: =E_CURRENCY_ISSR_208021942_REP -> CNY | F71: =[5]Model!E156 -> 283.62288 | G71: =[5]Model!F156 -> 326.04712 | H71: =[5]Model!G156 -> 456.57086 | I71: =[5]Model!H156 -> 558.34089 | J71: =[5]Model!I156 -> 688.00284 | K71: =[5]Model!J156 -> 1197.3341 | L71: =[5]Model!K156 -> 1402.3585 | M71: =[5]Model!L156 -> 1379.5347 | ... W71: =[5]Model!V156 -> 106764.81
A72: Additional Balance Sheet Items
B73: Total US$ debt (in US$) | C73: TOT_USD_DEBT
B74: % US$ debt hedged (principal) | C74: TOT_PCT_USD_DEBT_HEDGED
B75: % Floating debt (local currency debt) | C75: FLOATING_PCT_LOCAL_DEBT
B76: % floating debt hedged (rates) | C76: FLOATING_PCT_LOCAL_DEBT_HEDGED
B77: Net debt | C77: NET_DEBT | D77: =E_CURRENCY_ISSR_208021942_REP -> CNY | F77: =F58+F59+F62+F63-F42 -> -89.838758 | G77: =G58+G59+G62+G63-G42 -> -98.539043 | H77: =H58+H59+H62+H63-H42 -> -52.524122 | I77: =I58+I59+I62+I63-I42 -> -84.896097 | J77: =J58+J59+J62+J63-J42 -> -79.318084 | K77: =K58+K59+K62+K63-K42 -> -135.6074 | L77: =L58+L59+L62+L63-L42 -> -86.828371 | M77: =M58+M59+M62+M63-M42 -> -237.00027 | ... W77: =W58+W59+W62+W63-W42 -> -57962.587
B78: Capitalized operating leases (off-balance sheet) | C78: CAP_LEASES | D78: =E_CURRENCY_ISSR_208021942_REP -> CNY
B79: Deferred income taxes | C79: DEF_INC_TAX | D79: =E_CURRENCY_ISSR_208021942_REP -> CNY
B80: Associates (mkt value) used in EV calculation | C80: MV_ASSOCIATES | D80: =E_CURRENCY_ISSR_208021942_REP -> CNY
B81: Net debt adjustment | C81: NET_DEBT_ADJ | D81: =E_CURRENCY_ISSR_208021942_REP -> CNY
B82: Company borrowing margin | C82: CO_BOR_MARGIN
B83: Unfunded pensions & other provisions | C83: UNF_PENS | D83: =E_CURRENCY_ISSR_208021942_REP -> CNY
B84: Unfunded pension liabilities (off balance sheet) | C84: UNF_PENS_OFF | D84: =E_CURRENCY_ISSR_208021942_REP -> CNY
B85: Unfunded pension liabilities & other, used in EV | C85: UNF_PENS_LIAB_OTH | D85: =E_CURRENCY_ISSR_208021942_REP -> CNY
B86: Adjustment for unfunded pensions & goodwill | C86: ADJ_UNF_PENS_GOOD | D86: =E_CURRENCY_ISSR_208021942_REP -> CNY
B87: Other GCI adjustments | C87: OTH_GCI_ADJ | D87: =E_CURRENCY_ISSR_208021942_REP -> CNY
B88: GCI inflator | C88: GCI_INFL
B89: Minority interest | C89: BAL_MINO_INT | D89: =E_CURRENCY_ISSR_208021942_REP -> CNY | F89: =F69 -> 0 | G89: =G69 -> 0 | H89: =H69 -> 0 | I89: =I69 -> 0 | J89: =J69 -> 0 | K89: =K69 -> 0 | L89: =L69 -> 0 | M89: =M69 -> 0 | ... W89: =W69 -> 87.91857
B90: Right-of-use assets (op lease assets under US GAAP) | C90: ROU_ASSET | D90: =E_CURRENCY_ISSR_208021942_REP -> CNY
A91: Cash Flow Statement
B92: Minority interest add-back | C92: CF_INC_MINORITY | D92: =E_CURRENCY_ISSR_208021942_REP -> CNY | F92: =[5]Model!E203 -> 0 | G92: =[5]Model!F203 -> 0 | H92: =[5]Model!G203 -> 0 | I92: =[5]Model!H203 -> 0 | J92: =[5]Model!I203 -> 0 | K92: =[5]Model!J203 -> 0 | L92: =[5]Model!K203 -> 0 | M92: =[5]Model!L203 -> 0 | ... W92: =[5]Model!V203 -> 0
B93: Depreciation & amortization add-back | C93: DEPR_AMORT | D93: =E_CURRENCY_ISSR_208021942_REP -> CNY | F93: =[5]Model!E204 -> 2.9175 | G93: =[5]Model!F204 -> 2.9064 | H93: =[5]Model!G204 -> 5.5002109 | I93: =[5]Model!H204 -> 12.386816 | J93: =[5]Model!I204 -> 15.647583 | K93: =[5]Model!J204 -> 24.312536 | L93: =[5]Model!K204 -> 47.28339 | M93: =[5]Model!L204 -> 53.90865 | ... W93: =[5]Model!V204 -> 1033.7668
B94: (Increase)/decrease in working capital | C94: WORK_CAP | D94: =E_CURRENCY_ISSR_208021942_REP -> CNY | F94: =[5]Model!E207 -> -103.0863 | G94: =[5]Model!F207 -> -17.036771 | H94: =[5]Model!G207 -> -65.523676 | I94: =[5]Model!H207 -> -55.47726 | J94: =[5]Model!I207 -> -67.257162 | K94: =[5]Model!J207 -> -123.55225 | L94: =[5]Model!K207 -> -246.49032 | M94: =[5]Model!L207 -> 215.88285 | ... W94: =[5]Model!V207 -> -11206.324
B95: Other operating cash flow items | C95: OTH_OP_CF | D95: =E_CURRENCY_ISSR_208021942_REP -> CNY | F95: =[5]Model!E205+[5]Model!E206+[5]Model!E211 -> 93.858114 | G95: =[5]Model!F205+[5]Model!F206+[5]Model!F211 -> -5.6817365 | H95: =[5]Model!G205+[5]Model!G206+[5]Model!G211 -> 7.4072801 | I95: =[5]Model!H205+[5]Model!H206+[5]Model!H211 -> 7.9059903 | J95: =[5]Model!I205+[5]Model!I206+[5]Model!I211 -> -10.167133 | K95: =[5]Model!J205+[5]Model!J206+[5]Model!J211 -> 0.26835951 | L95: =[5]Model!K205+[5]Model!K206+[5]Model!K211 -> 15.179845 | M95: =[5]Model!L205+[5]Model!L206+[5]Model!L211 -> 19.002912 | ... W95: =[5]Model!V205+[5]Model!V206+[5]Model!V211 -> 0
B96: Cash flow from operating activities | C96: CF_OPS | D96: =E_CURRENCY_ISSR_208021942_REP -> CNY | F96: =[5]Model!E212 -> 46.2641 | G96: =[5]Model!F212 -> 45.9356 | H96: =[5]Model!G212 -> 26.742583 | I96: =[5]Model!H212 -> 57.214081 | J96: =[5]Model!I212 -> 32.673616 | K96: =[5]Model!J212 -> 6.3154283 | L96: =[5]Model!K212 -> -72.936174 | M96: =[5]Model!L212 -> 320.62674 | ... W96: =[5]Model!V212 -> 24402.996
B97: Capital expenditures, Capex | C97: CAPEX | D97: =E_CURRENCY_ISSR_208021942_REP -> CNY | F97: =[5]Model!E214 -> -5.0335872 | G97: =[5]Model!F214 -> -39.018598 | H97: =[5]Model!G214 -> -74.19092 | I97: =[5]Model!H214 -> -28.249245 | J97: =[5]Model!I214 -> -37.638732 | K97: =[5]Model!J214 -> -130.77671 | L97: =[5]Model!K214 -> -135.73533 | M97: =[5]Model!L214 -> -68.7789 | ... W97: =[5]Model!V214 -> -2068.5433
B98: Acquisitions | C98: ACQ | D98: =E_CURRENCY_ISSR_208021942_REP -> CNY | F98: =IF([5]Model!E215<0,[5]Model!E215,0) -> 0 | G98: =IF([5]Model!F215<0,[5]Model!F215,0) -> 0 | H98: =IF([5]Model!G215<0,[5]Model!G215,0) -> 0 | I98: =IF([5]Model!H215<0,[5]Model!H215,0) -> 0 | J98: =IF([5]Model!I215<0,[5]Model!I215,0) -> 0 | K98: =IF([5]Model!J215<0,[5]Model!J215,0) -> 0 | L98: =IF([5]Model!K215<0,[5]Model!K215,0) -> 0 | M98: =IF([5]Model!L215<0,[5]Model!L215,0) -> 0 | ... W98: =IF([5]Model!V215<0,[5]Model!V215,0) -> 0
B99: Divestitures | C99: DIVEST | D99: =E_CURRENCY_ISSR_208021942_REP -> CNY | F99: =IF([5]Model!E215<0,0,[5]Model!E215) -> 0 | G99: =IF([5]Model!F215<0,0,[5]Model!F215) -> 0 | H99: =IF([5]Model!G215<0,0,[5]Model!G215) -> 0 | I99: =IF([5]Model!H215<0,0,[5]Model!H215) -> 0 | J99: =IF([5]Model!I215<0,0,[5]Model!I215) -> 0 | K99: =IF([5]Model!J215<0,0,[5]Model!J215) -> 0 | L99: =IF([5]Model!K215<0,0,[5]Model!K215) -> 0 | M99: =IF([5]Model!L215<0,0,[5]Model!L215) -> 0 | ... W99: =IF([5]Model!V215<0,0,[5]Model!V215) -> 0
B100: Other investing cash flow items | C100: OTH_INV_CF | D100: =E_CURRENCY_ISSR_208021942_REP -> CNY | F100: =[5]Model!E216+[5]Model!E217 -> -1.6594772 | G100: =[5]Model!F216+[5]Model!F217 -> 3.0015795 | H100: =[5]Model!G216+[5]Model!G217 -> -3 | I100: =[5]Model!H216+[5]Model!H217 -> 1.0036752 | J100: =[5]Model!I216+[5]Model!I217 -> 0 | K100: =[5]Model!J216+[5]Model!J217 -> -191.1936 | L100: =[5]Model!K216+[5]Model!K217 -> 126.69744 | M100: =[5]Model!L216+[5]Model!L217 -> -84.135478 | ... W100: =[5]Model!V216+[5]Model!V217 -> 0
...

Sheet Model
A2: Eoptolink (300502.SZ)
A3: In Rmb millions | X3: 2014 | Y3: 2014 | Z3: 2014 | AA3: 2014 | AB3: =X3+1 -> 2015 | AC3: =Y3+1 -> 2015 | AD3: =Z3+1 -> 2015 | AE3: =AA3+1 -> 2015 | AF3: =AB3+1 -> 2016 | AG3: =AC3+1 -> 2016 | AH3: =AD3+1 -> 2016 | AI3: =AE3+1 -> 2016 | ... CE3: =CA3+1 -> 2028
E4: 2011 | F4: 2012 | G4: 2013 | H4: 2014 | I4: 2015 | J4: 2016 | K4: 2017 | L4: =K4+1 -> 2018 | M4: =L4+1 -> 2019 | N4: =M4+1 -> 2020 | O4: =N4+1 -> 2021 | P4: =O4+1 -> 2022 | Q4: =P4+1 -> 2023 | R4: =Q4+1 -> 2024 | S4: =R4+1 -> 2025 | ... V4: =U4+1 -> 2028 | X4: 1Q14 | Y4: 2Q14 | Z4: 3Q14 | AA4: 4Q14 | AB4: 1Q15 | AC4: 2Q15 | AD4: 3Q15 | AE4: 4Q15 | AF4: 1Q16 | AG4: 2Q16 | AH4: 3Q16 | AI4: 4Q16 | AJ4: 1Q17 | AK4: 2Q17 | AL4: 3Q17 | AM4: 4Q17 | AN4: 1Q18 | AO4: 2Q18 | AP4: 3Q18 | AQ4: 4Q18 | AR4: 1Q19 | AS4: 2Q19 | AT4: 3Q19 | AU4: 4Q19 | AV4: 1Q20 | AW4: 2Q20 | AX4: 3Q20 | AY4: 4Q20 | AZ4: 1Q21 | BA4: 2Q21 | BB4: 3Q21 | BC4: 4Q21 | BD4: 1Q22 | BE4: 2Q22 | BF4: 3Q22 | BG4: 4Q22 | BH4: 1Q23 | BI4: 2Q23 | BJ4: 3Q23 | BK4: 4Q23 | BL4: 1Q24 | BM4: 2Q24 | BN4: 3Q24 | BO4: 4Q24 | BP4: 1Q25 | BQ4: 2Q25 | BR4: 3Q25 | BS4: 4Q25 | BT4: 1Q26 | BU4: 2Q26 | BV4: 3Q26 | BW4: 4Q26 | BX4: 1Q27 | BY4: 2Q27 | BZ4: 3Q27 | CA4: 4Q27 | CB4: 1Q28 | CC4: 2Q28 | CD4: 3Q28 | CE4: 4Q28
B5: Income statements | E5: =E4 -> 2011 | F5: =F4 -> 2012 | G5: =G4 -> 2013 | H5: =H4 -> 2014 | I5: =I4 -> 2015 | J5: =J4 -> 2016 | K5: =K4 -> 2017 | L5: =L4 -> 2018 | ... V5: =V4 -> 2028 | X5: =X4 -> 1Q14 | Y5: =Y4 -> 2Q14 | Z5: =Z4 -> 3Q14 | AA5: =AA4 -> 4Q14 | AB5: =AB4 -> 1Q15 | AC5: =AC4 -> 2Q15 | AD5: =AD4 -> 3Q15 | AE5: =AE4 -> 4Q15 | ... CE5: =CE4 -> 4Q28
BS6: =AVERAGE(BT6:BU6) -> 5225.8037 | BT6: =7000-BT40 -> 4225.8037 | BU6: =9000-BT40 -> 6225.8037 | BV6: =BT6/BQ40-1 -> 0.78321375 | BW6: =BU6/BQ40-1 -> 1.6271781
B7: Total sales/revenues | E7: 304.92843 | F7: 347.56807 | G7: 461.049 | H7: 522.63427 | I7: 615.11958 | J7: 713.93165 | K7: 877.36536 | L7: 759.95028 | M7: 1164.8737 | N7: 1997.9377 | O7: 2908.3761 | P7: =SUMIF($X$3:$BS$3,P$4,$X7:$BS7) -> 3310.5738 | Q7: =SUMIF($X$3:$BS$3,Q$4,$X7:$BS7) -> 3097.6058 | R7: =SUMIF($X$3:$BS$3,R$4,$X7:$BS7) -> 8646.8311 | S7: =SUMIF($X$3:$BS$3,S$4,$X7:$BS7) -> 24841.855 | T7: =SUMIF($X$3:$CA$3,T$4,$X7:$CA7) -> 51456.539 | U7: =SUMIF($X$3:$CA$3,U$4,$X7:$CA7) -> 73910.591 | V7: =SUMIF($X$3:$CE$3,V$4,$X7:$CE7) -> 84975.376 | X7: 0 | Y7: 0 | Z7: 0 | AA7: 0 | AB7: 141.26116 | AC7: 166.47504 | AD7: 142.20005 | AE7: 165.18332 | AF7: 146.321 | AG7: 192.79163 | AH7: 170.51717 | AI7: 204.30185 | AJ7: 191.53571 | AK7: 239.17685 | AL7: 231.21159 | AM7: 215.44121 | AN7: 177.50893 | AO7: 158.56943 | AP7: 197.98657 | AQ7: 225.88536 | AR7: 223.88642 | AS7: 256.45334 | AT7: 290.90559 | AU7: 393.62833 | AV7: 270.03089 | AW7: 566.52075 | AX7: 600.90347 | AY7: 560.48265 | AZ7: 624.32716 | BA7: 816.87541 | BB7: 578.08835 | BC7: 889.08514 | BD7: 738.5133 | BE7: 740.33465 | BF7: 935.65916 | BG7: 896.06668 | BH7: 600.22289 | BI7: 704.46093 | BJ7: 782.36373 | BK7: 1010.5582 | BL7: 1112.8539 | BM7: 1614.8209 | BN7: 2402.761 | BO7: 3516.3953 | BP7: 4052.2565 | BQ7: 6384.9137 | BR7: =16504.7912113-SUM(BP7:BQ7) -> 6067.6209 | BS7: =24841.85484022-SUM(BP7:BR7) -> 8337.0636 | BT7: 8337.902 | BU7: =Assumption!S5 -> 11283.248 | BV7: =Assumption!T5 -> 15163.921 | BW7: =Assumption!U5 -> 16671.468 | BX7: =Assumption!V5 -> 15172.087 | BY7: =Assumption!W5 -> 16800.28 | BZ7: =Assumption!X5 -> 21661.32 | CA7: =Assumption!Y5 -> 20276.903 | CB7: =Assumption!Z5 -> 14673.648 | ... CE7: =Assumption!AC5 -> 24684.879
B8: COGS | E8: 213.53676 | F8: 234.62009 | G8: 330.78362 | H8: 363.06989 | I8: 446.55322 | J8: 525.653 | K8: 666.78476 | L8: 611.69329 | M8: 760.4448 | N8: 1261.4845 | O8: 1972.7089 | P8: =SUMIF($X$3:$BS$3,P$4,$X8:$BS8) -> 2096.8585 | Q8: =SUMIF($X$3:$BS$3,Q$4,$X8:$BS8) -> 2137.6564 | R8: =SUMIF($X$3:$BS$3,R$4,$X8:$BS8) -> 4780.1919 | S8: =SUMIF($X$3:$BS$3,S$4,$X8:$BS8) -> 12966.05 | T8: =SUMIF($X$3:$CA$3,T$4,$X8:$CA8) -> 26649.771 | U8: =SUMIF($X$3:$CA$3,U$4,$X8:$CA8) -> 38031.235 | V8: =SUMIF($X$3:$CE$3,V$4,$X8:$CE8) -> 43619.538 | X8: 0 | Y8: 0 | Z8: 0 | AA8: 0 | AB8: 101.0667 | AC8: 121.38813 | AD8: 103.18521 | AE8: 120.91319 | AF8: 110.12175 | AG8: 143.06903 | AH8: 117.13324 | AI8: 155.32899 | AJ8: 142.59412 | AK8: 178.4853 | AL8: 171.31631 | AM8: 174.38903 | AN8: 150.9458 | AO8: 136.60422 | AP8: 155.17415 | AQ8: 168.96912 | AR8: 157.5587 | AS8: 173.87351 | AT8: 187.61455 | AU8: 241.39804 | AV8: 174.83516 | AW8: 348.03935 | AX8: 367.81341 | AY8: 370.79657 | AZ8: 433.70046 | BA8: 534.25111 | BB8: 405.85493 | BC8: 598.9024 | BD8: 493.94298 | BE8: 485.96081 | BF8: 583.91813 | BG8: 533.03662 | BH8: 395.88123 | BI8: 525.06195 | BJ8: 577.71866 | BK8: 638.99454 | BL8: 645.40063 | BM8: 908.16532 | BN8: 1404.8835 | BO8: 1821.7425 | BP8: 2080.4393 | BQ8: 3406.7652 | BR8: =8706.77662539-SUM(BP8:BQ8) -> 3219.5722 | BS8: =12966.04997921-SUM(BP8:BR8) -> 4259.2734 | BT8: =4238.90975812 -> 4238.9098 | BU8: =(BU7-BU12) -> 5899.644 | BV8: =(BV7-BV12) -> 7864.1978 | BW8: =(BW7-BW12) -> 8647.0191 | BX8: =(BX7-BX12) -> 8221.0385 | BY8: =(BY7-BY12) -> 8701.5586 | BZ8: =(BZ7-BZ12) -> 10874.892 | CA8: =(CA7-CA12) -> 10233.746 | CB8: =(CB7-CB12) -> 8375.8874 | ... CE8: =(CE7-CE12) -> 12326.371
B9: Others | BB9: 0 | BC9: 0 | BD9: 0 | BE9: 0 | BF9: 0 | BG9: 0 | BH9: 0 | BI9: 0 | BJ9: 0 | BK9: 0 | BL9: 0 | BR9: 0 | BS9: 0 | BT9: 0 | BU9: 0 | BV9: 0 | BW9: 0 | BX9: 0 | BY9: 0 | BZ9: 0 | CA9: 0 | CB9: 0 | CC9: 0 | CD9: 0 | CE9: 0
B10: Total COGS | E10: =E8+E9 -> 213.53676 | F10: =F8+F9 -> 234.62009 | G10: =G8+G9 -> 330.78362 | H10: =H8+H9 -> 363.06989 | I10: =I8+I9 -> 446.55322 | J10: =J8+J9 -> 525.653 | K10: =K8+K9 -> 666.78476 | L10: =L8+L9 -> 611.69329 | ... V10: =V8+V9 -> 43619.538 | X10: =X8+X9 -> 0 | Y10: =Y8+Y9 -> 0 | Z10: =Z8+Z9 -> 0 | AA10: =AA8+AA9 -> 0 | AB10: =AB8+AB9 -> 101.0667 | AC10: =AC8+AC9 -> 121.38813 | AD10: =AD8+AD9 -> 103.18521 | AE10: =AE8+AE9 -> 120.91319 | ... BO10: =BO8+BO9 -> 1821.7425 | BP10: =BP8+BP52 -> 2080.4393 | BQ10: =BQ8+BQ52 -> 3406.7652 | BR10: =BR8+BR9 -> 3219.5722 | BS10: =BS8+BS9 -> 4259.2734 | BT10: =BT8+BT9 -> 4238.9098 | BU10: =BU8+BU9 -> 5899.644 | BV10: =BV8+BV9 -> 7864.1978 | BW10: =BW8+BW9 -> 8647.0191 | BX10: =BX8+BX9 -> 8221.0385 | BY10: =BY8+BY9 -> 8701.5586 | ... CE10: =CE8+CE9 -> 12326.371
B12: Gross profit | E12: =+E7-E10 -> 91.39167 | F12: =+F7-F10 -> 112.94797 | G12: =+G7-G10 -> 130.26538 | H12: =+H7-H10 -> 159.56438 | I12: =+I7-I10 -> 168.56636 | J12: =+J7-J10 -> 188.27865 | K12: =+K7-K10 -> 210.5806 | L12: =+L7-L10 -> 148.25699 | ... V12: =+V7-V10 -> 41355.837 | X12: =+X7-X8 -> 0 | Y12: =+Y7-Y8 -> 0 | Z12: =+Z7-Z8 -> 0 | AA12: =+AA7-AA8 -> 0 | AB12: =+AB7-AB8 -> 40.19446 | AC12: =+AC7-AC8 -> 45.086918 | AD12: =+AD7-AD8 -> 39.014841 | AE12: =+AE7-AE8 -> 44.270139 | ... BT12: =+BT7-BT8 -> 4098.9923 | BU12: =+Assumption!S354 -> 5383.6042 | BV12: =+Assumption!T354 -> 7299.7231 | BW12: =+Assumption!U354 -> 8024.4494 | BX12: =+Assumption!V354 -> 6951.0483 | BY12: =+Assumption!W354 -> 8098.7216 | BZ12: =+Assumption!X354 -> 10786.429 | CA12: =+Assumption!Y354 -> 10043.157 | CB12: =+Assumption!Z354 -> 6297.7609 | ... CE12: =+Assumption!AC354 -> 12358.508
B13: Gross margin % | E13: =E12/E$7 -> 0.29971515 | F13: =F12/F$7 -> 0.32496649 | G13: =G12/G$7 -> 0.28254129 | H13: =H12/H$7 -> 0.30530792 | I13: =I12/I$7 -> 0.27403836 | J13: =J12/J$7 -> 0.26372083 | K13: =K12/K$7 -> 0.24001472 | L13: =L12/L$7 -> 0.19508775 | ... V13: =V12/V$7 -> 0.48668025 | AB13: =AB12/AB$7 -> 0.28454008 | AC13: =AC12/AC$7 -> 0.27083289 | AD13: =AD12/AD$7 -> 0.27436588 | AE13: =AE12/AE$7 -> 0.2680061 | AF13: =AF12/AF$7 -> 0.24739618 | AG13: =AG12/AG$7 -> 0.25790852 | AH13: =AH12/AH$7 -> 0.3130707 | AI13: =AI12/AI$7 -> 0.23970835 | ... CE13: =CE12/CE$7 -> 0.50065094
B15: Operating expense | E15: =E16+E17+E18+E19 -> 24.478799 | F15: =F16+F17+F18+F19 -> 33.851155 | G15: =G16+G17+G18+G19 -> 35.526742 | H15: =H16+H17+H18+H19 -> 48.705217 | I15: =I16+I17+I18+I19 -> 54.969527 | J15: =J16+J17+J18+J19 -> 64.604849 | K15: =K16+K17+K18+K19 -> 81.967153 | L15: =L16+L17+L18+L19 -> 105.1715 | ... S15: =S16+S17+S18+S19 -> 1167.3515 | T15: =SUMIF($X$3:$CA$3,T$4,$X15:$CA15) -> 1278.2996 | U15: =SUMIF($X$3:$CA$3,U$4,$X15:$CA15) -> 1534.6485 | V15: =SUMIF($X$3:$CE$3,V$4,$X15:$CE15) -> 1872.9189 | X15: =X16+X17+X18+X19 -> 0 | Y15: =Y16+Y17+Y18+Y19 -> 0 | Z15: =Z16+Z17+Z18+Z19 -> 0 | AA15: =AA16+AA17+AA18+AA19 -> 0 | AB15: =AB16+AB17+AB18+AB19 -> 11.046365 | AC15: =AC16+AC17+AC18+AC19 -> 14.398526 | AD15: =AD16+AD17+AD18+AD19 -> 13.369982 | AE15: =AE16+AE17+AE18+AE19 -> 16.154654 | ... CE15: =CE16+CE17+CE18+CE19 -> 776.25314
B16: Sales tax | E16: 1.0309883 | F16: 3.1413119 | G16: 1.5832431 | H16: 2.7907413 | I16: 3.6306729 | J16: 3.0253489 | K16: 2.3547487 | L16: 7.4679543 | M16: 6.1521281 | N16: 7.6608041 | O16: 7.9212035 | P16: =SUMIF($X$3:$BS$3,P$4,$X16:$BS16) -> 7.3868155 | Q16: =SUMIF($X$3:$BS$3,Q$4,$X16:$BS16) -> 16.80748 | R16: =SUMIF($X$3:$BS$3,R$4,$X16:$BS16) -> 71.857215 | S16: =SUMIF($X$3:$BS$3,S$4,$X16:$BS16) -> 74.911176 | T16: =SUMIF($X$3:$CA$3,T$4,$X16:$CA16) -> 81.486163 | U16: =SUMIF($X$3:$CA$3,U$4,$X16:$CA16) -> 61.369259 | V16: =SUMIF($X$3:$CE$3,V$4,$X16:$CE16) -> 307.13928 | X16: 0 | Y16: 0 | Z16: 0 | AA16: 0 | AB16: 1.5314792 | AC16: 1.1248105 | AD16: 0.11648197 | AE16: 0.85790132 | AF16: 0.70039975 | AG16: 0 | AH16: 0.91776698 | AI16: 1.4071822 | AJ16: 0.77571446 | AK16: 0.56946445 | AL16: 0.16460057 | AM16: 0.84496926 | AN16: 1.6107755 | AO16: 2.2172791 | AP16: 1.2419138 | AQ16: 2.3979858 | AR16: 1.0782531 | AS16: 1.8466857 | AT16: 1.4132913 | AU16: 1.813898 | AV16: 0.92888749 | AW16: 2.0577146 | AX16: 2.14177 | AY16: 2.5324319 | AZ16: 1.9915005 | BA16: 2.3494767 | BB16: 1.5592145 | BC16: 2.0210119 | BD16: 0.92598769 | BE16: 2.3907829 | BF16: 1.2308839 | BG16: 2.839161 | BH16: 2.5980494 | BI16: 5.4607112 | BJ16: 6.0369273 | BK16: 2.7117924 | BL16: 2.3094055 | BM16: 4.5301155 | BN16: 3.0626743 | BO16: 61.95502 | BP16: 3.3646597 | BQ16: 9.2938471 | BR16: =16.67433136-SUM(BP16:BQ16) -> 4.0158245 | BS16: =74.91117562-SUM(BP16:BR16) -> 58.236844 | BT16: =45.68400251 -> 45.684003 | BU16: =BU$7*BU78 -> 9.3686788 | BV16: =BV$7*BV78 -> 12.590869 | BW16: =BW$7*BW78 -> 13.842613 | BX16: =BX$7*BX78 -> 12.59765 | BY16: =BY$7*BY78 -> 13.949567 | BZ16: =BZ$7*BZ78 -> 17.985774 | CA16: =CA$7*CA78 -> 16.836268 | CB16: =CB$7*CB78 -> 14.673648 | ... CE16: =CE$7*CE78 -> 246.84879
B17: Marketing expense | E17: 4.5849908 | F17: 5.3915111 | G17: 6.9554956 | H17: 8.8869006 | I17: 9.3767561 | J17: 10.459758 | K17: 13.323467 | L17: 18.534026 | M17: 25.773565 | N17: 33.337902 | O17: 35.69091 | P17: =SUMIF($X$3:$BS$3,P$4,$X17:$BS17) -> 52.507976 | Q17: =SUMIF($X$3:$BS$3,Q$4,$X17:$BS17) -> 37.571976 | R17: =SUMIF($X$3:$BS$3,R$4,$X17:$BS17) -> 97.51957 | S17: =SUMIF($X$3:$BS$3,S$4,$X17:$BS17) -> 150.85483 | T17: =SUMIF($X$3:$CA$3,T$4,$X17:$CA17) -> 177.36132 | U17: =SUMIF($X$3:$CA$3,U$4,$X17:$CA17) -> 205.12464 | V17: =SUMIF($X$3:$CE$3,V$4,$X17:$CE17) -> 232.34682 | X17: 0 | Y17: 0 | Z17: 0 | AA17: 0 | AB17: 1.5783795 | AC17: 2.3241503 | AD17: 2.2919335 | AE17: 3.1822928 | AF17: 1.6415447 | AG17: 2.9033209 | AH17: 2.9379438 | AI17: 2.9769489 | AJ17: 2.7911682 | AK17: 2.6116458 | AL17: 2.7289171 | AM17: 5.1917361 | AN17: 3.4130193 | AO17: 4.3386544 | AP17: 3.8057829 | AQ17: 6.9765691 | AR17: 4.4209237 | AS17: 5.8629806 | AT17: 6.4967112 | AU17: 8.9929497 | AV17: 4.8875584 | AW17: 6.8180389 | AX17: 9.8500048 | AY17: 11.7823 | AZ17: 6.5554816 | BA17: 11.511421 | BB17: 9.1558312 | BC17: 8.4681769 | BD17: 6.4221203 | BE17: 14.141306 | BF17: 14.577638 | BG17: 17.366911 | BH17: 7.5350968 | BI17: 9.4922095 | BJ17: 8.411287 | BK17: 12.133382 | BL17: 20.426691 | BM17: 19.066037 | BN17: 23.14776 | BO17: 34.879081 | BP17: 37.831489 | BQ17: 47.133141 | BR17: =123.32511108-SUM(BP17:BQ17) -> 38.360481 | BS17: =150.85483325-SUM(BP17:BR17) -> 27.529722 | BT17: =35.61554813 -> 35.615548 | BU17: =+Assumption!S382 -> 41.796829 | BV17: =+Assumption!T382 -> 45.431336 | BW17: =+Assumption!U382 -> 54.517603 | BX17: =+Assumption!V382 -> 38.973682 | BY17: =+Assumption!W382 -> 41.024929 | BZ17: =+Assumption!X382 -> 51.281161 | CA17: =+Assumption!Y382 -> 73.844872 | CB17: =+Assumption!Z382 -> 44.145896 | ... CE17: =+Assumption!AC382 -> 83.644856
B18: Administrative expense | E18: 8.0882101 | F18: 11.025813 | G18: 10.786341 | H18: 18.838611 | I18: 18.541846 | J18: 21.863592 | K18: 21.367831 | L18: 26.504851 | M18: 33.66914 | N18: 31.563373 | O18: 33.888913 | P18: =SUMIF($X$3:$BS$3,P$4,$X18:$BS18) -> 84.517118 | Q18: =SUMIF($X$3:$BS$3,Q$4,$X18:$BS18) -> 76.212946 | R18: =SUMIF($X$3:$BS$3,R$4,$X18:$BS18) -> 169.0172 | S18: =SUMIF($X$3:$BS$3,S$4,$X18:$BS18) -> 239.44167 | T18: =SUMIF($X$3:$CA$3,T$4,$X18:$CA18) -> 289.14307 | U18: =SUMIF($X$3:$CA$3,U$4,$X18:$CA18) -> 318.15458 | V18: =SUMIF($X$3:$CE$3,V$4,$X18:$CE18) -> 349.03276 | X18: 0 | Y18: 0 | Z18: 0 | AA18: 0 | AB18: 2.5544568 | AC18: 4.606866 | AD18: 5.5437444 | AE18: 5.8209754 | AF18: 3.4462947 | AG18: 4.8410948 | AH18: 6.3344629 | AI18: 7.2266912 | AJ18: 2.6947803 | AK18: 3.4804127 | AL18: 2.700852 | AM18: =K18-SUM(AJ18:AL18) -> 12.491786 | AN18: 6.7830925 | AO18: 8.9636208 | AP18: 8.0879261 | AQ18: 2.6702117 | AR18: 6.2110254 | AS18: 7.9146465 | AT18: 7.6946224 | AU18: 11.848846 | AV18: 6.1076825 | AW18: 10.909877 | AX18: 7.9960088 | AY18: 6.5498047 | AZ18: 6.7433262 | BA18: 7.4346159 | BB18: 7.540505 | BC18: 12.170466 | BD18: 6.6248605 | BE18: 33.071019 | BF18: 19.983569 | BG18: 24.83767 | BH18: 17.439729 | BI18: 18.00179 | BJ18: 21.867661 | BK18: 18.903765 | BL18: 28.608848 | BM18: 39.091534 | BN18: 34.512275 | BO18: 66.804544 | BP18: 59.79066 | BQ18: 65.115232 | BR18: =187.87912994-SUM(BP18:BQ18) -> 62.973238 | BS18: =239.44167025-SUM(BP18:BR18) -> 51.56254 | BT18: =62.31596336 -> 62.315963 | BU18: =+Assumption!S383 -> 66.884915 | BV18: =+Assumption!T383 -> 72.700995 | BW18: =+Assumption!U383 -> 87.241194 | BX18: =+Assumption!V383 -> 69.994007 | BY18: =+Assumption!W383 -> 76.357098 | BZ18: =+Assumption!X383 -> 79.538644 | CA18: =+Assumption!Y383 -> 92.264827 | CB18: =+Assumption!Z383 -> 76.787208 | ... CE18: =+Assumption!AC383 -> 101.2195
B19: R&D | E19: 10.77461 | F19: 14.292519 | G19: 16.201662 | H19: 18.188965 | I19: 23.420253 | J19: 29.256149 | K19: =SUM(AJ19:AM19) -> 44.921107 | L19: 52.66467 | M19: 81.343198 | N19: 85.08282 | O19: 108.42423 | P19: =SUMIF($X$3:$BS$3,P$4,$X19:$BS19) -> 187.24136 | Q19: =SUMIF($X$3:$BS$3,Q$4,$X19:$BS19) -> 133.7745 | R19: =SUMIF($X$3:$BS$3,R$4,$X19:$BS19) -> 403.16862 | S19: =SUMIF($X$3:$BS$3,S$4,$X19:$BS19) -> 702.14385 | T19: =SUMIF($X$3:$CA$3,T$4,$X19:$CA19) -> 730.30909 | U19: =SUMIF($X$3:$CA$3,U$4,$X19:$CA19) -> 950 | V19: =SUMIF($X$3:$CE$3,V$4,$X19:$CE19) -> 984.4 | X19: 0 | Y19: 0 | Z19: 0 | AA19: 0 | AB19: 5.38205 | AC19: 6.3426992 | AD19: 5.4178219 | AE19: 6.2934847 | AF19: 5.9991611 | AG19: 7.9044569 | AH19: 6.991204 | AI19: 8.3763757 | AJ19: 9.8066283 | AK19: 12.245855 | AL19: 11.838033 | AM19: 11.03059 | AN19: 12.301369 | AO19: 16.310709 | AP19: 13.307034 | AQ19: 10.745558 | AR19: 11.85216 | AS19: 19.61628 | AT19: 23.723885 | AU19: 26.150873 | AV19: 15.025456 | AW19: 24.094791 | AX19: 25.910296 | AY19: 20.052277 | AZ19: 17.726631 | BA19: 15.523039 | BB19: 21.661675 | BC19: 53.512887 | BD19: 36.82674 | BE19: 28.363201 | BF19: 46.24608 | BG19: 75.805341 | BH19: 31.577936 | BI19: 29.23529 | BJ19: 39.469997 | BK19: 33.491279 | BL19: 53.18913 | BM19: 76.380596 | BN19: 71.286388 | BO19: 202.31251 | BP19: 117.88532 | BQ19: 215.8303 | BR19: =501.27453672-SUM(BP19:BQ19) -> 167.55892 | BS19: =702.14384824-SUM(BP19:BR19) -> 200.86931 | BT19: =119.90908567 -> 119.90909 | BU19: =+Assumption!S384 -> 160.23 | BV19: =+Assumption!T384 -> 167.86 | BW19: =+Assumption!U384 -> 282.31 | BX19: =+Assumption!V384 -> 190 | BY19: =+Assumption!W384 -> 209 | BZ19: =+Assumption!X384 -> 218.5 | CA19: =+Assumption!Y384 -> 332.5 | CB19: =+Assumption!Z384 -> 196.88 | ... CE19: =+Assumption!AC384 -> 344.54
B20: Operating income | E20: =+E12-E15 -> 66.91287 | F20: =+F12-F15 -> 79.09682 | G20: =+G12-G15 -> 94.738635 | H20: =+H12-H15 -> 110.85916 | I20: =+I12-I15 -> 113.59683 | J20: =+J12-J15 -> 123.6738 | K20: =+K12-K15 -> 128.61345 | L20: =+L12-L15 -> 43.085493 | ... V20: =+V12-V15 -> 39482.918 | X20: =X12-X15 -> 0 | Y20: =Y12-Y15 -> 0 | Z20: =Z12-Z15 -> 0 | AA20: =AA12-AA15 -> 0 | AB20: =AB12-AB15 -> 29.148095 | AC20: =AC12-AC15 -> 30.688392 | AD20: =AD12-AD15 -> 25.644859 | AE20: =AE12-AE15 -> 28.115484 | ... CE20: =CE12-CE15 -> 11582.255
B22: Other income (loss)
B23: Finance cost | E23: =E24+E25 -> 0 | F23: =F24+F25 -> 0 | G23: =G24+G25 -> 0 | H23: =H24+H25 -> 0 | I23: =I24+I25 -> 0 | J23: =J24+J25 -> 0 | K23: =K24+K25 -> 0 | L23: =L24+L25 -> 1.5070399 | ... V23: =V24+V25 -> 32 | X23: =X24+X25 -> 0 | Y23: =Y24+Y25 -> 0 | Z23: =Z24+Z25 -> 0 | AA23: =AA24+AA25 -> 0 | AB23: =AB24+AB25 -> 0 | AC23: =AC24+AC25 -> 0 | AD23: =AD24+AD25 -> 0 | AE23: =AE24+AE25 -> 0 | ... CE23: =CE24+CE25 -> 8
B24: Interest income | E24: 0 | F24: 0 | G24: 0 | H24: 0 | I24: 0 | J24: 0 | K24: 0 | L24: 1.6758867 | M24: 3.8919589 | N24: 2.6946375 | O24: 24.816541 | P24: =SUMIF($X$3:$CA$3,P$4,$X24:$CA24) -> 21.513061 | Q24: =SUMIF($X$3:$CA$3,Q$4,$X24:$CA24) -> 74.556974 | R24: =SUMIF($X$3:$CA$3,R$4,$X24:$CA24) -> 72.840411 | S24: =SUMIF($X$3:$CA$3,S$4,$X24:$CA24) -> 77.949111 | T24: =SUMIF($X$3:$CA$3,T$4,$X24:$CA24) -> 32 | U24: =SUMIF($X$3:$CA$3,U$4,$X24:$CA24) -> 32 | V24: =SUMIF($X$3:$CE$3,V$4,$X24:$CE24) -> 32 | X24: 0 | Y24: 0 | Z24: 0 | AA24: 0 | AB24: 0 | AC24: 0 | AD24: 0 | AE24: 0 | AF24: 0 | AG24: 0 | AH24: 0 | AI24: 0 | AJ24: 0 | AK24: 0 | AL24: 0 | AM24: 0 | AN24: 0.21279226 | AO24: 0.21279226 | AP24: 1.0100423 | AQ24: 0 | AR24: 1.0207775 | AS24: 0.89600147 | AT24: 0.7709664 | AU24: 1.2042135 | AV24: 0.80168869 | AW24: 0.51127851 | AX24: 0.41057836 | AY24: 0.97109194 | AZ24: 5.188926 | BA24: 6.7689806 | BB24: 6.3738236 | BC24: 6.484811 | BD24: 4.2031735 | BE24: 5.097521 | BF24: 5.46163 | BG24: 6.7507367 | BH24: 11.37104 | BI24: 13.281795 | BJ24: 26.392859 | BK24: 23.51128 | BL24: 22.630113 | BM24: 23.78794 | BN24: 16.924509 | BO24: 9.4978485 | BP24: 7.7676161 | BQ24: 8.8523463 | BR24: =37.57344289-SUM(BP24:BQ24) -> 20.95348 | BS24: =77.94911125-SUM(BP24:BR24) -> 40.375668 | BT24: 8 | BU24: 8 | BV24: 8 | BW24: 8 | BX24: 8 | BY24: 8 | BZ24: 8 | CA24: 8 | CB24: 8 | CC24: 8 | CD24: 8 | CE24: 8
B25: Interest expense | E25: 0 | F25: 0 | G25: 0 | H25: 0 | I25: 0 | J25: 0 | K25: 0 | L25: -0.16884679 | M25: 0 | N25: =SUM(AV25:AY25) -> -1.1574752 | O25: =SUM(AZ25:BC25) -> -0.28331815 | P25: =SUMIF($X$3:$CA$3,P$4,$X25:$CA25) -> 0 | Q25: =SUMIF($X$3:$CA$3,Q$4,$X25:$CA25) -> -1.5481576 | R25: =SUMIF($X$3:$CA$3,R$4,$X25:$CA25) -> -1.3764114 | S25: =SUMIF($X$3:$CA$3,S$4,$X25:$CA25) -> -1.186448 | T25: =SUMIF($X$3:$CA$3,T$4,$X25:$CA25) -> 0 | U25: =SUMIF($X$3:$CA$3,U$4,$X25:$CA25) -> 0 | V25: =SUMIF($X$3:$CE$3,V$4,$X25:$CE25) -> 0 | X25: 0 | Y25: 0 | Z25: 0 | AA25: 0 | AB25: 0 | AC25: 0 | AD25: 0 | AE25: 0 | AF25: 0 | AG25: 0 | AH25: 0 | AI25: 0 | AJ25: 0 | AK25: 0 | AL25: 0 | AM25: 0 | AN25: -0.07954927 | AO25: -0.07954927 | AP25: -0.00730599 | AQ25: -0.00244226 | AR25: 0 | AS25: 0 | AT25: 0 | AU25: 0 | AV25: 0 | AW25: -0.06289191 | AX25: -1.0945833 | AY25: 0 | AZ25: -0.28331815 | BA25: 0 | BB25: 0 | BC25: 0 | BD25: 0 | BE25: 0 | BF25: 0 | BG25: 0 | BH25: 0 | BI25: 0 | BJ25: 0 | BK25: -1.5481576 | BL25: 0 | BM25: 0 | BN25: -1.0469028 | BO25: -0.32950863 | BP25: -0.30235204 | BQ25: -0.32073607 | BR25: =-0.91317087-SUM(BP25:BQ25) -> -0.29008276 | BS25: =-1.18644797-SUM(BP25:BR25) -> -0.2732771 | BT25: 0 | BU25: 0 | BV25: 0 | BW25: 0 | BX25: 0 | BY25: 0 | BZ25: 0 | CA25: 0 | CB25: 0 | CC25: 0 | CD25: 0 | CE25: 0
B26: Impairement loss | E26: -4.6515779 | F26: -3.4960642 | G26: -4.8385604 | H26: -6.5136737 | I26: -7.1912244 | J26: -8.8061087 | K26: -14.462745 | L26: -25.976368 | M26: 22.731227 | N26: -44.011707 | O26: -55.467909 | P26: =SUMIF($X$3:$CA$3,P$4,$X26:$CA26) -> -127.90719 | Q26: =SUMIF($X$3:$CA$3,Q$4,$X26:$CA26) -> -17.09093 | R26: =SUMIF($X$3:$CA$3,R$4,$X26:$CA26) -> -79.479127 | S26: =SUMIF($X$3:$CA$3,S$4,$X26:$CA26) -> -203.27471 | T26: =SUMIF($X$3:$CA$3,T$4,$X26:$CA26) -> 0 | U26: =SUMIF($X$3:$CA$3,U$4,$X26:$CA26) -> 0 | V26: =SUMIF($X$3:$CE$3,V$4,$X26:$CE26) -> 0 | X26: 0 | Y26: 0 | Z26: 0 | AA26: 0 | AB26: -0.52031621 | AC26: -1.6788491 | AD26: -1.5138356 | AE26: -3.4782235 | AF26: -0.37438521 | AG26: -5.0878055 | AH26: 0.43037909 | AI26: -3.7742971 | AJ26: -0.33384969 | AK26: -6.8074322 | AL26: -1.6927326 | AM26: -5.6287301 | AN26: -7.8002539 | AO26: -10.639208 | AP26: -0.35709419 | AQ26: -7.179812 | AR26: -2.6942899 | AS26: 3.2718168 | AT26: 9.7305844 | AU26: 13.881802 | AV26: -12.137102 | AW26: -9.1521584 | AX26: -10.249426 | AY26: -12.473021 | AZ26: -25.623578 | BA26: -19.555796 | BB26: -1.8666259 | BC26: -8.4219096 | BD26: -30.042973 | BE26: -15.982685 | BF26: -29.548448 | BG26: -52.33308 | BH26: -5.3841943 | BI26: -27.736162 | BJ26: 16.814579 | BK26: -0.78515197 | BL26: -11.863557 | BM26: -5.4648797 | BN26: -3.3488203 | BO26: -58.801869 | BP26: -16.816659 | BQ26: -145.84896 | BR26: =-203.2747145-SUM(BP26:BQ26) -> -40.609092 | BS26: 0 | BT26: 0 | BU26: 0 | BV26: 0 | BW26: 0 | BX26: 0 | BY26: 0 | BZ26: 0 | CA26: 0 | CB26: 0 | CC26: 0 | CD26: 0 | CE26: 0
B27: Profit/(loss) on disposal of assets (pre-tax) | E27: 0 | F27: 0 | G27: 0 | H27: 0 | I27: 0 | J27: 0 | K27: =SUMIF($X$3:$BC$3,K$4,$X27:$BC27) -> 0.0014594 | L27: =SUMIF($X$3:$BC$3,L$4,$X27:$BC27) -> -0.00519486 | M27: =SUMIF($X$3:$BC$3,M$4,$X27:$BC27) -> -0.23568619 | N27: =SUMIF($X$3:$BC$3,N$4,$X27:$BC27) -> 0 | O27: =SUMIF($X$3:$BC$3,O$4,$X27:$BC27) -> 0 | P27: =SUMIF($X$3:$CA$3,P$4,$X27:$CA27) -> 0 | Q27: =SUMIF($X$3:$CA$3,Q$4,$X27:$CA27) -> 0 | R27: =SUMIF($X$3:$CA$3,R$4,$X27:$CA27) -> 0 | S27: =SUMIF($X$3:$CA$3,S$4,$X27:$CA27) -> 0 | T27: =SUMIF($X$3:$CA$3,T$4,$X27:$CA27) -> 0 | U27: =SUMIF($X$3:$CA$3,U$4,$X27:$CA27) -> 0 | V27: =SUMIF($X$3:$CE$3,V$4,$X27:$CE27) -> 0 | X27: 0 | Y27: 0 | Z27: 0 | AA27: 0 | AB27: 0 | AC27: 0 | AD27: 0 | AE27: 0 | AF27: 0 | AG27: 0 | AH27: 0 | AI27: =J27-SUM(AF27:AH27) -> 0 | AJ27: 0 | AK27: 0 | AL27: 0 | AM27: 0.0014594 | AN27: 0 | AO27: -0.00028033 | AP27: -0.00491453 | AQ27: 0 | AR27: -0.015131 | AS27: 0 | AT27: -4.206e-05 | AU27: -0.22051313 | AV27: 0 | AW27: 0 | AX27: 0 | AY27: 0 | AZ27: 0 | BA27: 0 | BB27: 0 | BC27: 0 | BD27: 0 | BE27: 0 | BF27: 0 | BG27: 0 | BH27: 0 | BI27: 0 | BJ27: 0 | BK27: 0 | BL27: 0 | BM27: 0 | BN27: 0 | BO27: 0 | BP27: 0 | BQ27: 0 | BR27: 0
B28: Foreign exchange gain/(loss) | E28: -1.2759848 | F28: 0.87583712 | G28: 0.63505934 | H28: -0.39697851 | I28: -1.2495179 | J28: 2.2459649 | K28: -1.0793135 | L28: 8.8697317 | M28: 1.6406342 | N28: -10.819674 | O28: -16.981929 | P28: =SUMIF($X$3:$CA$3,P$4,$X28:$CA28) -> 103.00442 | Q28: =SUMIF($X$3:$CA$3,Q$4,$X28:$CA28) -> 35.235133 | R28: =SUMIF($X$3:$CA$3,R$4,$X28:$CA28) -> 107.85263 | S28: =SUMIF($X$3:$CA$3,S$4,$X28:$CA28) -> -292.07134 | T28: =SUMIF($X$3:$CA$3,T$4,$X28:$CA28) -> 0 | U28: =SUMIF($X$3:$CA$3,U$4,$X28:$CA28) -> 0 | V28: =SUMIF($X$3:$CE$3,V$4,$X28:$CE28) -> 0 | X28: 0 | Y28: 0 | Z28: 0 | AA28: 0 | AB28: -0.03317053 | AC28: -0.23142713 | AD28: -1.2083 | AE28: 0.22337968 | AF28: 0.22431057 | AG28: 0.42130472 | AH28: 0.49871425 | AI28: 1.1016353 | AJ28: -0.0815715 | AK28: -0.17061527 | AL28: -0.75027908 | AM28: -0.07684766 | AN28: -1.5106389 | AO28: 5.4321046 | AP28: 5.9292237 | AQ28: -0.74069781 | AR28: -3.6336342 | AS28: 3.4605056 | AT28: 5.769466 | AU28: -3.9557033 | AV28: 2.2717544 | AW28: -0.79329007 | AX28: -1.6649782 | AY28: -10.63316 | AZ28: 3.1867865 | BA28: -6.8254145 | BB28: 1.6321898 | BC28: -14.975491 | BD28: -3.3635052 | BE28: 62.102671 | BF28: 85.303093 | BG28: -41.037838 | BH28: -25.583344 | BI28: 95.360524 | BJ28: -15.398042 | BK28: -19.144005 | BL28: -1.832293 | BM28: 22.833825 | BN28: 8.0869905 | BO28: 78.764112 | BP28: 25.621481 | BQ28: 166.3353 | BR28: =-255.41106663-SUM(BP23:BR23,BP28:BQ28) -> -484.02812 | BS28: 0 | BT28: 0 | BU28: 0 | BV28: 0 | BW28: 0 | BX28: 0 | BY28: 0 | BZ28: 0 | CA28: 0 | CB28: 0 | CC28: 0 | CD28: 0 | CE28: 0
B29: Income (loss) from associates | E29: 0 | F29: 0 | G29: 0 | H29: =SUMIF($X$3:$BC$3,H$4,$X29:$BC29) -> 0 | I29: =SUMIF($X$3:$BC$3,I$4,$X29:$BC29) -> 0 | J29: =SUMIF($X$3:$BC$3,J$4,$X29:$BC29) -> 0 | K29: =SUMIF($X$3:$BC$3,K$4,$X29:$BC29) -> 0 | L29: =SUMIF($X$3:$BC$3,L$4,$X29:$BC29) -> -3.1526989 | M29: =SUMIF($X$3:$BC$3,M$4,$X29:$BC29) -> -1.3165856 | N29: =SUMIF($X$3:$BC$3,N$4,$X29:$BC29) -> 0.28141801 | O29: =SUMIF($X$3:$BC$3,O$4,$X29:$BC29) -> -3.7562863 | P29: =SUMIF($X$3:$CA$3,P$4,$X29:$CA29) -> -1.97635 | Q29: =SUMIF($X$3:$CA$3,Q$4,$X29:$CA29) -> 0 | R29: =SUMIF($X$3:$CA$3,R$4,$X29:$CA29) -> 0 | S29: =SUMIF($X$3:$CA$3,S$4,$X29:$CA29) -> 0 | T29: =SUMIF($X$3:$CA$3,T$4,$X29:$CA29) -> 0 | U29: =SUMIF($X$3:$CA$3,U$4,$X29:$CA29) -> 0 | V29: =SUMIF($X$3:$CE$3,V$4,$X29:$CE29) -> 0 | X29: 0 | Y29: 0 | Z29: 0 | AA29: 0 | AB29: 0 | AC29: 0 | AD29: 0 | AE29: 0 | AF29: 0 | AG29: 0 | AH29: 0 | AI29: 0 | AJ29: 0 | AK29: 0 | AL29: 0 | AM29: 0 | AN29: 0 | AO29: 0 | AP29: 0 | AQ29: -3.1526989 | AR29: -1.2742773 | AS29: -0.66912725 | AT29: -1.1364825 | AU29: 1.7633014 | AV29: 0.79623006 | AW29: 0.95373568 | AX29: -1.5917059 | AY29: 0.12315822 | AZ29: -0.11154186 | BA29: -2.1641403 | BB29: -0.74584312 | BC29: -0.73476107 | BD29: -2.3436388 | BE29: -1.0160269 | BF29: 0 | BG29: 1.3833157 | BH29: 0 | BI29: 0 | BJ29: 0 | BK29: 0 | BL29: 0 | BM29: 0 | BN29: 0 | BO29: 0 | BP29: 0 | BQ29: 0 | BR29: 0 | BS29: 0 | BT29: 0 | BU29: 0 | BV29: 0 | BW29: 0 | BX29: 0 | BY29: 0 | BZ29: 0 | CA29: 0 | CB29: 0 | CC29: 0 | CD29: 0 | CE29: 0
B30: Share of results in jointly controlled entities | E30: 0 | F30: 0 | G30: 0 | H30: 0 | I30: 0 | J30: 0 | K30: 0 | L30: 0 | M30: 0 | N30: 0 | O30: 0 | P30: =SUMIF($X$3:$CA$3,P$4,$X30:$CA30) -> 0 | Q30: =SUMIF($X$3:$CA$3,Q$4,$X30:$CA30) -> 2 | R30: =SUMIF($X$3:$CA$3,R$4,$X30:$CA30) -> 10 | S30: =SUMIF($X$3:$CA$3,S$4,$X30:$CA30) -> 10 | T30: =SUMIF($X$3:$CA$3,T$4,$X30:$CA30) -> 0 | U30: =SUMIF($X$3:$CA$3,U$4,$X30:$CA30) -> 0 | V30: =SUMIF($X$3:$CE$3,V$4,$X30:$CE30) -> 0 | X30: 0 | Y30: 0 | Z30: 0 | AA30: 0 | AB30: 0 | AC30: 0 | AD30: 0 | AE30: 0 | AF30: 0 | AG30: 0 | AH30: 0 | AI30: 0 | AJ30: 0 | AK30: 0 | AL30: 0 | AM30: 0 | AN30: 0 | AO30: 0 | AP30: 0 | AQ30: 0 | AR30: 0 | AS30: 0 | AT30: 0 | AU30: 0 | AV30: 0 | AW30: 0 | AX30: 0 | AY30: 0 | AZ30: 0 | BA30: 0 | BB30: 0 | BC30: 0 | BD30: 0 | BE30: 0 | BF30: 0 | BG30: 0 | BH30: 0 | BI30: 0 | BJ30: 1 | BK30: 1 | BL30: 1 | BM30: 2 | BN30: 3 | BO30: 4 | BP30: 5 | BQ30: 5 | BR30: 0 | BS30: 0 | BT30: 0 | BU30: 0 | BV30: 0 | BW30: 0 | BX30: 0 | BY30: 0 | BZ30: 0 | CA30: 0 | CB30: 0 | CC30: 0 | CD30: 0 | CE30: 0
B31: Other non-operating income/expense | E31: =+E32-E23-E26-E27-E29-E30-E28 -> 1.6425902 | F31: =+F32-F23-F26-F27-F29-F30-F28 -> 1.1003392 | G31: =+G32-G23-G26-G27-G29-G30-G28 -> 2.824073 | H31: =+H32-H23-H26-H27-H29-H30-H28 -> 4.2469028 | I31: =+I32-I23-I26-I27-I29-I30-I28 -> 5.3171258 | J31: =+J32-J23-J26-J27-J29-J30-J28 -> 10.914922 | K31: =+K32-K23-K26-K27-K29-K30-K28 -> 14.46454 | L31: =+L32-L23-L26-L27-L29-L30-L28 -> 11.182371 | ... O31: =+O32-O23-O26-O27-O29-O30-O28 -> 65.004174 | P31: =SUMIF($X$3:$CA$3,P$4,$X31:$CA31) -> 151.16892 | Q31: =SUMIF($X$3:$CA$3,Q$4,$X31:$CA31) -> -0.00736915 | R31: =SUMIF($X$3:$CA$3,R$4,$X31:$CA31) -> -0.70405333 | S31: =SUMIF($X$3:$CA$3,S$4,$X31:$CA31) -> 565.84909 | T31: =SUMIF($X$3:$CA$3,T$4,$X31:$CA31) -> 153.11671 | U31: =SUMIF($X$3:$CA$3,U$4,$X31:$CA31) -> 0 | V31: =SUMIF($X$3:$CE$3,V$4,$X31:$CE31) -> 0 | X31: =+X32-X23-X26-X27-X29-X30-X28 -> 0 | Y31: =+Y32-Y23-Y26-Y27-Y29-Y30-Y28 -> 0 | Z31: =+Z32-Z23-Z26-Z27-Z29-Z30-Z28 -> 0 | AA31: =+AA32-AA23-AA26-AA27-AA29-AA30-AA28 -> 0 | AB31: =+AB32-AB23-AB26-AB27-AB29-AB30-AB28 -> 0.51978401 | AC31: =+AC32-AC23-AC26-AC27-AC29-AC30-AC28 -> 2.4493645 | AD31: =+AD32-AD23-AD26-AD27-AD29-AD30-AD28 -> 0.47678098 | AE31: =+AE32-AE23-AE26-AE27-AE29-AE30-AE28 -> 1.8711963 | ... BT31: =+BT32-BT23-BT26-BT27-BT29-BT30-BT28 -> -596.88329 | BU31: 200 | BV31: 250 | BW31: 300 | BX31: 0 | BY31: 0 | BZ31: 0 | CA31: 0 | CB31: 0 | CC31: 0 | CD31: 0 | CE31: 0
B32: Other income (loss) | E32: =+E33-E20 -> -4.2849725 | F32: =+F33-F20 -> -1.5198879 | G32: =+G33-G20 -> -1.379428 | H32: =+H33-H20 -> -2.6637495 | I32: =+I33-I20 -> -3.1236165 | J32: =+J33-J20 -> 4.3547783 | K32: =+K33-K20 -> -1.0760583 | L32: =+L33-L20 -> -7.5751188 | ... O32: =+O33-O20 -> 13.331272 | P32: =SUM(P24:P31) -> 145.80287 | Q32: =SUM(Q24:Q31) -> 93.14565 | R32: =SUM(R24:R31) -> 109.13345 | S32: =SUM(S24:S31) -> 157.2657 | T32: =SUM(T24:T31) -> 185.11671 | U32: =SUM(U24:U31) -> 32 | V32: =SUM(V24:V31) -> 32 | X32: =+X33-X20 -> 0 | Y32: =+Y33-Y20 -> 0 | Z32: =+Z33-Z20 -> 0 | AA32: =+AA33-AA20 -> 0 | AB32: =+AB33-AB20 -> -0.03370273 | AC32: =+AC33-AC20 -> 0.53908822 | AD32: =+AD33-AD20 -> -2.2453546 | AE32: =+AE33-AE20 -> -1.3836475 | ... BT32: =+BT33-BT20 -> -588.88329 | BU32: =SUM(BU24:BU31) -> 208 | BV32: =SUM(BV24:BV31) -> 258 | BW32: =SUM(BW24:BW31) -> 308 | BX32: =SUM(BX24:BX31) -> 8 | BY32: =SUM(BY24:BY31) -> 8 | BZ32: =SUM(BZ24:BZ31) -> 8 | CA32: =SUM(CA24:CA31) -> 8 | CB32: =SUM(CB24:CB31) -> 8 | ... CE32: =SUM(CE24:CE31) -> 8
B33: Pre-tax profit | E33: 62.627898 | F33: 77.576932 | G33: 93.359207 | H33: 108.19541 | I33: =SUM(AB33:AE33) -> 110.47321 | J33: 128.02858 | K33: =SUM(AJ33:AM33) -> 127.53739 | L33: 35.510374 | M33: 243.95119 | N33: 561.5991 | O33: 763.07318 | P33: =P20+P32 -> 1027.8648 | Q33: =Q20+Q32 -> 788.72812 | R33: =R20+R32 -> 3234.21 | S33: =S20+S32 -> 10865.719 | T33: =T20+T32 -> 23713.586 | U33: =U20+U32 -> 34376.707 | V33: =V20+V32 -> 39514.918 | X33: 0 | Y33: 0 | Z33: 0 | AA33: 0 | AB33: 29.114392 | AC33: 31.227481 | AD33: 23.399505 | AE33: 26.731837 | AF33: 25.347175 | AG33: 32.56913 | AH33: 40.459621 | AI33: 29.652653 | AJ33: 35.276249 | AK33: 38.867553 | AL33: 40.757933 | AM33: 12.635653 | AN33: -4.2153316 | AO33: -13.294118 | AP33: 24.253633 | AQ33: 28.766191 | AR33: 38.241664 | AS33: 56.844217 | AT33: 61.945019 | AU33: 86.920293 | AV33: 66.227378 | AW33: 158.56193 | AX33: 177.4593 | AY33: 159.3505 | AZ33: 136.99556 | BA33: 243.10482 | BB33: 157.34392 | BC33: 225.62886 | BD33: 156.25975 | BE33: 367.73023 | BF33: 338.76758 | BG33: 165.10727 | BH33: 127.79097 | BI33: 200.39036 | BJ33: 157.87317 | BK33: 302.67362 | BL33: 372.37105 | BM33: 608.80106 | BN33: 888.62074 | BO33: 1364.4172 | BP33: 1773.2538 | BQ33: 2675.1314 | BR33: =7050.53350656-SUM(BP33:BQ33) -> 2602.1483 | BS33: =10865.71903686-SUM(BP33:BR33) -> 3815.1855 | BT33: =3246.58439536 -> 3246.5844 | BU33: =BU20+BU32 -> 5313.3237 | BV33: =BV20+BV32 -> 7259.1399 | BW33: =BW20+BW32 -> 7894.538 | BX33: =BX20+BX32 -> 6647.483 | BY33: =BY20+BY32 -> 7766.39 | BZ33: =BZ20+BZ32 -> 10427.123 | CA33: =CA20+CA32 -> 9535.711 | CB33: =CB20+CB32 -> 5973.2741 | ... CE33: =CE20+CE32 -> 11590.255
B36: Income taxes | E36: 10.053113 | F36: 11.829224 | G36: 14.000439 | H36: 15.79688 | I36: 16.022886 | J36: 22.741796 | K36: 16.446483 | L36: 3.6780402 | M36: 31.094637 | N36: 69.840693 | O36: 101.14704 | P36: =SUMIF($X$3:$BS$3,P$4,$X36:$BS36) -> 124.28375 | Q36: =SUMIF($X$3:$BS$3,Q$4,$X36:$BS36) -> 100.36703 | R36: =SUMIF($X$3:$BS$3,R$4,$X36:$BS36) -> 396.39641 | S36: =SUMIF($X$3:$BS$3,S$4,$X36:$BS36) -> 1312.4428 | T36: =SUMIF($X$3:$CA$3,T$4,$X36:$CA36) -> 2964.1982 | U36: =SUMIF($X$3:$CA$3,U$4,$X36:$CA36) -> 4297.0884 | V36: =SUMIF($X$3:$CE$3,V$4,$X36:$CE36) -> 4939.3648 | X36: 0 | Y36: 0 | Z36: 0 | AA36: 0 | AB36: 4.3355021 | AC36: 4.5909181 | AD36: 3.4291732 | AE36: 3.6672928 | AF36: 3.8682969 | AG36: 5.5777014 | AH36: 8.4337011 | AI36: 4.8620965 | AJ36: 5.3998228 | AK36: 6.0853736 | AL36: 6.7949636 | AM36: -1.833677 | AN36: -0.57791537 | AO36: -1.7769813 | AP36: 3.6836035 | AQ36: 2.3493333 | AR36: 5.8303189 | AS36: 8.592563 | AT36: 9.6268265 | AU36: 7.0449281 | AV36: 10.01117 | AW36: 23.561218 | AX36: 26.828291 | AY36: 9.4400132 | AZ36: 24.58961 | BA36: 32.505567 | BB36: 15.481628 | BC36: 28.570231 | BD36: 23.836916 | BE36: 39.066172 | BF36: 37.420229 | BG36: 23.960435 | BH36: 19.956156 | BI36: 19.86029 | BJ36: 16.674549 | BK36: 43.87603 | BL36: 47.830512 | BM36: 68.1995 | BN36: 107.68996 | BO36: 172.67644 | BP36: 200.72805 | BQ36: 305.3629 | BR36: =723.44099872-SUM(BP36:BQ36) -> 217.35006 | BS36: =1312.44281971-SUM(BP36:BR36) -> 589.00182 | BT36: =+BT87*BT33 -> 405.82305 | BU36: =+BU87*BU33 -> 664.16547 | BV36: =+BV87*BV33 -> 907.39248 | BW36: =+BW87*BW33 -> 986.81725 | BX36: =+BX87*BX33 -> 830.93537 | BY36: =+BY87*BY33 -> 970.79875 | BZ36: =+BZ87*BZ33 -> 1303.3904 | CA36: =+CA87*CA33 -> 1191.9639 | ... CE36: =+CE87*CE33 -> 1448.7818
B37: Minority interest | E37: =+E33-E36-E40 -> 0 | F37: =+F33-F36-F40 -> 0 | G37: =+G33-G36-G40 -> 0 | H37: =+H33-H36-H40 -> 0 | I37: =+I33-I36-I40 -> 0 | J37: =+J33-J36-J40 -> 0 | K37: =+K33-K36-K40 -> 0 | L37: =+L33-L36-L40 -> 0 | ... O37: =+O33-O36-O40 -> 0 | P37: =SUMIF($X$3:$BS$3,P$4,$X37:$BS37) -> -2.8421709e-14 | Q37: =SUMIF($X$3:$BS$3,Q$4,$X37:$BS37) -> 4.2632564e-14 | R37: =SUMIF($X$3:$BS$3,R$4,$X37:$BS37) -> -1.1368684e-13 | S37: =SUMIF($X$3:$BS$3,S$4,$X37:$BS37) -> 21.353487 | T37: =SUMIF($X$3:$CA$3,T$4,$X37:$CA37) -> 66.565083 | U37: =SUMIF($X$3:$CA$3,U$4,$X37:$CA37) -> 0 | V37: =SUMIF($X$3:$CE$3,V$4,$X37:$CE37) -> 0 | X37: =+X33-X36-X40 -> 0 | Y37: =+Y33-Y36-Y40 -> 0 | Z37: =+Z33-Z36-Z40 -> 0 | AA37: =+AA33-AA36-AA40 -> 0 | AB37: =+AB33-AB36-AB40 -> 0 | AC37: =+AC33-AC36-AC40 -> 0 | AD37: =+AD33-AD36-AD40 -> 0 | AE37: =+AE33-AE36-AE40 -> 0 | ... AO37: =+AO33-AO36-AO40 -> 0 | AP37: =+AP33-AP36-AP40-AP38-AP39 -> 0 | AQ37: =+AQ33-AQ36-AQ40-AQ38-AQ39 -> -3.5527137e-15 | AR37: =+AR33-AR36-AR40-AR38-AR39 -> 7.1054274e-15 | AS37: =+AS33-AS36-AS40-AS38-AS39 -> -7.1054274e-15 | AT37: =+AT33-AT36-AT40-AT38-AT39 -> 0 | AU37: =+AU33-AU36-AU40-AU38-AU39 -> 0 | AV37: =+AV33-AV36-AV40-AV38-AV39 -> -7.1054274e-15 | AW37: =+AW33-AW36-AW40-AW38-AW39 -> 0 | ... BT37: =+BT33-BT36-BT40-BT38-BT39 -> 66.565083 | BU37: =+Assumption!S197 -> 0 | BV37: =+Assumption!T197 -> 0 | BW37: =+Assumption!U197 -> 0 | BX37: =+Assumption!V197 -> 0 | BY37: =+Assumption!W197 -> 0 | BZ37: =+Assumption!X197 -> 0 | CA37: =+Assumption!Y197 -> 0 | CB37: =+Assumption!Z197 -> 0 | ... CE37: =+Assumption!AC197 -> 0
B38: Preferred dividends | E38: 0 | F38: 0 | G38: 0 | H38: 0 | I38: 0 | J38: 0 | K38: 0 | L38: 0 | M38: 0 | N38: 0 | O38: 0 | P38: =SUMIF($X$3:$BS$3,P$4,$X38:$BS38) -> 0 | Q38: =SUMIF($X$3:$BS$3,Q$4,$X38:$BS38) -> 0 | R38: =SUMIF($X$3:$BS$3,R$4,$X38:$BS38) -> 0 | S38: =SUMIF($X$3:$BS$3,S$4,$X38:$BS38) -> 0 | T38: =SUMIF($X$3:$CA$3,T$4,$X38:$CA38) -> 0 | U38: =SUMIF($X$3:$CA$3,U$4,$X38:$CA38) -> 0 | V38: =SUMIF($X$3:$CE$3,V$4,$X38:$CE38) -> 0 | AJ38: 0 | AK38: 0 | AL38: 0 | AM38: 0 | AN38: 0 | AO38: 0 | AP38: 0 | AQ38: 0 | AR38: 0 | AS38: 0 | AT38: 0 | AU38: 0 | AV38: 0 | AW38: 0 | AX38: 0 | AY38: 0 | AZ38: 0 | BA38: 0 | BB38: 0 | BC38: 0 | BD38: 0 | BE38: 0 | BF38: 0 | BG38: 0 | BH38: 0 | BI38: 0 | BJ38: 0 | BK38: 0 | BL38: 0 | BM38: 0 | BN38: 0 | BO38: 0 | BP38: 0 | BQ38: 0 | BR38: 0 | BS38: 0
B39: Extraordinary gain/(loss) | E39: 0 | F39: 0 | G39: 0 | H39: 0 | I39: 0 | J39: 0 | K39: 0 | L39: 0 | M39: 0 | N39: 0 | O39: 0 | P39: =SUMIF($X$3:$BS$3,P$4,$X39:$BS39) -> 0 | Q39: =SUMIF($X$3:$BS$3,Q$4,$X39:$BS39) -> 0 | R39: =SUMIF($X$3:$BS$3,R$4,$X39:$BS39) -> 0 | S39: =SUMIF($X$3:$BS$3,S$4,$X39:$BS39) -> 0 | T39: =SUMIF($X$3:$CA$3,T$4,$X39:$CA39) -> 0 | U39: =SUMIF($X$3:$CA$3,U$4,$X39:$CA39) -> 0 | V39: =SUMIF($X$3:$CE$3,V$4,$X39:$CE39) -> 0 | AJ39: 0 | AK39: 0 | AL39: 0 | AM39: 0 | AN39: 0 | AO39: 0 | AP39: 0 | AQ39: 0 | AR39: 0 | AS39: 0 | AT39: 0 | AU39: 0 | AV39: 0 | AW39: 0 | AX39: 0 | AY39: 0 | AZ39: 0 | BA39: 0 | BB39: 0 | BC39: 0 | BD39: 0 | BE39: 0 | BF39: 0 | BG39: 0 | BH39: 0 | BI39: 0 | BJ39: 0 | BK39: 0 | BL39: 0 | BM39: 0 | BN39: 0 | BO39: 0 | BP39: 0 | BQ39: 0 | BR39: 0 | BS39: 0
B40: Net income | E40: 52.574785 | F40: 65.747708 | G40: 79.358767 | H40: 92.398535 | I40: =SUM(AB40:AE40) -> 94.450328 | J40: 105.28678 | K40: =SUM(AJ40:AM40) -> 111.09091 | L40: 31.832334 | M40: 212.85656 | N40: 491.7584 | O40: 661.92614 | P40: =+P33-P36-P37-P38+P39 -> 903.58109 | Q40: =+Q33-Q36-Q37-Q38+Q39 -> 688.3611 | R40: =+R33-R36-R37-R38+R39 -> 2837.8136 | S40: =+S33-S36-S37-S38+S39 -> 9531.9227 | T40: =+T33-T36-T37-T38+T39 -> 20682.823 | U40: =+U33-U36-U37-U38+U39 -> 30079.619 | V40: =+V33-V36-V37-V38+V39 -> 34575.554 | X40: 0 | Y40: 0 | Z40: 0 | AA40: 0 | AB40: 24.77889 | AC40: 26.636562 | AD40: 19.970332 | AE40: 23.064544 | AF40: 21.478878 | AG40: 26.991428 | AH40: 32.02592 | AI40: 24.790557 | AJ40: 29.876426 | AK40: 32.78218 | AL40: 33.96297 | AM40: 14.46933 | AN40: -3.6374163 | AO40: -11.517137 | AP40: 20.570029 | AQ40: 26.416858 | AR40: 32.411345 | AS40: 48.251654 | AT40: 52.318192 | AU40: 79.875365 | AV40: 56.216207 | AW40: 135.00071 | AX40: 150.63101 | AY40: 149.91048 | AZ40: 112.40595 | BA40: 210.59926 | BB40: 141.86229 | BC40: 197.05863 | BD40: 132.42284 | BE40: 328.66406 | BF40: 301.34736 | BG40: 141.14684 | BH40: 107.83481 | BI40: 180.53007 | BJ40: 141.19862 | BK40: 258.79759 | BL40: 324.54053 | BM40: 540.60156 | BN40: 780.93078 | BO40: 1191.7408 | BP40: 1572.5258 | BQ40: 2369.7685 | BR40: =6327.09250784-SUM(BP40:BQ40) -> 2384.7982 | BS40: =9531.92273017-SUM(BP40:BR40) -> 3204.8302 | BT40: =2774.19626334 -> 2774.1963 | BU40: =+BU33-BU36-BU37-BU38+BU39 -> 4649.1583 | BV40: =+BV33-BV36-BV37-BV38+BV39 -> 6351.7474 | BW40: =+BW33-BW36-BW37-BW38+BW39 -> 6907.7207 | BX40: =+BX33-BX36-BX37-BX38+BX39 -> 5816.5476 | BY40: =+BY33-BY36-BY37-BY38+BY39 -> 6795.5912 | BZ40: =+BZ33-BZ36-BZ37-BZ38+BZ39 -> 9123.7327 | CA40: =+CA33-CA36-CA37-CA38+CA39 -> 8343.7472 | CB40: =+CB33-CB36-CB37-CB38+CB39 -> 5226.6149 | ... CE40: =+CE33-CE36-CE37-CE38+CE39 -> 10141.473
BP42: 1572.5258 | BQ42: 2369.7685 | BR42: 2667.2627 | BS42: 2827.4641 | BT42: 2907.2087 | BU42: 3522.6027 | BV42: 3867.5049 | BW42: 4315.6189
B43: EBIT | E43: =+E20 -> 66.91287 | F43: =+F20 -> 79.09682 | G43: =+G20 -> 94.738635 | H43: =+H20 -> 110.85916 | I43: =+I20 -> 113.59683 | J43: =+J20 -> 123.6738 | K43: =+K20 -> 128.61345 | L43: =+L20 -> 43.085493 | ... V43: =+V20 -> 39482.918 | X43: =+X20 -> 0 | Y43: =+Y20 -> 0 | Z43: =+Z20 -> 0 | AA43: =+AA20 -> 0 | AB43: =+AB20 -> 29.148095 | AC43: =+AC20 -> 30.688392 | AD43: =+AD20 -> 25.644859 | AE43: =+AE20 -> 28.115484 | ... CE43: =+CE20 -> 11582.255
B44: Depreciation | E44: 2.7811 | F44: 2.8049 | G44: 5.2721238 | H44: 12.068054 | I44: 15.214017 | J44: 23.896633 | K44: 46.862284 | L44: 53.2327 | M44: 33.982678 | N44: 49.141343 | O44: 71.317677 | P44: 84.048261 | Q44: =+Q177 -> 102.96081 | R44: =+R177 -> 183.45433 | S44: =+S177 -> 364.45805 | T44: =+T177 -> 592.4618 | U44: =+U177 -> 830.39922 | V44: =+V177 -> 1018.9813 | X44: 0 | Y44: 0 | Z44: 0 | AA44: 0 | AB44: 3.5434411 | AC44: 3.5434411 | AD44: 3.5434411 | AE44: 3.5434411 | AF44: 3.5434411 | AG44: 3.5434411 | AH44: 8.3934916 | AI44: 8.3934916 | AJ44: 10.121043 | AK44: 10.121043 | AL44: 13.23213 | AM44: 13.23213 | AN44: 14.875004 | AO44: 14.875004 | AP44: 11.691995 | AQ44: 11.691995 | AR44: 8.1215811 | AS44: 8.1215811 | AT44: 7.4564708 | AU44: 7.4564708 | AV44: 10.170185 | AW44: 10.170185 | AX44: 14.159874 | AY44: 14.159874 | AZ44: 16.80757 | BA44: 16.80757 | BB44: 18.716404 | BC44: 18.716404 | BD44: 21.372308 | BE44: 21.372308 | BF44: 22.10798 | BG44: 22.10798 | BH44: 23.489918 | BI44: 23.489918 | BJ44: 23 | BK44: =Q44-SUM(BH44:BJ44) -> 32.980978 | BL44: =+$R44/4 -> 45.863583 | BM44: =+$R44/4 -> 45.863583 | BN44: =+$R44/4 -> 45.863583 | BO44: =+$R44/4 -> 45.863583 | BP44: =+$S44/4 -> 91.114512 | BQ44: =+$S44/4 -> 91.114512 | BR44: =+$S44/4 -> 91.114512 | BS44: =+$S44/4 -> 91.114512 | BT44: =+$T44/4 -> 148.11545 | BU44: =+$T44/4 -> 148.11545 | BV44: =+$T44/4 -> 148.11545 | BW44: =+$T44/4 -> 148.11545 | BX44: =+$U44/4 -> 207.5998 | BY44: =+$U44/4 -> 207.5998 | BZ44: =+$U44/4 -> 207.5998 | CA44: =+$U44/4 -> 207.5998 | CB44: =+$V44/4 -> 254.74532 | CC44: =+$V44/4 -> 254.74532 | CD44: =+$V44/4 -> 254.74532 | CE44: =+$V44/4 -> 254.74532
B45: Amortization | E45: 0.1364 | F45: 0.1015 | G45: 0.22808715 | H45: 0.31876193 | I45: 0.43356578 | J45: 0.41590236 | K45: 0.42110674 | L45: 0.67595024 | M45: 0.86882171 | N45: 0.86558615 | O45: 0.92521985 | P45: 12.941235 | Q45: =+Q185 -> 23.211583 | R45: =+R185 -> 27.029862 | S45: =+S185 -> 23.245681 | T45: =+T185 -> 19.991286 | U45: =+U185 -> 17.192506 | V45: =+V185 -> 14.785555 | X45: 0 | Y45: 0 | Z45: 0 | AA45: 0 | AB45: 0.105294 | AC45: 0.105294 | AD45: 0.105294 | AE45: 0.105294 | AF45: 0.105294 | AG45: 0.105294 | AH45: 0.10265718 | AI45: 0.10265718 | AJ45: 0.10299609 | AK45: 0.10299609 | AL45: 0.10755728 | AM45: 0.10755728 | AN45: 0.13538499 | AO45: 0.13538499 | AP45: 0.20259013 | AQ45: 0.20259013 | AR45: 0.21348275 | AS45: 0.21348275 | AT45: 0.2209281 | AU45: 0.2209281 | AV45: 0.2168658 | AW45: 0.2168658 | AX45: 0.21592728 | AY45: 0.21592728 | AZ45: 0.22147509 | BA45: 0.22147509 | BB45: 0.24113483 | BC45: 0.24113483 | BD45: 1.6318823 | BE45: 1.6318823 | BF45: 4.8387352 | BG45: 4.8387352 | BH45: 5.4242451 | BI45: 5.4242451 | BJ45: 5 | BK45: =Q45-SUM(BH45:BJ45) -> 7.3630932 | BL45: =+$R45/4 -> 6.7574656 | BM45: =+$R45/4 -> 6.7574656 | BN45: =+$R45/4 -> 6.7574656 | BO45: =+$R45/4 -> 6.7574656 | BP45: =+$S45/4 -> 5.8114204 | BQ45: =+$S45/4 -> 5.8114204 | BR45: =+$S45/4 -> 5.8114204 | BS45: =+$S45/4 -> 5.8114204 | BT45: =+$T45/4 -> 4.9978215 | BU45: =+$T45/4 -> 4.9978215 | BV45: =+$T45/4 -> 4.9978215 | BW45: =+$T45/4 -> 4.9978215 | BX45: =+$U45/4 -> 4.2981265 | BY45: =+$U45/4 -> 4.2981265 | BZ45: =+$U45/4 -> 4.2981265 | CA45: =+$U45/4 -> 4.2981265 | CB45: =+$V45/4 -> 3.6963888 | CC45: =+$V45/4 -> 3.6963888 | CD45: =+$V45/4 -> 3.6963888 | CE45: =+$V45/4 -> 3.6963888
B46: EBITDA | E46: =+E43+E44+E45 -> 69.83037 | F46: =+F43+F44+F45 -> 82.00322 | G46: =+G43+G44+G45 -> 100.23885 | H46: =+H43+H44+H45 -> 123.24598 | I46: =+I43+I44+I45 -> 129.24441 | J46: =+J43+J44+J45 -> 147.98634 | K46: =+K43+K44+K45 -> 175.89684 | L46: =+L43+L44+L45 -> 96.994142 | ... V46: =+V43+V44+V45 -> 40516.685 | X46: =+X43+X44+X45 -> 0 | Y46: =+Y43+Y44+Y45 -> 0 | Z46: =+Z43+Z44+Z45 -> 0 | AA46: =+AA43+AA44+AA45 -> 0 | AB46: =+AB43+AB44+AB45 -> 32.79683 | AC46: =+AC43+AC44+AC45 -> 34.337127 | AD46: =+AD43+AD44+AD45 -> 29.293594 | AE46: =+AE43+AE44+AE45 -> 31.764219 | ... CE46: =+CE43+CE44+CE45 -> 11840.696
B48: EPS - basic | E48: =+E40/E55 -> 0.67857143 | F48: =+F40/F55 -> 0.80714286 | G48: =+G40/G55 -> 0.97142857 | H48: =+H40/H55 -> 1.1357143 | I48: =SUMIF($X$3:$BS$3,I$4,$X48:$BS48) -> 1.156739 | J48: =SUMIF($X$3:$BS$3,J$4,$X48:$BS48) -> 1.0357143 | K48: =SUMIF($X$3:$BS$3,K$4,$X48:$BS48) -> 0.52328571 | L48: =SUMIF($X$3:$BS$3,L$4,$X48:$BS48) -> 0.095285714 | M48: =SUMIF($X$3:$BS$3,M$4,$X48:$BS48) -> 0.64114286 | N48: =SUMIF($X$3:$BS$3,N$4,$X48:$BS48) -> 1.0817857 | O48: =SUMIF($X$3:$BS$3,O$4,$X48:$BS48) -> 0.71122449 | P48: =SUMIF($X$3:$BS$3,P$4,$X48:$BS48) -> 0.90908163 | ... S48: =SUMIF($X$3:$BS$3,S$4,$X48:$BS48) -> 6.8527362 | T48: =SUMIF($X$3:$CA$3,T$4,$X48:$CA48) -> 14.863034 | U48: =SUMIF($X$3:$CA$3,U$4,$X48:$CA48) -> 21.615734 | V48: =SUMIF($X$3:$CE$3,V$4,$X48:$CE48) -> 24.846591 | X48: 0 | Y48: 0 | Z48: 0 | AA48: 0 | AB48: =+AB40/AB55 -> 0.30714286 | AC48: =+AC40/AC55 -> 0.32142857 | AD48: =+AD40/AD55 -> 0.24509612 | AE48: =+AE40/AE55 -> 0.28307143 | AF48: =+AF40/AF55 -> 0.26428571 | AG48: =+AG40/AG55 -> 0.24842857 | AH48: =+AH40/AH55 -> 0.29478571 | AI48: =+AI40/AI55 -> 0.22821429 | ... CE48: =+CE40/CE55 -> 7.2878376
B49: EPS - fully diluted | E49: =+E40/E56 -> 0.67857143 | F49: =+F40/F56 -> 0.80714286 | G49: =+G40/G56 -> 0.97142857 | H49: =+H40/H56 -> 1.1357143 | I49: =SUMIF($X$3:$BS$3,I$4,$X49:$BS49) -> 1.156739 | J49: =SUMIF($X$3:$BS$3,J$4,$X49:$BS49) -> 1.0357143 | K49: =SUMIF($X$3:$BS$3,K$4,$X49:$BS49) -> 0.52328571 | L49: =SUMIF($X$3:$BS$3,L$4,$X49:$BS49) -> 0.095285714 | M49: =SUMIF($X$3:$BS$3,M$4,$X49:$BS49) -> 0.64114286 | N49: =SUMIF($X$3:$BS$3,N$4,$X49:$BS49) -> 1.0817857 | O49: =SUMIF($X$3:$BS$3,O$4,$X49:$BS49) -> 0.71122449 | P49: =SUMIF($X$3:$BS$3,P$4,$X49:$BS49) -> 0.90908163 | ... S49: =SUMIF($X$3:$BS$3,S$4,$X49:$BS49) -> 6.8527362 | T49: =SUMIF($X$3:$CA$3,T$4,$X49:$CA49) -> 14.863034 | U49: =SUMIF($X$3:$CA$3,U$4,$X49:$CA49) -> 21.615734 | V49: =SUMIF($X$3:$CE$3,V$4,$X49:$CE49) -> 24.846591 | X49: 0 | Y49: 0 | Z49: 0 | AA49: 0 | AB49: =+AB40/AB56 -> 0.30714286 | AC49: =+AC40/AC56 -> 0.32142857 | AD49: =+AD40/AD56 -> 0.24509612 | AE49: =+AE40/AE56 -> 0.28307143 | AF49: =+AF40/AF56 -> 0.26428571 | AG49: =+AG40/AG56 -> 0.24842857 | AH49: =+AH40/AH56 -> 0.29478571 | AI49: =+AI40/AI56 -> 0.22821429 | ... CE49: =+CE40/CE56 -> 7.2878376
B50: EPS (based on current shares outstanding) | E50: =E40/E58 -> 0.67857143 | F50: =F40/F58 -> 0.80714286 | G50: =G40/G58 -> 0.97142857 | H50: =H40/H58 -> 1.1357143 | I50: =I40/I58 -> 1.156739 | J50: =J40/J58 -> 1.0357143 | K50: =K40/K58 -> 0.52328571 | L50: =L40/L58 -> 0.095285714 | ... V50: =V40/V58 -> 24.849055
B53: Common dividends declared | E53: 0 | F53: 0 | G53: 0 | H53: 0 | I53: 0 | J53: =+J54*J58 -> 12.808682 | K53: =+K54*K58 -> 23.989327 | L53: =+L54*L58 -> 90.767489 | M53: =+M54*M58 -> 59.759194 | N53: =+N54*N58 -> 54.549628 | O53: =+O54*O58 -> 111.68223 | P53: =+P54*P58 -> 347.88227 | Q53: =+Q54*Q58 -> 202.94513 | R53: 318.963 | S53: =+S62 -> 953.19227 | T53: =+T62 -> 2068.2823 | U53: =+U62 -> 3007.9619 | V53: =+V62 -> 3457.5554 | AZ53: =AZ55*1.4 -> 994.01204 | BA53: =BA55*1.4 -> 1391.4865 | BB53: =BB55*1.4 -> 1391.2442 | BC53: =BC55*1.4 -> 1391.4794 | BD53: =BD55*1.4 -> 1391.6823 | BE53: =BE55*1.4 -> 1391.5355 | BF53: =BF55*1.4 -> 1391.38 | BG53: =BG55*1.4 -> 1391.6886 | ... CE53: =CE55*1.4 -> 1948.1858
B54: Dividends per share | E54: 0 | F54: 0 | G54: 0 | H54: 0 | I54: 0 | J54: 0.126 | K54: 0.113 | L54: 0.2717 | M54: 0.18 | N54: 0.12 | O54: 0.12 | P54: 0.35 | Q54: 0.155 | R54: =+R53/R58 -> 0.22923506 | S54: =+S62/S55 -> 0.68504839 | T54: =+T62/T55 -> 1.4864508 | U54: =+U62/U55 -> 2.1617878 | V54: =+V62/V55 -> 2.4849055
B55: Weighted avg. adj. shares outstanding (mn) | E55: 77.47863 | F55: 81.457337 | G55: 81.692849 | H55: 81.3572 | I55: =I40/I48 -> 81.652239 | J55: =J40/J48 -> 101.6562 | K55: =K40/K48 -> 212.29493 | L55: =L40/L48 -> 334.07247 | M55: =M40/M48 -> 331.99552 | N55: =N40/N48 -> 454.58023 | O55: =O40/O48 -> 930.68525 | P55: =P40/P48 -> 993.94934 | ... R55: =R40/R48 -> 1391.4233 | S55: =R55 -> 1391.4233 | T55: =S55 -> 1391.4233 | U55: =T55 -> 1391.4233 | V55: =U55 -> 1391.4233 | AB55: 80.675456 | AC55: 82.869305 | AD55: 81.47959 | AE55: 81.47959 | AF55: 81.27143 | AG55: 108.64865 | AH55: 108.64136 | AI55: 108.62842 | AJ55: 108.64155 | AK55: 325.95917 | AL55: 325.89553 | AM55: 332.62827 | AN55: 332.83547 | AO55: 333.14033 | AP55: 333.69688 | AQ55: 333.78701 | AR55: 333.6462 | AS55: 333.59169 | AT55: 330.97817 | AU55: 331.04059 | AV55: 331.10093 | AW55: 463.46491 | AX55: 463.37818 | AY55: 507.06614 | AZ55: 710.0086 | BA55: 993.91896 | BB55: 993.74588 | BC55: 993.91385 | BD55: 994.05882 | BE55: 993.95396 | BF55: 993.84287 | BG55: 994.06326 | BH55: 993.68234 | BI55: 1391.4233 | BJ55: 1391.4233 | BK55: 1391.4233 | BL55: 1391.4233 | BM55: 1391.4233 | BN55: 1391.4233 | BO55: 1391.4233 | BP55: 1391.4233 | BQ55: 1389.261 | BR55: 1391.5613 | BS55: 1391.5613 | BT55: 1391.5613 | BU55: 1391.5613 | BV55: 1391.5613 | BW55: 1391.5613 | BX55: 1391.5613 | BY55: 1391.5613 | BZ55: 1391.5613 | CA55: 1391.5613 | CB55: 1391.5613 | CC55: 1391.5613 | CD55: 1391.5613 | CE55: 1391.5613 | CT55: =+A7 -> 0
B56: Fully diluted shares outstanding (mn) | E56: 77.47863 | F56: 81.457337 | G56: 81.692849 | H56: 81.3572 | I56: =I40/I49 -> 81.652239 | J56: =J40/J49 -> 101.6562 | K56: 212.29493 | L56: 334.07247 | M56: =M40/M49 -> 331.99552 | N56: =N40/N49 -> 454.58023 | O56: =O40/O49 -> 930.68525 | P56: =P40/P49 -> 993.94934 | Q56: =Q40/Q49 -> 1309.3234 | R56: =R40/R49 -> 1391.4233 | S56: =R56 -> 1391.4233 | T56: =S56 -> 1391.4233 | U56: =T56 -> 1391.4233 | V56: =U56 -> 1391.4233 | AB56: 80.675456 | AC56: 82.869305 | AD56: 81.47959 | AE56: 81.47959 | AF56: 81.27143 | AG56: 108.64865 | AH56: 108.64136 | AI56: 108.62842 | AJ56: 108.64155 | AK56: 325.95917 | AL56: 325.89553 | AM56: 332.62827 | AN56: 332.83547 | AO56: 333.14033 | AP56: 333.69688 | AQ56: 333.78701 | AR56: 333.6462 | AS56: 333.59169 | AT56: 330.97817 | AU56: 331.04059 | AV56: 331.10093 | AW56: 463.46491 | AX56: 463.37818 | AY56: 507.06614 | AZ56: 710.0086 | BA56: 993.91896 | BB56: 993.74588 | BC56: 993.91385 | BD56: 994.05882 | BE56: 993.95396 | BF56: 993.84287 | BG56: 994.06326 | BH56: 993.68234 | BI56: 1391.4233 | BJ56: 1391.4233 | BK56: 1391.4233 | BL56: 1391.4233 | BM56: 1391.4233 | BN56: 1391.4233 | BO56: 1391.4233 | BP56: 1391.4233 | BQ56: 1389.261 | BR56: 1391.5613 | BS56: 1391.5613 | BT56: 1391.5613 | BU56: 1391.5613 | BV56: 1391.5613 | BW56: 1391.5613 | BX56: 1391.5613 | BY56: 1391.5613 | BZ56: 1391.5613 | CA56: 1391.5613 | CB56: 1391.5613 | CC56: 1391.5613 | CD56: 1391.5613 | CE56: 1391.5613
B57: Period end shares outstanding (mn) | E57: =+E56 -> 77.47863 | F57: =+F56 -> 81.457337 | G57: =+G56 -> 81.692849 | H57: =+H56 -> 81.3572 | I57: =+I56 -> 81.652239 | J57: =+J56 -> 101.6562 | K57: 212.29493 | L57: 334.07247 | M57: =+M56 -> 331.99552 | N57: =+N56 -> 454.58023 | O57: =+O56 -> 930.68525 | P57: =+P56 -> 993.94934 | Q57: =+Q56 -> 1309.3234 | R57: =+R56 -> 1391.4233 | S57: =R57 -> 1391.4233 | T57: =S57 -> 1391.4233 | U57: =T57 -> 1391.4233 | V57: =U57 -> 1391.4233 | AB57: =+AB56 -> 80.675456 | AC57: =+AC56 -> 82.869305 | AD57: 58.199707 | AE57: =+AE56 -> 81.47959 | AF57: =+AF56 -> 81.27143 | AG57: =+AG56 -> 108.64865 | AH57: =+AH56 -> 108.64136 | AI57: =+AI56 -> 108.62842 | AJ57: =+AJ56 -> 108.64155 | AK57: =+AK56 -> 325.95917 | AL57: =+AL56 -> 325.89553 | ... CE57: =+CE56 -> 1391.5613
B58: Current shares outstanding | E58: =+E57 -> 77.47863 | F58: =+F57 -> 81.457337 | G58: =+G57 -> 81.692849 | H58: =+H57 -> 81.3572 | I58: =+I57 -> 81.652239 | J58: =+J57 -> 101.6562 | K58: =+K57 -> 212.29493 | L58: =+L57 -> 334.07247 | ... R58: =+R57 -> 1391.4233 | S58: =R58 -> 1391.4233 | T58: =S58 -> 1391.4233 | U58: =T58 -> 1391.4233 | V58: =U58 -> 1391.4233
B60: Dividend payout
B61: Net income | E61: =E40 -> 52.574785 | F61: =F40 -> 65.747708 | G61: =G40 -> 79.358767 | H61: =H40 -> 92.398535 | I61: =I40 -> 94.450328 | J61: =J40 -> 105.28678 | K61: =K40 -> 111.09091 | L61: =L40 -> 31.832334 | ... V61: =V40 -> 34575.554
B62: Dividend declared | E62: =E53 -> 0 | F62: =F53 -> 0 | G62: =G53 -> 0 | H62: =H53 -> 0 | I62: =I53 -> 0 | J62: =J53 -> 12.808682 | K62: =K53 -> 23.989327 | L62: =L53 -> 90.767489 | ... R62: =R53 -> 318.963 | S62: =+S63*S40 -> 953.19227 | T62: =+T63*T40 -> 2068.2823 | U62: =+U63*U40 -> 3007.9619 | V62: =+V63*V40 -> 3457.5554
B63: Payout ratio | E63: =E62/E61 -> 0 | F63: =F62/F61 -> 0 | G63: =G62/G61 -> 0 | H63: =H62/H61 -> 0 | I63: =I62/I61 -> 0 | J63: =J62/J61 -> 0.12165517 | K63: =K62/K61 -> 0.21594322 | L63: =L62/L61 -> 2.8514243 | ... R63: =R62/R61 -> 0.11239744 | S63: 0.1 | T63: 0.1 | U63: 0.1 | V63: 0.1
B65: Growth YoY% | E65: =E4 -> 2011 | F65: =F4 -> 2012 | G65: =G4 -> 2013 | H65: =H4 -> 2014 | I65: =I4 -> 2015 | J65: =J4 -> 2016 | K65: =K4 -> 2017 | L65: =L4 -> 2018 | ... V65: =V4 -> 2028 | X65: =X4 -> 1Q14 | Y65: =Y4 -> 2Q14 | Z65: =Z4 -> 3Q14 | AA65: =AA4 -> 4Q14 | AB65: =AB4 -> 1Q15 | AC65: =AC4 -> 2Q15 | AD65: =AD4 -> 3Q15 | AE65: =AE4 -> 4Q15 | ... CE65: =CE4 -> 4Q28
B66: Revenue | E66: =IF(ISERROR(E7/D7-1)," ",(E7/D7-1)) | F66: =IF(ISERROR(F7/E7-1)," ",(F7/E7-1)) -> 0.13983491 | G66: =IF(ISERROR(G7/F7-1)," ",(G7/F7-1)) -> 0.32649987 | H66: =IF(ISERROR(H7/G7-1)," ",(H7/G7-1)) -> 0.13357642 | I66: =IF(ISERROR(I7/H7-1)," ",(I7/H7-1)) -> 0.1769599 | J66: =IF(ISERROR(J7/I7-1)," ",(J7/I7-1)) -> 0.16063881 | K66: =IF(ISERROR(K7/J7-1)," ",(K7/J7-1)) -> 0.22892067 | L66: =IF(ISERROR(L7/K7-1)," ",(L7/K7-1)) -> -0.13382689 | ... V66: =IF(ISERROR(V7/U7-1)," ",(V7/U7-1)) -> 0.149705 | AA66: =IF(ISERROR(AA7/#REF!-1),"",AA7/#REF!-1) | AB66: =IF(ISERROR(AB7/X7-1),"",AB7/X7-1) | AC66: =IF(ISERROR(AC7/Y7-1),"",AC7/Y7-1) | AD66: =IF(ISERROR(AD7/Z7-1),"",AD7/Z7-1) | AE66: =IF(ISERROR(AE7/AA7-1),"",AE7/AA7-1) | AF66: =IF(ISERROR(AF7/AB7-1),"",AF7/AB7-1) -> 0.035819093 | AG66: =IF(ISERROR(AG7/AC7-1),"",AG7/AC7-1) -> 0.15808127 | AH66: =IF(ISERROR(AH7/AD7-1),"",AH7/AD7-1) -> 0.1991358 | AI66: =IF(ISERROR(AI7/AE7-1),"",AI7/AE7-1) -> 0.23681883 | ... CE66: =IF(ISERROR(CE7/CA7-1),"",CE7/CA7-1) -> 0.21738897
B67: Gross profit | E67: =IF(ISERROR(E12/D12-1)," ",(E12/D12-1)) | F67: =IF(ISERROR(F12/E12-1)," ",(F12/E12-1)) -> 0.23586729 | G67: =IF(ISERROR(G12/F12-1)," ",(G12/F12-1)) -> 0.15332193 | H67: =IF(ISERROR(H12/G12-1)," ",(H12/G12-1)) -> 0.22491782 | I67: =IF(ISERROR(I12/H12-1)," ",(I12/H12-1)) -> 0.056415952 | J67: =IF(ISERROR(J12/I12-1)," ",(J12/I12-1)) -> 0.11694084 | K67: =IF(ISERROR(K12/J12-1)," ",(K12/J12-1)) -> 0.11845183 | L67: =IF(ISERROR(L12/K12-1)," ",(L12/K12-1)) -> -0.29596082 | ... V67: =IF(ISERROR(V12/U12-1)," ",(V12/U12-1)) -> 0.15263601 | AA67: =IF(ISERROR(AA12/#REF!-1),"",AA12/#REF!-1) | AB67: =IF(ISERROR(AB12/X12-1),"",AB12/X12-1) | AC67: =IF(ISERROR(AC12/Y12-1),"",AC12/Y12-1) | AD67: =IF(ISERROR(AD12/Z12-1),"",AD12/Z12-1) | AE67: =IF(ISERROR(AE12/AA12-1),"",AE12/AA12-1) | AF67: =IF(ISERROR(AF12/AB12-1),"",AF12/AB12-1) -> -0.099396867 | AG67: =IF(ISERROR(AG12/AC12-1),"",AG12/AC12-1) -> 0.10281664 | AH67: =IF(ISERROR(AH12/AD12-1),"",AH12/AD12-1) -> 0.36829803 | AI67: =IF(ISERROR(AI12/AE12-1),"",AI12/AE12-1) -> 0.10622781 | ... CE67: =IF(ISERROR(CE12/CA12-1),"",CE12/CA12-1) -> 0.23054012
B68: Operating income | E68: =IF(ISERROR(E43/D43-1)," ",(E43/D43-1)) | F68: =IF(ISERROR(F43/E43-1)," ",(F43/E43-1)) -> 0.18208679 | G68: =IF(ISERROR(G43/F43-1)," ",(G43/F43-1)) -> 0.19775529 | H68: =IF(ISERROR(H43/G43-1)," ",(H43/G43-1)) -> 0.17015793 | I68: =IF(ISERROR(I43/H43-1)," ",(I43/H43-1)) -> 0.024694996 | J68: =IF(ISERROR(J43/I43-1)," ",(J43/I43-1)) -> 0.088708196 | K68: =IF(ISERROR(K43/J43-1)," ",(K43/J43-1)) -> 0.039940926 | L68: =IF(ISERROR(L43/K43-1)," ",(L43/K43-1)) -> -0.66500009 | ... V68: =IF(ISERROR(V43/U43-1)," ",(V43/U43-1)) -> 0.14960708 | AL68: =IF(ISERROR(AL20/AH20-1),"",AL20/AH20-1)+A1 -> 0.17292484 | AM68: =IF(ISERROR(AM20/AI20-1),"",AM20/AI20-1)+B1 -> -0.60348999 | AN68: =IF(ISERROR(AN20/AJ20-1),"",AN20/AJ20-1)+C1 -> -0.92532335 | AO68: =IF(ISERROR(AO20/AK20-1),"",AO20/AK20-1)+D1 -> -1.2360955 | AP68: =IF(ISERROR(AP20/AL20-1),"",AP20/AL20-1)+E1 -> -0.61449232 | AQ68: =IF(ISERROR(AQ20/AM20-1),"",AQ20/AM20-1)+F1 -> 1.9692512 | AR68: =IF(ISERROR(AR20/AN20-1),"",AR20/AN20-1)+G1 -> 16.420635 | AS68: =IF(ISERROR(AS20/AO20-1),"",AS20/AO20-1)+H1 -> -5.7986797 | ... BA68: =IF(ISERROR(BA20/AW20-1),"",BA20/AW20-1)+P1 -> 0.40781433 | BB68: =IF(ISERROR(BB20/AX20-1),"",BB20/AX20-1) -> -0.29315244 | BC68: =IF(ISERROR(BC20/AY20-1),"",BC20/AY20-1) -> 0.43853773 | BD68: =IF(ISERROR(BD20/AZ20-1),"",BD20/AZ20-1)+W1 -> 0.22943276 | BE68: =IF(ISERROR(BE20/BA20-1),"",BE20/BA20-1)+X1 -> -0.28232951 | BF68: =IF(ISERROR(BF20/BB20-1),"",BF20/BB20-1)+Y1 -> 1.0383209 | BG68: =IF(ISERROR(BG20/BC20-1),"",BG20/BC20-1)+Z1 -> 0.13163288 | BH68: =IF(ISERROR(BH20/BD20-1),"",BH20/BD20-1)+AA1 -> -0.25070758 | BI68: =IF(ISERROR(BI20/BE20-1),"",BI20/BE20-1)+AB1 -> -0.33557834 | BJ68: =IF(ISERROR(BJ20/BF20-1),"",BJ20/BF20-1)+AC1 -> -0.5222179 | BK68: =IF(ISERROR(BK20/BG20-1),"",BK20/BG20-1)+AD1 -> 0.25659514 | ... CE68: =IF(ISERROR(CE20/CA20-1),"",CE20/CA20-1)+AX1 -> 0.21563873
B69: Profit before tax | E69: =IF(ISERROR(E33/D33-1)," ",(E33/D33-1)) | F69: =IF(ISERROR(F33/E33-1)," ",(F33/E33-1)) -> 0.23869609 | G69: =IF(ISERROR(G33/F33-1)," ",(G33/F33-1)) -> 0.2034403 | H69: =IF(ISERROR(H33/G33-1)," ",(H33/G33-1)) -> 0.15891532 | I69: =IF(ISERROR(I33/H33-1)," ",(I33/H33-1)) -> 0.021052644 | J69: =IF(ISERROR(J33/I33-1)," ",(J33/I33-1)) -> 0.1589106 | K69: =IF(ISERROR(K33/J33-1)," ",(K33/J33-1)) -> -0.0038365694 | L69: =IF(ISERROR(L33/K33-1)," ",(L33/K33-1)) -> -0.72156891 | ... V69: =IF(ISERROR(V33/U33-1)," ",(V33/U33-1)) -> 0.14946782 | AA69: =IF(ISERROR(AA33/#REF!-1)," ",(AA33/#REF!-1)) | AB69: =IF(ISERROR(AB33/X33-1)," ",(AB33/X33-1)) | AC69: =IF(ISERROR(AC33/Y33-1)," ",(AC33/Y33-1)) | AD69: =IF(ISERROR(AD33/Z33-1)," ",(AD33/Z33-1)) | AE69: =IF(ISERROR(AE33/AA33-1)," ",(AE33/AA33-1)) | AF69: =IF(ISERROR(AF33/AB33-1)," ",(AF33/AB33-1)) -> -0.12939364 | AG69: =IF(ISERROR(AG33/AC33-1)," ",(AG33/AC33-1)) -> 0.042963736 | AH69: =IF(ISERROR(AH33/AD33-1)," ",(AH33/AD33-1)) -> 0.72908024 | AI69: =IF(ISERROR(AI33/AE33-1)," ",(AI33/AE33-1)) -> 0.10926359 | ... CE69: =IF(ISERROR(CE33/CA33-1)," ",(CE33/CA33-1)) -> 0.21545782
B70: Net income to common shareholders | E70: =IF(ISERROR(E40/D40-1)," ",(E40/D40-1)) | F70: =IF(ISERROR(F40/E40-1)," ",(F40/E40-1)) -> 0.25055591 | G70: =IF(ISERROR(G40/F40-1)," ",(G40/F40-1)) -> 0.20701953 | H70: =IF(ISERROR(H40/G40-1)," ",(H40/G40-1)) -> 0.16431414 | I70: =IF(ISERROR(I40/H40-1)," ",(I40/H40-1)) -> 0.022205908 | J70: =IF(ISERROR(J40/I40-1)," ",(J40/I40-1)) -> 0.11473179 | K70: =IF(ISERROR(K40/J40-1)," ",(K40/J40-1)) -> 0.055126791 | L70: =IF(ISERROR(L40/K40-1)," ",(L40/K40-1)) -> -0.71345689 | ... V70: =IF(ISERROR(V40/U40-1)," ",(V40/U40-1)) -> 0.14946782 | AA70: =IF(ISERROR(AA40/#REF!-1)," ",(AA40/#REF!-1)) | AB70: =IF(ISERROR(AB40/X40-1)," ",(AB40/X40-1)) | AC70: =IF(ISERROR(AC40/Y40-1)," ",(AC40/Y40-1)) | AD70: =IF(ISERROR(AD40/Z40-1)," ",(AD40/Z40-1)) | AE70: =IF(ISERROR(AE40/AA40-1)," ",(AE40/AA40-1)) | AF70: =IF(ISERROR(AF40/AB40-1)," ",(AF40/AB40-1)) -> -0.13317837 | AG70: =IF(ISERROR(AG40/AC40-1)," ",(AG40/AC40-1)) -> 0.013322512 | AH70: =IF(ISERROR(AH40/AD40-1)," ",(AH40/AD40-1)) -> 0.60367493 | AI70: =IF(ISERROR(AI40/AE40-1)," ",(AI40/AE40-1)) -> 0.074834024 | ... CE70: =IF(ISERROR(CE40/CA40-1)," ",(CE40/CA40-1)) -> 0.21545782
B71: EBITDA | E71: =IF(ISERROR(E20/D20-1)," ",(E20/D20-1)) | F71: =IF(ISERROR(F20/E20-1)," ",(F20/E20-1)) -> 0.18208679 | G71: =IF(ISERROR(G20/F20-1)," ",(G20/F20-1)) -> 0.19775529 | H71: =IF(ISERROR(H20/G20-1)," ",(H20/G20-1)) -> 0.17015793 | I71: =IF(ISERROR(I46/H46-1)," ",(I46/H46-1)) -> 0.048670417 | J71: =IF(ISERROR(J46/I46-1)," ",(J46/I46-1)) -> 0.14501147 | K71: =IF(ISERROR(K46/J46-1)," ",(K46/J46-1)) -> 0.18860188 | L71: =IF(ISERROR(L46/K46-1)," ",(L46/K46-1)) -> -0.4485737 | M71: =IF(ISERROR(M46/L46-1)," ",(M46/L46-1)) -> 2.0140206 | N71: =IF(ISERROR(N46/M46-1)," ",(N46/M46-1)) -> 1.1509552 | O71: =IF(ISERROR(O46/N46-1)," ",(O46/N46-1)) -> 0.30719598 | P71: =IF(ISERROR(P46/O46-1)," ",(P46/O46-1)) -> 0.19108221 | ... V71: =IF(ISERROR(V46/U46-1)," ",(V46/U46-1)) -> 0.15129408 | AA71: =IF(ISERROR(AA20/#REF!-1),"",AA20/#REF!-1) | AB71: =IF(ISERROR(AB20/X20-1),"",AB20/X20-1) | AC71: =IF(ISERROR(AC20/Y20-1),"",AC20/Y20-1) | AD71: =IF(ISERROR(AD20/Z20-1),"",AD20/Z20-1) | AE71: =IF(ISERROR(AE20/AA20-1),"",AE20/AA20-1) | AF71: =IF(ISERROR(AF20/AB20-1),"",AF20/AB20-1) -> -0.16248878 | AG71: =IF(ISERROR(AG20/AC20-1),"",AG20/AC20-1) -> 0.11031334 | AH71: =IF(ISERROR(AH20/AD20-1),"",AH20/AD20-1) -> 0.41168847 | AI71: =IF(ISERROR(AI20/AE20-1),"",AI20/AE20-1) -> 0.030950074 | ... CE71: =IF(ISERROR(CE20/CA20-1),"",CE20/CA20-1) -> 0.21563873
B72: EBIT | E72: =IF(ISERROR(E43/D43-1)," ",(E43/D43-1)) | F72: =IF(ISERROR(F43/E43-1)," ",(F43/E43-1)) -> 0.18208679 | G72: =IF(ISERROR(G43/F43-1)," ",(G43/F43-1)) -> 0.19775529 | H72: =IF(ISERROR(H43/G43-1)," ",(H43/G43-1)) -> 0.17015793 | I72: =IF(ISERROR(I43/H43-1)," ",(I43/H43-1)) -> 0.024694996 | J72: =IF(ISERROR(J43/I43-1)," ",(J43/I43-1)) -> 0.088708196 | K72: =IF(ISERROR(K43/J43-1)," ",(K43/J43-1)) -> 0.039940926 | L72: =IF(ISERROR(L43/K43-1)," ",(L43/K43-1)) -> -0.66500009 | ... V72: =IF(ISERROR(V43/U43-1)," ",(V43/U43-1)) -> 0.14960708 | AA72: =IF(ISERROR(AA43/#REF!-1)," ",(AA43/#REF!-1)) | AB72: =IF(ISERROR(AB43/X43-1)," ",(AB43/X43-1)) | AC72: =IF(ISERROR(AC43/Y43-1)," ",(AC43/Y43-1)) | AD72: =IF(ISERROR(AD43/Z43-1)," ",(AD43/Z43-1)) | AE72: =IF(ISERROR(AE43/AA43-1)," ",(AE43/AA43-1)) | AF72: =IF(ISERROR(AF43/AB43-1)," ",(AF43/AB43-1)) -> -0.16248878 | AG72: =IF(ISERROR(AG43/AC43-1)," ",(AG43/AC43-1)) -> 0.11031334 | AH72: =IF(ISERROR(AH43/AD43-1)," ",(AH43/AD43-1)) -> 0.41168847 | AI72: =IF(ISERROR(AI43/AE43-1)," ",(AI43/AE43-1)) -> 0.030950074 | ... CE72: =IF(ISERROR(CE43/CA43-1)," ",(CE43/CA43-1)) -> 0.21563873
B73: EPS | E73: =E48/D48-1 -> #DIV/0! | F73: =F48/E48-1 -> 0.18947368 | G73: =G48/F48-1 -> 0.20353982 | H73: =H48/G48-1 -> 0.16911765 | I73: =I48/H48-1 -> 0.018512309 | J73: =J48/I48-1 -> -0.10462576 | K73: =K48/J48-1 -> -0.49475862 | L73: =L48/K48-1 -> -0.81790882 | ... V73: =V48/U48-1 -> 0.14946782 | AL73: =AL48/AH48-1 -> -0.64647444 | AM73: =AM48/AI48-1 -> -0.80938967 | AN73: =AN48/AJ48-1 -> -1.0397403 | AO73: =AO48/AK48-1 -> -1.34375 | AP73: =AP48/AL48-1 -> -0.40849897 | AQ73: =AQ48/AM48-1 -> 0.81937603 | AR73: =AR48/AN48-1 -> -9.8888889 | AS73: =AS48/AO48-1 -> -5.1838843 | ... CE73: =CE48/CA48-1 -> 0.21545782
B75: Margin analysis | E75: =E4 -> 2011 | F75: =F4 -> 2012 | G75: =G4 -> 2013 | H75: =H4 -> 2014 | I75: =I4 -> 2015 | J75: =J4 -> 2016 | K75: =K4 -> 2017 | L75: =L4 -> 2018 | ... V75: =V4 -> 2028 | X75: =X4 -> 1Q14 | Y75: =Y4 -> 2Q14 | Z75: =Z4 -> 3Q14 | AA75: =AA4 -> 4Q14 | AB75: =AB4 -> 1Q15 | AC75: =AC4 -> 2Q15 | AD75: =AD4 -> 3Q15 | AE75: =AE4 -> 4Q15 | ... CE75: =CE4 -> 4Q28
B76: % of sales
B77: Operating expense | E77: =E15/E7 -> 0.080277197 | F77: =F15/F7 -> 0.097394318 | G77: =G15/G7 -> 0.077056327 | H77: =H15/H7 -> 0.093191779 | I77: =I15/I7 -> 0.08936397 | J77: =J15/J7 -> 0.090491644 | K77: =K15/K7 -> 0.093424195 | L77: =L15/L7 -> 0.13839261 | ... V77: =V15/V7 -> 0.022040725 | AB77: =AB15/AB7 -> 0.078198181 | AC77: =AC15/AC7 -> 0.086490597 | AD77: =AD15/AD7 -> 0.094022342 | AE77: =AE15/AE7 -> 0.097798336 | AF77: =AF15/AF7 -> 0.080558499 | AG77: =AG15/AG7 -> 0.081169875 | AH77: =AH15/AH7 -> 0.1007604 | AI77: =AI15/AI7 -> 0.097831705 | ... CE77: =CE15/CE7 -> 0.031446504
B78: Sales tax | E78: =IF(ISERROR(E16/E$7)," ",E16/E$7) -> 0.003381083 | F78: =IF(ISERROR(F16/F$7)," ",F16/F$7) -> 0.0090379762 | G78: =IF(ISERROR(G16/G$7)," ",G16/G$7) -> 0.0034340019 | H78: =IF(ISERROR(H16/H$7)," ",H16/H$7) -> 0.0053397594 | I78: =IF(ISERROR(I16/I$7)," ",I16/I$7) -> 0.0059023856 | J78: =IF(ISERROR(J16/J$7)," ",J16/J$7) -> 0.004237589 | K78: =IF(ISERROR(K16/K$7)," ",K16/K$7) -> 0.0026838861 | L78: =IF(ISERROR(L16/L$7)," ",L16/L$7) -> 0.0098268984 | ... V78: =IF(ISERROR(V16/V$7)," ",V16/V$7) -> 0.0036144504 | AB78: =IF(ISERROR(AB16/AB$7)," ",AB16/AB$7) -> 0.010841474 | AC78: =IF(ISERROR(AC16/AC$7)," ",AC16/AC$7) -> 0.0067566311 | AD78: =IF(ISERROR(AD16/AD$7)," ",AD16/AD$7) -> 0.00081914156 | AE78: =IF(ISERROR(AE16/AE$7)," ",AE16/AE$7) -> 0.0051936315 | AF78: =IF(ISERROR(AF16/AF$7)," ",AF16/AF$7) -> 0.0047867342 | AG78: =IF(ISERROR(AG16/AG$7)," ",AG16/AG$7) -> 0 | AH78: =IF(ISERROR(AH16/AH$7)," ",AH16/AH$7) -> 0.0053822555 | AI78: =IF(ISERROR(AI16/AI$7)," ",AI16/AI$7) -> 0.0068877604 | ... BR78: =IF(ISERROR(BR16/BR$7)," ",BR16/BR$7) -> 0.00066184499 | BS78: 0.00083031753 | BT78: 0.00083031753 | BU78: 0.00083031753 | BV78: 0.00083031753 | BW78: 0.00083031753 | BX78: 0.00083031753 | BY78: 0.00083031753 | BZ78: 0.00083031753 | CA78: 0.00083031753 | CB78: 0.001 | CC78: 0.001 | CD78: 0.001 | CE78: 0.01
B79: Marketing expense | E79: =IF(ISERROR(E17/E$7)," ",E17/E$7) -> 0.015036285 | F79: =IF(ISERROR(F17/F$7)," ",F17/F$7) -> 0.015512101 | G79: =IF(ISERROR(G17/G$7)," ",G17/G$7) -> 0.015086239 | H79: =IF(ISERROR(H17/H$7)," ",H17/H$7) -> 0.017004053 | I79: =IF(ISERROR(I17/I$7)," ",I17/I$7) -> 0.015243794 | J79: =IF(ISERROR(J17/J$7)," ",J17/J$7) -> 0.014650924 | K79: =IF(ISERROR(K17/K$7)," ",K17/K$7) -> 0.015185768 | L79: =IF(ISERROR(L17/L$7)," ",L17/L$7) -> 0.024388471 | ... V79: =IF(ISERROR(V17/V$7)," ",V17/V$7) -> 0.0027342841 | AB79: =IF(ISERROR(AB17/AB$7)," ",AB17/AB$7) -> 0.011173486 | AC79: =IF(ISERROR(AC17/AC$7)," ",AC17/AC$7) -> 0.013960953 | AD79: =IF(ISERROR(AD17/AD$7)," ",AD17/AD$7) -> 0.01611767 | AE79: =IF(ISERROR(AE17/AE$7)," ",AE17/AE$7) -> 0.019265218 | AF79: =IF(ISERROR(AF17/AF$7)," ",AF17/AF$7) -> 0.011218791 | AG79: =IF(ISERROR(AG17/AG$7)," ",AG17/AG$7) -> 0.015059372 | AH79: =IF(ISERROR(AH17/AH$7)," ",AH17/AH$7) -> 0.017229607 | AI79: =IF(ISERROR(AI17/AI$7)," ",AI17/AI$7) -> 0.014571327 | ... CE79: =IF(ISERROR(CE17/CE$7)," ",CE17/CE$7) -> 0.0033885059
B80: Administrative expense | E80: =IF(ISERROR(E18/E$7)," ",E18/E$7) -> 0.026524946 | F80: =IF(ISERROR(F18/F$7)," ",F18/F$7) -> 0.031722745 | G80: =IF(ISERROR(G18/G$7)," ",G18/G$7) -> 0.023395217 | H80: =IF(ISERROR(H18/H$7)," ",H18/H$7) -> 0.036045495 | I80: =IF(ISERROR(I18/I$7)," ",I18/I$7) -> 0.030143481 | J80: =IF(ISERROR(J18/J$7)," ",J18/J$7) -> 0.030624209 | K80: =IF(ISERROR(K18/K$7)," ",K18/K$7) -> 0.024354541 | L80: =IF(ISERROR(L18/L$7)," ",L18/L$7) -> 0.034877086 | ... V80: =IF(ISERROR(V18/V$7)," ",V18/V$7) -> 0.0041074577 | AB80: =IF(ISERROR(AB18/AB$7)," ",AB18/AB$7) -> 0.018083222 | AC80: =IF(ISERROR(AC18/AC$7)," ",AC18/AC$7) -> 0.027673013 | AD80: =IF(ISERROR(AD18/AD$7)," ",AD18/AD$7) -> 0.038985531 | AE80: =IF(ISERROR(AE18/AE$7)," ",AE18/AE$7) -> 0.035239486 | AF80: =IF(ISERROR(AF18/AF$7)," ",AF18/AF$7) -> 0.023552974 | AG80: =IF(ISERROR(AG18/AG$7)," ",AG18/AG$7) -> 0.025110503 | AH80: =IF(ISERROR(AH18/AH$7)," ",AH18/AH$7) -> 0.037148534 | AI80: =IF(ISERROR(AI18/AI$7)," ",AI18/AI$7) -> 0.035372618 | ... CE80: =IF(ISERROR(CE18/CE$7)," ",CE18/CE$7) -> 0.0041004658
B81: R&D | E81: =IF(ISERROR(E19/E$7)," ",E19/E$7) -> 0.035334882 | F81: =IF(ISERROR(F19/F$7)," ",F19/F$7) -> 0.041121496 | G81: =IF(ISERROR(G19/G$7)," ",G19/G$7) -> 0.035140869 | H81: =IF(ISERROR(H19/H$7)," ",H19/H$7) -> 0.034802472 | I81: =IF(ISERROR(I19/I$7)," ",I19/I$7) -> 0.038074309 | J81: =IF(ISERROR(J19/J$7)," ",J19/J$7) -> 0.040978922 | K81: =IF(ISERROR(K19/K$7)," ",K19/K$7) -> 0.0512 | L81: =IF(ISERROR(L19/L$7)," ",L19/L$7) -> 0.069300151 | ... V81: =IF(ISERROR(V19/V$7)," ",V19/V$7) -> 0.011584532 | AB81: =IF(ISERROR(AB19/AB$7)," ",AB19/AB$7) -> 0.0381 | AC81: =IF(ISERROR(AC19/AC$7)," ",AC19/AC$7) -> 0.0381 | AD81: =IF(ISERROR(AD19/AD$7)," ",AD19/AD$7) -> 0.0381 | AE81: =IF(ISERROR(AE19/AE$7)," ",AE19/AE$7) -> 0.0381 | AF81: =IF(ISERROR(AF19/AF$7)," ",AF19/AF$7) -> 0.041 | AG81: =IF(ISERROR(AG19/AG$7)," ",AG19/AG$7) -> 0.041 | AH81: =IF(ISERROR(AH19/AH$7)," ",AH19/AH$7) -> 0.041 | AI81: =IF(ISERROR(AI19/AI$7)," ",AI19/AI$7) -> 0.041 | ... CE81: =IF(ISERROR(CE19/CE$7)," ",CE19/CE$7) -> 0.013957533
B82: Gross margin | E82: =IF(ISERROR(E12/E$7)," ",E12/E$7) -> 0.29971515 | F82: =IF(ISERROR(F12/F$7)," ",F12/F$7) -> 0.32496649 | G82: =IF(ISERROR(G12/G$7)," ",G12/G$7) -> 0.28254129 | H82: =IF(ISERROR(H12/H$7)," ",H12/H$7) -> 0.30530792 | I82: =IF(ISERROR(I12/I$7)," ",I12/I$7) -> 0.27403836 | J82: =IF(ISERROR(J12/J$7)," ",J12/J$7) -> 0.26372083 | K82: =IF(ISERROR(K12/K$7)," ",K12/K$7) -> 0.24001472 | L82: =IF(ISERROR(L12/L$7)," ",L12/L$7) -> 0.19508775 | ... V82: =IF(ISERROR(V12/V$7)," ",V12/V$7) -> 0.48668025 | AB82: =IF(ISERROR(AB12/AB$7)," ",AB12/AB$7) -> 0.28454008 | AC82: =IF(ISERROR(AC12/AC$7)," ",AC12/AC$7) -> 0.27083289 | AD82: =IF(ISERROR(AD12/AD$7)," ",AD12/AD$7) -> 0.27436588 | AE82: =IF(ISERROR(AE12/AE$7)," ",AE12/AE$7) -> 0.2680061 | AF82: =IF(ISERROR(AF12/AF$7)," ",AF12/AF$7) -> 0.24739618 | AG82: =IF(ISERROR(AG12/AG$7)," ",AG12/AG$7) -> 0.25790852 | AH82: =IF(ISERROR(AH12/AH$7)," ",AH12/AH$7) -> 0.3130707 | AI82: =IF(ISERROR(AI12/AI$7)," ",AI12/AI$7) -> 0.23970835 | ... CE82: =IF(ISERROR(CE12/CE$7)," ",CE12/CE$7) -> 0.50065094
B83: Operating margin | E83: =IF(ISERROR(E20/E$7)," ",E20/E$7) -> 0.21943795 | F83: =IF(ISERROR(F20/F$7)," ",F20/F$7) -> 0.22757217 | G83: =IF(ISERROR(G20/G$7)," ",G20/G$7) -> 0.20548496 | H83: =IF(ISERROR(H20/H$7)," ",H20/H$7) -> 0.21211614 | I83: =IF(ISERROR(I20/I$7)," ",I20/I$7) -> 0.18467439 | J83: =IF(ISERROR(J20/J$7)," ",J20/J$7) -> 0.17322919 | K83: =IF(ISERROR(K20/K$7)," ",K20/K$7) -> 0.14659052 | L83: =IF(ISERROR(L20/L$7)," ",L20/L$7) -> 0.056695146 | ... V83: =IF(ISERROR(V20/V$7)," ",V20/V$7) -> 0.46463953 | AB83: =IF(ISERROR(AB20/AB$7)," ",AB20/AB$7) -> 0.2063419 | AC83: =IF(ISERROR(AC20/AC$7)," ",AC20/AC$7) -> 0.1843423 | AD83: =IF(ISERROR(AD20/AD$7)," ",AD20/AD$7) -> 0.18034353 | AE83: =IF(ISERROR(AE20/AE$7)," ",AE20/AE$7) -> 0.17020776 | AF83: =IF(ISERROR(AF20/AF$7)," ",AF20/AF$7) -> 0.16683768 | AG83: =IF(ISERROR(AG20/AG$7)," ",AG20/AG$7) -> 0.17673864 | AH83: =IF(ISERROR(AH20/AH$7)," ",AH20/AH$7) -> 0.2123103 | AI83: =IF(ISERROR(AI20/AI$7)," ",AI20/AI$7) -> 0.14187665 | ... CE83: =IF(ISERROR(CE20/CE$7)," ",CE20/CE$7) -> 0.46920444
B84: EBITDA margin | E84: =IF(ISERROR(E46/E$7)," ",E46/E$7) -> 0.22900577 | F84: =IF(ISERROR(F46/F$7)," ",F46/F$7) -> 0.23593428 | G84: =IF(ISERROR(G46/G$7)," ",G46/G$7) -> 0.21741474 | H84: =IF(ISERROR(H46/H$7)," ",H46/H$7) -> 0.23581688 | I84: =IF(ISERROR(I46/I$7)," ",I46/I$7) -> 0.21011267 | J84: =IF(ISERROR(J46/J$7)," ",J46/J$7) -> 0.20728362 | K84: =IF(ISERROR(K46/K$7)," ",K46/K$7) -> 0.200483 | L84: =IF(ISERROR(L46/L$7)," ",L46/L$7) -> 0.12763222 | ... V84: =IF(ISERROR(V46/V$7)," ",V46/V$7) -> 0.47680502 | AB84: =IF(ISERROR(AB46/AB$7)," ",AB46/AB$7) -> 0.23217161 | AC84: =IF(ISERROR(AC46/AC$7)," ",AC46/AC$7) -> 0.20625991 | AD84: =IF(ISERROR(AD46/AD$7)," ",AD46/AD$7) -> 0.2060027 | AE84: =IF(ISERROR(AE46/AE$7)," ",AE46/AE$7) -> 0.19229677 | AF84: =IF(ISERROR(AF46/AF$7)," ",AF46/AF$7) -> 0.19177419 | AG84: =IF(ISERROR(AG46/AG$7)," ",AG46/AG$7) -> 0.19566444 | AH84: =IF(ISERROR(AH46/AH$7)," ",AH46/AH$7) -> 0.26213607 | AI84: =IF(ISERROR(AI46/AI$7)," ",AI46/AI$7) -> 0.1834629 | ... AS84: =IF(ISERROR(AS46/AS$7)," ",AS46/AS$7) -> 0.21709328 | AT84: =IF(ISERROR(AT20/AT$7)," ",AT20/AT$7) -> 0.21987385 | AU84: =IF(ISERROR(AU20/AU$7)," ",AU20/AU$7) -> 0.26274461 | AV84: =IF(ISERROR(AV20/AV$7)," ",AV20/AV$7) -> 0.25273458 | AW84: =IF(ISERROR(AW20/AW$7)," ",AW20/AW$7) -> 0.30819872 | AX84: =IF(ISERROR(AX20/AX$7)," ",AX20/AX$7) -> 0.31151755 | AY84: =IF(ISERROR(AY20/AY$7)," ",AY20/AY$7) -> 0.26543063 | AZ84: =IF(ISERROR(AZ20/AZ$7)," ",AZ20/AZ$7) -> 0.2524474 | BA84: =IF(ISERROR(BA20/BA$7)," ",BA20/BA$7) -> 0.30090972 | ... CE84: =IF(ISERROR(CE20/CE$7)," ",CE20/CE$7) -> 0.46920444
B85: EBIT margin | E85: =IF(ISERROR(E43/E$7)," ",E43/E$7) -> 0.21943795 | F85: =IF(ISERROR(F43/F$7)," ",F43/F$7) -> 0.22757217 | G85: =IF(ISERROR(G43/G$7)," ",G43/G$7) -> 0.20548496 | H85: =IF(ISERROR(H43/H$7)," ",H43/H$7) -> 0.21211614 | I85: =IF(ISERROR(I43/I$7)," ",I43/I$7) -> 0.18467439 | J85: =IF(ISERROR(J43/J$7)," ",J43/J$7) -> 0.17322919 | K85: =IF(ISERROR(K43/K$7)," ",K43/K$7) -> 0.14659052 | L85: =IF(ISERROR(L43/L$7)," ",L43/L$7) -> 0.056695146 | ... V85: =IF(ISERROR(V43/V$7)," ",V43/V$7) -> 0.46463953 | AB85: =IF(ISERROR(AB43/AB$7)," ",AB43/AB$7) -> 0.2063419 | AC85: =IF(ISERROR(AC43/AC$7)," ",AC43/AC$7) -> 0.1843423 | AD85: =IF(ISERROR(AD43/AD$7)," ",AD43/AD$7) -> 0.18034353 | AE85: =IF(ISERROR(AE43/AE$7)," ",AE43/AE$7) -> 0.17020776 | AF85: =IF(ISERROR(AF43/AF$7)," ",AF43/AF$7) -> 0.16683768 | AG85: =IF(ISERROR(AG43/AG$7)," ",AG43/AG$7) -> 0.17673864 | AH85: =IF(ISERROR(AH43/AH$7)," ",AH43/AH$7) -> 0.2123103 | AI85: =IF(ISERROR(AI43/AI$7)," ",AI43/AI$7) -> 0.14187665 | ... CE85: =IF(ISERROR(CE43/CE$7)," ",CE43/CE$7) -> 0.46920444
B86: Pre-tax margin | E86: =IF(ISERROR(E33/E$7)," ",E33/E$7) -> 0.20538557 | F86: =IF(ISERROR(F33/F$7)," ",F33/F$7) -> 0.22319925 | G86: =IF(ISERROR(G33/G$7)," ",G33/G$7) -> 0.20249303 | H86: =IF(ISERROR(H33/H$7)," ",H33/H$7) -> 0.20701937 | I86: =IF(ISERROR(I33/I$7)," ",I33/I$7) -> 0.17959632 | J86: =IF(ISERROR(J33/J$7)," ",J33/J$7) -> 0.1793289 | K86: =IF(ISERROR(K33/K$7)," ",K33/K$7) -> 0.14536406 | L86: =IF(ISERROR(L33/L$7)," ",L33/L$7) -> 0.046727233 | ... V86: =IF(ISERROR(V33/V$7)," ",V33/V$7) -> 0.46501611 | AB86: =IF(ISERROR(AB33/AB$7)," ",AB33/AB$7) -> 0.20610331 | AC86: =IF(ISERROR(AC33/AC$7)," ",AC33/AC$7) -> 0.18758055 | AD86: =IF(ISERROR(AD33/AD$7)," ",AD33/AD$7) -> 0.16455342 | AE86: =IF(ISERROR(AE33/AE$7)," ",AE33/AE$7) -> 0.16183133 | AF86: =IF(ISERROR(AF33/AF$7)," ",AF33/AF$7) -> 0.17322992 | AG86: =IF(ISERROR(AG33/AG$7)," ",AG33/AG$7) -> 0.16893435 | AH86: =IF(ISERROR(AH33/AH$7)," ",AH33/AH$7) -> 0.23727594 | AI86: =IF(ISERROR(AI33/AI$7)," ",AI33/AI$7) -> 0.14514139 | ... CE86: =IF(ISERROR(CE33/CE$7)," ",CE33/CE$7) -> 0.46952852
B87: Effective tax rate (excl. income from associate) | E87: =+E36/E33 -> 0.16052132 | F87: =IF(F36/F33<0,0%,F36/F33) -> 0.15248378 | G87: =IF(G36/G33<0,0%,G36/G33) -> 0.14996313 | H87: =IF(H36/H33<0,0%,H36/H33) -> 0.14600323 | I87: =IF(I36/I33<0,0%,I36/I33) -> 0.14503865 | J87: =IF(J36/J33<0,0%,J36/J33) -> 0.17763062 | K87: =IF(K36/K33<0,0%,K36/K33) -> 0.12895421 | L87: =IF(L36/L33<0,0%,L36/L33) -> 0.1035765 | M87: =IF(M36/M33<0,0%,M36/M33) -> 0.12746253 | ... V87: =IF(V36/V33<0,0%,V36/V33) -> 0.125 | AB87: =+AB36/AB33 -> 0.14891268 | AC87: =+AC36/AC33 -> 0.14701532 | AD87: =+AD36/AD33 -> 0.14654896 | AE87: =+AE36/AE33 -> 0.13718821 | AF87: =+AF36/AF33 -> 0.15261255 | AG87: =+AG36/AG33 -> 0.17125731 | AH87: =+AH36/AH33 -> 0.20844736 | AI87: =+AI36/AI33 -> 0.16396835 | AJ87: =IF(AJ36/AJ33<0,0%,AJ36/AJ33) -> 0.15307248 | AK87: =IF(AK36/AK33<0,0%,AK36/AK33) -> 0.15656693 | AL87: =IF(AL36/AL33<0,0%,AL36/AL33) -> 0.16671512 | AM87: =IF(AM36/AM33<0,0%,AM36/AM33) -> 0 | AN87: =IF(AN36/AN33<0,0%,AN36/AN33) -> 0.13709844 | AO87: =IF(AO36/AO33<0,0%,AO36/AO33) -> 0.13366673 | AP87: =IF(AP36/AP33<0,0%,AP36/AP33) -> 0.15187842 | AQ87: =IF(AQ36/AQ33<0,0%,AQ36/AQ33) -> 0.081669949 | ... BR87: =IF(BR36/BR33<0,0%,BR36/BR33) -> 0.08352716 | BS87: 0.11 | BT87: 0.125 | BU87: 0.125 | BV87: 0.125 | BW87: 0.125 | BX87: 0.125 | BY87: 0.125 | BZ87: 0.125 | CA87: 0.125 | CB87: 0.125 | CC87: 0.125 | CD87: 0.125 | CE87: 0.125
B88: Net margins | E88: =IF(ISERROR(E40/E$7)," ",E40/E$7) -> 0.1724168 | F88: =IF(ISERROR(F40/F$7)," ",F40/F$7) -> 0.18916498 | G88: =IF(ISERROR(G40/G$7)," ",G40/G$7) -> 0.17212654 | H88: =IF(ISERROR(H40/H$7)," ",H40/H$7) -> 0.17679387 | I88: =IF(ISERROR(I40/I$7)," ",I40/I$7) -> 0.15354791 | J88: =IF(ISERROR(J40/J$7)," ",J40/J$7) -> 0.1474746 | K88: =IF(ISERROR(K40/K$7)," ",K40/K$7) -> 0.12661875 | L88: =IF(ISERROR(L40/L$7)," ",L40/L$7) -> 0.04188739 | ... V88: =IF(ISERROR(V40/V$7)," ",V40/V$7) -> 0.40688909 | X88: =IF(ISERROR(X40/X$7)," ",X40/X$7) | Y88: =IF(ISERROR(Y40/Y$7)," ",Y40/Y$7) | Z88: =IF(ISERROR(Z40/Z$7)," ",Z40/Z$7) | AA88: =IF(ISERROR(AA40/AA$7)," ",AA40/AA$7) | AB88: =IF(ISERROR(AB40/AB$7)," ",AB40/AB$7) -> 0.17541192 | AC88: =IF(ISERROR(AC40/AC$7)," ",AC40/AC$7) -> 0.16000334 | AD88: =IF(ISERROR(AD40/AD$7)," ",AD40/AD$7) -> 0.14043829 | AE88: =IF(ISERROR(AE40/AE$7)," ",AE40/AE$7) -> 0.13962998 | ... CE88: =IF(ISERROR(CE40/CE$7)," ",CE40/CE$7) -> 0.41083746
B90: Quarterly distribution | X90: =X4 -> 1Q14 | Y90: =Y4 -> 2Q14 | Z90: =Z4 -> 3Q14 | AA90: =AA4 -> 4Q14 | AB90: =AB4 -> 1Q15 | AC90: =AC4 -> 2Q15 | AD90: =AD4 -> 3Q15 | AE90: =AE4 -> 4Q15 | ... BC90: =BC4 -> 4Q21
B91: Revenue | X91: =X7/$I$7 -> 0 | Y91: =Y7/$I$7 -> 0 | Z91: =Z7/$I$7 -> 0 | AA91: =AA7/$I$7 -> 0 | AB91: =AB7/$I$7 -> 0.22964829 | AC91: =AC7/$I$7 -> 0.27063851 | AD91: =AD7/$I$7 -> 0.23117464 | AE91: =AE7/$I$7 -> 0.26853856 | AF91: =AF7/$J$7 -> 0.204951 | AG91: =AG7/$J$7 -> 0.27004214 | AH91: =AH7/$J$7 -> 0.23884243 | AI91: =AI7/$J$7 -> 0.28616443 | AJ91: =AJ7/$K$7 -> 0.21830781 | AK91: =AK7/$K$7 -> 0.27260804 | AL91: =AL7/$K$7 -> 0.26352942 | AM91: =AM7/$K$7 -> 0.24555473 | AN91: =AN7/$L$7 -> 0.23357966 | AO91: =AO7/$L$7 -> 0.20865763 | AP91: =AP7/$L$7 -> 0.26052568 | AQ91: =AQ7/$L$7 -> 0.29723702 | AR91: =AR7/$L$7 -> 0.29460666 | AS91: =AS7/$L$7 -> 0.33746068 | AT91: =AT7/$M$7 -> 0.24973145 | AU91: =AU7/$M$7 -> 0.33791504 | AV91: =AV7/$M$7 -> 0.2318113 | AW91: =AW7/$N$7 -> 0.28355275 | AX91: =AX7/$N$7 -> 0.30076186 | AY91: =AY7/$N$7 -> 0.28053059 | AZ91: =AZ7/$O$7 -> 0.21466521 | BA91: =BA7/$O$7 -> 0.28086994 | BB91: =BB7/$O$7 -> 0.19876671 | BC91: =BC7/$O$7 -> 0.30569814
B92: Net income to common shareholders | X92: =X40/$I$40 -> 0 | Y92: =Y40/$I$40 -> 0 | Z92: =Z40/$I$40 -> 0 | AA92: =AA40/$I$40 -> 0 | AB92: =AB40/$I$40 -> 0.26234838 | AC92: =AC40/$I$40 -> 0.28201662 | AD92: =AD40/$I$40 -> 0.2114374 | AE92: =AE40/$I$40 -> 0.24419761 | AF92: =AF40/$J$40 -> 0.20400355 | AG92: =AG40/$J$40 -> 0.25636103 | AH92: =AH40/$J$40 -> 0.30417797 | AI92: =AI40/$J$40 -> 0.23545744 | AJ92: =AJ40/$K$40 -> 0.26893674 | AK92: =AK40/$K$40 -> 0.29509328 | AL92: =AL40/$K$40 -> 0.30572232 | AM92: =AM40/$K$40 -> 0.13024765 | AN92: =AN40/$L$40 -> -0.11426797 | AO92: =AO40/$L$40 -> -0.36180624 | AP92: =AP40/$L$40 -> 0.64619923 | AQ92: =AQ40/$L$40 -> 0.82987499 | AR92: =AR40/$M$40 -> 0.15226848 | AS92: =AS40/$M$40 -> 0.22668625 | AT92: =AT40/$M$40 -> 0.24579084 | AU92: =AU40/$M$40 -> 0.37525443 | AV92: =AV40/$M$40 -> 0.26410371 | AW92: =AW40/$N$40 -> 0.27452649 | AX92: =AX40/$N$40 -> 0.306311 | AY92: =AY40/$N$40 -> 0.3048458 | AZ92: =AZ40/$O$40 -> 0.16981646 | BA92: =BA40/$O$40 -> 0.31816127 | BB92: =BB40/$O$40 -> 0.21431741 | BC92: =BC40/$O$40 -> 0.29770487
B94: Other income statement assumptions
B96: Interest income calculation:
B97: Previous cash balance
B98: Interest income as a % of cash
B100: Interest expense calculation:
B101: Total debt | E101: =E143+E139 -> 17 | F101: =F143+F139 -> 0 | G101: =G143+G139 -> 10 | H101: =H143+H139 -> 5 | I101: =I143+I139 -> 0 | J101: =J143+J139 -> 0 | K101: =K143+K139 -> 21.238513 | L101: =L143+L139 -> 0 | ... V101: =V143+V139 -> 3.6224246
B102: Interest charges | E102: =E25 -> 0 | F102: =F25 -> 0 | G102: =G25 -> 0 | H102: =H25 -> 0 | I102: =I25 -> 0 | J102: =J25 -> 0 | K102: =K25 -> 0 | L102: =L25 -> -0.16884679 | ... V102: =V25 -> 0
B103: Effective interest rate | E103: =IFERROR(-E102/AVERAGE(D101:E101),"") -> 0 | F103: =IFERROR(-F102/AVERAGE(E101:F101),"") -> 0 | G103: =IFERROR(-G102/AVERAGE(F101:G101),"") -> 0 | H103: =IFERROR(-H102/AVERAGE(G101:H101),"") -> 0 | I103: =IFERROR(-I102/AVERAGE(H101:I101),"") -> 0 | J103: =IFERROR(-J102/AVERAGE(I101:J101),"") | K103: =IFERROR(-K102/AVERAGE(J101:K101),"") -> 0 | L103: =IFERROR(-L102/AVERAGE(K101:L101),"") -> 0.015900058 | ... S103: =IFERROR(-S102/AVERAGE(R101:S101),"") -> 0.32480369
B105: Interest income calculation:
B106: Cash balance | E106: =E121 -> 106.83876 | F106: =F121 -> 98.539043 | G106: =G121 -> 62.524122 | H106: =H121 -> 89.896097 | I106: =I121 -> 79.318084 | J106: =J121 -> 135.6074 | K106: =K121 -> 108.06688 | L106: =L121 -> 237.00027 | ... V106: =V121 -> 57966.209
B107: Interest income | E107: =E24 -> 0 | F107: =F24 -> 0 | G107: =G24 -> 0 | H107: =H24 -> 0 | I107: =I24 -> 0 | J107: =J24 -> 0 | K107: =K24 -> 0 | L107: =L24 -> 1.6758867 | ... V107: =V24 -> 32
B108: Interest income as % of cash | E108: =E107/AVERAGE(D106:E106) -> 0 | F108: =F107/AVERAGE(E106:F106) -> 0 | G108: =G107/AVERAGE(F106:G106) -> 0 | H108: =H107/AVERAGE(G106:H106) -> 0 | I108: =I107/AVERAGE(H106:I106) -> 0 | J108: =J107/AVERAGE(I106:J106) -> 0 | K108: =K107/AVERAGE(J106:K106) -> 0 | L108: =L107/AVERAGE(K106:L106) -> 0.0097133943 | ... S108: =S107/AVERAGE(R106:S106) -> 0.015979919
B110: Income from associates:
B111: Interests in an associate | E111: 0 | F111: 0 | G111: 0 | H111: 0 | I111: 0 | J111: 0 | K111: 0 | L111: 0 | M111: 0 | N111: 0 | O111: 0 | P111: 0 | Q111: 0 | R111: 0 | S111: 0
B112: As a % of interest in associates | E112: 0 | F112: 0 | G112: 0 | H112: 0 | I112: 0 | J112: 0 | K112: 0 | L112: 0 | M112: 0 | N112: 0 | O112: 0 | P112: 0 | Q112: 0 | R112: 0 | S112: 0
B114: Income from jointly controlled entities:
B115: Interest in a jointly controlled entity | E115: 0 | F115: 0 | G115: 0 | H115: 0 | I115: 0 | J115: 0 | K115: 0 | L115: 0 | M115: 0 | N115: 0 | O115: 0 | P115: 0 | Q115: 0 | R115: 0 | S115: 0
B116: As a % of interest in jointly controlled entities | E116: 0 | F116: 0 | G116: 0 | H116: 0 | I116: 0 | J116: 0 | K116: 0 | L116: 0 | M116: 0 | N116: 0 | O116: 0 | P116: 0 | Q116: 0 | R116: 0 | S116: 0
B119: Balance sheet | E119: =E4 -> 2011 | F119: =F4 -> 2012 | G119: =G4 -> 2013 | H119: =H4 -> 2014 | I119: =I4 -> 2015 | J119: =J4 -> 2016 | K119: =K4 -> 2017 | L119: =L4 -> 2018 | ... V119: =V4 -> 2028 | AR119: 3Q25
B121: Cash and equivalents | E121: 106.83876 | F121: 98.539043 | G121: 62.524122 | H121: 89.896097 | I121: 79.318084 | J121: 135.6074 | K121: 108.06688 | L121: 237.00027 | M121: 253.4036 | N121: 1931.4 | O121: 1579.7782 | P121: 1784.9685 | Q121: 2515.3232 | R121: 1600.2691 | S121: 8155.6139 | T121: =S121+T230 -> 15393.753 | U121: =T121+U230 -> 39089.312 | V121: =U121+V230 -> 57966.209 | AR121: 5438.6257
B122: Account receivable | E122: 85.102423 | F122: 86.140899 | G122: 146.06797 | H122: 197.93571 | I122: 222.84344 | J122: 292.11327 | K122: 424.13408 | L122: 330.83004 | M122: 311.92776 | N122: 368.8736 | O122: 577.20938 | P122: 695.4281 | Q122: 741.12716 | R122: 2549.7892 | S122: =4437.50948109+4.3730615 -> 4441.8825 | T122: =+T7*T161*2/365-S122 -> 11450.187 | U122: =+U7*U161*2/365-T122 -> 13401.641 | V122: =+V7*V161*2/365-U122 -> 17498.723 | AR122: =1.37032032+3993.17881662 -> 3994.5491
B123: Inventory/stocks | E123: 72.280689 | F123: 80.490802 | G123: 115.46273 | H123: 124.84104 | I123: 207.71725 | J123: 283.69802 | K123: 433.53856 | L123: 291.23773 | M123: 352.13864 | N123: 971.78566 | O123: 1526.1823 | P123: 1469.2036 | Q123: 963.3482 | R123: 4132.0672 | S123: 7234.3335 | T123: =+T162*T10*2/365-S123 -> 16127.598 | U123: =+U162*U10*2/365-T123 -> 17211.642 | V123: =+V162*V10*2/365-U123 -> 21026.46 | AR123: 6602.5576
...

Sheet Assumption
A1: =TODAY() -> 46224
A2: Eoptolink (300502.SZ)
B3: 1Q22 | C3: 2Q22 | D3: 3Q22 | E3: 4Q22 | F3: 1Q23 | G3: 2Q23 | H3: 3Q23 | I3: 4Q23 | J3: 1Q24 | K3: 2Q24 | L3: 3Q24 | M3: 4Q24 | N3: 1Q25 | O3: 2Q25 | P3: 3Q25 | Q3: 4Q25 | R3: 1Q26 | S3: 2Q26E | T3: 3Q26E | U3: 4Q26E | V3: 1Q27E | W3: 2Q27E | X3: 3Q27E | Y3: 4Q27E | Z3: 1Q28E | AA3: 2Q28E | AB3: 3Q28E | AC3: 4Q28E | AF3: 2014 | AG3: 2015 | AH3: 2016 | AI3: 2017 | AJ3: 2018 | AK3: 2019 | AL3: 2020 | AM3: 2021 | AN3: 2022 | AO3: 2023 | AP3: 2024 | AQ3: 2025E | AR3: 2026E | AS3: 2027E | AT3: 2028E
A5: Revenue (Rmb million) | B5: =+Model!BD7 -> 738.5133 | C5: =+Model!BE7 -> 740.33465 | D5: =+Model!BF7 -> 935.65916 | E5: =+Model!BG7 -> 896.06668 | F5: =+Model!BH7 -> 600.22289 | G5: =+Model!BI7 -> 704.46093 | H5: =+Model!BJ7 -> 782.36373 | I5: =+Model!BK7 -> 1010.5582 | ... R5: =+Model!BT7 -> 8337.902 | S5: =SUM(S6:S9) -> 11283.248 | T5: =SUM(T6:T9) -> 15163.921 | U5: =SUM(U6:U9) -> 16671.468 | V5: =SUM(V6:V9) -> 15172.087 | W5: =SUM(W6:W9) -> 16800.28 | X5: =SUM(X6:X9) -> 21661.32 | Y5: =SUM(Y6:Y9) -> 20276.903 | Z5: =SUM(Z6:Z9) -> 14673.648 | ... AC5: =SUM(AC6:AC9) -> 24684.879 | AF5: =Model!H7 -> 522.63427 | AG5: =Model!I7 -> 615.11958 | AH5: =Model!J7 -> 713.93165 | AI5: =Model!K7 -> 877.36536 | AJ5: =Model!L7 -> 759.95028 | AK5: =Model!M7 -> 1164.8737 | AL5: =Model!N7 -> 1997.9377 | AM5: =Model!O7 -> 2908.3761 | AN5: =Model!P7 -> 3310.5738 | AO5: =+SUM(AO6:AO9) -> 3097.6058 | AP5: =+SUM(AP6:AP9) -> 8646.8311 | AQ5: =+SUM(AQ6:AQ9) -> 24841.855 | AR5: =+SUM(AR6:AR9) -> 51456.539 | AS5: =+SUM(AS6:AS9) -> 73910.591 | AT5: =SUM(Z5:AC5) -> 84975.376
A6: Optical transceviers | B6: =+B43 -> 705.6 | C6: =+C43 -> 733.6 | D6: =+D43 -> 924.58 | E6: =+E43 -> 887.02 | F6: =+F43 -> 589.3576 | G6: =+G43 -> 696.891 | H6: =+H43 -> 767.68495 | I6: =+I43 -> 998.67055 | ... AC6: =+AC43 -> 24667.178 | AF6: 405.38 | AG6: 463.67 | AH6: 573.95 | AI6: 671.18 | AJ6: 633.85 | AK6: 1100.68 | AL6: 1941.71 | AM6: 2839.99 | AN6: 3248.49 | AO6: =SUM(F6:I6) -> 3052.6041 | AP6: =SUM(J6:M6) -> 8560.4431 | AQ6: =SUM(N6:Q6) -> 24766.139 | AR6: =SUM(R6:U6) -> 51386.363 | AS6: =SUM(V6:Y6) -> 73842.675 | AT6: =SUM(Z6:AC6) -> 84905.064
A7: PON | B7: 15 | C7: 3 | D7: 4 | E7: 2 | F7: =+B7*(1+F13) -> 4.5 | G7: =+C7*(1+G13) -> 3.3 | H7: =+D7*(1+H13) -> 4.4 | I7: =+E7*(1+I13) -> 2.2 | J7: =+F7*(1+J13) -> 4.725 | K7: =+G7*(1+K13) -> 3.465 | L7: =+H7*(1+L13) -> 4.62 | M7: =+I7*(1+M13) -> 2.31 | ... AC7: =+Y7*(1+AC13) -> 2.8078194 | AF7: 80.53 | AG7: 88.57 | AH7: 99.3 | AI7: 155.32 | AJ7: 85.14 | AK7: 43.09 | AL7: 34.31 | AM7: 43.09 | AN7: 26.34 | AO7: =SUM(F7:I7) -> 14.4 | AP7: =SUM(J7:M7) -> 15.12 | AQ7: =SUM(N7:Q7) -> 15.876 | AR7: =SUM(R7:U7) -> 16.6698 | AS7: =SUM(V7:Y7) -> 17.50329 | AT7: =SUM(Z7:AC7) -> 18.378455
A8: Optical components | B8: =+B5-B6-B7 -> 17.913304 | C8: =+C5-C6-C7 -> 3.7346523 | D8: =+D5-D6-D7 -> 7.0791565 | E8: =+E5-E6-E7 -> 7.0466779 | F8: =+B8*(1+F14) -> 5.3739912 | G8: =+C8*(1+G14) -> 4.1081175 | H8: =+D8*(1+H14) -> 7.7870722 | I8: =+E8*(1+I14) -> 7.7513457 | J8: =+F8*(1+J14) -> 5.6426907 | K8: =+G8*(1+K14) -> 4.3135234 | L8: =+H8*(1+L14) -> 8.1764258 | M8: =+I8*(1+M14) -> 8.1389129 | ... AC8: =+Y8*(1+AC14) -> 9.8928995 | AF8: 35.66 | AG8: 57.83 | AH8: 40.68 | AI8: 50.86 | AJ8: 40.96 | AK8: 21.1 | AL8: 21.92 | AM8: 25.29 | AN8: 35.75 | AO8: =SUM(F8:I8) -> 25.020526 | AP8: =SUM(J8:M8) -> 26.271553 | AQ8: =SUM(N8:Q8) -> 27.58513 | AR8: =SUM(R8:U8) -> 28.964387 | AS8: =SUM(V8:Y8) -> 30.412606 | AT8: =SUM(Z8:AC8) -> 31.933237
A9: Others | B9: 0 | C9: 0 | D9: 0 | E9: =+AN9 -> -0.00620947 | F9: =+F5-SUM(F6:F8) -> 0.99129994 | G9: =+G5-SUM(G6:G8) -> 0.16181643 | H9: =+H5-SUM(H6:H8) -> 2.4917046 | I9: =+I5-SUM(I6:I8) -> 1.936303 | J9: =+J5-SUM(J6:J8) -> 10.948123 | K9: =+K5-SUM(K6:K8) -> 6.0635235 | L9: =+L5-SUM(L6:L8) -> 9.5953365 | M9: =+M5-SUM(M6:M8) -> 18.389489 | ... R9: =+R5-SUM(R6:R8) -> 9.5427455 | S9: 5 | T9: 5 | U9: 5 | V9: 5 | W9: 5 | X9: 5 | Y9: 5 | Z9: 5 | AA9: 5 | AB9: 5 | AC9: 5 | AF9: =+AF5-SUM(AF6:AF8) -> 1.0642683 | AG9: =+AG5-SUM(AG6:AG8) -> 5.0495751 | AH9: =+AH5-SUM(AH6:AH8) -> 0.00165081 | AI9: =+AI5-SUM(AI6:AI8) -> 0.00536178 | AJ9: =+AJ5-SUM(AJ6:AJ8) -> 0.0002845 | AK9: =+AK5-SUM(AK6:AK8) -> 0.00368236 | AL9: =+AL5-SUM(AL6:AL8) -> -0.00225373 | AM9: =+AM5-SUM(AM6:AM8) -> 0.00606376 | AN9: =+AN5-SUM(AN6:AN8) -> -0.00620947 | AO9: =SUM(F9:I9) -> 5.581124 | AP9: =SUM(J9:M9) -> 44.996472 | AQ9: =SUM(N9:Q9) -> 32.254681 | AR9: =SUM(R9:U9) -> 24.542745 | AS9: =SUM(V9:Y9) -> 20 | AT9: =SUM(Z9:AC9) -> 20
A11: YoY | AG11: =+AG5/AF5-1 -> 0.1769599 | AH11: =+AH5/AG5-1 -> 0.16063881 | AI11: =+AI5/AH5-1 -> 0.22892067 | AJ11: =+AJ5/AI5-1 -> -0.13382689 | AK11: =+AK5/AJ5-1 -> 0.5328288 | AL11: =+AL5/AK5-1 -> 0.71515399 | AM11: =+AM5/AL5-1 -> 0.45568903 | AN11: =+AN5/AM5-1 -> 0.13828945 | ... AT11: =+AT5/AS5-1 -> 0.149705
A12: Optical transceviers | F12: =+F6/B6-1 -> -0.16474263 | G12: =+G6/C6-1 -> -0.050039531 | H12: =+H6/D6-1 -> -0.16969332 | I12: =+I6/E6-1 -> 0.12587151 | J12: =+J6/F6-1 -> 0.85208112 | K12: =+K6/G6-1 -> 1.297316 | L12: =+L6/H6-1 -> 2.1007111 | M12: =+M6/I6-1 -> 2.4921996 | ... AC12: =+AC6/Y6-1 -> 0.21754256 | AG12: =+AG6/AF6-1 -> 0.14379101 | AH12: =+AH6/AG6-1 -> 0.23784157 | AI12: =+AI6/AH6-1 -> 0.169405 | AJ12: =+AJ6/AI6-1 -> -0.055618463 | AK12: =+AK6/AJ6-1 -> 0.73649917 | AL12: =+AL6/AK6-1 -> 0.76410037 | AM12: =+AM6/AL6-1 -> 0.46262315 | AN12: =+AN6/AM6-1 -> 0.14383853 | ... AT12: =+AT6/AS6-1 -> 0.14981024
A13: PON | F13: -0.7 | G13: 0.1 | H13: 0.1 | I13: 0.1 | J13: 0.05 | K13: 0.05 | L13: 0.05 | M13: 0.05 | N13: 0.05 | O13: 0.05 | P13: 0.05 | Q13: 0.05 | R13: 0.05 | S13: 0.05 | T13: 0.05 | U13: 0.05 | V13: 0.05 | W13: 0.05 | X13: 0.05 | Y13: 0.05 | Z13: 0.05 | AA13: 0.05 | AB13: 0.05 | AC13: 0.05 | AG13: =+AG7/AF7-1 -> 0.099838569 | AH13: =+AH7/AG7-1 -> 0.12114712 | AI13: =+AI7/AH7-1 -> 0.56414904 | AJ13: =+AJ7/AI7-1 -> -0.45184136 | AK13: =+AK7/AJ7-1 -> -0.49389241 | AL13: =+AL7/AK7-1 -> -0.20375957 | AM13: =+AM7/AL7-1 -> 0.25590207 | AN13: =+AN7/AM7-1 -> -0.38872128 | ... AT13: =+AT7/AS7-1 -> 0.05
A14: Optical components | F14: -0.7 | G14: 0.1 | H14: 0.1 | I14: 0.1 | J14: 0.05 | K14: 0.05 | L14: 0.05 | M14: 0.05 | N14: 0.05 | O14: 0.05 | P14: 0.05 | Q14: 0.05 | R14: 0.05 | S14: 0.05 | T14: 0.05 | U14: 0.05 | V14: 0.05 | W14: 0.05 | X14: 0.05 | Y14: 0.05 | Z14: 0.05 | AA14: 0.05 | AB14: 0.05 | AC14: 0.05 | AG14: =+AG8/AF8-1 -> 0.62170499 | AH14: =+AH8/AG8-1 -> -0.29655888 | AI14: =+AI8/AH8-1 -> 0.25024582 | AJ14: =+AJ8/AI8-1 -> -0.19465199 | AK14: =+AK8/AJ8-1 -> -0.48486328 | AL14: =+AL8/AK8-1 -> 0.038862559 | AM14: =+AM8/AL8-1 -> 0.15374088 | AN14: =+AN8/AM8-1 -> 0.41360221 | ... AT14: =+AT8/AS8-1 -> 0.05
A15: Others | AO15: =SUM(F15:I15) -> 0 | AP15: =SUM(J15:M15) -> 0 | AQ15: =SUM(N15:Q15) -> 0 | AR15: =SUM(R15:U15) -> 0 | AS15: =SUM(V15:Y15) -> 0 | AT15: =SUM(W15:Z15) -> 0
A17: Mix | B17: =SUM(B18:B21) -> 1 | C17: =SUM(C18:C21) -> 1 | D17: =SUM(D18:D21) -> 1 | E17: =SUM(E18:E21) -> 0.99999307 | F17: =SUM(F18:F21) -> 1 | G17: =SUM(G18:G21) -> 1 | H17: =SUM(H18:H21) -> 1 | I17: =SUM(I18:I21) -> 1 | ... AC17: =SUM(AC18:AC21) -> 1 | AF17: =SUM(AF18:AF21) -> 1 | AG17: =SUM(AG18:AG21) -> 1 | AH17: =SUM(AH18:AH21) -> 1 | AI17: =SUM(AI18:AI21) -> 1 | AJ17: =SUM(AJ18:AJ21) -> 1 | AK17: =SUM(AK18:AK21) -> 1 | AL17: =SUM(AL18:AL21) -> 1 | AM17: =SUM(AM18:AM21) -> 1 | ... AT17: =SUM(AT18:AT21) -> 1
A18: Optical transceviers | B18: =+B6/B$5 -> 0.95543303 | C18: =+C6/C$5 -> 0.99090323 | D18: =+D6/D$5 -> 0.98815898 | E18: =+E6/E$5 -> 0.98990401 | F18: =+F6/F$5 -> 0.98189791 | G18: =+G6/G$5 -> 0.98925429 | H18: =+H6/H$5 -> 0.98123791 | I18: =+I6/I$5 -> 0.98823655 | ... AC18: =+AC6/AC$5 -> 0.99928293 | AF18: =+AF6/AF$5 -> 0.77564757 | AG18: =+AG6/AG$5 -> 0.7537884 | AH18: =+AH6/AH$5 -> 0.8039285 | AI18: =+AI6/AI$5 -> 0.76499487 | AJ18: =+AJ6/AJ$5 -> 0.83406772 | AK18: =+AK6/AK$5 -> 0.94489215 | AL18: =+AL6/AL$5 -> 0.97185711 | AM18: =+AM6/AM$5 -> 0.97648651 | ... AT18: =+AT6/AT$5 -> 0.99917256
A19: PON | B19: =+B7/B$5 -> 0.020311076 | C19: =+C7/C$5 -> 0.0040522215 | D19: =+D7/D$5 -> 0.004275061 | E19: =+E7/E$5 -> 0.0022319768 | F19: =+F7/F$5 -> 0.0074972149 | G19: =+G7/G$5 -> 0.0046844329 | H19: =+H7/H$5 -> 0.0056239826 | I19: =+I7/I$5 -> 0.0021770146 | ... AC19: =+AC7/AC$5 -> 0.00011374654 | AF19: =+AF7/AF$5 -> 0.15408481 | AG19: =+AG7/AG$5 -> 0.14398826 | AH19: =+AH7/AH$5 -> 0.13908894 | AI19: =+AI7/AI$5 -> 0.17703001 | AJ19: =+AJ7/AJ$5 -> 0.11203364 | AK19: =+AK7/AK$5 -> 0.036991135 | AL19: =+AL7/AL$5 -> 0.017172707 | AM19: =+AM7/AM$5 -> 0.014815828 | ... AT19: =+AT7/AT$5 -> 0.00021627977
A20: Optical components | B20: =+B8/B$5 -> 0.024255899 | C20: =+C8/C$5 -> 0.0050445461 | D20: =+D8/D$5 -> 0.0075659566 | E20: =+E8/E$5 -> 0.0078640106 | F20: =+F8/F$5 -> 0.0089533259 | G20: =+G8/G$5 -> 0.005831576 | H20: =+H8/H$5 -> 0.0099532633 | I20: =+I8/I$5 -> 0.0076703605 | ... AC20: =+AC8/AC$5 -> 0.0004007676 | AF20: =+AF8/AF$5 -> 0.06823127 | AG20: =+AG8/AG$5 -> 0.094014241 | AH20: =+AH8/AH$5 -> 0.056980244 | AI20: =+AI8/AI$5 -> 0.057969008 | AJ20: =+AJ8/AJ$5 -> 0.053898263 | AK20: =+AK8/AK$5 -> 0.018113552 | AL20: =+AL8/AL$5 -> 0.010971313 | AM20: =+AM8/AM$5 -> 0.0086955742 | ... AT20: =+AT8/AT$5 -> 0.000375794
A21: Others | B21: =+B9/B$5 -> 0 | C21: =+C9/C$5 -> 0 | D21: =+D9/D$5 -> 0 | E21: =+E9/E$5 -> -6.9296964e-06 | F21: =+F9/F$5 -> 0.001651553 | G21: =+G9/G$5 -> 0.00022970249 | H21: =+H9/H$5 -> 0.0031848417 | I21: =+I9/I$5 -> 0.0019160728 | ... AC21: =+AC9/AC$5 -> 0.00020255315 | AF21: =+AF9/AF$5 -> 0.0020363539 | AG21: =+AG9/AG$5 -> 0.0082090952 | AH21: =+AH9/AH$5 -> 2.3122802e-06 | AI21: =+AI9/AI$5 -> 6.1112283e-06 | AJ21: =+AJ9/AJ$5 -> 3.7436659e-07 | AK21: =+AK9/AK$5 -> 3.1611668e-06 | AL21: =+AL9/AL$5 -> -1.1280281e-06 | AM21: =+AM9/AM$5 -> 2.0849298e-06 | ... AT21: =+AT9/AT$5 -> 0.0002353623
A23: Optical transceivers revenue by specs | B23: =SUM(B24:B30) -> 705.6 | C23: =SUM(C24:C30) -> 733.6 | D23: =SUM(D24:D30) -> 924.58 | E23: =SUM(E24:E30) -> 887.02 | F23: =SUM(F24:F30) -> 589.3576 | G23: =SUM(G24:G30) -> 696.891 | H23: =SUM(H24:H30) -> 767.68495 | I23: =SUM(I24:I30) -> 998.67055 | ... AC23: =SUM(AC24:AC30) -> 22550.178 | AM23: =SUM(AM24:AM30) -> 2839.9 | AN23: =SUM(AN24:AN30) -> 3249.07 | AO23: =SUM(AO24:AO30) -> 3052.6041 | AP23: =SUM(AP24:AP30) -> 8560.4431 | AQ23: =SUM(AQ24:AQ30) -> 24766.139 | AR23: =SUM(AR24:AR30) -> 51386.363 | AS23: =SUM(AS24:AS31) -> 73842.62 | AT23: =SUM(AT24:AT31) -> 79612.564
A24: 25G or below | B24: =+B53+B272 -> 242.2 | C24: =+C53+C272 -> 242.2 | D24: =+D53+D272 -> 252.58 | E24: =+E53+E272 -> 231.82 | F24: =+F53+F272 -> 203.1366 | G24: =+G53+G272 -> 198.8635 | H24: =+H53+H272 -> 201.65745 | I24: =+I53+I272 -> 150.05155 | ... AC24: =+AC53+AC272 -> 67.167805 | AM24: =+AM53+AM272 -> 1060.29 | AN24: =+AN53+AN272 -> 967.07 | AO24: =+AO53+AO272 -> 753.7091 | AP24: =+AP53+AP272 -> 463.089 | AQ24: =+AQ53+AQ272 -> 412.00478 | AR24: =+AR53+AR272 -> 366.76157 | AS24: =+AS53+AS272 -> 326.66512 | AT24: =+AT53+AT272 -> 291.10697
A25: 40G | B25: =+B54+B273 -> 364 | C25: =+C54+C273 -> 364 | D25: =+D54+D273 -> 431.2 | E25: =+E54+E273 -> 375.2 | F25: =+F54+F273 -> 238.07 | G25: =+G54+G273 -> 296.058 | H25: =+H54+H273 -> 327.978 | I25: =+I54+I273 -> 211.47 | ... AC25: =+AC54+AC273 -> 45.139474 | AM25: =+AM54+AM273 -> 1604.61 | AN25: =+AN54+AN273 -> 1534.4 | AO25: =+AO54+AO273 -> 1073.576 | AP25: =+AP54+AP273 -> 353.04717 | AQ25: =+AQ54+AQ273 -> 282.61532 | AR25: =+AR54+AR273 -> 245.93786 | AS25: =+AS54+AS273 -> 214.1592 | AT25: =+AT54+AT273 -> 186.60993
A26: 100G | B26: =+B55+B274 -> 84 | C26: =+C55+C274 -> 96.6 | D26: =+D55+D274 -> 121.8 | E26: =+E55+E274 -> 109.2 | F26: =+F55+F274 -> 44.345 | G26: =+G55+G274 -> 46.9175 | H26: =+H55+H274 -> 56.7175 | I26: =+I55+I274 -> 54.39 | ... AC26: =+AC55+AC274 -> 29.666577 | AM26: =+AM55+AM274 -> 140 | AN26: =+AN55+AN274 -> 411.6 | AO26: =+AO55+AO274 -> 202.37 | AP26: =+AP55+AP274 -> 68.032825 | AQ26: =+AQ55+AQ274 -> 99.526053 | AR26: =+AR55+AR274 -> 92.740268 | AS26: =+AS55+AS274 -> 86.608802 | AT26: =+AT55+AT274 -> 81.067877
A27: 200G | B27: =+B56+B275 -> 15.4 | C27: =+C56+C275 -> 30.8 | D27: =+D56+D275 -> 46.2 | E27: =+E56+E275 -> 61.6 | F27: =+F56+F275 -> 19.71 | G27: =+G56+G275 -> 39.42 | H27: =+H56+H275 -> 49.932 | I27: =+I56+I275 -> 57.159 | ... AC27: =+AC56+AC275 -> 48.652264 | AM27: =+AM56+AM275 -> 35 | AN27: =+AN56+AN275 -> 154 | AO27: =+AO56+AO275 -> 166.221 | AP27: =+AP56+AP275 -> 127.7208 | AQ27: =+AQ56+AQ275 -> 124.31491 | AR27: =+AR56+AR275 -> 127.88684 | AS27: =+AS56+AS275 -> 131.72061 | AT27: =+AT56+AT275 -> 135.82296
A28: 400G | B28: =+B57+B276 -> 0 | C28: =+C57+C276 -> 0 | D28: =+D57+D276 -> 72.8 | E28: =+E57+E276 -> 109.2 | F28: =+F57+F276 -> 84.096 | G28: =+G57+G276 -> 115.632 | H28: =+H57+H276 -> 131.4 | I28: =+I57+I276 -> 525.6 | ... AC28: =+AC57+AC276 -> 154.22434 | AM28: =+AM57+AM276 -> 0 | AN28: =+AN57+AN276 -> 182 | AO28: =+AO57+AO276 -> 856.728 | AP28: =+AP57+AP276 -> 5927.9533 | AQ28: =+AQ57+AQ276 -> 7450.1698 | AR28: =+AR57+AR276 -> 1785.3568 | AS28: =+AS57+AS276 -> 652.78337 | AT28: =+AT57+AT276 -> 616.89738
A29: 800G | B29: =+B58+B277 -> 0 | C29: =+C58+C277 -> 0 | D29: =+D58+D277 -> 0 | E29: =+E58+E277 -> 0 | F29: =+F58+F277 -> 0 | G29: =+G58+G277 -> 0 | H29: =+H58+H277 -> 0 | I29: =+I58+I277 -> 0 | ... AC29: =+AC58+AC277 -> 4413.9776 | AM29: =+AM58+AM277 -> 0 | AN29: =+AN58+AN277 -> 0 | AO29: =+AO58+AO277 -> 0 | AP29: =+AP58+AP277 -> 1620.6 | AQ29: =+AQ58+AQ277 -> 15463.108 | AR29: =+AR58+AR277 -> 26010.367 | AS29: =+AS58+AS277 -> 24573.386 | AT29: =+AT58+AT277 -> 17632.556
A30: 1.6T | B30: =+B59 -> 0 | C30: =+C59 -> 0 | D30: =+D59 -> 0 | E30: =+E59 -> 0 | F30: =+F59 -> 0 | G30: =+G59 -> 0 | H30: =+H59 -> 0 | I30: =+I59 -> 0 | ... AC30: =+AC59 -> 17791.35 | AM30: =+AM59 -> 0 | AN30: =+AN59 -> 0 | AO30: =+AO59 -> 0 | AP30: =+AP59 -> 0 | AQ30: =+AQ59 -> 934.4 | AR30: =+AR59 -> 22757.312 | AS30: =+AS59 -> 47857.352 | AT30: =+AT59 -> 60668.503
A31: 3.2T | AR31: =AR29/AQ29-1 -> 0.68209178 | AS31: =AS29/AR29-1 -> -0.055246479
AR32: =AR30/AQ30-1 -> 23.355 | AS32: =AS30/AR30-1 -> 1.102944
A33: Mix | B33: =+B23/B$23 -> 1 | C33: =+C23/C$23 -> 1 | D33: =+D23/D$23 -> 1 | E33: =+E23/E$23 -> 1 | F33: =+F23/F$23 -> 1 | G33: =+G23/G$23 -> 1 | H33: =+H23/H$23 -> 1 | I33: =+I23/I$23 -> 1 | ... AC33: =+AC23/AC$23 -> 1 | AM33: =+AM23/AM$23 -> 1 | AN33: =+AN23/AN$23 -> 1 | AO33: =+AO23/AO$23 -> 1 | AP33: =+AP23/AP$23 -> 1 | AQ33: =+AQ23/AQ$23 -> 1 | AR33: =+AR23/AR$23 -> 1 | AS33: =+AS23/AS$23 -> 1 | AT33: =+AT23/AT$23 -> 1
A34: 25G or below | B34: =+B24/B$23 -> 0.34325397 | C34: =+C24/C$23 -> 0.33015267 | D34: =+D24/D$23 -> 0.2731835 | E34: =+E24/E$23 -> 0.26134698 | F34: =+F24/F$23 -> 0.34467461 | G34: =+G24/G$23 -> 0.28535811 | H34: =+H24/H$23 -> 0.26268256 | I34: =+I24/I$23 -> 0.1502513 | ... AC34: =+AC24/AC$23 -> 0.0029785931 | AM34: =+AM24/AM$23 -> 0.3733547 | AN34: =+AN24/AN$23 -> 0.29764517 | AO34: =+AO24/AO$23 -> 0.24690693 | AP34: =+AP24/AP$23 -> 0.054096381 | AQ34: =+AQ24/AQ$23 -> 0.01663581 | AR34: =+AR24/AR$23 -> 0.0071373328 | AS34: =+AS24/AS$23 -> 0.0044238019 | AT34: =+AT24/AT$23 -> 0.0036565456
A35: 40G | B35: =+B25/B$23 -> 0.51587302 | C35: =+C25/C$23 -> 0.49618321 | D35: =+D25/D$23 -> 0.46637392 | E35: =+E25/E$23 -> 0.42298934 | F35: =+F25/F$23 -> 0.4039483 | G35: =+G25/G$23 -> 0.42482684 | H35: =+H25/H$23 -> 0.42722995 | I35: =+I25/I$23 -> 0.21175151 | ... AC35: =+AC25/AC$23 -> 0.0020017347 | AM35: =+AM25/AM$23 -> 0.56502342 | AN35: =+AN25/AN$23 -> 0.47225822 | AO35: =+AO25/AO$23 -> 0.35169186 | AP35: =+AP25/AP$23 -> 0.041241693 | AQ35: =+AQ25/AQ$23 -> 0.01141136 | AR35: =+AR25/AR$23 -> 0.004786053 | AS35: =+AS25/AS$23 -> 0.0029002114 | AT35: =+AT25/AT$23 -> 0.0023439759
A36: 100G | B36: =+B26/B$23 -> 0.11904762 | C36: =+C26/C$23 -> 0.13167939 | D36: =+D26/D$23 -> 0.13173549 | E36: =+E26/E$23 -> 0.12310884 | F36: =+F26/F$23 -> 0.075242942 | G36: =+G26/G$23 -> 0.067324015 | H36: =+H26/H$23 -> 0.073881219 | I36: =+I26/I$23 -> 0.054462405 | ... AC36: =+AC26/AC$23 -> 0.0013155806 | AM36: =+AM26/AM$23 -> 0.04929751 | AN36: =+AN26/AN$23 -> 0.1266824 | AO36: =+AO26/AO$23 -> 0.066294217 | AP36: =+AP26/AP$23 -> 0.0079473485 | AQ36: =+AQ26/AQ$23 -> 0.0040186342 | AR36: =+AR26/AR$23 -> 0.0018047642 | AS36: =+AS26/AS$23 -> 0.0011728837 | AT36: =+AT26/AT$23 -> 0.0010182799
A37: 200G | B37: =+B27/B$23 -> 0.021825397 | C37: =+C27/C$23 -> 0.041984733 | D37: =+D27/D$23 -> 0.049968634 | E37: =+E27/E$23 -> 0.06944601 | F37: =+F27/F$23 -> 0.033443193 | G37: =+G27/G$23 -> 0.056565517 | H37: =+H27/H$23 -> 0.065042307 | I37: =+I27/I$23 -> 0.057235091 | ... AC37: =+AC27/AC$23 -> 0.0021575113 | AM37: =+AM27/AM$23 -> 0.012324378 | AN37: =+AN27/AN$23 -> 0.047398179 | AO37: =+AO27/AO$23 -> 0.054452197 | AP37: =+AP27/AP$23 -> 0.014919882 | AQ37: =+AQ27/AQ$23 -> 0.0050195516 | AR37: =+AR27/AR$23 -> 0.0024887311 | AS37: =+AS27/AS$23 -> 0.001783802 | AT37: =+AT27/AT$23 -> 0.0017060493
A38: 400G | B38: =+B28/B$23 -> 0 | C38: =+C28/C$23 -> 0 | D38: =+D28/D$23 -> 0.078738454 | E38: =+E28/E$23 -> 0.12310884 | F38: =+F28/F$23 -> 0.14269096 | G38: =+G28/G$23 -> 0.16592552 | H38: =+H28/H$23 -> 0.17116397 | I38: =+I28/I$23 -> 0.52629969 | ... AC38: =+AC28/AC$23 -> 0.0068391631 | AM38: =+AM28/AM$23 -> 0 | AN38: =+AN28/AN$23 -> 0.056016029 | AO38: =+AO28/AO$23 -> 0.2806548 | AP38: =+AP28/AP$23 -> 0.69248206 | AQ38: =+AQ28/AQ$23 -> 0.3008208 | AR38: =+AR28/AR$23 -> 0.034743787 | AS38: =+AS28/AS$23 -> 0.008840198 | AT38: =+AT28/AT$23 -> 0.007748744
A39: 800G | B39: =+B29/B$23 -> 0 | C39: =+C29/C$23 -> 0 | D39: =+D29/D$23 -> 0 | E39: =+E29/E$23 -> 0 | F39: =+F29/F$23 -> 0 | G39: =+G29/G$23 -> 0 | H39: =+H29/H$23 -> 0 | I39: =+I29/I$23 -> 0 | ... AC39: =+AC29/AC$23 -> 0.19574026 | AM39: =+AM29/AM$23 -> 0 | AN39: =+AN29/AN$23 -> 0 | AO39: =+AO29/AO$23 -> 0 | AP39: =+AP29/AP$23 -> 0.18931263 | AQ39: =+AQ29/AQ$23 -> 0.62436491 | AR39: =+AR29/AR$23 -> 0.50617257 | AS39: =+AS29/AS$23 -> 0.33278053 | AT39: =+AT29/AT$23 -> 0.22147957
A40: 1.6T | B40: =+B30/B$23 -> 0 | C40: =+C30/C$23 -> 0 | D40: =+D30/D$23 -> 0 | E40: =+E30/E$23 -> 0 | F40: =+F30/F$23 -> 0 | G40: =+G30/G$23 -> 0 | H40: =+H30/H$23 -> 0 | I40: =+I30/I$23 -> 0 | ... AC40: =+AC30/AC$23 -> 0.78896716 | AM40: =+AM30/AM$23 -> 0 | AN40: =+AN30/AN$23 -> 0 | AO40: =+AO30/AO$23 -> 0 | AP40: =+AP30/AP$23 -> 0 | AQ40: =+AQ30/AQ$23 -> 0.037728933 | AR40: =+AR30/AR$23 -> 0.44286676 | AS40: =+AS30/AS$23 -> 0.64809932 | AT40: =+AT30/AT$23 -> 0.76204684
A42: Optical transceviers | AM42: =+AM3 -> 2021 | AN42: =+AN3 -> 2022 | AO42: =+AO3 -> 2023 | AP42: =+AP3 -> 2024 | AQ42: =+AQ3 -> 2025E | AR42: =+AR3 -> 2026E | AS42: =+AS3 -> 2027E | AT42: =+AT3 -> 2028E
A43: Revenue | B43: =+SUM(B44:B45) -> 705.6 | C43: =+SUM(C44:C45) -> 733.6 | D43: =+SUM(D44:D45) -> 924.58 | E43: =+SUM(E44:E45) -> 887.02 | F43: =+SUM(F44:F45) -> 589.3576 | G43: =+SUM(G44:G45) -> 696.891 | H43: =+SUM(H44:H45) -> 767.68495 | I43: =+SUM(I44:I45) -> 998.67055 | ... AC43: =+SUM(AC44:AC45) -> 24667.178 | AM43: =+SUM(AM44:AM45) -> 2839.99 | AN43: =+SUM(AN44:AN45) -> 3248.49 | AO43: =+SUM(AO44:AO45) -> 3052.6041 | AP43: =+SUM(AP44:AP45) -> 8560.4431 | AQ43: =+SUM(AQ44:AQ45) -> 24766.139 | AR43: =+SUM(AR44:AR45) -> 51386.363 | AS43: =+SUM(AS44:AS45) -> 73842.675 | AT43: =+SUM(AT44:AT45) -> 79612.564
A44: Overseas | B44: =+B48 -> 565.4 | C44: =+C48 -> 589.2 | D44: =+D48 -> 758.6 | E44: =+E48 -> 748.8 | F44: =+F48 -> 452.1231 | G44: =+G48 -> 543.944 | H44: =+H48 -> 595.262 | I44: =+I48 -> 839.379 | ... AC44: =+AC48 -> 24361.805 | AM44: =+AM48 -> 2243.135 | AN44: =+AN48 -> 2661.6 | AO44: =+AO48 -> 2430.7081 | AP44: =+AP48 -> 7718.9953 | AQ44: =+AQ48 -> 23650.919 | AR44: =+AR48 -> 50121.687 | AS44: =+AS48 -> 72596.492 | AT44: =+AT48 -> 78454.888
A45: Domestic | B45: =+B267 -> 140.2 | C45: =+C267 -> 144.4 | D45: =+D267 -> 165.98 | E45: =+E267 -> 138.22 | F45: =+F267 -> 137.2345 | G45: =+G267 -> 152.947 | H45: =+H267 -> 172.42295 | I45: =+I267 -> 159.29155 | ... AC45: =+AC267 -> 305.37278 | AM45: =+AM267 -> 596.855 | AN45: =+AN267 -> 586.89 | AO45: =+AO267 -> 621.896 | AP45: =+AP267 -> 841.44779 | AQ45: =+AQ267 -> 1115.2198 | AR45: =+AR267 -> 1264.6757 | AS45: =+AS267 -> 1246.1828 | AT45: =+AT267 -> 1157.6764
A47: Overseas
A48: Overseas revenue | B48: =+B52 -> 565.4 | C48: =+C52 -> 589.2 | D48: =+D52 -> 758.6 | E48: =+E52 -> 748.8 | F48: =+F52 -> 452.1231 | G48: =+G52 -> 543.944 | H48: =+H52 -> 595.262 | I48: =+I52 -> 839.379 | ... AC48: =+AC52 -> 24361.805 | AM48: 2243.135 | AN48: 2661.6 | AO48: =+AO52 -> 2430.7081 | AP48: =+AP52 -> 7718.9953 | AQ48: =+AQ52 -> 23650.919 | AR48: =+AR52 -> 50121.687 | AS48: =+AS52 -> 72596.492 | AT48: =+AT52 -> 78454.888
A49: Overseas shipment | B49: =+B62 -> 1.1 | C49: =+C62 -> 1.12 | D49: =+D62 -> 1.28 | E49: =+E62 -> 1.2 | F49: =+F62 -> 0.85 | G49: =+G62 -> 0.963 | H49: =+H62 -> 1.018 | I49: =+I62 -> 0.8535 | ... AC49: =+AC62 -> 5.0749525 | AM49: =+AM62 -> 4.55 | AN49: =+AN62 -> 4.7 | AO49: =+AO62 -> 3.6845 | AP49: =+AP62 -> 3.871 | AQ49: =+AQ62 -> 8.6186 | AR49: =+AR62 -> 12.73482 | AS49: =+AS62 -> 16.516029 | AT49: =+AT62 -> 18.457448
A50: Overseas ASP | B50: =+B48/B49 -> 514 | C50: =+C48/C49 -> 526.07143 | D50: =+D48/D49 -> 592.65625 | E50: =+E48/E49 -> 624 | F50: =+F48/F49 -> 531.90953 | G50: =+G48/G49 -> 564.8432 | H50: =+H48/H49 -> 584.73674 | I50: =+I48/I49 -> 983.45518 | ... AC50: =+AC48/AC49 -> 4800.4006 | AM50: =+AM48/AM49 -> 492.9967 | AN50: =+AN48/AN49 -> 566.29787 | AO50: =+AO48/AO49 -> 659.71179 | AP50: =+AP48/AP49 -> 1994.0572 | AQ50: =+AQ48/AQ49 -> 2744.1718 | AR50: =+AR48/AR49 -> 3935.7986 | AS50: =+AS48/AS49 -> 4395.5173 | AT50: =+AT48/AT49 -> 4250.5816
A52: Revenue (Rmb mn) | B52: =SUM(B53:B57) -> 565.4 | C52: =SUM(C53:C57) -> 589.2 | D52: =SUM(D53:D57) -> 758.6 | E52: =SUM(E53:E57) -> 748.8 | F52: =SUM(F53:F59) -> 452.1231 | G52: =SUM(G53:G59) -> 543.944 | H52: =SUM(H53:H59) -> 595.262 | I52: =SUM(I53:I59) -> 839.379 | J52: =SUM(J53:J59) -> 966.04542 | K52: =SUM(K53:K59) -> 1392.8975 | L52: =SUM(L53:L59) -> 2132.3729 | M52: =SUM(M53:M59) -> 3227.6795 | ... Y52: =SUM(Y53:Y59) -> 19933.672 | Z52: =SUM(Z53:Z60) -> 14402.893 | AA52: =SUM(AA53:AA60) -> 18841.749 | AB52: =SUM(AB53:AB60) -> 26140.94 | AC52: =SUM(AC53:AC60) -> 24361.805 | AM52: =+SUM(AM53:AM59) -> 2243.2433 | AN52: =+SUM(AN53:AN59) -> 2662 | AO52: =+SUM(AO53:AO59) -> 2430.7081 | AP52: =+SUM(AP53:AP59) -> 7718.9953 | AQ52: =+SUM(AQ53:AQ59) -> 23650.919 | AR52: =+SUM(AR53:AR59) -> 50121.687 | AS52: =+SUM(AS53:AS59) -> 72596.492 | AT52: =+SUM(AT53:AT59) -> 78454.888
A53: 25G or below | B53: =+B203 -> 138.4 | C53: =+C203 -> 138.4 | D53: =+D203 -> 138.4 | E53: =+E203 -> 138.4 | F53: =+F203 -> 109.4571 | G53: =+G203 -> 105.184 | H53: =+H203 -> 98.61 | I53: =+I203 -> 65.74 | ... N53: =+N203 -> 26.698657 | O53: =+O63*O92 -> 26.698657 | P53: =+P63*P92 -> 26.698657 | Q53: =+Q63*Q92 -> 26.698657 | R53: =+R63*R92 -> 22.827352 | S53: =+S63*S92 -> 22.827352 | T53: =+T63*T92 -> 22.827352 | U53: =+U63*U92 -> 22.827352 | V53: =+V63*V92 -> 19.517386 | ... AC53: =+AC63*AC92 -> 16.687365 | AM53: =+AM92*AM63 -> 623.7 | AN53: =+AN92*AN63 -> 553.6 | AO53: =SUM(F53:I53) -> 378.9911 | AP53: =SUM(J53:M53) -> 124.906 | AQ53: =SUM(N53:Q53) -> 106.79463 | AR53: =SUM(R53:U53) -> 91.309409 | AS53: =SUM(V53:Y53) -> 78.069544 | AT53: =SUM(Z53:AC53) -> 66.74946
A54: 40G | B54: =+B204 -> 336 | C54: =+C204 -> 336 | D54: =+D204 -> 392 | E54: =+E204 -> 347.2 | F54: =+F204 -> 212.8 | G54: =+G204 -> 270.788 | H54: =+H204 -> 292.6 | I54: =+I204 -> 186.2 | ... N54: =+N204 -> 48.013 | O54: =+O64*O93 -> 48.013 | P54: =+P64*P93 -> 48.013 | Q54: =+Q64*Q93 -> 48.013 | R54: =+R64*R93 -> 41.051115 | S54: =+S64*S93 -> 41.051115 | T54: =+T64*T93 -> 41.051115 | U54: =+U64*U93 -> 41.051115 | V54: =+V64*V93 -> 35.098703 | ... AC54: =+AC64*AC93 -> 30.009391 | AM54: =+AM93*AM64 -> 1491.21 | AN54: =+AN93*AN64 -> 1411.2 | AO54: =SUM(F54:I54) -> 962.388 | AP54: =SUM(J54:M54) -> 252.7 | AQ54: =SUM(N54:Q54) -> 192.052 | AR54: =SUM(R54:U54) -> 164.20446 | AS54: =SUM(V54:Y54) -> 140.39481 | AT54: =SUM(Z54:AC54) -> 120.03757
A55: 100G | B55: =+B205 -> 75.6 | C55: =+C205 -> 84 | D55: =+D205 -> 109.2 | E55: =+E205 -> 92.4 | F55: =+F205 -> 39.2 | G55: =+G205 -> 39.2 | H55: =+H205 -> 49 | I55: =+I205 -> 44.1 | ... N55: =+N205 -> 7.871605 | O55: =+O65*O94 -> 7.871605 | P55: =+P65*P94 -> 26.5335 | Q55: =+Q65*Q94 -> 26.5335 | R55: =+R65*R94 -> 7.1041235 | S55: =+S65*S94 -> 7.1041235 | T55: =+T65*T94 -> 23.946484 | U55: =+U65*U94 -> 23.946484 | V55: =+V65*V94 -> 6.4114715 | ... AC55: =+AC65*AC94 -> 19.504561 | AM55: =+AM94*AM65 -> 93.333333 | AN55: =+AN94*AN65 -> 361.2 | AO55: =SUM(F55:I55) -> 171.5 | AP55: =SUM(J55:M55) -> 37.24 | AQ55: =SUM(N55:Q55) -> 68.81021 | AR55: =SUM(R55:U55) -> 62.101215 | AS55: =SUM(V55:Y55) -> 56.046346 | AT55: =SUM(Z55:AC55) -> 50.581827
A56: 200G | B56: =+B206 -> 15.4 | C56: =+C206 -> 30.8 | D56: =+D206 -> 46.2 | E56: =+E206 -> 61.6 | F56: =+F206 -> 6.57 | G56: =+G206 -> 13.14 | H56: =+H206 -> 23.652 | I56: =+I206 -> 17.739 | ... N56: =+N206 -> 5.3217 | O56: =+O66*O95 -> 5.3217 | P56: =+P66*P95 -> 5.3217 | Q56: =+Q66*Q95 -> 5.3217 | R56: =+R66*R95 -> 5.055615 | S56: =+S66*S95 -> 5.055615 | T56: =+T66*T95 -> 5.055615 | U56: =+U66*U95 -> 5.055615 | V56: =+V66*V95 -> 4.8028343 | ... AC56: =+AC66*AC95 -> 4.5626925 | AM56: =+AM95*AM66 -> 35 | AN56: =+AN95*AN66 -> 154 | AO56: =SUM(F56:I56) -> 61.101 | AP56: =SUM(J56:M56) -> 23.652 | AQ56: =SUM(N56:Q56) -> 21.2868 | AR56: =SUM(R56:U56) -> 20.22246 | AS56: =SUM(V56:Y56) -> 19.211337 | AT56: =SUM(Z56:AC56) -> 18.25077
A57: 400G | B57: =+B207 -> 0 | C57: =+C207 -> 0 | D57: =+D207 -> 72.8 | E57: =+E207 -> 109.2 | F57: =+F207 -> 84.096 | G57: =+G207 -> 115.632 | H57: =+H207 -> 131.4 | I57: =+I207 -> 525.6 | ... N57: =+N207 -> 2383.4646 | O57: =+O144+O207 -> 1879.7427 | P57: =+P144+P207 -> 1272.1491 | Q57: =+Q144+Q207 -> 1329.111 | R57: =+R144+R207 -> 1011.8142 | S57: =+S144+S207 -> 170.8857 | T57: =+T144+T207 -> 34.17714 | U57: =+U144+U207 -> 17.08857 | V57: =+V144+V207 -> 16.575913 | ... AC57: =+AC144+AC207 -> 15.422434 | AM57: =+AM96*AM67 -> 0 | AN57: =+AN96*AN67 -> 182 | AO57: =SUM(F57:I57) -> 856.728 | AP57: =SUM(J57:M57) -> 5659.8973 | AQ57: =SUM(N57:Q57) -> 6864.4674 | AR57: =SUM(R57:U57) -> 1233.9656 | AS57: =SUM(V57:Y57) -> 65.278337 | AT57: =SUM(Z57:AC57) -> 61.689738
A58: 800G | B58: =+B208 -> 0 | C58: =+C208 -> 0 | D58: =+D208 -> 0 | E58: =+E208 -> 0 | F58: =+F208 -> 0 | G58: =+G208 -> 0 | H58: =+H208 -> 0 | I58: =+I208 -> 0 | ... N58: =+N208 -> 1315.7082 | O58: =+O145+O208 -> 4132.53 | P58: =+P145+P208 -> 4095.3 | Q58: =+Q145+Q208 -> 5919.57 | R58: =+R145+R208 -> 5643.6957 | S58: =+S145+S208 -> 6105.72 | T58: =+T145+T208 -> 7021.578 | U58: =+U145+U208 -> 7021.578 | V58: =+V145+V208 -> 6246.1516 | ... AC58: =+AC145+AC208 -> 4367.2689 | AO58: =SUM(F58:I58) -> 0 | AP58: =SUM(J58:M58) -> 1620.6 | AQ58: =SUM(N58:Q58) -> 15463.108 | AR58: =SUM(R58:U58) -> 25792.572 | AS58: =SUM(V58:Y58) -> 24380.14 | AT58: =SUM(Z58:AC58) -> 17469.075
A59: 1.6T | B59: =+B209 -> 0 | C59: =+C209 -> 0 | D59: =+D209 -> 0 | E59: =+E209 -> 0 | F59: =+F209 -> 0 | G59: =+G209 -> 0 | H59: =+H209 -> 0 | I59: =+I209 -> 0 | ... N59: =+N209 -> 0 | O59: =+O146+O209 -> 0 | P59: =+P146+P209 -> 280.32 | Q59: =+Q146+Q209 -> 654.08 | R59: =+R146+R209 -> 1303.488 | S59: =+S146+S209 -> 4597.248 | T59: =+T146+T209 -> 7662.08 | U59: =+U146+U209 -> 9194.496 | V59: =+V146+V209 -> 8550.8813 | ... AC59: =+AC146+AC209 -> 17791.35 | AO59: =SUM(F59:I59) -> 0 | AP59: =SUM(J59:M59) -> 0 | AQ59: =SUM(N59:Q59) -> 934.4 | AR59: =SUM(R59:U59) -> 22757.312 | AS59: =SUM(V59:Y59) -> 47857.352 | AT59: =SUM(Z59:AC59) -> 60668.503
A60: 3.2T | AA60: =AA70*AA99 -> 1058.5 | AB60: =AB70*AB99 -> 2117 | AC60: =AC70*AC99 -> 2117 | AT60: =SUM(Z60:AC60) -> 5292.5
A62: Shipment (mn units) | B62: =SUM(B63:B67) -> 1.1 | C62: =SUM(C63:C67) -> 1.12 | D62: =SUM(D63:D67) -> 1.28 | E62: =SUM(E63:E67) -> 1.2 | F62: =SUM(F63:F67) -> 0.85 | G62: =SUM(G63:G67) -> 0.963 | H62: =SUM(H63:H67) -> 1.018 | I62: =SUM(I63:I67) -> 0.8535 | J62: =SUM(J63:J69) -> 0.533 | K62: =SUM(K63:K69) -> 0.815 | L62: =SUM(L63:L69) -> 1.098 | M62: =SUM(M63:M69) -> 1.425 | N62: =SUM(N63:N69) -> 1.6358 | O62: =SUM(O63:O69) -> 2.3128 | P62: =SUM(P63:P69) -> 2.055 | Q62: =SUM(Q63:Q69) -> 2.615 | ... AC62: =SUM(AC63:AC69) -> 5.0749525 | AM62: =SUM(AM63:AM67) -> 4.55 | AN62: =SUM(AN63:AN67) -> 4.7 | AO62: =SUM(AO63:AO69) -> 3.6845 | AP62: =SUM(AP63:AP69) -> 3.871 | AQ62: =SUM(AQ63:AQ69) -> 8.6186 | AR62: =SUM(AR63:AR69) -> 12.73482 | AS62: =SUM(AS63:AS69) -> 16.516029 | AT62: =SUM(AT63:AT69) -> 18.457448
A63: 25G or below | B63: 0.4 | C63: 0.4 | D63: 0.4 | E63: 0.4 | F63: 0.333 | G63: 0.32 | H63: 0.3 | I63: 0.2 | J63: 0.1 | K63: 0.1 | L63: 0.1 | M63: 0.1 | N63: =+J63*(1+N73) -> 0.09 | O63: =+K63*(1+O73) -> 0.09 | P63: =+L63*(1+P73) -> 0.09 | Q63: =+M63*(1+Q73) -> 0.09 | R63: =+N63*(1+R73) -> 0.081 | S63: =+O63*(1+S73) -> 0.081 | T63: =+P63*(1+T73) -> 0.081 | U63: =+Q63*(1+U73) -> 0.081 | ... AC63: =+Y63*(1+AC73) -> 0.06561 | AM63: 1.8 | AN63: 1.6 | AO63: =SUM(F63:I63) -> 1.153 | AP63: =SUM(J63:M63) -> 0.4 | AQ63: =SUM(N63:Q63) -> 0.36 | AR63: =SUM(R63:U63) -> 0.324 | AS63: =SUM(V63:Y63) -> 0.2916 | AT63: =SUM(Z63:AC63) -> 0.26244
A64: 40G | B64: 0.6 | C64: 0.6 | D64: 0.7 | E64: 0.62 | F64: 0.4 | G64: 0.509 | H64: 0.55 | I64: 0.35 | J64: 0.05 | K64: 0.15 | L64: 0.15 | M64: 0.15 | N64: 0.1 | O64: 0.1 | P64: 0.1 | Q64: 0.1 | R64: =+N64*(1+R74) -> 0.09 | S64: =+O64*(1+S74) -> 0.09 | T64: =+P64*(1+T74) -> 0.09 | U64: =+Q64*(1+U74) -> 0.09 | V64: =+R64*(1+V74) -> 0.081 | W64: =+S64*(1+W74) -> 0.081 | X64: =+T64*(1+X74) -> 0.081 | Y64: =+U64*(1+Y74) -> 0.081 | ... AC64: =+Y64*(1+AC74) -> 0.0729 | AM64: 2.63 | AN64: 2.52 | AO64: =SUM(F64:I64) -> 1.809 | AP64: =SUM(J64:M64) -> 0.5 | AQ64: =SUM(N64:Q64) -> 0.4 | AR64: =SUM(R64:U64) -> 0.36 | AS64: =SUM(V64:Y64) -> 0.324 | AT64: =SUM(Z64:AC64) -> 0.2916
A65: 100G | B65: 0.09 | C65: 0.1 | D65: 0.13 | E65: 0.11 | F65: 0.08 | G65: 0.08 | H65: 0.1 | I65: 0.09 | J65: 0.02 | K65: 0.02 | L65: 0.02 | M65: 0.02 | N65: =+J65*(1+N75) -> 0.0178 | O65: =+K65*(1+O75) -> 0.0178 | P65: 0.06 | Q65: 0.06 | R65: =+N65*(1+R75) -> 0.01691 | S65: =+O65*(1+S75) -> 0.01691 | T65: =+P65*(1+T75) -> 0.057 | U65: =+Q65*(1+U75) -> 0.057 | V65: =+R65*(1+V75) -> 0.0160645 | W65: =+S65*(1+W75) -> 0.0160645 | X65: =+T65*(1+X75) -> 0.05415 | Y65: =+U65*(1+Y75) -> 0.05415 | ... AC65: =+Y65*(1+AC75) -> 0.0514425 | AM65: 0.1 | AN65: 0.43 | AO65: =SUM(F65:I65) -> 0.35 | AP65: =SUM(J65:M65) -> 0.08 | AQ65: =SUM(N65:Q65) -> 0.1556 | AR65: =SUM(R65:U65) -> 0.14782 | AS65: =SUM(V65:Y65) -> 0.140429 | AT65: =SUM(Z65:AC65) -> 0.13340755
A66: 200G | B66: 0.01 | C66: 0.02 | D66: 0.03 | E66: 0.04 | F66: 0.005 | G66: 0.01 | H66: 0.018 | I66: 0.0135 | J66: 0.005 | K66: 0.005 | L66: 0.005 | M66: 0.005 | N66: 0.005 | O66: 0.005 | P66: 0.005 | Q66: 0.005 | R66: 0.005 | S66: 0.005 | T66: 0.005 | U66: 0.005 | V66: 0.005 | W66: 0.005 | X66: 0.005 | Y66: 0.005 | Z66: 0.005 | AA66: 0.005 | AB66: 0.005 | AC66: 0.005 | AM66: 0.02 | AN66: 0.1 | AO66: =SUM(F66:I66) -> 0.0465 | AP66: =SUM(J66:M66) -> 0.02 | AQ66: =SUM(N66:Q66) -> 0.02 | AR66: =SUM(R66:U66) -> 0.02 | AS66: =SUM(V66:Y66) -> 0.02 | AT66: =SUM(Z66:AC66) -> 0.02
A67: 400G | B67: 0 | C67: 0 | D67: 0.02 | E67: 0.03 | F67: 0.032 | G67: 0.044 | H67: 0.05 | I67: 0.2 | J67: 0.348 | K67: 0.51 | L67: 0.743 | M67: 0.9 | N67: 1.1 | O67: 0.99 | P67: 0.67 | Q67: 0.7 | R67: 0.573 | S67: 0.1 | T67: 0.02 | U67: 0.01 | V67: 0.01 | W67: 0.01 | X67: 0.01 | Y67: 0.01 | Z67: 0.01 | AA67: 0.01 | AB67: 0.01 | AC67: 0.01 | AM67: 0 | AN67: 0.05 | AO67: =SUM(F67:I67) -> 0.326 | AP67: =SUM(J67:M67) -> 2.501 | AQ67: =SUM(N67:Q67) -> 3.46 | AR67: =SUM(R67:U67) -> 0.703 | AS67: =SUM(V67:Y67) -> 0.04 | AT67: =SUM(Z67:AC67) -> 0.04
A68: 800G | F68: 0 | G68: 0 | H68: 0 | I68: 0 | J68: 0.01 | K68: 0.03 | L68: 0.08 | M68: 0.25 | N68: 0.323 | O68: 1.11 | P68: 1.1 | Q68: 1.59 | R68: 1.63 | S68: 2 | T68: 2.3 | U68: 2.3 | V68: 2.2 | W68: 2.2 | X68: 2.2 | Y68: 2.2 | Z68: =V68*0.85 -> 1.87 | AA68: =W68*0.85 -> 1.87 | AB68: =X68*0.85 -> 1.87 | AC68: =Y68*0.85 -> 1.87 | AO68: =SUM(F68:I68) -> 0 | AP68: =SUM(J68:M68) -> 0.37 | AQ68: =SUM(N68:Q68) -> 4.123 | AR68: =SUM(R68:U68) -> 8.23 | AS68: =SUM(V68:Y68) -> 8.8 | AT68: =SUM(Z68:AC68) -> 7.48
A69: 1.6T | P69: 0.03 | Q69: 0.07 | R69: 0.15 | S69: 0.6 | T69: 1 | U69: 1.2 | V69: 1.2 | W69: 1.5 | X69: 2.2 | Y69: 2 | Z69: =V69*(1+40%) -> 1.68 | AA69: =W69*(1+50%) -> 2.25 | AB69: =X69*(1+50%) -> 3.3 | AC69: =Y69*(1+50%) -> 3 | AO69: =SUM(F69:I69) -> 0 | AP69: =SUM(J69:M69) -> 0 | AQ69: =SUM(N69:Q69) -> 0.1 | AR69: =SUM(R69:U69) -> 2.95 | AS69: =SUM(V69:Y69) -> 6.9 | AT69: =SUM(Z69:AC69) -> 10.23
A70: 3.2T | AA70: 0.1 | AB70: 0.2 | AC70: 0.2 | AR70: =SUM(R70:U70) -> 0 | AS70: =SUM(V70:Y70) -> 0 | AT70: =SUM(Z70:AC70) -> 0.5
AQ71: =+AQ58/AQ68/7.3 -> 513.76037 | AR71: =+AR58/AR68/7.3 -> 429.31094 | AS71: =+AS58/AS68/7.3 -> 379.5165
A72: Shipment YoY | AQ72: =+AQ59/AQ69/7.3 -> 1280 | AR72: =+AR59/AR69/7.3 -> 1056.7593 | AS72: =+AS59/AS69/7.3 -> 950.11617
A73: 25G or below | J73: -0.1 | K73: -0.1 | L73: -0.1 | M73: -0.1 | N73: -0.1 | O73: -0.1 | P73: -0.1 | Q73: -0.1 | R73: -0.1 | S73: -0.1 | T73: -0.1 | U73: -0.1 | V73: -0.1 | W73: -0.1 | X73: -0.1 | Y73: -0.1 | Z73: -0.1 | AA73: -0.1 | AB73: -0.1 | AC73: -0.1 | AN73: =+AN63/AM63-1 -> -0.11111111 | AO73: =+AO63/AN63-1 -> -0.279375 | AP73: =+AP63/AO63-1 -> -0.65307892 | AQ73: =+AQ63/AP63-1 -> -0.1 | AR73: =+AR63/AQ63-1 -> -0.1 | AS73: =+AS63/AR63-1 -> -0.1 | AT73: =+AT63/AS63-1 -> -0.1
A74: 40G | J74: -0.1 | K74: -0.1 | L74: -0.1 | M74: -0.1 | N74: -0.1 | O74: -0.1 | P74: -0.1 | Q74: -0.1 | R74: -0.1 | S74: -0.1 | T74: -0.1 | U74: -0.1 | V74: -0.1 | W74: -0.1 | X74: -0.1 | Y74: -0.1 | Z74: -0.1 | AA74: -0.1 | AB74: -0.1 | AC74: -0.1 | AN74: =+AN64/AM64-1 -> -0.041825095 | AO74: =+AO64/AN64-1 -> -0.28214286 | AP74: =+AP64/AO64-1 -> -0.7236042 | AQ74: =+AQ64/AP64-1 -> -0.2 | AR74: =+AR64/AQ64-1 -> -0.1 | AS74: =+AS64/AR64-1 -> -0.1 | AT74: =+AT64/AS64-1 -> -0.1
A75: 100G | J75: -0.45 | K75: -0.45 | L75: -0.45 | M75: -0.45 | N75: -0.11 | O75: -0.11 | P75: -0.11 | Q75: -0.11 | R75: -0.05 | S75: -0.05 | T75: -0.05 | U75: -0.05 | V75: -0.05 | W75: -0.05 | X75: -0.05 | Y75: -0.05 | Z75: -0.05 | AA75: -0.05 | AB75: -0.05 | AC75: -0.05 | AN75: =+AN65/AM65-1 -> 3.3 | AO75: =+AO65/AN65-1 -> -0.18604651 | AP75: =+AP65/AO65-1 -> -0.77142857 | AQ75: =+AQ65/AP65-1 -> 0.945 | AR75: =+AR65/AQ65-1 -> -0.05 | AS75: =+AS65/AR65-1 -> -0.05 | AT75: =+AT65/AS65-1 -> -0.05
A76: 200G | J76: =+J66/F66-1 -> 0 | K76: =+K66/G66-1 -> -0.5 | L76: =+L66/H66-1 -> -0.72222222 | M76: =+M66/I66-1 -> -0.62962963 | N76: =+N66/J66-1 -> 0 | O76: =+O66/K66-1 -> 0 | P76: =+P66/L66-1 -> 0 | Q76: =+Q66/M66-1 -> 0 | ... AC76: =+AC66/Y66-1 -> 0 | AN76: =+AN66/AM66-1 -> 4 | AO76: =+AO66/AN66-1 -> -0.535 | AP76: =+AP66/AO66-1 -> -0.56989247 | AQ76: =+AQ66/AP66-1 -> 0 | AR76: =+AR66/AQ66-1 -> 0 | AS76: =+AS66/AR66-1 -> 0 | AT76: =+AT66/AS66-1 -> 0
A77: 400G | J77: =+J67/F67-1 -> 9.875 | K77: =+K67/G67-1 -> 10.590909 | L77: =+L67/H67-1 -> 13.86 | M77: =+M67/I67-1 -> 3.5 | N77: =+N67/J67-1 -> 2.1609195 | O77: =+O67/K67-1 -> 0.94117647 | P77: =+P67/L67-1 -> -0.098250336 | Q77: =+Q67/M67-1 -> -0.22222222 | ... AC77: =+AC67/Y67-1 -> 0 | AO77: =+AO67/AN67-1 -> 5.52 | AP77: =+AP67/AO67-1 -> 6.6717791 | AQ77: =+AQ67/AP67-1 -> 0.38344662 | AR77: =+AR67/AQ67-1 -> -0.79682081 | AS77: =+AS67/AR67-1 -> -0.943101 | AT77: =+AT67/AS67-1 -> 0
A78: 800G | P78: =+P68/L68-1 -> 12.75 | Q78: =+Q68/M68-1 -> 5.36 | R78: =+R68/N68-1 -> 4.0464396 | S78: =+S68/O68-1 -> 0.8018018 | T78: =+T68/P68-1 -> 1.0909091 | U78: =+U68/Q68-1 -> 0.44654088 | V78: =+V68/R68-1 -> 0.34969325 | W78: =+W68/S68-1 -> 0.1 | ... AC78: =+AC68/Y68-1 -> -0.15 | AQ78: =+AQ68/AP68-1 -> 10.143243 | AR78: =+AR68/AQ68-1 -> 0.99611933 | AS78: =+AS68/AR68-1 -> 0.069258809 | AT78: =+AT68/AS68-1 -> -0.15
A79: 1.6T | V79: =+V69/R69-1 -> 7 | W79: =+W69/S69-1 -> 1.5 | X79: =+X69/T69-1 -> 1.2 | Y79: =+Y69/U69-1 -> 0.66666667 | Z79: =+Z69/V69-1 -> 0.4 | AA79: =+AA69/W69-1 -> 0.5 | AB79: =+AB69/X69-1 -> 0.5 | AC79: =+AC69/Y69-1 -> 0.5 | AS79: =+AS69/AR69-1 -> 1.3389831 | AT79: =+AT69/AS69-1 -> 0.4826087
A81: ASP (US$) | AM81: =+AM91/7.3 -> 67.537057 | AN81: =+AN91/7.3 -> 77.586709 | AO81: =+AO91/7.3 -> 90.371478 | AP81: =+AP91/7.3 -> 273.15852 | AQ81: =+AQ91/7.3 -> 375.91395 | AR81: =+AR91/7.3 -> 539.15049 | AS81: =+AS91/7.3 -> 602.12566 | AT81: =+AT91/7.3 -> 582.27146
A82: 25G or below | AM82: =+AM92/7.3 -> 47.465753 | AN82: =+AN92/7.3 -> 47.39726 | AO82: =+AO92/7.3 -> 45.027397 | AP82: =+AP92/7.3 -> 42.776027 | AQ82: =+AQ92/7.3 -> 40.637226 | AR82: =+AR92/7.3 -> 38.605365 | AS82: =+AS92/7.3 -> 36.675096 | AT82: =+AT92/7.3 -> 34.841342
A83: 40G | AM83: =+AM93/7.3 -> 77.671233 | AN83: =+AN93/7.3 -> 76.712329 | AO83: =+AO93/7.3 -> 72.876712 | AP83: =+AP93/7.3 -> 69.232877 | AQ83: =+AQ93/7.3 -> 65.771233 | AR83: =+AR93/7.3 -> 62.482671 | AS83: =+AS93/7.3 -> 59.358538 | AT83: =+AT93/7.3 -> 56.390611
A84: 100G | AM84: =+AM94/7.3 -> 127.85388 | AN84: =+AN94/7.3 -> 115.06849 | AO84: =+AO94/7.3 -> 67.123288 | AP84: =+AP94/7.3 -> 63.767123 | AQ84: =+AQ94/7.3 -> 60.578767 | AR84: =+AR94/7.3 -> 57.549829 | AS84: =+AS94/7.3 -> 54.672337 | AT84: =+AT94/7.3 -> 51.93872
A85: 200G | AM85: =+AM95/7.3 -> 239.72603 | AN85: =+AN95/7.3 -> 210.9589 | AO85: =+AO95/7.3 -> 180 | AP85: =+AP95/7.3 -> 162 | AQ85: =+AQ95/7.3 -> 145.8 | AR85: =+AR95/7.3 -> 138.51 | AS85: =+AS95/7.3 -> 131.5845 | AT85: =+AT95/7.3 -> 125.00527
A86: 400G | AM86: =+AM96/7.3 -> 623.28767 | AN86: =+AN96/7.3 -> 498.63014 | AO86: =+AO96/7.3 -> 360 | AP86: 306 | AQ86: =+AP86*0.85 -> 260.1 | AR86: 234.09 | AS86: 222.3855 | AT86: 222.3855
A87: 800G | AM87: =+AM97/7.3 -> 0 | AN87: =+AN97/7.3 -> 0 | AO87: 0 | AP87: 600 | AQ87: =+AP87*0.85 -> 510 | AR87: =+AQ87*0.82 -> 418.2 | AS87: =+AR87*0.9 -> 376.38 | AT87: =+AS87*0.85 -> 319.923
A88: 1.6T | AO88: =+AO98/7.3 -> 0 | AP88: 0 | AQ88: 1280 | AR88: =+AQ88*0.82 -> 1049.6 | AS88: =+AR88*0.9 -> 944.64 | AT88: =+AS88*0.86 -> 812.3904
A89: 3.2T | AT89: 1450
A91: ASP (Rmb) with no tariff impact | AM91: =+AM52/AM62 -> 493.02051 | AN91: =+AN52/AN62 -> 566.38298 | AO91: =+AO52/AO62 -> 659.71179 | AP91: =+AP52/AP62 -> 1994.0572 | AQ91: =+AQ52/AQ62 -> 2744.1718 | AR91: =+AR52/AR62 -> 3935.7986 | AS91: =+AS52/AS62 -> 4395.5173 | AT91: =+AT52/AT62 -> 4250.5816
A92: 25G or below | B92: 346 | C92: 346 | D92: 346 | E92: 346 | F92: =+$AO92 -> 328.7 | G92: =+$AO92 -> 328.7 | H92: =+$AO92 -> 328.7 | I92: =+$AO92 -> 328.7 | J92: =+$AP92 -> 312.265 | K92: =+$AP92 -> 312.265 | L92: =+$AP92 -> 312.265 | M92: =+$AP92 -> 312.265 | N92: =+$AQ92 -> 296.65175 | O92: =+$AQ92 -> 296.65175 | P92: =+$AQ92 -> 296.65175 | Q92: =+$AQ92 -> 296.65175 | R92: =+$AR92 -> 281.81916 | S92: =+$AR92 -> 281.81916 | T92: =+$AR92 -> 281.81916 | U92: =+$AR92 -> 281.81916 | V92: =+$AS92 -> 267.7282 | W92: =+$AS92 -> 267.7282 | X92: =+$AS92 -> 267.7282 | Y92: =+$AS92 -> 267.7282 | Z92: =+$AT92 -> 254.34179 | AA92: =+$AT92 -> 254.34179 | AB92: =+$AT92 -> 254.34179 | AC92: =+$AT92 -> 254.34179 | AM92: 346.5 | AN92: 346 | AO92: =+AN92*(1+AO102) -> 328.7 | AP92: =+AO92*(1+AP102) -> 312.265 | AQ92: =+AP92*(1+AQ102) -> 296.65175 | AR92: =+AQ92*(1+AR102) -> 281.81916 | AS92: =+AR92*(1+AS102) -> 267.7282 | AT92: =+AS92*(1+AT102) -> 254.34179
A93: 40G | B93: 560 | C93: 560 | D93: 560 | E93: 560 | F93: =+$AO93 -> 532 | G93: =+$AO93 -> 532 | H93: =+$AO93 -> 532 | I93: =+$AO93 -> 532 | J93: =+$AP93 -> 505.4 | K93: =+$AP93 -> 505.4 | L93: =+$AP93 -> 505.4 | M93: =+$AP93 -> 505.4 | N93: =+$AQ93 -> 480.13 | O93: =+$AQ93 -> 480.13 | P93: =+$AQ93 -> 480.13 | Q93: =+$AQ93 -> 480.13 | R93: =+$AR93 -> 456.1235 | S93: =+$AR93 -> 456.1235 | T93: =+$AR93 -> 456.1235 | U93: =+$AR93 -> 456.1235 | V93: =+$AS93 -> 433.31732 | W93: =+$AS93 -> 433.31732 | X93: =+$AS93 -> 433.31732 | Y93: =+$AS93 -> 433.31732 | Z93: =+$AT93 -> 411.65146 | AA93: =+$AT93 -> 411.65146 | AB93: =+$AT93 -> 411.65146 | AC93: =+$AT93 -> 411.65146 | AM93: 567 | AN93: =80*7 -> 560 | AO93: =+AN93*(1+AO103) -> 532 | AP93: =+AO93*(1+AP103) -> 505.4 | AQ93: =+AP93*(1+AQ103) -> 480.13 | AR93: =+AQ93*(1+AR103) -> 456.1235 | AS93: =+AR93*(1+AS103) -> 433.31732 | AT93: =+AS93*(1+AT103) -> 411.65146
A94: 100G | B94: 840 | C94: 840 | D94: 840 | E94: 840 | F94: =+$AO94 -> 490 | G94: =+$AO94 -> 490 | H94: =+$AO94 -> 490 | I94: =+$AO94 -> 490 | J94: =+$AP94 -> 465.5 | K94: =+$AP94 -> 465.5 | L94: =+$AP94 -> 465.5 | M94: =+$AP94 -> 465.5 | N94: =+$AQ94 -> 442.225 | O94: =+$AQ94 -> 442.225 | P94: =+$AQ94 -> 442.225 | Q94: =+$AQ94 -> 442.225 | R94: =+$AR94 -> 420.11375 | S94: =+$AR94 -> 420.11375 | T94: =+$AR94 -> 420.11375 | U94: =+$AR94 -> 420.11375 | V94: =+$AS94 -> 399.10806 | W94: =+$AS94 -> 399.10806 | X94: =+$AS94 -> 399.10806 | Y94: =+$AS94 -> 399.10806 | Z94: =+$AT94 -> 379.15266 | AA94: =+$AT94 -> 379.15266 | AB94: =+$AT94 -> 379.15266 | AC94: =+$AT94 -> 379.15266 | AM94: =+AN94/0.9 -> 933.33333 | AN94: =120*7 -> 840 | AO94: =70*7 -> 490 | AP94: =+AO94*(1+AP104) -> 465.5 | AQ94: =+AP94*(1+AQ104) -> 442.225 | AR94: =+AQ94*(1+AR104) -> 420.11375 | AS94: =+AR94*(1+AS104) -> 399.10806 | AT94: =+AS94*(1+AT104) -> 379.15266
A95: 200G | B95: 1540 | C95: 1540 | D95: 1540 | E95: 1540 | F95: =+$AO95 -> 1314 | G95: =+$AO95 -> 1314 | H95: =+$AO95 -> 1314 | I95: =+$AO95 -> 1314 | J95: =+$AP95 -> 1182.6 | K95: =+$AP95 -> 1182.6 | L95: =+$AP95 -> 1182.6 | M95: =+$AP95 -> 1182.6 | N95: =+$AQ95 -> 1064.34 | O95: =+$AQ95 -> 1064.34 | P95: =+$AQ95 -> 1064.34 | Q95: =+$AQ95 -> 1064.34 | R95: =+$AR95 -> 1011.123 | S95: =+$AR95 -> 1011.123 | T95: =+$AR95 -> 1011.123 | U95: =+$AR95 -> 1011.123 | V95: =+$AS95 -> 960.56685 | W95: =+$AS95 -> 960.56685 | X95: =+$AS95 -> 960.56685 | Y95: =+$AS95 -> 960.56685 | Z95: =+$AT95 -> 912.53851 | AA95: =+$AT95 -> 912.53851 | AB95: =+$AT95 -> 912.53851 | AC95: =+$AT95 -> 912.53851 | AM95: =250*7 -> 1750 | AN95: =220*7 -> 1540 | AO95: 1314 | AP95: 1182.6 | AQ95: 1064.34 | AR95: 1011.123 | AS95: 960.56685 | AT95: =AS95*0.95 -> 912.53851
A96: 400G | B96: 3640 | C96: 3640 | D96: 3640 | E96: 3640 | F96: =+$AO96 -> 2628 | G96: =+$AO96 -> 2628 | H96: =+$AO96 -> 2628 | I96: =+$AO96 -> 2628 | J96: =+I96*0.93 -> 2444.04 | K96: =+$AP96 -> 2233.8 | L96: =+$AP96 -> 2233.8 | M96: =+$AP96 -> 2233.8 | N96: =+M96*0.97 -> 2166.786 | O96: =+$AQ96 -> 1898.73 | P96: =+$AQ96 -> 1898.73 | Q96: =+$AQ96 -> 1898.73 | R96: =+Q96*0.93 -> 1765.8189 | S96: =+$AR96 -> 1708.857 | T96: =+$AR96 -> 1708.857 | U96: =+$AR96 -> 1708.857 | V96: =+U96*0.97 -> 1657.5913 | W96: =+$AS96 -> 1623.4142 | X96: =+$AS96 -> 1623.4142 | Y96: =+$AS96 -> 1623.4142 | Z96: =$AT96 -> 1542.2434 | AA96: =$AT96 -> 1542.2434 | AB96: =$AT96 -> 1542.2434 | AC96: =$AT96 -> 1542.2434 | AM96: =650*7 -> 4550 | AN96: =520*7 -> 3640 | AO96: 2628 | AP96: =+AP86*7.3 -> 2233.8 | AQ96: =+AQ86*7.3 -> 1898.73 | AR96: =+AR86*7.3 -> 1708.857 | AS96: =+AS86*7.3 -> 1623.4142 | AT96: =AS96*0.95 -> 1542.2434
A97: 800G | F97: =+$AO97 -> 5152.9412 | G97: =+$AO97 -> 5152.9412 | H97: =+$AO97 -> 5152.9412 | I97: =+$AO97 -> 5152.9412 | J97: =+$AP97 -> 4380 | K97: =+$AP97 -> 4380 | L97: =+$AP97 -> 4380 | M97: =+$AP97 -> 4380 | N97: =+M97*0.93 -> 4073.4 | O97: =+$AQ97 -> 3723 | P97: =+$AQ97 -> 3723 | Q97: =+$AQ97 -> 3723 | R97: =+Q97*0.93 -> 3462.39 | S97: =+$AR97 -> 3052.86 | T97: =+$AR97 -> 3052.86 | U97: =+$AR97 -> 3052.86 | V97: =+U97*0.93 -> 2839.1598 | W97: =+$AS97 -> 2747.574 | X97: =+$AS97 -> 2747.574 | Y97: =+$AS97 -> 2747.574 | Z97: =$AT97 -> 2335.4379 | AA97: =$AT97 -> 2335.4379 | AB97: =$AT97 -> 2335.4379 | AC97: =$AT97 -> 2335.4379 | AM97: 0 | AN97: 0 | AO97: =+AP97/0.85 -> 5152.9412 | AP97: =+AP87*7.3 -> 4380 | AQ97: =+AQ87*7.3 -> 3723 | AR97: =+AR87*7.3 -> 3052.86 | AS97: =+AS87*7.3 -> 2747.574 | AT97: =+AT87*7.3 -> 2335.4379
A98: 1.6T | F98: =+$AO98 -> 0 | G98: =+$AO98 -> 0 | H98: =+$AO98 -> 0 | I98: =+$AO98 -> 0 | J98: =+$AP98 -> 0 | K98: =+$AP98 -> 0 | L98: =+$AP98 -> 0 | M98: =+$AP98 -> 0 | N98: =+$AQ98 -> 9344 | O98: =+$AQ98 -> 9344 | P98: =+$AQ98 -> 9344 | Q98: =+$AQ98 -> 9344 | R98: =+Q98*0.93 -> 8689.92 | S98: =+$AR98 -> 7662.08 | T98: =+$AR98 -> 7662.08 | U98: =+$AR98 -> 7662.08 | V98: =+U98*0.93 -> 7125.7344 | W98: =+$AS98 -> 6895.872 | X98: =+$AS98 -> 6895.872 | Y98: =+$AS98 -> 6895.872 | Z98: =$AT98 -> 5930.4499 | AA98: =$AT98 -> 5930.4499 | AB98: =$AT98 -> 5930.4499 | AC98: =$AT98 -> 5930.4499 | AM98: 0 | AN98: 0 | AO98: 0 | AP98: =+AP88*7.3 -> 0 | AQ98: =+AQ88*7.3 -> 9344 | AR98: =+AR88*7.3 -> 7662.08 | AS98: =+AS88*7.3 -> 6895.872 | AT98: =+AT88*7.3 -> 5930.4499
A99: 3.2T | AA99: =$AT99 -> 10585 | AB99: =AA99 -> 10585 | AC99: =AB99 -> 10585 | AT99: =+AT89*7.3 -> 10585
A101: ASP change%
A102: 25G or below | C102: =+C92/B92-1 -> 0 | D102: =+D92/C92-1 -> 0 | E102: =+E92/D92-1 -> 0 | F102: =+F92/E92-1 -> -0.05 | G102: =+G92/F92-1 -> 0 | H102: =+H92/G92-1 -> 0 | I102: =+I92/H92-1 -> 0 | J102: =+J92/I92-1 -> -0.05 | ... AC102: =+AC92/AB92-1 -> 0 | AN102: =+AN92/AM92-1 -> -0.0014430014 | AO102: -0.05 | AP102: -0.05 | AQ102: -0.05 | AR102: -0.05 | AS102: -0.05 | AT102: -0.05
A103: 40G | C103: =+C93/B93-1 -> 0 | D103: =+D93/C93-1 -> 0 | E103: =+E93/D93-1 -> 0 | F103: =+F93/E93-1 -> -0.05 | G103: =+G93/F93-1 -> 0 | H103: =+H93/G93-1 -> 0 | I103: =+I93/H93-1 -> 0 | J103: =+J93/I93-1 -> -0.05 | ... AC103: =+AC93/AB93-1 -> 0 | AN103: =+AN93/AM93-1 -> -0.012345679 | AO103: -0.05 | AP103: -0.05 | AQ103: -0.05 | AR103: -0.05 | AS103: -0.05 | AT103: -0.05
A104: 100G | C104: =+C94/B94-1 -> 0 | D104: =+D94/C94-1 -> 0 | E104: =+E94/D94-1 -> 0 | F104: =+F94/E94-1 -> -0.41666667 | G104: =+G94/F94-1 -> 0 | H104: =+H94/G94-1 -> 0 | I104: =+I94/H94-1 -> 0 | J104: =+J94/I94-1 -> -0.05 | ... AC104: =+AC94/AB94-1 -> 0 | AN104: =+AN94/AM94-1 -> -0.1 | AO104: -0.05 | AP104: -0.05 | AQ104: -0.05 | AR104: -0.05 | AS104: -0.05 | AT104: -0.05
A105: 200G | C105: =+C95/B95-1 -> 0 | D105: =+D95/C95-1 -> 0 | E105: =+E95/D95-1 -> 0 | F105: =+F95/E95-1 -> -0.14675325 | G105: =+G95/F95-1 -> 0 | H105: =+H95/G95-1 -> 0 | I105: =+I95/H95-1 -> 0 | J105: =+J95/I95-1 -> -0.1 | ... AC105: =+AC95/AB95-1 -> 0 | AN105: =+AN95/AM95-1 -> -0.12 | AO105: =+AO95/AN95-1 -> -0.14675325 | AP105: =+AP95/AO95-1 -> -0.1 | AQ105: =+AQ95/AP95-1 -> -0.1 | AR105: =+AR95/AQ95-1 -> -0.05 | AS105: =+AS95/AR95-1 -> -0.05 | AT105: =+AT95/AS95-1 -> -0.05
A106: 400G | C106: =+C96/B96-1 -> 0 | D106: =+D96/C96-1 -> 0 | E106: =+E96/D96-1 -> 0 | F106: =+F96/E96-1 -> -0.27802198 | G106: =+G96/F96-1 -> 0 | H106: =+H96/G96-1 -> 0 | I106: =+I96/H96-1 -> 0 | J106: =+J96/I96-1 -> -0.07 | ... AC106: =+AC96/AB96-1 -> 0 | AN106: =+AN96/AM96-1 -> -0.2 | AO106: =+AO96/AN96-1 -> -0.27802198 | AP106: =+AP96/AO96-1 -> -0.15 | AQ106: =+AQ96/AP96-1 -> -0.15 | AR106: =+AR96/AQ96-1 -> -0.1 | AS106: =+AS96/AR96-1 -> -0.05 | AT106: =+AT96/AS96-1 -> -0.05
A107: 800G | G107: =+G97/F97-1 -> 0 | H107: =+H97/G97-1 -> 0 | I107: =+I97/H97-1 -> 0 | J107: =+J97/I97-1 -> -0.15 | K107: =+K97/J97-1 -> 0 | L107: =+L97/K97-1 -> 0 | M107: =+M97/L97-1 -> 0 | N107: =+N97/M97-1 -> -0.07 | ... AC107: =+AC97/AB97-1 -> 0 | AP107: =+AP97/AO97-1 -> -0.15 | AQ107: =+AQ97/AP97-1 -> -0.15 | AR107: =+AR97/AQ97-1 -> -0.18 | AS107: =+AS97/AR97-1 -> -0.1 | AT107: =+AT97/AS97-1 -> -0.15
A108: 1.6T | O108: =+O98/N98-1 -> 0 | P108: =+P98/O98-1 -> 0 | Q108: =+Q98/P98-1 -> 0 | R108: =+R98/Q98-1 -> -0.07 | S108: =+S98/R98-1 -> -0.11827957 | T108: =+T98/S98-1 -> 0 | U108: =+U98/T98-1 -> 0 | V108: =+V98/U98-1 -> -0.07 | ... AC108: =+AC98/AB98-1 -> 0 | AR108: =+AR98/AQ98-1 -> -0.18 | AS108: =+AS98/AR98-1 -> -0.1 | AT108: =+AT98/AS98-1 -> -0.14
A110: Unit costs
A111: 25G or below | B111: 242.2 | C111: =+B111*(1+C121) -> 238.74 | D111: =+C111*(1+D121) -> 235.28 | E111: =+D111*(1+E121) -> 224.9 | F111: =+E111*(1+F121) -> 230.09 | G111: =+F111*(1+G121) -> 295.83 | H111: =+G111*(1+H121) -> 282.682 | I111: =+H111*(1+I121) -> 266.247 | J111: =+I111*(1+J121) -> 249.812 | ... AC111: =+AB111*(1+AC121) -> 216.22117
A112: 40G | B112: 369.6 | C112: =+B112*(1+C122) -> 364 | D112: =+C112*(1+D122) -> 347.2 | E112: =+D112*(1+E122) -> 347.2 | F112: =+E112*(1+F122) -> 345.8 | G112: =+F112*(1+G122) -> 388.36 | H112: =+G112*(1+H122) -> 394.212 | I112: =+H112*(1+I122) -> 393.68 | J112: =+I112*(1+J122) -> 373.996 | ... AC112: =+AB112*(1+AC122) -> 341.87914
...
