Workbook
Name \0: #REF!
Name \0: #REF!
Name \a: #REF!
Name \a: #REF!
Name \b: #REF!
Name \b: #REF!
Name \c: #REF!
Name \c: #N/A
Name \d: #REF!
Name \d: #N/A
Name \e: #REF!
Name \e: #REF!
Name \f: #REF!
Name \f: #REF!
Name \g: #REF!
Name \g: #REF!
Name \h: #REF!
Name \h: #REF!
Name \i: #REF!
Name \i: #N/A
Name \j: #REF!
Name \j: #N/A
Name \k: #REF!
Name \k: #REF!
Name \l: #REF!
Name \l: #REF!
Name \m: #REF!
Name \m: #N/A
Name \P: #REF!
Name \P: #REF!
Name \q: #REF!
Name \q: #REF!
Name \s: #REF!
Name \s: #REF!
Name \u: #REF!
Name \u: #REF!
Name \v: #N/A
Name \x: #REF!
Name \x: #REF!
Name \z: #REF!
Name \z: #N/A
Name ___________DIV01: #REF!
Name ___________DIV01: #REF!
Name ___________DIV86: #REF!
Name ___________DIV86: #REF!
Name ___________DIV87: #REF!
Name ___________DIV87: #REF!
Name ___________DIV88: #REF!
Name ___________DIV88: #REF!
Name ___________DIV89: #REF!
Name ___________DIV89: #REF!
Name ___________DIV90: #REF!
Name ___________DIV90: #REF!
Name ___________DIV91: #REF!
Name ___________DIV91: #REF!
Name ___________DIV92: #REF!
Name ___________DIV92: #REF!
Name ___________DIV93: #REF!
Name ___________DIV93: #REF!
Name ___________DIV94: #REF!

Sheet Cover page
B9: Ronald Keung, CFA
B10: +852 2978 0856
B11: ronald.keung@gs.com
B12: Goldman Sachs (Asia) L.L.C
B14: Key statistics
B15: Rating | E15: Neutral
E16: Zhipu
E17: 2513.HK
B19: Currency | E19: HK$
B20: Target price (HK$) | E20: 1880 | BN20: =#REF!+#REF!-#REF! -> #REF!
B26: Colour coding
B27: Hard-coded | D27: Linked to the file | F27: Assumptions
B30: Source: Company data, Datastream, Goldman Sachs Research estimates.

Sheet Model
A3: December year-end (Rmb mn) | F3: 2022 | G3: 2023 | H3: 2024 | I3: 2025 | J3: =I3+1 -> 2026 | K3: =J3+1 -> 2027 | L3: =K3+1 -> 2028 | M3: =L3+1 -> 2029 | N3: =M3+1 -> 2030 | O3: =N3+1 -> 2031 | P3: =O3+1 -> 2032 | Q3: =P3+1 -> 2033 | ... S3: =R3+1 -> 2035 | U3: 1H24 | V3: 2H24 | W3: 1H25 | X3: 2H25 | Y3: 1H26E | Z3: 2H26E
B4: Revenue | F4: =Revenue!F5 -> 57.409 | G4: =Revenue!G5 -> 124.538 | H4: =Revenue!H5 -> 312.414 | I4: =Revenue!I5 -> 724.334 | J4: =Revenue!J5 -> 6339.2276 | K4: =Revenue!K5 -> 23724.729 | L4: =Revenue!L5 -> 58809.369 | M4: =Revenue!M5 -> 120603.6 | ... S4: =Revenue!S5 -> 1282827.2 | U4: =Revenue!U5 -> 44.909 | V4: =Revenue!V5 -> 267.505 | W4: =Revenue!W5 -> 190.877 | X4: =Revenue!X5 -> 533.457 | Y4: =Revenue!Y5 -> 1115.7648 | Z4: =Revenue!Z5 -> 5223.4628
C5: yoy % | H5: =H4/G4-1 -> 1.5085837 | I5: =I4/H4-1 -> 1.3185069 | J5: =J4/I4-1 -> 7.7518018 | K5: =K4/J4-1 -> 2.7425269 | L5: =L4/K4-1 -> 1.4788215 | M5: =M4/L4-1 -> 1.0507549 | N5: =N4/M4-1 -> 0.82080436 | O5: =O4/N4-1 -> 0.64620893 | ... S5: =S4/R4-1 -> 0.26126355 | W5: =W4/U4-1 -> 3.2503062 | X5: =X4/V4-1 -> 0.9941945 | Y5: =Y4/W4-1 -> 4.8454649 | Z5: =Z4/X4-1 -> 8.7917223
B7: Cost of sales | F7: =Revenue!F118 -> -26.049 | G7: =Revenue!G118 -> -44.056 | H7: =Revenue!H118 -> -136.525 | I7: =Revenue!I118 -> -427.678 | J7: =Revenue!J118 -> -4527.7268 | K7: =Revenue!K118 -> -17264.397 | L7: =Revenue!L118 -> -42438.455 | M7: =Revenue!M118 -> -85122.007 | ... S7: =Revenue!S118 -> -811651.86 | U7: =Revenue!U118 -> -22.95 | V7: =Revenue!V118 -> -113.575 | W7: =Revenue!W118 -> -95.453 | X7: =Revenue!X118 -> -332.225 | Y7: =Revenue!Y118 -> -735.38446 | Z7: =Revenue!Z118 -> -3792.3423
B9: Gross (loss)/profit | F9: =F4+F7 -> 31.36 | G9: =G4+G7 -> 80.482 | H9: =H4+H7 -> 175.889 | I9: =I4+I7 -> 296.656 | J9: =J4+J7 -> 1811.5008 | K9: =K4+K7 -> 6460.3325 | L9: =L4+L7 -> 16370.914 | M9: =M4+M7 -> 35481.597 | ... S9: =S4+S7 -> 471175.34 | U9: =U4+U7 -> 21.959 | V9: =V4+V7 -> 153.93 | W9: =W4+W7 -> 95.424 | X9: =X4+X7 -> 201.232 | Y9: =Y4+Y7 -> 380.38034 | Z9: =Z4+Z7 -> 1431.1205
C10: yoy % | G10: =G9/F9-1 -> 1.5663903 | H10: =H9/G9-1 -> 1.1854452 | I10: =I9/H9-1 -> 0.68660917 | J10: =J9/I9-1 -> 5.1064021 | K10: =K9/J9-1 -> 2.5662874 | L10: =L9/K9-1 -> 1.5340668 | M10: =M9/L9-1 -> 1.1673559 | N10: =N9/M9-1 -> 0.9293395 | ... S10: =S9/R9-1 -> 0.29461363 | W10: =W9/U9-1 -> 3.3455531 | X10: =X9/V9-1 -> 0.30729552 | Y10: =Y9/W9-1 -> 2.9862125 | Z10: =Z9/X9-1 -> 6.1117937
C11: margin % | G11: =G9/G4 -> 0.64624452 | H11: =H9/H4 -> 0.56299974 | I11: =I9/I4 -> 0.40955692 | J11: =J9/J4 -> 0.2857605 | K11: =K9/K4 -> 0.27230374 | L11: =L9/L4 -> 0.27837255 | M11: =M9/M4 -> 0.29420014 | N11: =N9/N4 -> 0.31173693 | ... S11: =S9/S4 -> 0.36729448 | U11: =U9/U4 -> 0.48896658 | V11: =V9/V4 -> 0.5754285 | W11: =W9/W4 -> 0.49992403 | X11: =X9/X4 -> 0.37722253 | Y11: =Y9/Y4 -> 0.34091445 | Z11: =Z9/Z4 -> 0.27397926
B13: Other income | F13: 1.784 | G13: 9.965 | H13: 19.281 | I13: 14.839 | J13: =J66 -> 33.14836 | K13: =K66 -> 432.84256 | L13: =L66 -> 199.21519 | M13: =M66 -> 414.59592 | N13: =N66 -> 560.09699 | O13: =O66 -> 913.91537 | P13: =P66 -> 1673.757 | Q13: =Q66 -> 2943.3992 | ... S13: =S66 -> 7823.4091 | U13: 4.174 | V13: =H13-U13 -> 15.107 | W13: 4.614 | X13: =I13-W13 -> 10.225 | Y13: =Y69 -> 16.736472 | Z13: =Z69 -> 16.411888
B14: Selling and distribution expenses | F14: -15.139 | G14: -101.198 | H14: -387.475 | I14: -390.869 | J14: =-J82 -> -508.1297 | K14: =-K82 -> -736.78807 | L14: =-L82 -> -1105.1821 | M14: =-M82 -> -1602.514 | N14: =-N82 -> -2251.5322 | O14: =-O82 -> -3072.2157 | P14: =-P82 -> -4080.0561 | Q14: =-Q82 -> -5284.6723 | ... S14: =-S82 -> -8288.5624 | U14: -144.194 | V14: =H14-U14 -> -243.281 | W14: -208.57 | X14: =I14-W14 -> -182.299 | Y14: =-Y82 -> -245.46826 | Z14: =-Z82 -> -262.66144
B15: Administrative expenses | F15: -32.316 | G15: -66.302 | H15: -133.603 | I15: -505.357 | J15: =-J92 -> -656.9641 | K15: =-K92 -> -952.59794 | L15: =-L92 -> -1428.8969 | M15: =-M92 -> -2071.9005 | N15: =-N92 -> -2911.0202 | O15: =-O92 -> -3972.0871 | P15: =-P92 -> -5275.1303 | Q15: =-Q92 -> -6832.5862 | ... S15: =-S92 -> -10716.335 | U15: -51.452 | V15: =H15-U15 -> -82.151 | W15: -185.165 | X15: =I15-W15 -> -320.192 | Y15: =-Y92 -> -334.72944 | Z15: =-Z92 -> -322.23466
B16: Research and development expenses | F16: -84.377 | G16: -528.884 | H16: -2195.436 | I16: -3180.443 | J16: =-J102 -> -5724.7974 | K16: =-K102 -> -10877.115 | L16: =-L102 -> -16304.795 | M16: =-M102 -> -26087.673 | N16: =-N102 -> -40435.893 | O16: =-O102 -> -56003.711 | P16: =-P102 -> -71096.712 | Q16: =-Q102 -> -84509.106 | ... S16: =-S102 -> -104512.45 | U16: -859.217 | V16: =H16-U16 -> -1336.219 | W16: -1594.661 | X16: =I16-W16 -> -1585.782 | Y16: =-Y102 -> -2789.412 | Z16: =-Z102 -> -2935.3854
B17: Impairment losses on financial assets | F17: -0.031 | G17: -19.786 | H17: -17.008 | I17: -21.576 | J17: 0 | K17: 0 | L17: 0 | M17: 0 | N17: 0 | O17: 0 | P17: 0 | Q17: 0 | R17: 0 | S17: 0 | U17: -0.763 | V17: =H17-U17 -> -16.245 | W17: -10.867 | X17: =I17-W17 -> -10.709 | Y17: 0 | Z17: 0
B19: Operating profit | F19: =F9+SUM(F13:F17) -> -98.719 | G19: =G9+SUM(G13:G17) -> -625.723 | H19: =H9+SUM(H13:H17) -> -2538.352 | I19: =I9+SUM(I13:I17) -> -3786.75 | J19: =J9+SUM(J13:J17) -> -5045.242 | K19: =K9+SUM(K13:K17) -> -5673.326 | L19: =L9+SUM(L13:L17) -> -2268.745 | M19: =M9+SUM(M13:M17) -> 6134.1057 | ... S19: =S9+SUM(S13:S17) -> 355481.4 | U19: =U9+SUM(U13:U17) -> -1029.493 | V19: =V9+SUM(V13:V17) -> -1508.859 | W19: =W9+SUM(W13:W17) -> -1899.225 | X19: =X9+SUM(X13:X17) -> -1887.525 | Y19: =Y9+SUM(Y13:Y17) -> -2972.4929 | Z19: =Z9+SUM(Z13:Z17) -> -2072.7491
C20: margin % | G20: =G19/G$4 -> -5.024354 | H20: =H19/H$4 -> -8.1249624 | I20: =I19/I$4 -> -5.2279059 | J20: =J19/J$4 -> -0.79587646 | K20: =K19/K$4 -> -0.23913132 | L20: =L19/L$4 -> -0.038577951 | M20: =M19/M$4 -> 0.050861712 | N20: =N19/N$4 -> 0.10664012 | ... S20: =S19/S$4 -> 0.27710779 | U20: =U19/U$4 -> -22.92398 | V20: =V19/V$4 -> -5.640489 | W20: =W19/W$4 -> -9.949994 | X20: =X19/X$4 -> -3.5382889 | Y20: =Y19/Y$4 -> -2.6640855 | Z20: =Z19/Z$4 -> -0.39681515
C21: yoy % | G21: =-(G19/F19-1) -> -5.3384252 | H21: =-(H19/G19-1) -> -3.0566704 | I21: =I19/H19-1 -> 0.49181437 | J21: =J19/I19-1 -> 0.33234093 | K21: =K19/J19-1 -> 0.12449035 | L21: =L19/K19-1 -> -0.60010319 | M21: =M19/L19-1 -> -3.7037441 | N21: =N19/M19-1 -> 2.8176223 | O21: =O19/N19-1 -> 1.4443622 | P21: =P19/O19-1 -> 0.86030547 | ... S21: =S19/R19-1 -> 0.37835329 | W21: =-(W19/U19-1) -> -0.84481585 | X21: =-(X19/V19-1) -> -0.25096182 | Y21: =-(Y19/W19-1) -> -0.56510834 | Z21: =-(Z19/X19-1) -> -0.098130696
B23: Adj. operating profit - non-IFRS | F23: =F19+SUM(F46) -> -97.695 | G23: =G19+SUM(G46) -> -620.221 | H23: =H19+SUM(H46) -> -2514.773 | I23: =I19+SUM(I46) -> -3228.485 | J23: =J19+SUM(J46) -> -4375.324 | K23: =K19+SUM(K46) -> -4869.4244 | L23: =L19+SUM(L46) -> -1304.063 | M23: =M19+SUM(M46) -> 7195.2558 | ... S23: =S19+SUM(S46) -> 357361.3 | U23: =U19+SUM(U46) -> -1025.276 | V23: =V19+SUM(V46) -> -1489.497 | W23: =W19+SUM(W46) -> -1740.373 | X23: =X19+SUM(X46) -> -1488.112 | Y23: =Y19+SUM(Y46) -> -2637.5339 | Z23: =Z19+SUM(Z46) -> -1737.7901
C24: margin % | G24: =G23/G$4 -> -4.9801747 | H24: =H23/H$4 -> -8.0494888 | I24: =I23/I$4 -> -4.4571772 | J24: =J23/J$4 -> -0.69019829 | K24: =K23/K$4 -> -0.20524678 | L24: =L23/L$4 -> -0.022174409 | M24: =M23/M$4 -> 0.059660372 | N24: =N23/N$4 -> 0.11195565 | ... S24: =S23/S$4 -> 0.27857321 | U24: =U23/U$4 -> -22.830079 | V24: =V23/V$4 -> -5.568109 | W24: =W23/W$4 -> -9.1177722 | X24: =X23/X$4 -> -2.7895632 | Y24: =Y23/Y$4 -> -2.3638798 | Z24: =Z23/Z$4 -> -0.33268929
C25: yoy % | G25: =G23/F23-1 -> 5.3485439 | H25: =H23/G23-1 -> 3.0546402 | I25: =I23/H23-1 -> 0.28380772 | J25: =J23/I23-1 -> 0.35522514 | K25: =K23/J23-1 -> 0.11292886 | L25: =L23/K23-1 -> -0.73219359 | M25: =M23/L23-1 -> -6.5175675 | N25: =N23/M23-1 -> 2.4168297 | ... S25: =S23/R23-1 -> 0.37652092 | W25: =W23/U23-1 -> 0.6974678 | X25: =X23/V23-1 -> -0.0009298441 | Y25: =Y23/W23-1 -> 0.51549919 | Z25: =Z23/X23-1 -> 0.16778182
B27: Finance costs | F27: -5.694 | G27: -26.332 | H27: -38.321 | I27: -74.315 | J27: =-J111 -> -35.705665 | K27: =-K111 -> -35.705665 | L27: =-L111 -> -35.705665 | M27: =-M111 -> -35.705665 | N27: =-N111 -> -35.705665 | O27: =-O111 -> -35.705665 | P27: =-P111 -> -35.705665 | Q27: =-Q111 -> -35.705665 | ... S27: =-S111 -> -35.705665 | U27: -12.212 | V27: =H27-U27 -> -26.109 | W27: -53.27 | X27: =I27-W27 -> -21.045 | Y27: =-Y111 -> -17.852833 | Z27: =-Z111 -> -17.852833
B28: Share of profits less losses of associates | F28: 0 | G28: -0.453 | H28: 21.254 | I28: 54.982 | J28: 0 | K28: 0 | L28: 0 | M28: 0 | N28: 0 | O28: 0 | P28: 0 | Q28: 0 | R28: 0 | S28: 0 | U28: 0.324 | V28: =H28-U28 -> 20.93 | W28: 14.147 | X28: =I28-W28 -> 40.835 | Y28: 0 | Z28: 0
B29: Changes in fair value of financial instruments | F29: 5.972 | G29: 26.002 | H29: 66.271 | I29: 25.278 | J29: 0 | K29: =J29 -> 0 | L29: =K29 -> 0 | M29: =L29 -> 0 | N29: =M29 -> 0 | O29: =N29 -> 0 | P29: =O29 -> 0 | Q29: =P29 -> 0 | R29: =Q29 -> 0 | S29: =R29 -> 0 | U29: 7.004 | V29: =H29-U29 -> 59.267 | W29: 9.791 | X29: =I29-W29 -> 15.487 | Y29: 0 | Z29: 0
B30: Changes in the carrying amounts of financial instruments | F30: -45.209 | G30: -161.471 | H30: -468.859 | I30: -937.362 | J30: 0 | K30: 0 | L30: 0 | M30: 0 | N30: 0 | O30: 0 | P30: 0 | Q30: 0 | R30: 0 | S30: 0 | U30: -201.174 | V30: =H30-U30 -> -267.685 | W30: -429.295 | X30: =I30-W30 -> -508.067 | Y30: 0 | Z30: 0
B32: (Loss)/Profit before tax | F32: =SUM(F19,F27:F30) -> -143.65 | G32: =SUM(G19,G27:G30) -> -787.977 | H32: =SUM(H19,H27:H30) -> -2958.007 | I32: =SUM(I19,I27:I30) -> -4718.167 | J32: =SUM(J19,J27:J30) -> -5080.9477 | K32: =SUM(K19,K27:K30) -> -5709.0316 | L32: =SUM(L19,L27:L30) -> -2304.4506 | M32: =SUM(M19,M27:M30) -> 6098.4001 | ... S32: =SUM(S19,S27:S30) -> 355445.7 | U32: =SUM(U19,U27:U30) -> -1235.551 | V32: =SUM(V19,V27:V30) -> -1722.456 | W32: =SUM(W19,W27:W30) -> -2357.852 | X32: =SUM(X19,X27:X30) -> -2360.315 | Y32: =SUM(Y19,Y27:Y30) -> -2990.3457 | Z32: =SUM(Z19,Z27:Z30) -> -2090.602
B33: Income tax expense | F33: 0 | G33: 0 | H33: 0 | I33: 0 | J33: =-J115 -> 0 | K33: =-K115 -> 0 | L33: =-L115 -> 0 | M33: =-M115 -> -1097.712 | N33: =-N115 -> -4208.7587 | O33: =-O115 -> -10297.014 | P33: =-P115 -> -19161.12 | Q33: =-Q115 -> -31293.511 | ... S33: =-S115 -> -63980.226 | U33: 0 | V33: =H33-U33 -> 0 | W33: 0 | X33: 0 | Y33: 0 | Z33: 0
B35: Net profit/(loss) | F35: =F32+F33 -> -143.65 | G35: =G32+G33 -> -787.977 | H35: =H32+H33 -> -2958.007 | I35: =I32+I33 -> -4718.167 | J35: =J32+J33 -> -5080.9477 | K35: =K32+K33 -> -5709.0316 | L35: =L32+L33 -> -2304.4506 | M35: =M32+M33 -> 5000.6881 | ... S35: =S32+S33 -> 291465.47 | U35: =U32+U33 -> -1235.551 | V35: =V32+V33 -> -1722.456 | W35: =W32+W33 -> -2357.852 | X35: =X32+X33 -> -2360.315 | Y35: =Y32+Y33 -> -2990.3457 | Z35: =Z32+Z33 -> -2090.602
C36: Attributable to equity holders of the company | F36: -143.374 | G36: -787.96 | H36: -2956.491 | I36: -4698.203 | J36: =J35*J39 -> -5059.4487 | K36: =K35*K39 -> -5684.875 | L36: =L35*L39 -> -2294.6998 | M36: =M35*M39 -> 4979.5286 | N36: =N35*N39 -> 19092.106 | O36: =O35*O39 -> 46710.134 | P36: =P35*P39 -> 86920.199 | Q36: =Q35*Q39 -> 141956.12 | ... S36: =S35*S39 -> 290232.19 | U36: -1235.551 | V36: =H36-U36 -> -1720.94 | W36: -2351.173 | X36: =I36-W36 -> -2347.03 | Y36: =Y35*Y39 -> -2977.6927 | Z36: =J36-Y36 -> -2081.756
C37: Attributable to non-controlling interests | F37: =F35-F36 -> -0.276 | G37: =G35-G36 -> -0.017 | H37: =H35-H36 -> -1.516 | I37: =I35-I36 -> -19.964 | J37: =J35-J36 -> -21.499035 | K37: =K35-K36 -> -24.15665 | L37: =L35-L36 -> -9.7508317 | M37: =M35-M36 -> 21.159433 | ... S37: =S35-S36 -> 1233.2791 | U37: =U35-U36 -> 0 | V37: =H37-U37 -> -1.516 | W37: =W35-W36 -> -6.679 | X37: =I37-W37 -> -13.285 | Y37: =Y35-Y36 -> -12.653062 | Z37: =Z35-Z36 -> -8.845973
B39: Net profit attributable to equity holders of the company % | F39: =F36/F35 -> 0.99807866 | G39: =G36/G35 -> 0.99997843 | H39: =H36/H35 -> 0.99948749 | I39: =I36/I35 -> 0.9957687 | J39: =I39 -> 0.9957687 | K39: =J39 -> 0.9957687 | L39: =K39 -> 0.9957687 | M39: =L39 -> 0.9957687 | N39: =M39 -> 0.9957687 | O39: =N39 -> 0.9957687 | P39: =O39 -> 0.9957687 | Q39: =P39 -> 0.9957687 | ... S39: =R39 -> 0.9957687 | Y39: =J39 -> 0.9957687 | Z39: =Z36/Z35 -> 0.9957687
B40: Net profit attributable to non-controlling interests % | F40: =F37/F35 -> 0.0019213366 | G40: =G37/G35 -> 2.1574234e-05 | H40: =H37/H35 -> 0.00051250724 | I40: =I37/I35 -> 0.0042313042 | J40: =I40 -> 0.0042313042 | K40: =J40 -> 0.0042313042 | L40: =K40 -> 0.0042313042 | M40: =L40 -> 0.0042313042 | N40: =M40 -> 0.0042313042 | O40: =N40 -> 0.0042313042 | P40: =O40 -> 0.0042313042 | Q40: =P40 -> 0.0042313042 | ... S40: =R40 -> 0.0042313042 | Y40: =J40 -> 0.0042313042 | Z40: =Z37/Z35 -> 0.0042313042
B42: Allocation of loss attributable to financial instruments | F42: 39.483 | G42: 343.06 | H42: 1562.449 | I42: 2779.727 | J42: 1000 | K42: 1000 | L42: 1000 | M42: 1000 | N42: 1000 | O42: 1000 | P42: 1000 | Q42: 1000 | R42: 1000 | S42: 1000 | U42: 647.975 | V42: =H42-U42 -> 914.474 | W42: 1357.897 | X42: =I42-W42 -> 1421.83 | Y42: 500 | Z42: =J42-Y42 -> 500
B43: Net profit attributable to ordinary equity shareholders | F43: =F36+F42 -> -103.891 | G43: =G36+G42 -> -444.9 | H43: =H36+H42 -> -1394.042 | I43: =I36+I42 -> -1918.476 | J43: =J36+J42 -> -4059.4487 | K43: =K36+K42 -> -4684.875 | L43: =L36+L42 -> -1294.6998 | M43: =M36+M42 -> 5979.5286 | ... S43: =S36+S42 -> 291232.19 | U43: =U36+U42 -> -587.576 | V43: =V36+V42 -> -806.466 | W43: =W36+W42 -> -993.276 | X43: =X36+X42 -> -925.2 | Y43: =Y36+Y42 -> -2477.6927 | Z43: =Z36+Z42 -> -1581.756
B45: Non-IFRS adjustments
C46: Add: share-based compensation expeneses | F46: 1.024 | G46: 5.502 | H46: 23.579 | I46: 558.265 | J46: =J118 -> 669.918 | K46: =K118 -> 803.9016 | L46: =L118 -> 964.68192 | M46: =M118 -> 1061.1501 | N46: =N118 -> 1167.2651 | O46: =O118 -> 1283.9916 | P46: =P118 -> 1412.3908 | Q46: =Q118 -> 1553.6299 | ... S46: =S118 -> 1879.8922 | U46: 4.217 | V46: =H46-U46 -> 19.362 | W46: 158.852 | X46: =I46-W46 -> 399.413 | Y46: =J46/2 -> 334.959 | Z46: =J46-Y46 -> 334.959
C47: Add: changes in the carrying amounts of financial instruments | F47: =-F30 -> 45.209 | G47: =-G30 -> 161.471 | H47: =-H30 -> 468.859 | I47: =-I30 -> 937.362 | J47: =-J30 -> 0 | K47: =-K30 -> 0 | L47: =-L30 -> 0 | M47: =-M30 -> 0 | ... S47: =-S30 -> 0 | U47: =-U30 -> 201.174 | V47: =H47-U47 -> 267.685 | W47: =-W30 -> 429.295 | X47: =I47-W47 -> 508.067 | Y47: 0 | Z47: 0
C48: Others | I48: 40.568 | J48: 0 | K48: 0 | L48: 0 | M48: 0 | N48: 0 | O48: 0 | P48: 0 | Q48: 0 | R48: 0 | S48: 0 | W48: 17.731 | X48: =I48-W48 -> 22.837 | Y48: 0 | Z48: 0
B50: Adj. net profit/(loss) - non-IFRS | F50: =F35+SUM(F46:F48) -> -97.417 | G50: =G35+SUM(G46:G48) -> -621.004 | H50: =H35+SUM(H46:H48) -> -2465.569 | I50: =I35+SUM(I46:I48) -> -3181.972 | J50: =J35+SUM(J46:J48) -> -4411.0297 | K50: =K35+SUM(K46:K48) -> -4905.13 | L50: =L35+SUM(L46:L48) -> -1339.7687 | M50: =M35+SUM(M46:M47) -> 6061.8382 | N50: =N35+SUM(N46:N47) -> 20340.499 | O50: =O35+SUM(O46:O47) -> 48192.61 | P50: =P35+SUM(P46:P47) -> 88701.939 | Q50: =Q35+SUM(Q46:Q47) -> 144112.96 | R50: =R35+SUM(R46:R47) -> 213160.15 | S50: =S35+SUM(S46:S47) -> 293345.36 | U50: =U35+SUM(U46:U48) -> -1030.16 | V50: =V35+SUM(V46:V48) -> -1435.409 | W50: =W35+SUM(W46:W48) -> -1751.974 | X50: =X35+SUM(X46:X48) -> -1429.998 | Y50: =Y35+SUM(Y46:Y48) -> -2655.3867 | Z50: =Z35+SUM(Z46:Z48) -> -1755.643
C51: margin % | G51: =G50/G$4 -> -4.986462 | H51: =H50/H$4 -> -7.8919927 | I51: =I50/I$4 -> -4.3929624 | J51: =J50/J$4 -> -0.69583078 | K51: =K50/K$4 -> -0.20675178 | L51: =L50/L$4 -> -0.022781552 | M51: =M50/M$4 -> 0.050262496 | N51: =N50/N$4 -> 0.092627095 | ... S51: =S50/S$4 -> 0.22867099 | U51: =U50/U$4 -> -22.938832 | V51: =V50/V$4 -> -5.3659147 | W51: =W50/W$4 -> -9.1785495 | X51: =X50/X$4 -> -2.6806247 | Y51: =Y50/Y$4 -> -2.3798803 | Z51: =Z50/Z$4 -> -0.33610711
C52: yoy % | G52: =-(G50/F50-1) -> -5.3746985 | H52: =-(H50/G50-1) -> -2.9702949 | I52: =I50/H50-1 -> 0.29056295 | J52: =J50/I50-1 -> 0.3862566 | K52: =K50/J50-1 -> 0.11201474 | L52: =L50/K50-1 -> -0.72686377 | M52: =M50/L50-1 -> -5.5245408 | N52: =N50/M50-1 -> 2.3555002 | O52: =O50/N50-1 -> 1.3692934 | P52: =P50/O50-1 -> 0.84057138 | ... S52: =S50/R50-1 -> 0.37617358 | W52: =-(W50/U50-1) -> -0.70068145 | X52: =-(X50/V50-1) -> 0.0037696573 | Y52: =-(Y50/W50-1) -> -0.51565418 | Z52: =-(Z50/X50-1) -> -0.22772408
B54: Weighted average number of ordinary shares (mn) | F54: =13.320289*10 -> 133.20289 | G54: =15.100831*10 -> 151.00831 | H54: 159.87523 | I54: 159.52222 | J54: =AVERAGE(Y54:Z54) -> 455.73309 | K54: =Z54*1.01 -> 470.27932 | L54: =K54*1.01 -> 474.98211 | M54: =L54*1.01 -> 479.73194 | N54: =M54*1.01 -> 484.52925 | O54: =N54*1.01 -> 489.37455 | P54: =O54*1.01 -> 494.26829 | Q54: =P54*1.01 -> 499.21098 | R54: =Q54*1.01 -> 504.20309 | S54: =R54*1.01 -> 509.24512 | U54: =H54 -> 159.87523 | V54: =I54 -> 159.52222 | W54: =I54 -> 159.52222 | X54: =W54 -> 159.52222 | Y54: 445.84309 | Z54: 465.62309
B55: Diluted average number of ordinary shares (mn) | F55: =F54 -> 133.20289 | G55: =G54 -> 151.00831 | H55: =H54 -> 159.87523 | I55: =I54 -> 159.52222 | J55: =J54 -> 455.73309 | K55: =K54 -> 470.27932 | L55: =L54 -> 474.98211 | M55: =M54 -> 479.73194 | ... S55: =S54 -> 509.24512 | U55: =U54 -> 159.87523 | V55: =V54 -> 159.52222 | W55: =W54 -> 159.52222 | X55: =X54 -> 159.52222 | Y55: 445.84309 | Z55: 465.62309
C56: yoy % | G56: =G55/F55-1 -> 0.13367142 | H56: =H55/G55-1 -> 0.058718093 | I56: =I55/H55-1 -> -0.0022080344 | J56: =J55/I55-1 -> 1.8568628 | K56: =K55/J55-1 -> 0.031918312 | L56: =L55/K55-1 -> 0.01 | M56: =M55/L55-1 -> 0.01 | N56: =N55/M55-1 -> 0.01 | ... S56: =S55/R55-1 -> 0.01
B58: EPS (Rmb) - basic | F58: =F$43/F54 -> -0.77994554 | G58: =G$43/G54 -> -2.9461955 | H58: =H$43/H54 -> -8.7195621 | I58: =I$43/I54 -> -12.026387 | J58: =J$43/J54 -> -8.9075135 | K58: =K$43/K54 -> -9.9618988 | L58: =L$43/L54 -> -2.7257864 | M58: =M$43/M54 -> 12.464312 | ... S58: =S$43/S54 -> 571.89001 | U58: =U$43/U54 -> -3.675216 | V58: =V$43/V54 -> -5.0555089 | W58: =W$43/W54 -> -6.2265683 | X58: =X$43/X54 -> -5.799819 | Y58: =Y$43/Y54 -> -5.5573198 | Z58: =Z$43/Z54 -> -3.3970738
B59: EPS (Rmb) - diluted | F59: =F$43/F55 -> -0.77994554 | G59: =G$43/G55 -> -2.9461955 | H59: =H$43/H55 -> -8.7195621 | I59: =I$43/I55 -> -12.026387 | J59: =J$43/J55 -> -8.9075135 | K59: =K$43/K55 -> -9.9618988 | L59: =L$43/L55 -> -2.7257864 | M59: =M$43/M55 -> 12.464312 | ... S59: =S$43/S55 -> 571.89001 | U59: =U$43/U55 -> -3.675216 | V59: =V$43/V55 -> -5.0555089 | W59: =W$43/W55 -> -6.2265683 | X59: =X$43/X55 -> -5.799819 | Y59: =Y$43/Y55 -> -5.5573198 | Z59: =Z$43/Z55 -> -3.3970738
B60: Adj. EPS (Rmb) - basic | F60: =F$50/F54 -> -0.73134299 | G60: =G$50/G54 -> -4.112383 | H60: =H$50/H54 -> -15.421832 | I60: =I$50/I54 -> -19.946889 | J60: =J$50/J54 -> -9.6789761 | K60: =K$50/K54 -> -10.430248 | L60: =L$50/L54 -> -2.8206719 | M60: =M$50/M54 -> 12.635886 | ... S60: =S$50/S54 -> 576.03962 | U60: =U$50/U54 -> -6.4435247 | V60: =V$50/V54 -> -8.9981759 | W60: =W$50/W54 -> -10.982633 | X60: =X$50/X54 -> -8.9642559 | Y60: =Y$50/Y54 -> -5.9558772 | Z60: =Z$50/Z54 -> -3.7705239
B61: Adj. EPS (Rmb) - diluted | F61: =F$50/F55 -> -0.73134299 | G61: =G$50/G55 -> -4.112383 | H61: =H$50/H55 -> -15.421832 | I61: =I$50/I55 -> -19.946889 | J61: =J$50/J55 -> -9.6789761 | K61: =K$50/K55 -> -10.430248 | L61: =L$50/L55 -> -2.8206719 | M61: =M$50/M55 -> 12.635886 | ... S61: =S$50/S55 -> 576.03962 | U61: =U$50/U55 -> -6.4435247 | V61: =V$50/V55 -> -8.9981759 | W61: =W$50/W55 -> -10.982633 | X61: =X$50/X55 -> -8.9642559 | Y61: =Y$50/Y55 -> -5.9558772 | Z61: =Z$50/Z55 -> -3.7705239
A63: Key P&L assumptions
B65: Other income
C66: Interest income | F66: 1.426 | G66: 11.236 | H66: 13.406 | I66: 14.83 | J66: =J72*J73 -> 33.14836 | K66: =K72*K73 -> 432.84256 | L66: =L72*L73 -> 199.21519 | M66: =M72*M73 -> 414.59592 | N66: =N72*N73 -> 560.09699 | O66: =O72*O73 -> 913.91537 | P66: =P72*P73 -> 1673.757 | Q66: =Q72*Q73 -> 2943.3992 | ... S66: =S72*S73 -> 7823.4091 | U66: 4.163 | V66: =H66-U66 -> 9.243 | W66: 4.607 | X66: =I66-W66 -> 10.223
C67: Net (loss)/gain on disposal of PP&E and intangible assets | F67: 0 | G67: -1.539 | H67: 6.807 | I67: -0.265 | J67: 0 | K67: 0 | L67: 0 | M67: 0 | N67: 0 | O67: 0 | P67: 0 | Q67: 0 | R67: 0 | S67: 0 | U67: 0 | V67: =H67-U67 -> 6.807 | W67: -0.015 | X67: =I67-W67 -> -0.25
C68: Others | F68: 0.358 | G68: 0.268 | H68: -0.932 | I68: 0.274 | J68: 0 | K68: 0 | L68: 0 | M68: 0 | N68: 0 | O68: 0 | P68: 0 | Q68: 0 | R68: 0 | S68: 0 | U68: 0.011 | V68: =H68-U68 -> -0.943 | W68: 0.022 | X68: =I68-W68 -> 0.252
B69: Total | F69: =F13 -> 1.784 | G69: =G13 -> 9.965 | H69: =H13 -> 19.281 | I69: =I13 -> 14.839 | J69: =SUM(J66:J68) -> 33.14836 | K69: =SUM(K66:K68) -> 432.84256 | L69: =SUM(L66:L68) -> 199.21519 | M69: =SUM(M66:M68) -> 414.59592 | N69: =SUM(N66:N68) -> 560.09699 | O69: =SUM(O66:O68) -> 913.91537 | P69: =SUM(P66:P68) -> 1673.757 | Q69: =SUM(Q66:Q68) -> 2943.3992 | ... S69: =SUM(S66:S68) -> 7823.4091 | U69: =U13 -> 4.174 | V69: =V13 -> 15.107 | W69: =W13 -> 4.614 | X69: =X13 -> 10.225 | Y69: =Y4*Y70 -> 16.736472 | Z69: =J69-Y69 -> 16.411888
C70: As % of revenue | F70: =IFERROR(F69/F$4,"NM") -> 0.031075267 | G70: =IFERROR(G69/G$4,"NM") -> 0.080015738 | H70: =IFERROR(H69/H$4,"NM") -> 0.061716184 | I70: =IFERROR(I69/I$4,"NM") -> 0.020486405 | J70: =IFERROR(J69/J$4,"NM") -> 0.005229085 | K70: =IFERROR(K69/K$4,"NM") -> 0.018244362 | L70: =IFERROR(L69/L$4,"NM") -> 0.0033874737 | M70: =IFERROR(M69/M$4,"NM") -> 0.0034376744 | ... S70: =IFERROR(S69/S$4,"NM") -> 0.0060985682 | U70: =IFERROR(U69/U$4,"NM") -> 0.092943508 | V70: =IFERROR(V69/V$4,"NM") -> 0.056473711 | W70: =IFERROR(W69/W$4,"NM") -> 0.024172635 | X70: =IFERROR(X69/X$4,"NM") -> 0.019167431 | Y70: 0.015 | Z70: =IFERROR(Z69/Z$4,"NM") -> 0.0031419556
C71: % yoy change | G71: =G69/F69-1 -> 4.5857623 | H71: =H69/G69-1 -> 0.93487205 | I71: =I69/H69-1 -> -0.23038224 | J71: =J69/I69-1 -> 1.2338675 | K71: =K69/J69-1 -> 12.057737 | L71: =L69/K69-1 -> -0.53975138 | M71: =M69/L69-1 -> 1.0811461 | N71: =N69/M69-1 -> 0.3509467 | ... S71: =S69/R69-1 -> 0.57779766 | W71: =W69/U69-1 -> 0.10541447 | X71: =X69/V69-1 -> -0.32316145 | Y71: =Y69/W69-1 -> 2.6273238 | Z71: =Z69/X69-1 -> 0.60507462
B72: Gross cash of previous yeaer | G72: =SUM(F127,F128) -> 229.123 | H72: =SUM(G127,G128) -> 1249.391 | I72: =SUM(H127,H128) -> 2269.222 | J72: =SUM(I127,I128) -> 2367.74 | K72: =SUM(J127,J128) -> 30917.326 | L72: =SUM(K127,K128) -> 28459.313 | M72: =SUM(L127,L128) -> 29613.994 | N72: =SUM(M127,M128) -> 40006.928 | ... S72: =SUM(R127,R128) -> 558814.94
B73: Interest income % of cash | G73: =G66/G72 -> 0.049039162 | H73: =H66/H72 -> 0.010730028 | I73: =I66/I72 -> 0.0065352795 | J73: 0.014 | K73: 0.014 | L73: 0.007 | M73: 0.014 | N73: 0.014 | O73: 0.014 | P73: 0.014 | Q73: 0.014 | R73: 0.014 | S73: 0.014
B75: Selling and distribution expenses
C76: Advertising and marketing expenses | F76: 1.167 | G76: 54.868 | H76: 237.453 | I76: =(H76/H$82)*I$82 -> 239.53292 | J76: =(I76/I$82)*J$82 -> 311.39279 | K76: =(J76/J$82)*K$82 -> 451.51955 | L76: =(K76/K$82)*L$82 -> 677.27932 | M76: =(L76/L$82)*M$82 -> 982.05501 | N76: =(M76/M$82)*N$82 -> 1379.7873 | O76: =(N76/N$82)*O$82 -> 1882.7198 | P76: =(O76/O$82)*P$82 -> 2500.346 | ... S76: =(R76/R$82)*S$82 -> 5079.409 | U76: 80.713 | V76: =H76-U76 -> 156.74 | W76: 95.675
C77: Payroll cost | F77: 11.378 | G77: 30.334 | H77: 93.695 | I77: =(H77/H$82)*I$82 -> 94.5157 | J77: =(I77/I$82)*J$82 -> 122.87041 | K77: =(J77/J$82)*K$82 -> 178.16209 | L77: =(K77/K$82)*L$82 -> 267.24314 | M77: =(L77/L$82)*M$82 -> 387.50256 | N77: =(M77/M$82)*N$82 -> 544.44109 | O77: =(N77/N$82)*O$82 -> 742.88987 | P77: =(O77/O$82)*P$82 -> 986.59489 | ... S77: =(R77/R$82)*S$82 -> 2004.2502 | U77: 44.493 | V77: =H77-U77 -> 49.202 | W77: 71.744
C78: Technical service and consultation fees | F78: 0.21 | G78: 3.767 | H78: 21.963 | I78: =(H78/H$82)*I$82 -> 22.15538 | J78: =(I78/I$82)*J$82 -> 28.801994 | K78: =(J78/J$82)*K$82 -> 41.762891 | L78: =(K78/K$82)*L$82 -> 62.644337 | M78: =(L78/L$82)*M$82 -> 90.834288 | N78: =(M78/M$82)*N$82 -> 127.62218 | O78: =(N78/N$82)*O$82 -> 174.14046 | P78: =(O78/O$82)*P$82 -> 231.26724 | ... S78: =(R78/R$82)*S$82 -> 469.81533 | U78: 9.061 | V78: =H78-U78 -> 12.902 | W78: 8.778
C79: Computing service fees | F79: 0 | G79: 1.852 | H79: 12.84 | I79: =(H79/H$82)*I$82 -> 12.952469 | J79: =(I79/I$82)*J$82 -> 16.83821 | K79: =(J79/J$82)*K$82 -> 24.415404 | L79: =(K79/K$82)*L$82 -> 36.623106 | M79: =(L79/L$82)*M$82 -> 53.103504 | N79: =(M79/M$82)*N$82 -> 74.610423 | O79: =(N79/N$82)*O$82 -> 101.80592 | P79: =(O79/O$82)*P$82 -> 135.20336 | ... S79: =(R79/R$82)*S$82 -> 274.66325 | U79: 2.287 | V79: =H79-U79 -> 10.553 | W79: 20.564
C80: D&A | F80: 1.705 | G80: 5.615 | H80: 6.054 | I80: =(H80/H$82)*I$82 -> 6.1070286 | J80: =(I80/I$82)*J$82 -> 7.9391372 | K80: =(J80/J$82)*K$82 -> 11.511749 | L80: =(K80/K$82)*L$82 -> 17.267624 | M80: =(L80/L$82)*M$82 -> 25.038054 | N80: =(M80/M$82)*N$82 -> 35.178466 | O80: =(N80/N$82)*O$82 -> 48.001017 | P80: =(O80/O$82)*P$82 -> 63.74775 | ... S80: =(R80/R$82)*S$82 -> 129.50244 | U80: 2.956 | V80: =H80-U80 -> 3.098 | W80: 4.194
C81: Others | F81: =F82-SUM(F76,F77,F78,F79,F80) -> 0.679 | G81: =G82-SUM(G76,G77,G78,G79,G80) -> 4.762 | H81: =H82-SUM(H76,H77,H78,H79,H80) -> 15.47 | I81: =I82-SUM(I76,I77,I78,I79,I80) -> 15.605506 | J81: =(I81/I$82)*J$82 -> 20.287158 | K81: =(J81/J$82)*K$82 -> 29.416379 | L81: =(K81/K$82)*L$82 -> 44.124568 | M81: =(L81/L$82)*M$82 -> 63.980624 | N81: =(M81/M$82)*N$82 -> 89.892776 | O81: =(N81/N$82)*O$82 -> 122.65869 | P81: =(O81/O$82)*P$82 -> 162.89688 | Q81: =(P81/P$82)*Q$82 -> 210.99137 | ... S81: =(R81/R$82)*S$82 -> 330.92215 | U81: =U82-SUM(U76,U77,U78,U79,U80) -> 4.684 | V81: =H81-U81 -> 10.786 | W81: =W82-SUM(W76,W77,W78,W79,W80) -> 7.615
B82: Total | F82: =-F14 -> 15.139 | G82: =-G14 -> 101.198 | H82: =-H14 -> 387.475 | I82: =-I14 -> 390.869 | J82: =I82*(1+J84) -> 508.1297 | K82: =J82*(1+K84) -> 736.78807 | L82: =K82*(1+L84) -> 1105.1821 | M82: =L82*(1+M84) -> 1602.514 | N82: =M82*(1+N84) -> 2251.5322 | O82: =N82*(1+O84) -> 3072.2157 | P82: =O82*(1+P84) -> 4080.0561 | Q82: =P82*(1+Q84) -> 5284.6723 | ... S82: =R82*(1+S84) -> 8288.5624 | U82: =-U14 -> 144.194 | V82: =-V14 -> 243.281 | W82: =-W14 -> 208.57 | X82: =-X14 -> 182.299 | Y82: =Y4*Y83 -> 245.46826 | Z82: =J82-Y82 -> 262.66144
C83: As % of revenue | F83: =IFERROR(F82/F$4,"NM") -> 0.2637043 | G83: =IFERROR(G82/G$4,"NM") -> 0.81258732 | H83: =IFERROR(H82/H$4,"NM") -> 1.2402613 | I83: =IFERROR(I82/I$4,"NM") -> 0.53962537 | J83: =IFERROR(J82/J$4,"NM") -> 0.080156406 | K83: =IFERROR(K82/K$4,"NM") -> 0.031055699 | L83: =IFERROR(L82/L$4,"NM") -> 0.018792619 | M83: =IFERROR(M82/M$4,"NM") -> 0.013287447 | ... S83: =IFERROR(S82/S$4,"NM") -> 0.0064611683 | U83: =IFERROR(U82/U$4,"NM") -> 3.2108041 | V83: =IFERROR(V82/V$4,"NM") -> 0.90944468 | W83: =IFERROR(W82/W$4,"NM") -> 1.0926932 | X83: =IFERROR(X82/X$4,"NM") -> 0.34173139 | Y83: 0.22 | Z83: =IFERROR(Z82/Z$4,"NM") -> 0.050284927
C84: % yoy change | G84: =G82/F82-1 -> 5.6845895 | H84: =H82/G82-1 -> 2.82888 | I84: =I82/H82-1 -> 0.0087592748 | J84: 0.3 | K84: 0.45 | L84: 0.5 | M84: =L84*0.9 -> 0.45 | N84: =M84*0.9 -> 0.405 | O84: =N84*0.9 -> 0.3645 | P84: =O84*0.9 -> 0.32805 | Q84: =P84*0.9 -> 0.295245 | R84: =Q84*0.9 -> 0.2657205 | S84: =R84*0.9 -> 0.23914845 | W84: =W82/U82-1 -> 0.44645408 | X84: =X82/V82-1 -> -0.25066487 | Y84: =Y82/W82-1 -> 0.17691066 | Z84: =Z82/X82-1 -> 0.44082767
B86: Administrative expenses
C87: Payroll cost | F87: 20.923 | G87: 33.956 | H87: 78.369 | I87: =(H87/H$92)*I$92 -> 296.43288 | J87: =(I87/I$92)*J$92 -> 385.36275 | K87: =(J87/J$92)*K$92 -> 558.77599 | L87: =(K87/K$92)*L$92 -> 838.16398 | M87: =(L87/L$92)*M$92 -> 1215.3378 | N87: =(M87/M$92)*N$92 -> 1707.5496 | O87: =(N87/N$92)*O$92 -> 2329.9514 | P87: =(O87/O$92)*P$92 -> 3094.2919 | ... S87: =(R87/R$92)*S$92 -> 6285.9998 | U87: 29.041 | V87: =H87-U87 -> 49.328 | W87: 124.655
C88: Professional service fees | F88: 2.835 | G88: 11.931 | H88: 14.845 | I88: =(H88/H$92)*I$92 -> 56.151618 | J88: =(I88/I$92)*J$92 -> 72.997104 | K88: =(J88/J$92)*K$92 -> 105.8458 | L88: =(K88/K$92)*L$92 -> 158.7687 | M88: =(L88/L$92)*M$92 -> 230.21462 | N88: =(M88/M$92)*N$92 -> 323.45154 | O88: =(N88/N$92)*O$92 -> 441.34962 | P88: =(O88/O$92)*P$92 -> 586.13436 | ... S88: =(R88/R$92)*S$92 -> 1190.7217 | U88: 6.608 | V88: =H88-U88 -> 8.237 | W88: 28.345
C89: D&A | F89: 1.712 | G89: 7.674 | H89: 8.076 | I89: =(H89/H$92)*I$92 -> 30.547691 | J89: =(I89/I$92)*J$92 -> 39.711998 | K89: =(J89/J$92)*K$92 -> 57.582397 | L89: =(K89/K$92)*L$92 -> 86.373596 | M89: =(L89/L$92)*M$92 -> 125.24171 | N89: =(M89/M$92)*N$92 -> 175.96461 | O89: =(N89/N$92)*O$92 -> 240.10371 | P89: =(O89/O$92)*P$92 -> 318.86973 | ... S89: =(R89/R$92)*S$92 -> 647.77826 | U89: 5.656 | V89: =H89-U89 -> 2.42 | W89: 8.802
C90: Transportation and travel expenses | F90: 2.583 | G90: 3.914 | H90: 5.759 | I90: =(H90/H$92)*I$92 -> 21.783575 | J90: =(I90/I$92)*J$92 -> 28.318647 | K90: =(J90/J$92)*K$92 -> 41.062039 | L90: =(K90/K$92)*L$92 -> 61.593058 | M90: =(L90/L$92)*M$92 -> 89.309934 | N90: =(M90/M$92)*N$92 -> 125.48046 | O90: =(N90/N$92)*O$92 -> 171.21808 | P90: =(O90/O$92)*P$92 -> 227.38618 | ... S90: =(R90/R$92)*S$92 -> 461.93103 | U90: 2.559 | V90: =H90-U90 -> 3.2 | W90: 3.516
C91: Others | F91: =F92-SUM(F87,F88,F89,F90) -> 4.263 | G91: =G92-SUM(G87,G88,G89,G90) -> 8.827 | H91: =H92-SUM(H87,H88,H89,H90) -> 26.554 | I91: =I92-SUM(I87,I88,I89,I90) -> 100.44123 | J91: =(I91/I$92)*J$92 -> 130.5736 | K91: =(J91/J$92)*K$92 -> 189.33172 | L91: =(K91/K$92)*L$92 -> 283.99758 | M91: =(L91/L$92)*M$92 -> 411.79649 | N91: =(M91/M$92)*N$92 -> 578.57407 | O91: =(N91/N$92)*O$92 -> 789.46432 | P91: =(O91/O$92)*P$92 -> 1048.4481 | Q91: =(P91/P$92)*Q$92 -> 1357.9971 | ... S91: =(R91/R$92)*S$92 -> 2129.9039 | U91: =U92-SUM(U87,U88,U89,U90) -> 7.588 | V91: =H91-U91 -> 18.966 | W91: =W92-SUM(W87,W88,W89,W90) -> 19.847
B92: Total | F92: =-F15 -> 32.316 | G92: =-G15 -> 66.302 | H92: =-H15 -> 133.603 | I92: =-I15 -> 505.357 | J92: =I92*(1+J94) -> 656.9641 | K92: =J92*(1+K94) -> 952.59794 | L92: =K92*(1+L94) -> 1428.8969 | M92: =L92*(1+M94) -> 2071.9005 | N92: =M92*(1+N94) -> 2911.0202 | O92: =N92*(1+O94) -> 3972.0871 | P92: =O92*(1+P94) -> 5275.1303 | Q92: =P92*(1+Q94) -> 6832.5862 | ... S92: =R92*(1+S94) -> 10716.335 | U92: =-U15 -> 51.452 | V92: =-V15 -> 82.151 | W92: =-W15 -> 185.165 | X92: =-X15 -> 320.192 | Y92: =Y4*Y93 -> 334.72944 | Z92: =J92-Y92 -> 322.23466
C93: As % of revenue | F93: =IFERROR(F92/F$4,"NM") -> 0.56290825 | G93: =IFERROR(G92/G$4,"NM") -> 0.53238369 | H93: =IFERROR(H92/H$4,"NM") -> 0.42764729 | I93: =IFERROR(I92/I$4,"NM") -> 0.69768505 | J93: =IFERROR(J92/J$4,"NM") -> 0.10363472 | K93: =IFERROR(K92/K$4,"NM") -> 0.04015211 | L93: =IFERROR(L92/L$4,"NM") -> 0.024297096 | M93: =IFERROR(M92/M$4,"NM") -> 0.017179425 | ... S93: =IFERROR(S92/S$4,"NM") -> 0.0083536853 | U93: =IFERROR(U92/U$4,"NM") -> 1.1456946 | V93: =IFERROR(V92/V$4,"NM") -> 0.3071008 | W93: =IFERROR(W92/W$4,"NM") -> 0.97007497 | X93: =IFERROR(X92/X$4,"NM") -> 0.60022082 | Y93: 0.3 | Z93: =IFERROR(Z92/Z$4,"NM") -> 0.061689855
C94: % yoy change | G94: =G92/F92-1 -> 1.0516772 | H94: =H92/G92-1 -> 1.0150674 | I94: =I92/H92-1 -> 2.7825273 | J94: 0.3 | K94: 0.45 | L94: 0.5 | M94: =L94*0.9 -> 0.45 | N94: =M94*0.9 -> 0.405 | O94: =N94*0.9 -> 0.3645 | P94: =O94*0.9 -> 0.32805 | Q94: =P94*0.9 -> 0.295245 | R94: =Q94*0.9 -> 0.2657205 | S94: =R94*0.9 -> 0.23914845 | W94: =W92/U92-1 -> 2.5987911 | X94: =X92/V92-1 -> 2.8976032 | Y94: =Y92/W92-1 -> 0.80773602 | Z94: =Z92/X92-1 -> 0.0063794848
B96: Research and development expenses
C97: Computing service fees | F97: 14.633 | G97: 311.746 | H97: 1552.832 | I97: =H97/H$102*I$102 -> 2249.5275 | J97: =I97/I$102*J$102 -> 4049.1495 | K97: =J97/J$102*K$102 -> 7693.3841 | L97: =K97/K$102*L$102 -> 11532.383 | M97: =L97/L$102*M$102 -> 18451.812 | N97: =M97/M$102*N$102 -> 28600.309 | O97: =N97/N$102*O$102 -> 39611.428 | P97: =O97/O$102*P$102 -> 50286.708 | ... S97: =R97/R$102*S$102 -> 73921.662 | U97: 603.237 | V97: =H97-U97 -> 949.595 | W97: 1145.124
C98: Payroll cost | F98: 41.982 | G98: 137.296 | H98: 324.193 | I98: =I102-I97-SUM(I99:I101) -> 469.64583 | J98: =J102-J97-SUM(J99:J101) -> 845.36249 | K98: =K102-K97-SUM(K99:K101) -> 1606.1887 | L98: =L102-L97-SUM(L99:L101) -> 2407.6769 | M98: =M102-M97-SUM(M99:M101) -> 3852.2831 | N98: =N102-N97-SUM(N99:N101) -> 5971.0387 | O98: =O102-O97-SUM(O99:O101) -> 8269.8886 | P98: =P102-P97-SUM(P99:P101) -> 10498.624 | ... S98: =S102-S97-SUM(S99:S101) -> 15433.019 | U98: 107.988 | V98: =H98-U98 -> 216.205 | W98: 265.567
C99: D&A | F99: 14.689 | G99: 49.206 | H99: 259.038 | I99: =H99/H$102*I$102 -> 375.25831 | J99: =I99/I$102*J$102 -> 675.46495 | K99: =J99/J$102*K$102 -> 1283.3834 | L99: =K99/K$102*L$102 -> 1923.7917 | M99: =L99/L$102*M$102 -> 3078.0668 | N99: =M99/M$102*N$102 -> 4771.0035 | O99: =N99/N$102*O$102 -> 6607.8398 | P99: =O99/O$102*P$102 -> 8388.6526 | ... S99: =R99/R$102*S$102 -> 12331.353 | U99: 118.517 | V99: =H99-U99 -> 140.521 | W99: 123.966
C100: Technical service and consulatation fees | F100: 11.412 | G100: 25.184 | H100: 45.036 | I100: =H100/H$102*I$102 -> 65.241907 | J100: =I100/I$102*J$102 -> 117.43543 | K100: =J100/J$102*K$102 -> 223.12732 | L100: =K100/K$102*L$102 -> 334.46785 | M100: =L100/L$102*M$102 -> 535.14857 | N100: =M100/M$102*N$102 -> 829.48028 | O100: =N100/N$102*O$102 -> 1148.8302 | P100: =O100/O$102*P$102 -> 1458.4399 | ... S100: =R100/R$102*S$102 -> 2143.9125 | U100: 24.67 | V100: =H100-U100 -> 20.366 | W100: 52.209
C101: Others | F101: =F102-SUM(F97,F98,F99,F100) -> 1.661 | G101: =G102-SUM(G97,G98,G99,G100) -> 5.452 | H101: =H102-SUM(H97,H98,H99,H100) -> 14.337 | I101: =H101/H$102*I$102 -> 20.769456 | J101: =I101/I$102*J$102 -> 37.385021 | K101: =J101/J$102*K$102 -> 71.031539 | L101: =K101/K$102*L$102 -> 106.47628 | M101: =L101/L$102*M$102 -> 170.36204 | N101: =M101/M$102*N$102 -> 264.06117 | O101: =N101/N$102*O$102 -> 365.72472 | P101: =O101/O$102*P$102 -> 464.28753 | ... S101: =R101/R$102*S$102 -> 682.50453 | U101: =U102-SUM(U97,U98,U99,U100) -> 4.805 | V101: =H101-U101 -> 9.532 | W101: =W102-SUM(W97,W98,W99,W100) -> 7.795
B102: Total | F102: =-F16 -> 84.377 | G102: =-G16 -> 528.884 | H102: =-H16 -> 2195.436 | I102: =-I16 -> 3180.443 | J102: =I102*(1+J104) -> 5724.7974 | K102: =J102*(1+K104) -> 10877.115 | L102: =K102*(1+L104) -> 16304.795 | M102: =L102*(1+M104) -> 26087.673 | N102: =M102*(1+N104) -> 40435.893 | O102: =N102*(1+O104) -> 56003.711 | P102: =O102*(1+P104) -> 71096.712 | Q102: =P102*(1+Q104) -> 84509.106 | ... S102: =R102*(1+S104) -> 104512.45 | U102: =-U16 -> 859.217 | V102: =-V16 -> 1336.219 | W102: =-W16 -> 1594.661 | X102: =-X16 -> 1585.782 | Y102: =Y4*Y103 -> 2789.412 | Z102: =J102-Y102 -> 2935.3854
C103: As % of revenue | F103: =IFERROR(F102/F$4,"NM") -> 1.4697521 | G103: =IFERROR(G102/G$4,"NM") -> 4.2467681 | H103: =IFERROR(H102/H$4,"NM") -> 7.0273291 | I103: =IFERROR(I102/I$4,"NM") -> 4.3908515 | J103: =IFERROR(J102/J$4,"NM") -> 0.90307491 | K103: =IFERROR(K102/K$4,"NM") -> 0.45847162 | L103: =IFERROR(L102/L$4,"NM") -> 0.27724826 | M103: =IFERROR(M102/M$4,"NM") -> 0.21630923 | ... S103: =IFERROR(S102/S$4,"NM") -> 0.081470405 | U103: =IFERROR(U102/U$4,"NM") -> 19.132401 | V103: =IFERROR(V102/V$4,"NM") -> 4.9951178 | W103: =IFERROR(W102/W$4,"NM") -> 8.3543905 | X103: =IFERROR(X102/X$4,"NM") -> 2.972652 | Y103: 2.5 | Z103: =IFERROR(Z102/Z$4,"NM") -> 0.56196158
C104: % yoy change | G104: =G102/F102-1 -> 5.2681062 | H104: =H102/G102-1 -> 3.1510728 | I104: =I102/H102-1 -> 0.44866122 | J104: 0.8 | K104: 0.9 | L104: 0.499 | M104: 0.6 | N104: 0.55 | O104: =N104*0.7 -> 0.385 | P104: =O104*0.7 -> 0.2695 | Q104: =P104*0.7 -> 0.18865 | R104: =Q104*0.7 -> 0.132055 | S104: =R104*0.7 -> 0.0924385 | W104: =W102/U102-1 -> 0.85594675 | X104: =X102/V102-1 -> 0.18676804 | Y104: =Y102/W102-1 -> 0.74921943 | Z104: =Z102/X102-1 -> 0.8510649
B106: Finance cost
C107: Interest on lease liabilities | F107: 0.788 | G107: 7.498 | H107: 30.931 | I107: 32.795 | J107: =SUM(I157,I150)*J112 -> 26.633125 | K107: =SUM(J157,J150)*K112 -> 26.633125 | L107: =SUM(K157,K150)*L112 -> 26.633125 | M107: =SUM(L157,L150)*M112 -> 26.633125 | N107: =SUM(M157,M150)*N112 -> 26.633125 | O107: =SUM(N157,N150)*O112 -> 26.633125 | P107: =SUM(O157,O150)*P112 -> 26.633125 | Q107: =SUM(P157,P150)*Q112 -> 26.633125 | ... S107: =SUM(R157,R150)*S112 -> 26.633125 | U107: 11.84 | V107: =H107-U107 -> 19.091 | W107: 17.983
C108: Interest on bank loans | F108: 0 | G108: 0 | H108: 1.716 | I108: 4.741 | J108: =I149*J113 -> 9.07254 | K108: =J149*K113 -> 9.07254 | L108: =K149*L113 -> 9.07254 | M108: =L149*M113 -> 9.07254 | N108: =M149*N113 -> 9.07254 | O108: =N149*O113 -> 9.07254 | P108: =O149*P113 -> 9.07254 | Q108: =P149*Q113 -> 9.07254 | ... S108: =R149*S113 -> 9.07254 | U108: 0 | V108: =H108-U108 -> 1.716 | W108: 1.807
C109: Transaction costs in relation to the financial instruments | F109: 4.906 | G109: 16.488 | H109: 20.119 | I109: 31.277 | J109: 0 | K109: 0 | L109: 0 | M109: 0 | N109: 0 | O109: 0 | P109: 0 | Q109: 0 | R109: 0 | S109: 0 | U109: 5.185 | V109: =H109-U109 -> 14.934 | W109: 31.975
C110: FX loss/(gain), net | F110: =F111-SUM(F107,F108,F109) -> 0 | G110: =G111-SUM(G107,G108,G109) -> 2.346 | H110: =H111-SUM(H107,H108,H109) -> -14.445 | I110: =I111-SUM(I107,I108,I109) -> 5.502 | J110: 0 | K110: 0 | L110: 0 | M110: 0 | N110: 0 | O110: 0 | P110: 0 | Q110: 0 | R110: 0 | S110: 0 | U110: =U111-SUM(U107,U108,U109) -> -4.813 | V110: =H110-U110 -> -9.632 | W110: =W111-SUM(W107,W108,W109) -> 1.505
B111: Total | F111: =-F27 -> 5.694 | G111: =-G27 -> 26.332 | H111: =-H27 -> 38.321 | I111: =-I27 -> 74.315 | J111: =SUM(J107:J110) -> 35.705665 | K111: =SUM(K107:K110) -> 35.705665 | L111: =SUM(L107:L110) -> 35.705665 | M111: =SUM(M107:M110) -> 35.705665 | N111: =SUM(N107:N110) -> 35.705665 | O111: =SUM(O107:O110) -> 35.705665 | P111: =SUM(P107:P110) -> 35.705665 | Q111: =SUM(Q107:Q110) -> 35.705665 | ... S111: =SUM(S107:S110) -> 35.705665 | U111: =-U27 -> 12.212 | V111: =-V27 -> 26.109 | W111: =-W27 -> 53.27 | X111: =-X27 -> 21.045 | Y111: =J111/2 -> 17.852833 | Z111: =J111-Y111 -> 17.852833
B112: Interest % on lease liabilities | G112: =G107/(F150+F157) -> 0.58432045 | H112: =H107/(G150+G157) -> 0.11418625 | I112: =I107/(H150+H157) -> 0.048855301 | J112: =I112 -> 0.048855301 | K112: =J112 -> 0.048855301 | L112: =K112 -> 0.048855301 | M112: =L112 -> 0.048855301 | N112: =M112 -> 0.048855301 | O112: =N112 -> 0.048855301 | P112: =O112 -> 0.048855301 | Q112: =P112 -> 0.048855301 | ... S112: =R112 -> 0.048855301
B113: Interest % on bank loans | I113: =I108/(H149+H156) -> 0.034543812 | J113: 0.015 | K113: 0.015 | L113: 0.015 | M113: 0.015 | N113: 0.015 | O113: 0.015 | P113: 0.015 | Q113: 0.015 | R113: 0.015 | S113: 0.015
B115: Income tax | F115: =+F33 -> 0 | G115: =+G33 -> 0 | H115: =+H33 -> 0 | I115: =+I33 -> 0 | J115: =IF(J32>0,J32*J116,0) -> 0 | K115: =IF(K32>0,K32*K116,0) -> 0 | L115: =IF(L32>0,L32*L116,0) -> 0 | M115: =IF(M32>0,M32*M116,0) -> 1097.712 | N115: =IF(N32>0,N32*N116,0) -> 4208.7587 | O115: =IF(O32>0,O32*O116,0) -> 10297.014 | P115: =IF(P32>0,P32*P116,0) -> 19161.12 | Q115: =IF(Q32>0,Q32*Q116,0) -> 31293.511 | ... S115: =IF(S32>0,S32*S116,0) -> 63980.226
C116: % of pretax profits | F116: =F115/F32 -> 0 | G116: =G115/G32 -> 0 | H116: =H115/H32 -> 0 | I116: =I115/I32 -> 0 | J116: =IF(J32>0,18%,0) -> 0 | K116: =IF(K32>0,18%,0) -> 0 | L116: =IF(L32>0,18%,0) -> 0 | M116: =IF(M32>0,18%,0) -> 0.18 | N116: =IF(N32>0,18%,0) -> 0.18 | O116: =IF(O32>0,18%,0) -> 0.18 | P116: =IF(P32>0,18%,0) -> 0.18 | Q116: =IF(Q32>0,18%,0) -> 0.18 | ... S116: =IF(S32>0,18%,0) -> 0.18
B118: Share-based compensation | F118: =F46 -> 1.024 | G118: =G46 -> 5.502 | H118: =H46 -> 23.579 | I118: =I46 -> 558.265 | J118: =I118*(1+J120) -> 669.918 | K118: =J118*(1+K120) -> 803.9016 | L118: =K118*(1+L120) -> 964.68192 | M118: =L118*(1+M120) -> 1061.1501 | N118: =M118*(1+N120) -> 1167.2651 | O118: =N118*(1+O120) -> 1283.9916 | P118: =O118*(1+P120) -> 1412.3908 | Q118: =P118*(1+Q120) -> 1553.6299 | ... S118: =R118*(1+S120) -> 1879.8922
B119: Share-based compensation as % of revenue | F119: =F118/F4 -> 0.017836925 | G119: =G118/G4 -> 0.044179287 | H119: =H118/H4 -> 0.07547357 | I119: =I118/I4 -> 0.7707287 | J119: =J118/J4 -> 0.10567817 | K119: =K118/K4 -> 0.033884542 | L119: =L118/L4 -> 0.016403541 | M119: =L119 -> 0.016403541 | N119: =M119 -> 0.016403541 | O119: =N119 -> 0.016403541 | P119: =O119 -> 0.016403541 | Q119: =P119 -> 0.016403541 | R119: =Q119 -> 0.016403541 | S119: =R119 -> 0.016403541
B120: yoy % | G120: =G118/F118-1 -> 4.3730469 | H120: =H118/G118-1 -> 3.2855325 | I120: =I118/H118-1 -> 22.676365 | J120: 0.2 | K120: 0.2 | L120: 0.2 | M120: 0.1 | N120: 0.1 | O120: 0.1 | P120: 0.1 | Q120: 0.1 | R120: 0.1 | S120: 0.1
B122: Reported net loss - consolidated | F122: =F35 -> -143.65 | G122: =G35 -> -787.977 | H122: =H35 -> -2958.007 | I122: =I35 -> -4718.167 | J122: =J35 -> -5080.9477 | K122: =K35 -> -5709.0316 | L122: =L35 -> -2304.4506 | M122: =M35 -> 5000.6881 | ... S122: =S35 -> 291465.47
B123: Cumulative loss | F123: =SUM($F$122:F122) -> -143.65 | G123: =SUM($F$122:G122) -> -931.627 | H123: =SUM($F$122:H122) -> -3889.634 | I123: =SUM($F$122:I122) -> -8607.801 | J123: =SUM($F$122:J122) -> -13688.749 | K123: =SUM($F$122:K122) -> -19397.78 | L123: =SUM($F$122:L122) -> -21702.231 | M123: =SUM($F$122:M122) -> -16701.543 | ... S123: =SUM($F$122:S122) -> 782145.81
A125: Balance Sheet (Rmb mn) | F125: =F3 -> 2022 | G125: =G3 -> 2023 | H125: =H3 -> 2024 | I125: =I3 -> 2025 | J125: =J3 -> 2026 | K125: =K3 -> 2027 | L125: =L3 -> 2028 | M125: =M3 -> 2029 | ... S125: =S3 -> 2035 | U125: 1H24 | V125: 2H24 | W125: 1H25 | X125: 2H25 | Y125: 1H26 | Z125: 2H26
B126: Current assets
...

Sheet Revenue
F1: USD/CNY | G1: 7
A4: December year-end. Rmb$ mn. | F4: 2022 | G4: 2023 | H4: 2024 | I4: 2025 | J4: 2026E | K4: 2027E | L4: 2028E | M4: 2029E | N4: 2030E | O4: 2031 | P4: 2032 | Q4: 2033 | R4: 2034 | S4: 2035 | U4: 1H24 | V4: 2H24 | W4: 1H25 | X4: 2H25 | Y4: 1H26 | Z4: 2H26
B5: Revenue | F5: =SUM(F27,F29) -> 57.409 | G5: =SUM(G27,G29) -> 124.538 | H5: =SUM(H27,H29) -> 312.414 | I5: =SUM(I27,I29) -> 724.334 | J5: =SUM(J27,J29) -> 6339.2276 | K5: =SUM(K27,K29) -> 23724.729 | L5: =SUM(L27,L29) -> 58809.369 | M5: =SUM(M27,M29) -> 120603.6 | ... S5: =SUM(S27,S29) -> 1282827.2 | U5: =SUM(U27,U29) -> 44.909 | V5: =SUM(V27,V29) -> 267.505 | W5: =SUM(W27,W29) -> 190.877 | X5: =SUM(X27,X29) -> 533.457 | Y5: =SUM(Y27,Y29) -> 1115.7648 | Z5: =SUM(Z27,Z29) -> 5223.4628
B6: yoy % | G6: =G5/F5-1 -> 1.1693114 | H6: =H5/G5-1 -> 1.5085837 | I6: =I5/H5-1 -> 1.3185069 | J6: =J5/I5-1 -> 7.7518018 | K6: =K5/J5-1 -> 2.7425269 | L6: =L5/K5-1 -> 1.4788215 | M6: =M5/L5-1 -> 1.0507549 | N6: =N5/M5-1 -> 0.82080436 | ... S6: =S5/R5-1 -> 0.26126355 | W6: =W5/U5-1 -> 3.2503062 | X6: =X5/V5-1 -> 0.9941945 | Y6: =Y5/W5-1 -> 4.8454649 | Z6: =Z5/X5-1 -> 8.7917223
B8: By product lines:
B9: Open platform and API | H9: 48.484 | I9: 190.379 | J9: =J29 -> 5248.44 | K9: =K29 -> 21931 | L9: =L29 -> 56143.5 | M9: =M29 -> 116777.5 | N9: =N29 -> 214312 | O9: =O29 -> 354508.05 | P9: =P29 -> 537346.44 | Q9: =Q29 -> 757306.25 | ... S9: =S29 -> 1270029.7
B10: Enterprise-level agents | H10: 47.492 | I10: 165.687 | J10: =I10*(1+J16) -> 414.2175 | K10: =J10*(1+K16) -> 745.5915 | L10: =K10*(1+L16) -> 1230.226 | M10: =L10*(1+M16) -> 1931.4548 | N10: =M10*(1+N16) -> 2877.8676 | O10: =N10*(1+O16) -> 4057.7933 | P10: =O10*(1+P16) -> 5396.8652 | Q10: =P10*(1+Q16) -> 6746.0814 | ... S10: =R10*(1+S16) -> 8603.2777
B11: Enterprise-level general-purpose large models | H11: 214.502 | I11: 365.724 | J11: =I11*(1+J17) -> 672.93216 | K11: =J11*(1+K17) -> 1043.0448 | L11: =K11*(1+L17) -> 1428.9714 | M11: =L11*(1+M17) -> 1886.2423 | N11: =M11*(1+N17) -> 2395.5277 | O11: =N11*(1+O17) -> 2922.5438 | P11: =O11*(1+P17) -> 3419.3763 | Q11: =P11*(1+Q17) -> 3829.7014 | ... S11: =R11*(1+S17) -> 4179.7361
B12: Technical service and others | H12: 1.936 | I12: 2.544 | J12: =I12*(1+J18) -> 3.63792 | K12: =J12*(1+K18) -> 5.093088 | L12: =K12*(1+L18) -> 6.6719453 | M12: =L12*(1+M18) -> 8.4066511 | N12: =M12*(1+N18) -> 10.172048 | O12: =N12*(1+O18) -> 11.799575 | P12: =O12*(1+P18) -> 13.097529 | Q12: =P12*(1+Q18) -> 13.88338 | ... S12: =R12*(1+S18) -> 14.444269
B14: yoy %
B15: Open platform and API | I15: =I9/H9-1 -> 2.9266356 | J15: =J9/I9-1 -> 26.568377 | K15: =K9/J9-1 -> 3.178575 | L15: =L9/K9-1 -> 1.5600064 | M15: =M9/L9-1 -> 1.0799825 | N15: =N9/M9-1 -> 0.83521654 | O15: =O9/N9-1 -> 0.65416798 | P15: =P9/O9-1 -> 0.51575245 | ... S15: =S9/R9-1 -> 0.26359551
B16: Enterprise-level agents | I16: =I10/H10-1 -> 2.4887349 | J16: 1.5 | K16: 0.8 | L16: 0.65 | M16: =L16-8% -> 0.57 | N16: =M16-8% -> 0.49 | O16: =N16-8% -> 0.41 | P16: =O16-8% -> 0.33 | Q16: =P16-8% -> 0.25 | R16: =Q16-8% -> 0.17 | S16: =R16-8% -> 0.09
B17: Enterprise-level general-purpose large models | I17: =I11/H11-1 -> 0.7049911 | J17: 0.84 | K17: 0.55 | L17: 0.37 | M17: =L17-5% -> 0.32 | N17: =M17-5% -> 0.27 | O17: =N17-5% -> 0.22 | P17: =O17-5% -> 0.17 | Q17: =P17-5% -> 0.12 | R17: =Q17-5% -> 0.07 | S17: =R17-5% -> 0.02
B18: Technical service and others | I18: =I12/H12-1 -> 0.31404959 | J18: 0.43 | K18: 0.4 | L18: 0.31 | M18: =L18-5% -> 0.26 | N18: =M18-5% -> 0.21 | O18: =N18-5% -> 0.16 | P18: =O18-5% -> 0.11 | Q18: =P18-5% -> 0.06 | R18: 0.02 | S18: 0.02
B20: Revenue breakdown %
B21: Open platform and API | H21: =H9/$H$5 -> 0.15519151 | I21: =I9/$I$5 -> 0.26283317 | J21: =J9/$J$5 -> 0.82793052 | K21: =K9/K$5 -> 0.9243941 | L21: =L9/L$5 -> 0.95466931 | M21: =M9/M$5 -> 0.96827538 | N21: =N9/N$5 -> 0.97593955 | O21: =O9/O$5 -> 0.980658 | P21: =P9/P$5 -> 0.98383425 | Q21: =Q9/Q$5 -> 0.9862095 | R21: =R9/R$5 -> 0.98819694 | S21: =S9/S$5 -> 0.99002402
B22: Enterprise-level agents | H22: =H10/$H$5 -> 0.15201623 | I22: =I10/$I$5 -> 0.22874392 | J22: =J10/$J$5 -> 0.065341951 | K22: =K10/$K$5 -> 0.031426765 | L22: =L10/L$5 -> 0.020918877 | M22: =M10/M$5 -> 0.016014901 | N22: =N10/N$5 -> 0.013105308 | O22: =O10/O$5 -> 0.011224872 | P22: =P10/P$5 -> 0.0098811872 | Q22: =Q10/Q$5 -> 0.0087851508 | R22: =R10/R$5 -> 0.0077602396 | S22: =S10/S$5 -> 0.0067064977
B23: Enterprise-level general-purpose large models | H23: =H11/$H$5 -> 0.68659535 | I23: =I11/$I$5 -> 0.50491072 | J23: =J11/$J$5 -> 0.10615365 | K23: =K11/$K$5 -> 0.043964457 | L23: =L11/L$5 -> 0.024298364 | M23: =M11/M$5 -> 0.015640016 | N23: =N11/N$5 -> 0.010908816 | O23: =O11/O$5 -> 0.0080844878 | P23: =P11/P$5 -> 0.0062605783 | Q23: =Q11/Q$5 -> 0.0049872663 | R23: =R11/R$5 -> 0.004028899 | S23: =S11/S$5 -> 0.0032582223
B24: Technical service and others | H24: =H12/$H$5 -> 0.0061969054 | I24: =I12/$I$5 -> 0.0035121919 | J24: =J12/$J$5 -> 0.00057387433 | K24: =K12/$K$5 -> 0.00021467423 | L24: =L12/L$5 -> 0.00011345038 | M24: =M12/M$5 -> 6.9704808e-05 | N24: =N12/N$5 -> 4.6321735e-05 | O24: =O12/O$5 -> 3.2640579e-05 | P24: =P12/P$5 -> 2.3980427e-05 | Q24: =Q12/Q$5 -> 1.8079768e-05 | R24: =R12/R$5 -> 1.3923008e-05 | S24: =S12/S$5 -> 1.1259715e-05
B26: By deployment methods:
B27: On-premise deployment | F27: 54.815 | G27: 112.614 | H27: 263.93 | I27: 533.955 | J27: =SUM(J10:J12) -> 1090.7876 | K27: =SUM(K10:K12) -> 1793.7294 | L27: =SUM(L10:L12) -> 2665.8694 | M27: =SUM(M10:M12) -> 3826.1037 | N27: =SUM(N10:N12) -> 5283.5674 | O27: =SUM(O10:O12) -> 6992.1367 | P27: =SUM(P10:P12) -> 8829.339 | Q27: =SUM(Q10:Q12) -> 10589.666 | ... S27: =SUM(S10:S12) -> 12797.458 | U27: 26.806 | V27: =H27-U27 -> 237.124 | W27: 161.777 | X27: =I27-W27 -> 372.178 | Y27: =W27*(1+Y28) -> 388.2648 | Z27: =J27-Y27 -> 702.52278
B28: yoy % | G28: =G27/F27-1 -> 1.0544377 | H28: =H27/G27-1 -> 1.3436695 | I28: =I27/H27-1 -> 1.0230932 | J28: =J27/I27-1 -> 1.0428455 | K28: =K27/J27-1 -> 0.64443515 | L28: =L27/K27-1 -> 0.48621599 | M28: =M27/L27-1 -> 0.43521802 | N28: =N27/M27-1 -> 0.38092633 | ... S28: =S27/R27-1 -> 0.066023378 | W28: =W27/U27-1 -> 5.0351041 | X28: =X27/V27-1 -> 0.56955011 | Y28: 1.4 | Z28: =Z27/X27-1 -> 0.88759889
A29: a+b | B29: Cloud-based deployment | F29: 2.594 | G29: 11.924 | H29: 48.484 | I29: 190.379 | J29: =J35*0.5 -> 5248.44 | K29: =K35*0.5 -> 21931 | L29: =L35*0.5 -> 56143.5 | M29: =M35*0.5 -> 116777.5 | N29: =N35*0.5 -> 214312 | O29: =O35*0.5 -> 354508.05 | P29: =P35*0.5 -> 537346.44 | Q29: =Q35*0.5 -> 757306.25 | ... S29: =S35*0.5 -> 1270029.7 | U29: 18.103 | V29: =H29-U29 -> 30.381 | W29: 29.1 | X29: =I29-W29 -> 161.279 | Y29: =W29*(1+Y30) -> 727.5 | Z29: =J29-Y29 -> 4520.94
B30: yoy % | G30: =G29/F29-1 -> 3.5967618 | H30: =H29/G29-1 -> 3.0660852 | I30: =I29/H29-1 -> 2.9266356 | J30: =J29/I29-1 -> 26.568377 | K30: =K29/J29-1 -> 3.178575 | L30: =L29/K29-1 -> 1.5600064 | M30: =M29/L29-1 -> 1.0799825 | N30: =N29/M29-1 -> 0.83521654 | ... S30: =S29/R29-1 -> 0.26359551 | W30: =W29/U29-1 -> 0.60746838 | X30: =X29/V29-1 -> 4.3085481 | Y30: 24 | Z30: =Z29/X29-1 -> 27.031796
G32: 2025.3 | H32: 2025.12 | I32: 2026.3 | J32: 2026 | K32: 2027 | L32: =K32+1 -> 2028 | M32: =L32+1 -> 2029 | N32: =M32+1 -> 2030 | O32: =N32+1 -> 2031 | P32: =O32+1 -> 2032 | Q32: =P32+1 -> 2033 | R32: =Q32+1 -> 2034 | S32: =R32+1 -> 2035
C33: Year- end ARR ($ mn) | G33: =H33/10 -> 3.90625 | H33: =I33/6.4 -> 39.0625 | I33: 250 | J33: =SUM(J46+J57) -> 1499.5543 | K33: =SUM(K46+K57) -> 6266 | L33: =SUM(L46+L57) -> 16041 | M33: =SUM(M46+M57) -> 33365 | N33: =SUM(N46+N57) -> 61232 | O33: =SUM(O46+O57) -> 101288.01 | P33: =SUM(P46+P57) -> 153527.56 | Q33: =SUM(Q46+Q57) -> 216373.22 | ... S33: =SUM(S46+S57) -> 362865.64
D34: yoy % | I34: 6.4 | J34: =J33/H33-1 -> 37.38859 | K34: =K33/J33-1 -> 3.178575 | L34: =L33/K33-1 -> 1.5600064 | M34: =M33/L33-1 -> 1.0799825 | N34: =N33/M33-1 -> 0.83521654 | O34: =O33/N33-1 -> 0.65416798 | P34: =P33/O33-1 -> 0.51575245 | Q34: =Q33/P33-1 -> 0.4093445 | R34: =R33/Q33-1 -> 0.32719359 | S34: =S33/R33-1 -> 0.26359551
C35: Year-end ARR (Rmb mn) | G35: =G33*$G$1 -> 27.34375 | H35: =H33*$G$1 -> 273.4375 | I35: =I33*$G$1 -> 1750 | J35: =J33*$G$1 -> 10496.88 | K35: =K33*$G$1 -> 43862 | L35: =L33*$G$1 -> 112287 | M35: =M33*$G$1 -> 233555 | N35: =N33*$G$1 -> 428624 | ... S35: =S33*$G$1 -> 2540059.5
D36: yoy % | I36: 64 | J36: =J35/H35-1 -> 37.38859 | K36: =K35/J35-1 -> 3.178575 | L36: =L35/K35-1 -> 1.5600064 | M36: =M35/L35-1 -> 1.0799825 | N36: =N35/M35-1 -> 0.83521654 | O36: =O35/N35-1 -> 0.65416798 | P36: =P35/O35-1 -> 0.51575245 | Q36: =Q35/P35-1 -> 0.4093445 | R36: =R35/Q35-1 -> 0.32719359 | S36: =S35/R35-1 -> 0.26359551
B38: a | C38: API / pay-as-you-go
C39: Daily token volume (bn) | I39: =H33*$G$1/I43*1000/365 -> 218.40928 | J39: =I39*(1+J40) -> 4193.4582 | K39: =J39*(1+K40) -> 13350.053 | L39: =K39*(1+L40) -> 28780.969 | M39: =L39*(1+M40) -> 46069.595 | N39: =M39*(1+N40) -> 68010.104 | O39: =N39*(1+O40) -> 93921.793 | P39: =O39*(1+P40) -> 122548.98 | Q39: =P39*(1+Q40) -> 152431.14 | ... S39: =R39*(1+S40) -> 210594.21
D40: yoy % | J40: 18.2 | K40: 2.1835426 | L40: 1.1558693 | M40: 0.60069647 | N40: 0.47624705 | O40: =N40*0.8 -> 0.38099764 | P40: =O40*0.8 -> 0.30479811 | Q40: =P40*0.8 -> 0.24383849 | R40: =Q40*0.8 -> 0.19507079 | S40: =R40*0.8 -> 0.15605663
C41: Blended API price (per 1M tokens) | I41: =0.7*7 -> 4.9 | J41: =I41*(1+J42) -> 7.84 | K41: =J41*(1+K42) -> 10.192 | L41: =K41*(1+L42) -> 12.2304 | M41: =L41*(1+M42) -> 15.89952 | N41: =M41*(1+N42) -> 19.715405 | O41: =N41*(1+O42) -> 23.500763 | P41: =O41*(1+P42) -> 27.11048 | Q41: =P41*(1+Q42) -> 30.441815 | ... S41: =R41*(1+S42) -> 36.063753
D42: yoy % | J42: 0.6 | K42: 0.3 | L42: 0.2 | M42: 0.3 | N42: 0.24 | O42: =N42*0.8 -> 0.192 | P42: =O42*0.8 -> 0.1536 | Q42: =P42*0.8 -> 0.12288 | R42: =Q42*0.8 -> 0.098304 | S42: =R42*0.8 -> 0.0786432
C43: Realized price | I43: =I41*(1-I45) -> 3.43 | J43: =J41*(1-J45) -> 5.88 | K43: =K41*(1-K45) -> 8.1536 | L43: =L41*(1-L45) -> 9.78432 | M43: =M41*(1-M45) -> 12.719616 | N43: =N41*(1-N45) -> 15.772324 | O43: =O41*(1-O45) -> 18.80061 | P43: =P41*(1-P45) -> 21.688384 | ... S43: =S41*(1-S45) -> 28.851003
D44: yoy % | J44: =J43/I43-1 -> 0.71428571 | K44: =K43/J43-1 -> 0.38666667 | L44: =L43/K43-1 -> 0.2 | M44: =M43/L43-1 -> 0.3 | N44: =N43/M43-1 -> 0.24 | O44: =O43/N43-1 -> 0.192 | P44: =P43/O43-1 -> 0.1536 | Q44: =Q43/P43-1 -> 0.12288 | ... S44: =S43/R43-1 -> 0.0786432
D45: discount % | I45: 0.3 | J45: 0.25 | K45: 0.2 | L45: 0.2 | M45: 0.2 | N45: 0.2 | O45: 0.2 | P45: 0.2 | Q45: 0.2 | R45: 0.2 | S45: 0.2
B46: Revenue from API | J46: =J39*365*J43/$G$1/1000 -> 1285.7143 | K46: =K39*365*K43/$G$1/1000 -> 5675.8016 | L46: =L39*365*L43/$G$1/1000 -> 14683.544 | M46: =M39*365*M43/$G$1/1000 -> 30555.065 | N46: =N39*365*N43/$G$1/1000 -> 55932.463 | O46: =O39*365*O43/$G$1/1000 -> 92073.179 | P46: =P39*365*P43/$G$1/1000 -> 138589.94 | Q46: =Q39*365*Q43/$G$1/1000 -> 193565.99 | ... S46: =S39*365*S43/$G$1/1000 -> 316812.4
B47: yoy % | K47: =K46/J46-1 -> 3.4145124 | L47: =L46/K46-1 -> 1.5870432
B48: % of API | J48: =J46/J33 -> 0.85739763 | K48: =K46/K33 -> 0.90580938 | L48: =L46/L33 -> 0.91537583
B50: b | C50: Subscription - coding plan
C51: # of paid users (mn) | I51: 0.06 | J51: =0.24-I51 -> 0.18 | K51: =J51*(1+K52) -> 0.414 | L51: =K51*(1+L52) -> 0.828 | M51: =L51*(1+M52) -> 1.4904 | N51: =M51*(1+N52) -> 2.444256 | O51: =N51*(1+O52) -> 3.6957151 | P51: =O51*(1+P52) -> 5.20948 | Q51: =P51*(1+Q52) -> 6.9165224 | R51: =Q51*(1+R52) -> 8.7296472 | S51: =R51*(1+S52) -> 10.560387
D52: yoy % | J52: =J51/I51-1 -> 2 | K52: 1.3 | L52: 1 | M52: =L52*0.8 -> 0.8 | N52: =M52*0.8 -> 0.64 | O52: =N52*0.8 -> 0.512 | P52: =O52*0.8 -> 0.4096 | Q52: =P52*0.8 -> 0.32768 | R52: =Q52*0.8 -> 0.262144 | S52: =R52*0.8 -> 0.2097152
D53: # of total users
D54: % of paid users
C55: Monthly price | J55: =49*0.5+149*0.5 -> 99 | K55: =J55*(1+K56) -> 118.8 | L55: =K55*(1+L56) -> 136.62 | M55: =L55*(1+M56) -> 157.113 | N55: =M55*(1+N56) -> 180.67995 | O55: =N55*(1+O56) -> 207.78194 | P55: =O55*(1+P56) -> 238.94923 | Q55: =P55*(1+Q56) -> 274.79162 | R55: =Q55*(1+R56) -> 316.01036 | S55: =R55*(1+S56) -> 363.41192
D56: yoy % | J56: 0.3 | K56: 0.2 | L56: 0.15 | M56: =L56 -> 0.15 | N56: =M56 -> 0.15 | O56: =N56 -> 0.15 | P56: =O56 -> 0.15 | Q56: =P56 -> 0.15 | R56: =Q56 -> 0.15 | S56: =R56 -> 0.15
B57: Revenue from coding plan subscription | J57: =J55*J51*12 -> 213.84 | K57: =K55*K51*12 -> 590.1984 | L57: =L55*L51*12 -> 1357.4563 | M57: =M55*M51*12 -> 2809.9346 | N57: =N55*N51*12 -> 5299.5366 | O57: =O55*O51*12 -> 9214.8343 | P57: =P55*P51*12 -> 14937.615 | Q57: =Q55*Q51*12 -> 22807.229 | ... S57: =S55*S51*12 -> 46053.245
D58: yoy % | K58: =K57/J57-1 -> 1.76 | L58: =L57/K57-1 -> 1.3 | M58: =M57/L57-1 -> 1.07 | N58: =N57/M57-1 -> 0.886 | O58: =O57/N57-1 -> 0.7388 | P58: =P57/O57-1 -> 0.62104 | Q58: =Q57/P57-1 -> 0.526832 | R58: =R57/Q57-1 -> 0.4514656 | S58: =S57/R57-1 -> 0.39117248
D59: % of API | J59: =J57/J33 -> 0.14260237 | K59: =K57/K33 -> 0.094190616 | L59: =L57/L33 -> 0.084624171 | M59: =M57/M33 -> 0.08421803 | N59: =N57/N33 -> 0.086548482
B61: Revenue breakdown %
B62: On-premise deployment | F62: =F27/F$5 -> 0.95481545 | G62: =G27/G$5 -> 0.90425412 | H62: =H27/H$5 -> 0.84480849 | I62: =I27/I$5 -> 0.73716683 | J62: =J27/J$5 -> 0.17206948 | K62: =K27/K$5 -> 0.075605896 | L62: =L27/L$5 -> 0.045330691 | M62: =M27/M$5 -> 0.031724622 | ... S62: =S27/S$5 -> 0.0099759797 | U62: =U27/U$5 -> 0.59689595 | V62: =V27/V$5 -> 0.88642829 | W62: =W27/W$5 -> 0.8475458 | X62: =X27/X$5 -> 0.69767198 | Y62: =Y27/Y$5 -> 0.34798086 | Z62: =Z27/Z$5 -> 0.13449369
B63: Cloud-based deployment | F63: =F29/F$5 -> 0.045184553 | G63: =G29/G$5 -> 0.095745877 | H63: =H29/H$5 -> 0.15519151 | I63: =I29/I$5 -> 0.26283317 | J63: =J29/J$5 -> 0.82793052 | K63: =K29/K$5 -> 0.9243941 | L63: =L29/L$5 -> 0.95466931 | M63: =M29/M$5 -> 0.96827538 | ... S63: =S29/S$5 -> 0.99002402 | U63: =U29/U$5 -> 0.40310405 | V63: =V29/V$5 -> 0.11357171 | W63: =W29/W$5 -> 0.1524542 | X63: =X29/X$5 -> 0.30232802 | Y63: =Y29/Y$5 -> 0.65201914 | Z63: =Z29/Z$5 -> 0.86550631
B66: Operating metrics
B67: Number of institutional customers | F67: =SUM(F68,F70) -> 48 | G67: =SUM(G68,G70) -> 2873 | H67: =SUM(H68,H70) -> 5580 | I67: 8000+
B68: On-premise deployment | F68: 48 | G68: 61 | H68: 123 | W68: 95
C69: yoy % | G69: =G68/F68-1 -> 0.27083333 | H69: =H68/G68-1 -> 1.0163934
B70: Cloud-based deployment | F70: 0 | G70: 2812 | H70: 5457 | W70: 3061
C71: yoy % | H71: =H70/G70-1 -> 0.94061166
B73: Implied ARPU
B74: On-premise deployment (Rmb mn) | F74: =F27/F68 -> 1.1419792 | G74: =G27/G68 -> 1.8461311 | H74: =H27/H68 -> 2.1457724 | W74: =W27/W68 -> 1.7029158
C75: yoy % | G75: =G74/F74-1 -> 0.61660668 | H75: =H74/G74-1 -> 0.16230765
B76: Cloud-based deployment (Rmb k) | G76: =G29*1000/G70 -> 4.2403983 | H76: =H29*1000/H70 -> 8.8847352 | W76: =W29*1000/W70 -> 9.5066972
C77: yoy % | H77: =H76/G76-1 -> 1.0952596
B79: Token
B80: Token consumption volume (bn) | F80: =F82*365 -> 182.5 | G80: =G82*365 -> 766.5 | H80: =H82*366 -> 73200 | W80: =W82*180 -> 828000
C81: yoy % | G81: =G80/F80-1 -> 3.2 | H81: =H80/G80-1 -> 94.499022
B82: Average daily token consumption volume (bn) | F82: 0.5 | G82: 2.1 | H82: 200 | W82: 4600
B84: On-premise deployment by industry:
C85: Internet and technology | F85: 30.258 | G85: 76.177 | H85: 130.956 | U85: 11.598 | W85: 61.924
C86: Public services | F86: 19.752 | G86: 10.267 | H86: 57.967 | U86: 0.693 | W86: 47.533
C87: Telecommunications | F87: 1.504 | G87: 21.742 | H87: 42.731 | U87: 13.748 | W87: 22.045
C88: Traditional corporate | F88: 2.198 | G88: 0.939 | H88: 26.559 | U88: 0.064 | W88: 18.679
C89: Consumer electronics | F89: 0.915 | G89: 0.241 | H89: 3.405 | U89: 0.042 | W89: 9.177
C90: Others | F90: 0.188 | G90: 3.248 | H90: 2.312 | U90: 0.661 | W90: 2.419
B92: On-premise deployment breakdown by industry:
C93: Internet and technology | F93: =F85/F$27 -> 0.55200219 | G93: =G85/G$27 -> 0.67644343 | H93: =H85/H$27 -> 0.49617702 | U93: =U85/U$27 -> 0.43266433 | W93: =W85/W$27 -> 0.38277382
C94: Public services | F94: =F86/F$27 -> 0.36033932 | G94: =G86/G$27 -> 0.091169837 | H94: =H86/H$27 -> 0.2196302 | U94: =U86/U$27 -> 0.025852421 | W94: =W86/W$27 -> 0.29381803
C95: Telecommunications | F95: =F87/F$27 -> 0.027437745 | G95: =G87/G$27 -> 0.19306658 | H95: =H87/H$27 -> 0.16190278 | U95: =U87/U$27 -> 0.51287025 | W95: =W87/W$27 -> 0.13626783
C96: Traditional corporate | F96: =F88/F$27 -> 0.040098513 | G96: =G88/G$27 -> 0.0083382173 | H96: =H88/H$27 -> 0.10062895 | U96: =U88/U$27 -> 0.0023875252 | W96: =W88/W$27 -> 0.11546141
C97: Consumer electronics | F97: =F89/F$27 -> 0.016692511 | G97: =G89/G$27 -> 0.0021400536 | H97: =H89/H$27 -> 0.012901148 | U97: =U89/U$27 -> 0.0015668134 | W97: =W89/W$27 -> 0.056726234
C98: Others | F98: =F90/F$27 -> 0.0034297181 | G98: =G90/G$27 -> 0.028841885 | H98: =H90/H$27 -> 0.0087598985 | U98: =U90/U$27 -> 0.024658659 | W98: =W90/W$27 -> 0.014952682
B100: On-premise deployment by regions:
C101: Mainland China | F101: 54.815 | G101: 112.614 | H101: 262.479 | U101: 26.806 | V101: =H101-U101 -> 235.673 | W101: 142.99
C102: SEA | F102: 0 | G102: 0 | H102: 1.08 | U102: 0 | V102: =H102-U102 -> 1.08 | W102: 17.927
C103: Hong Kong | F103: 0 | G103: 0 | H103: 0.371 | U103: 0 | V103: =H103-U103 -> 0.371 | W103: 0
C104: Others | U104: 0 | V104: =H104-U104 -> 0 | W104: 0.86
B106: On-premise deployment by regions yoy%
C107: Mainland China | G107: =G101/F101-1 -> 1.0544377 | H107: =H101/G101-1 -> 1.3307848 | W107: =W101/U101-1 -> 4.3342535
C108: SEA
C109: Hong Kong
C110: Others
B112: On-premise deployment breakdown by regions:
C113: Mainland China | F113: =F101/F$27 -> 1 | G113: =G101/G$27 -> 1 | H113: =H101/H$27 -> 0.99450233 | U113: =U101/U$27 -> 1 | V113: =V101/V$27 -> 0.99388084 | W113: =W101/W$27 -> 0.88387101
C114: SEA | H114: =H102/H$27 -> 0.0040919941 | V114: =V102/V$27 -> 0.004554579 | W114: =W102/W$27 -> 0.11081303
C115: Hong Kong | H115: =H103/H$27 -> 0.0014056757 | V115: =V103/V$27 -> 0.0015645822 | W115: =W103/W$27 -> 0
C116: Others | V116: =V104/V$27 -> 0 | W116: =W104/W$27 -> 0.0053159596
B118: Cost of sales | F118: =SUM(F121:F122) -> -26.049 | G118: =SUM(G121:G122) -> -44.056 | H118: =SUM(H121:H122) -> -136.525 | I118: =SUM(I121:I122) -> -427.678 | J118: =SUM(J121:J122) -> -4527.7268 | K118: =SUM(K121:K122) -> -17264.397 | L118: =SUM(L121:L122) -> -42438.455 | M118: =SUM(M121:M122) -> -85122.007 | ... S118: =SUM(S121:S122) -> -811651.86 | U118: =SUM(U121:U122) -> -22.95 | V118: =SUM(V121:V122) -> -113.575 | W118: =SUM(W121:W122) -> -95.453 | X118: =SUM(X121:X122) -> -332.225 | Y118: =SUM(Y121:Y122) -> -735.38446 | Z118: =SUM(Z121:Z122) -> -3792.3423
B119: yoy % | G119: =G118/F118-1 -> 0.69127414 | H119: =H118/G118-1 -> 2.0988969 | I119: =I118/H118-1 -> 2.1325984 | J119: =J118/I118-1 -> 9.5867657 | K119: =K118/J118-1 -> 2.8130386 | L119: =L118/K118-1 -> 1.4581487 | M119: =M118/L118-1 -> 1.0057753 | N119: =N118/M118-1 -> 0.77556341 | ... S119: =S118/R118-1 -> 0.24268 | W119: =W118/U118-1 -> 3.1591721 | X119: =X118/V118-1 -> 1.9251596 | Y119: =Y118/W118-1 -> 6.7041524 | Z119: =Z118/X118-1 -> 10.414982
B121: On-premise deployment | F121: -25.429 | G121: -35.833 | H121: -89.674 | I121: =-(I27*(1-I165)) -> -273.299 | J121: =-(J27*(1-J165)) -> -512.67016 | K121: =-(K27*(1-K165)) -> -816.14689 | L121: =-(L27*(1-L165)) -> -1172.9825 | M121: =-(M27*(1-M165)) -> -1626.0941 | N121: =-(N27*(1-N165)) -> -2192.6805 | O121: =-(O27*(1-O165)) -> -2831.8154 | P121: =-(P27*(1-P165)) -> -3575.8823 | ... S121: =-(S27*(1-S165)) -> -5182.9705 | U121: -10.03 | V121: =H121-U121 -> -79.644 | W121: -66.237 | X121: =I121-W121 -> -207.062 | Y121: =Y162-Y27 -> -182.48446 | Z121: =Z162-Z27 -> -330.18571
...

Sheet Y&Q
B4: December year-end (Rmb mn) | F4: 2022 | G4: 2023 | H4: 2024 | I4: 2025 | J4: 2026E | K4: 2027E | L4: 2028E | M4: 2029E | N4: 2030E | O4: 2031 | P4: 2032 | Q4: 2033 | R4: 2034 | S4: 2035 | U4: 1H24 | V4: 2H24 | W4: 1H25 | X4: 2H25 | Y4: 1H26E | Z4: 2H26E
C5: On-premise deployment | F5: =Revenue!F27 -> 54.815 | G5: =Revenue!G27 -> 112.614 | H5: =Revenue!H27 -> 263.93 | I5: =Revenue!I27 -> 533.955 | J5: =Revenue!J27 -> 1090.7876 | K5: =Revenue!K27 -> 1793.7294 | L5: =Revenue!L27 -> 2665.8694 | M5: =Revenue!M27 -> 3826.1037 | ... S5: =Revenue!S27 -> 12797.458 | U5: =Revenue!U27 -> 26.806 | V5: =Revenue!V27 -> 237.124 | W5: =Revenue!W27 -> 161.777 | X5: =Revenue!X27 -> 372.178 | Y5: =Revenue!Y27 -> 388.2648 | Z5: =Revenue!Z27 -> 702.52278
D6: yoy % | H6: =H5/G5-1 -> 1.3436695 | I6: =I5/H5-1 -> 1.0230932 | J6: =J5/I5-1 -> 1.0428455 | K6: =K5/J5-1 -> 0.64443515 | L6: =L5/K5-1 -> 0.48621599 | M6: =M5/L5-1 -> 0.43521802 | N6: =N5/M5-1 -> 0.38092633 | O6: =O5/N5-1 -> 0.32337419 | ... S6: =S5/R5-1 -> 0.066023378
C7: Cloud-based deployment | F7: =Revenue!F29 -> 2.594 | G7: =Revenue!G29 -> 11.924 | H7: =Revenue!H29 -> 48.484 | I7: =Revenue!I29 -> 190.379 | J7: =Revenue!J29 -> 5248.44 | K7: =Revenue!K29 -> 21931 | L7: =Revenue!L29 -> 56143.5 | M7: =Revenue!M29 -> 116777.5 | ... S7: =Revenue!S29 -> 1270029.7 | U7: =Revenue!U29 -> 18.103 | V7: =Revenue!V29 -> 30.381 | W7: =Revenue!W29 -> 29.1 | X7: =Revenue!X29 -> 161.279 | Y7: =Revenue!Y29 -> 727.5 | Z7: =Revenue!Z29 -> 4520.94
D8: yoy % | H8: =H7/G7-1 -> 3.0660852 | I8: =I7/H7-1 -> 2.9266356 | J8: =J7/I7-1 -> 26.568377 | K8: =K7/J7-1 -> 3.178575 | L8: =L7/K7-1 -> 1.5600064 | M8: =M7/L7-1 -> 1.0799825 | N8: =N7/M7-1 -> 0.83521654 | O8: =O7/N7-1 -> 0.65416798 | ... S8: =S7/R7-1 -> 0.26359551
B9: Revenue | F9: =Revenue!F5 -> 57.409 | G9: =Revenue!G5 -> 124.538 | H9: =Revenue!H5 -> 312.414 | I9: =Revenue!I5 -> 724.334 | J9: =Revenue!J5 -> 6339.2276 | K9: =Revenue!K5 -> 23724.729 | L9: =Revenue!L5 -> 58809.369 | M9: =Revenue!M5 -> 120603.6 | ... S9: =Revenue!S5 -> 1282827.2 | U9: =Revenue!U5 -> 44.909 | V9: =Revenue!V5 -> 267.505 | W9: =Revenue!W5 -> 190.877 | X9: =Revenue!X5 -> 533.457 | Y9: =Revenue!Y5 -> 1115.7648 | Z9: =Revenue!Z5 -> 5223.4628
C10: yoy % | H10: =H9/G9-1 -> 1.5085837 | I10: =I9/H9-1 -> 1.3185069 | J10: =J9/I9-1 -> 7.7518018 | K10: =K9/J9-1 -> 2.7425269 | L10: =L9/K9-1 -> 1.4788215 | M10: =M9/L9-1 -> 1.0507549 | N10: =N9/M9-1 -> 0.82080436 | O10: =O9/N9-1 -> 0.64620893 | ... S10: =S9/R9-1 -> 0.26126355
C11: Cost of sales | F11: =Model!F7 -> -26.049 | G11: =Model!G7 -> -44.056 | H11: =Model!H7 -> -136.525 | I11: =Model!I7 -> -427.678 | J11: =Model!J7 -> -4527.7268 | K11: =Model!K7 -> -17264.397 | L11: =Model!L7 -> -42438.455 | M11: =Model!M7 -> -85122.007 | ... S11: =Model!S7 -> -811651.86 | U11: =Model!U7 -> -22.95 | V11: =Model!V7 -> -113.575 | W11: =Model!W7 -> -95.453 | X11: =Model!X7 -> -332.225 | Y11: =Model!Y7 -> -735.38446 | Z11: =Model!Z7 -> -3792.3423
D12: Amongst which: Inference cost | F12: =Revenue!F130 -> 0 | G12: =Revenue!G130 -> -11.996 | H12: =Revenue!H130 -> -30.173 | I12: =Revenue!I130 -> 0 | J12: =Revenue!J130 -> 0 | K12: =Revenue!K130 -> 0 | L12: =Revenue!L130 -> 0 | M12: =Revenue!M130 -> 0 | ... S12: =Revenue!S130 -> 0 | U12: =Revenue!U130 -> -8.451 | V12: =Revenue!V130 -> -21.722 | W12: =Revenue!W130 -> -35.845 | X12: =Revenue!X130 -> 0 | Y12: =Revenue!Y130 -> 0 | Z12: =Revenue!Z130 -> 0
B14: Gross (loss)/profit | F14: =Model!F9 -> 31.36 | G14: =Model!G9 -> 80.482 | H14: =Model!H9 -> 175.889 | I14: =Model!I9 -> 296.656 | J14: =Model!J9 -> 1811.5008 | K14: =Model!K9 -> 6460.3325 | L14: =Model!L9 -> 16370.914 | M14: =Model!M9 -> 35481.597 | ... S14: =Model!S9 -> 471175.34 | U14: =Model!U9 -> 21.959 | V14: =Model!V9 -> 153.93 | W14: =Model!W9 -> 95.424 | X14: =Model!X9 -> 201.232 | Y14: =Model!Y9 -> 380.38034 | Z14: =Model!Z9 -> 1431.1205
C15: yoy % | H15: =-(H14/G14-1) -> -1.1854452 | I15: =I14/H14-1 -> 0.68660917 | J15: =J14/I14-1 -> 5.1064021 | K15: =K14/J14-1 -> 2.5662874 | L15: =L14/K14-1 -> 1.5340668 | M15: =M14/L14-1 -> 1.1673559 | N15: =N14/M14-1 -> 0.9293395 | O15: =O14/N14-1 -> 0.74382603 | P15: =P14/O14-1 -> 0.55194837 | ... S15: =S14/R14-1 -> 0.29461363
C16: GP Margin % | G16: =G14/G9 -> 0.64624452 | H16: =H14/H9 -> 0.56299974 | I16: =I14/I9 -> 0.40955692 | J16: =J14/J9 -> 0.2857605 | K16: =K14/K9 -> 0.27230374 | L16: =L14/L9 -> 0.27837255 | M16: =M14/M9 -> 0.29420014 | N16: =N14/N9 -> 0.31173693 | ... S16: =S14/S9 -> 0.36729448 | U16: =U14/U9 -> 0.48896658 | V16: =V14/V9 -> 0.5754285 | W16: =W14/W9 -> 0.49992403 | X16: =X14/X9 -> 0.37722253 | Y16: =Y14/Y9 -> 0.34091445 | Z16: =Z14/Z9 -> 0.27397926
C18: Other income | I18: =Model!F13 -> 1.784 | J18: =Model!G13 -> 9.965 | K18: =Model!H13 -> 19.281 | L18: =Model!I13 -> 14.839 | M18: =Model!J13 -> 33.14836 | N18: =Model!K13 -> 432.84256 | O18: =Model!L13 -> 199.21519 | P18: =Model!M13 -> 414.59592 | ... S18: =Model!P13 -> 1673.757 | U18: =Model!R13 -> 4958.4363 | V18: =Model!S13 -> 7823.4091 | W18: =Model!T13 -> 0 | X18: =Model!U13 -> 4.174 | Y18: =Model!V13 -> 15.107 | Z18: =Model!W13 -> 4.614
C19: Selling and distribution expenses | F19: =Model!F14 -> -15.139 | G19: =Model!G14 -> -101.198 | H19: =Model!H14 -> -387.475 | I19: =Model!I14 -> -390.869 | J19: =Model!J14 -> -508.1297 | K19: =Model!K14 -> -736.78807 | L19: =Model!L14 -> -1105.1821 | M19: =Model!M14 -> -1602.514 | ... S19: =Model!S14 -> -8288.5624 | U19: =Model!U14 -> -144.194 | V19: =Model!V14 -> -243.281 | W19: =Model!W14 -> -208.57 | X19: =Model!X14 -> -182.299 | Y19: =Model!Y14 -> -245.46826 | Z19: =Model!Z14 -> -262.66144
C20: Administrative expenses | F20: =Model!F15 -> -32.316 | G20: =Model!G15 -> -66.302 | H20: =Model!H15 -> -133.603 | I20: =Model!I15 -> -505.357 | J20: =Model!J15 -> -656.9641 | K20: =Model!K15 -> -952.59794 | L20: =Model!L15 -> -1428.8969 | M20: =Model!M15 -> -2071.9005 | ... S20: =Model!S15 -> -10716.335 | U20: =Model!U15 -> -51.452 | V20: =Model!V15 -> -82.151 | W20: =Model!W15 -> -185.165 | X20: =Model!X15 -> -320.192 | Y20: =Model!Y15 -> -334.72944 | Z20: =Model!Z15 -> -322.23466
C21: Research and development expenses | F21: =Model!F16 -> -84.377 | G21: =Model!G16 -> -528.884 | H21: =Model!H16 -> -2195.436 | I21: =Model!I16 -> -3180.443 | J21: =Model!J16 -> -5724.7974 | K21: =Model!K16 -> -10877.115 | L21: =Model!L16 -> -16304.795 | M21: =Model!M16 -> -26087.673 | ... S21: =Model!S16 -> -104512.45 | U21: =Model!U16 -> -859.217 | V21: =Model!V16 -> -1336.219 | W21: =Model!W16 -> -1594.661 | X21: =Model!X16 -> -1585.782 | Y21: =Model!Y16 -> -2789.412 | Z21: =Model!Z16 -> -2935.3854
D22: Amongst which: Training cost | F22: =-Model!F97 -> -14.633 | G22: =-Model!G97 -> -311.746 | H22: =-Model!H97 -> -1552.832 | I22: =-Model!I97 -> -2249.5275 | J22: =-Model!J97 -> -4049.1495 | K22: =-Model!K97 -> -7693.3841 | L22: =-Model!L97 -> -11532.383 | M22: =-Model!M97 -> -18451.812 | ... S22: =-Model!S97 -> -73921.662 | U22: =-Model!U97 -> -603.237 | V22: =-Model!V97 -> -949.595 | W22: =-Model!W97 -> -1145.124 | X22: =-Model!X97 -> 0 | Y22: =-Model!Y97 -> 0 | Z22: =-Model!Z97 -> 0
B24: Operating profit | F24: =Model!F19 -> -98.719 | G24: =Model!G19 -> -625.723 | H24: =Model!H19 -> -2538.352 | I24: =Model!I19 -> -3786.75 | J24: =Model!J19 -> -5045.242 | K24: =Model!K19 -> -5673.326 | L24: =Model!L19 -> -2268.745 | M24: =Model!M19 -> 6134.1057 | ... S24: =Model!S19 -> 355481.4 | U24: =Model!U19 -> -1029.493 | V24: =Model!V19 -> -1508.859 | W24: =Model!W19 -> -1899.225 | X24: =Model!X19 -> -1887.525 | Y24: =Model!Y19 -> -2972.4929 | Z24: =Model!Z19 -> -2072.7491
B25: Adj. operating profit - non-IFRS | F25: =Model!F23 -> -97.695 | G25: =Model!G23 -> -620.221 | H25: =Model!H23 -> -2514.773 | I25: =Model!I23 -> -3228.485 | J25: =Model!J23 -> -4375.324 | K25: =Model!K23 -> -4869.4244 | L25: =Model!L23 -> -1304.063 | M25: =Model!M23 -> 7195.2558 | ... S25: =Model!S23 -> 357361.3 | U25: =Model!U23 -> -1025.276 | V25: =Model!V23 -> -1489.497 | W25: =Model!W23 -> -1740.373 | X25: =Model!X23 -> -1488.112 | Y25: =Model!Y23 -> -2637.5339 | Z25: =Model!Z23 -> -1737.7901
C26: yoy % | G26: =-(G25/F25-1) -> -5.3485439 | H26: =-(H25/G25-1) -> -3.0546402 | I26: =-(I25/H25-1) -> -0.28380772 | J26: =-(J25/I25-1) -> -0.35522514 | K26: =-(K25/J25-1) -> -0.11292886 | L26: =-(L25/K25-1) -> 0.73219359 | M26: =-(M25/L25-1) -> 6.5175675 | N26: =N25/M25-1 -> 2.4168297 | O26: =O25/N25-1 -> 1.3805335 | P26: =P25/O25-1 -> 0.84362507 | Q26: =Q25/P25-1 -> 0.62598871 | R26: =R25/Q25-1 -> 0.47975801 | S26: =S25/R25-1 -> 0.37652092 | W26: =-(W25/U25-1) -> -0.6974678 | X26: =-(X25/V25-1) -> 0.0009298441 | Y26: =-(Y25/W25-1) -> -0.51549919 | Z26: =-(Z25/X25-1) -> -0.16778182
C27: OP Margin % | G27: =G25/G9 -> -4.9801747 | H27: =H25/H9 -> -8.0494888 | I27: =I25/I9 -> -4.4571772 | J27: =J25/J9 -> -0.69019829 | K27: =K25/K9 -> -0.20524678 | L27: =L25/L5 -> -0.4891699 | M27: =M25/M5 -> 1.88057 | N27: =N25/N5 -> 4.6530993 | O27: =O25/O5 -> 8.3701637 | P27: =P25/P5 -> 12.220481 | Q27: =Q25/Q5 -> 16.5673 | R27: =R25/R5 -> 21.625577 | S27: =S25/S5 -> 27.924397 | W27: =W25/W9 -> -9.1177722 | X27: =X25/X9 -> -2.7895632 | Y27: =Y25/Y9 -> -2.3638798 | Z27: =Z25/Z9 -> -0.33268929
B29: (Loss)/Profit before tax | F29: =Model!F32 -> -143.65 | G29: =Model!G32 -> -787.977 | H29: =Model!H32 -> -2958.007 | I29: =Model!I32 -> -4718.167 | J29: =Model!J32 -> -5080.9477 | K29: =Model!K32 -> -5709.0316 | L29: =Model!L32 -> -2304.4506 | M29: =Model!M32 -> 6098.4001 | ... S29: =Model!S32 -> 355445.7 | U29: =Model!U32 -> -1235.551 | V29: =Model!V32 -> -1722.456 | W29: =Model!W32 -> -2357.852 | X29: =Model!X32 -> -2360.315 | Y29: =Model!Y32 -> -2990.3457 | Z29: =Model!Z32 -> -2090.602
C30: Income tax expense | F30: =Model!F33 -> 0 | G30: =Model!G33 -> 0 | H30: =Model!H33 -> 0 | I30: =Model!I33 -> 0 | J30: =Model!J33 -> 0 | K30: =Model!K33 -> 0 | L30: =Model!L33 -> 0 | M30: =Model!M33 -> -1097.712 | ... S30: =Model!S33 -> -63980.226 | U30: =Model!U33 -> 0 | V30: =Model!V33 -> 0 | W30: =Model!W33 -> 0 | X30: =Model!X33 -> 0 | Y30: =Model!Y33 -> 0 | Z30: =Model!Z33 -> 0
B31: Net profit/(loss) | F31: =Model!F35 -> -143.65 | G31: =Model!G35 -> -787.977 | H31: =Model!H35 -> -2958.007 | I31: =Model!I35 -> -4718.167 | J31: =Model!J35 -> -5080.9477 | K31: =Model!K35 -> -5709.0316 | L31: =Model!L35 -> -2304.4506 | M31: =Model!M35 -> 5000.6881 | ... S31: =Model!S35 -> 291465.47 | U31: =Model!U35 -> -1235.551 | V31: =Model!V35 -> -1722.456 | W31: =Model!W35 -> -2357.852 | X31: =Model!X35 -> -2360.315 | Y31: =Model!Y35 -> -2990.3457 | Z31: =Model!Z35 -> -2090.602
B32: Adj. net profit/(loss) - non-IFRS | F32: =Model!F50 -> -97.417 | G32: =Model!G50 -> -621.004 | H32: =Model!H50 -> -2465.569 | I32: =Model!I50 -> -3181.972 | J32: =Model!J50 -> -4411.0297 | K32: =Model!K50 -> -4905.13 | L32: =Model!L50 -> -1339.7687 | M32: =Model!M50 -> 6061.8382 | ... S32: =Model!S50 -> 293345.36 | U32: =Model!U50 -> -1030.16 | V32: =Model!V50 -> -1435.409 | W32: =Model!W50 -> -1751.974 | X32: =Model!X50 -> -1429.998 | Y32: =Model!Y50 -> -2655.3867 | Z32: =Model!Z50 -> -1755.643
C33: yoy % | G33: =-(G32/F32-1) -> -5.3746985 | H33: =-(H32/G32-1) -> -2.9702949 | I33: =-(I32/H32-1) -> -0.29056295 | J33: =-(J32/I32-1) -> -0.3862566 | K33: =-(K32/J32-1) -> -0.11201474 | L33: =-(L32/K32-1) -> 0.72686377 | M33: =-(M32/L32-1) -> 5.5245408 | N33: =N32/M32-1 -> 2.3555002 | O33: =O32/N32-1 -> 1.3692934 | P33: =P32/O32-1 -> 0.84057138 | Q33: =Q32/P32-1 -> 0.62468779 | R33: =R32/Q32-1 -> 0.47911855 | S33: =S32/R32-1 -> 0.37617358 | W33: =-(W32/U32-1) -> -0.70068145 | X33: =-(X32/V32-1) -> 0.0037696573 | Y33: =-(Y32/W32-1) -> -0.51565418 | Z33: =-(Z32/X32-1) -> -0.22772408
C34: NP Margin % | G34: =G32/G9 -> -4.986462 | H34: =H32/H9 -> -7.8919927 | I34: =I32/I9 -> -4.3929624 | J34: =J32/J9 -> -0.69583078 | K34: =K32/K9 -> -0.20675178 | L34: =L32/L9 -> -0.022781552 | M34: =M32/M9 -> 0.050262496 | N34: =N32/N9 -> 0.092627095 | ... S34: =S32/S9 -> 0.22867099 | W34: =W32/W9 -> -9.1785495 | X34: =X32/X9 -> -2.6806247 | Y34: =Y32/Y9 -> -2.3798803 | Z34: =Z32/Z9 -> -0.33610711
B36: GPM | G36: =G14/G9 -> 0.64624452 | H36: =H14/H9 -> 0.56299974 | I36: =I14/I9 -> 0.40955692 | J36: =J14/J9 -> 0.2857605 | K36: =K14/K9 -> 0.27230374 | L36: =L14/L9 -> 0.27837255 | M36: =M14/M9 -> 0.29420014 | N36: =N14/N9 -> 0.31173693 | ... S36: =S14/S9 -> 0.36729448 | U36: =U14/U9 -> 0.48896658 | V36: =V14/V9 -> 0.5754285 | W36: =W14/W9 -> 0.49992403 | X36: =X14/X9 -> 0.37722253 | Y36: =Y14/Y9 -> 0.34091445 | Z36: =Z14/Z9 -> 0.27397926
B37: Adj. OPM | G37: =G25/G9 -> -4.9801747 | H37: =H25/H9 -> -8.0494888 | I37: =I25/I9 -> -4.4571772 | J37: =J25/J9 -> -0.69019829 | K37: =K25/K9 -> -0.20524678 | L37: =L25/L5 -> -0.4891699 | M37: =M25/M5 -> 1.88057 | N37: =N25/N5 -> 4.6530993 | O37: =O25/O5 -> 8.3701637 | P37: =P25/P5 -> 12.220481 | Q37: =Q25/Q5 -> 16.5673 | R37: =R25/R5 -> 21.625577 | S37: =S25/S5 -> 27.924397 | U37: =U25/U5 -> -38.248004 | V37: =V25/V5 -> -6.2815109 | W37: =W25/W5 -> -10.757852 | X37: =X25/X5 -> -3.9983879 | Y37: =Y25/Y5 -> -6.7931316 | Z37: =Z25/Z5 -> -2.4736424
B38: Adj. NPM | G38: =G32/G9 -> -4.986462 | H38: =H32/H9 -> -7.8919927 | I38: =I32/I9 -> -4.3929624 | J38: =J32/J9 -> -0.69583078 | K38: =K32/K9 -> -0.20675178 | L38: =L32/L9 -> -0.022781552 | M38: =M32/M9 -> 0.050262496 | N38: =N32/N9 -> 0.092627095 | ... S38: =S32/S9 -> 0.22867099 | U38: =U32/U9 -> -22.938832 | V38: =V32/V9 -> -5.3659147 | W38: =W32/W9 -> -9.1785495 | X38: =X32/X9 -> -2.6806247 | Y38: =Y32/Y9 -> -2.3798803 | Z38: =Z32/Z9 -> -0.33610711

Sheet DCF+base-bull-bear
C1: 7
B2: Total market TAM - US$ mn | F2: 392.74387 | G2: 4963.0775 | H2: 15407.533 | I2: 36237.021 | J2: 71860.359 | K2: 125614.64
B3: Total market TAM - Rmb mn | F3: =F2*$C$1 -> 2749.2071 | G3: =G2*$C$1 -> 34741.542 | H3: =H2*$C$1 -> 107852.73 | I3: =I2*$C$1 -> 253659.15 | J3: =J2*$C$1 -> 503022.52 | K3: =K2*$C$1 -> 879302.5
B4: (Rmb mn) | C4: 2022 | D4: 2023 | E4: 2024 | F4: 2025 | G4: 2026 | H4: 2027 | I4: 2028 | J4: 2029 | K4: 2030 | L4: =K4+1 -> 2031 | M4: =L4+1 -> 2032 | N4: =M4+1 -> 2033 | O4: =N4+1 -> 2034 | P4: =O4+1 -> 2035 | R4: 2031-35E
B5: Revenue | C5: =Model!F4 -> 57.409 | D5: =Model!G4 -> 124.538 | E5: =Model!H4 -> 312.414 | F5: =Model!I4 -> 724.334 | G5: =Model!J4 -> 6339.2276 | H5: =Model!K4 -> 23724.729 | I5: =Model!L4 -> 58809.369 | J5: =Model!M4 -> 120603.6 | K5: =Model!N4 -> 219595.57 | L5: =K5*(1+L6) -> 340746.44 | M5: =L5*(1+M6) -> 472339.31 | N5: =M5*(1+N6) -> 581786.94 | O5: =N5*(1+O6) -> 639965.64 | P5: =O5*(1+P6) -> 671963.92 | R5: =SUM(L5:P5) -> 2706802.2
B6: yoy % | E6: =E5/D5-1 -> 1.5085837 | F6: =F5/E5-1 -> 1.3185069 | G6: =G5/F5-1 -> 7.7518018 | H6: =H5/G5-1 -> 2.7425269 | I6: =I5/H5-1 -> 1.4788215 | J6: =J5/I5-1 -> 1.0507549 | K6: =K5/J5-1 -> 0.82080436 | L6: 0.5517 | M6: =L6*0.7 -> 0.38619 | N6: =M6*0.6 -> 0.231714 | O6: 0.1 | P6: 0.05
B7: Amongst which: Open platform API revenue | E7: =Revenue!H9 -> 48.484 | F7: =Revenue!I9 -> 190.379 | G7: =Revenue!J9 -> 5248.44 | H7: =Revenue!K9 -> 21931 | I7: =Revenue!L9 -> 56143.5 | J7: =Revenue!M9 -> 116777.5 | K7: =Revenue!N9 -> 214312
B8: Implied % of China AI model revenue pool | G8: =G7/G$3 -> 0.15107101 | H8: =H7/H$3 -> 0.20334209 | I8: =I7/I$3 -> 0.22133442 | J8: =J7/J$3 -> 0.23215164 | K8: =K7/K$3 -> 0.24372955
B9: Incremental market share gain | H9: =H8-G8 -> 0.052271081 | I9: =I8-H8 -> 0.017992326 | J9: =J8-I8 -> 0.010817217 | K9: =K8-J8 -> 0.011577911
B11: Training cost as % of revenue | D11: =Model!G97/'DCF+base-bull-bear'!D5 -> 2.5032199 | E11: =Model!H97/'DCF+base-bull-bear'!E5 -> 4.9704303 | F11: =Model!I97/'DCF+base-bull-bear'!F5 -> 3.1056495 | G11: =Model!J97/'DCF+base-bull-bear'!G5 -> 0.63874493 | H11: =Model!K97/'DCF+base-bull-bear'!H5 -> 0.324277 | I11: =Model!L97/'DCF+base-bull-bear'!I5 -> 0.19609771 | J11: =Model!M97/'DCF+base-bull-bear'!J5 -> 0.15299553 | K11: =Model!N97/'DCF+base-bull-bear'!K5 -> 0.13024083 | ... P11: =Model!S97/'DCF+base-bull-bear'!P5 -> 0.11000838
B13: Non-GAAP operating profit | C13: =Model!F23 -> -97.695 | D13: =Model!G23 -> -620.221 | E13: =Model!H23 -> -2514.773 | F13: =Model!I23 -> -3228.485 | G13: =Model!J23 -> -4375.324 | H13: =Model!K23 -> -4869.4244 | I13: =Model!L23 -> -1304.063 | J13: =Model!M23 -> 7195.2558 | K13: =Model!N23 -> 24584.964 | L13: =L5*L14 -> 61334.36 | M13: =M5*M14 -> 94467.862 | N13: =N5*N14 -> 127993.13 | O13: =O5*O14 -> 154871.68 | P13: =P5*P14 -> 176054.55 | R13: =SUM(L13:P13) -> 614721.58
B14: Non-GAAP operating margin % | D14: =D13/D5 -> -4.9801747 | E14: =E13/E5 -> -8.0494888 | F14: =F13/F5 -> -4.4571772 | G14: =G13/G5 -> -0.69019829 | H14: =H13/H5 -> -0.20524678 | I14: =I13/I5 -> -0.022174409 | J14: =J13/J5 -> 0.059660372 | K14: =K13/K5 -> 0.11195565 | L14: 0.18 | M14: 0.2 | N14: 0.22 | O14: 0.242 | P14: 0.262 | R14: =R13/R5 -> 0.22710251
B15: Income tax rate % | C15: =IF(C13<0,0%,-18%) -> 0 | D15: =IF(D13<0,0%,-18%) -> 0 | E15: =IF(E13<0,0%,-18%) -> 0 | F15: =IF(F13<0,0%,-18%) -> 0 | G15: =IF(G13<0,0%,-18%) -> 0 | H15: =IF(H13<0,0%,-18%) -> 0 | I15: =IF(I13<0,0%,-18%) -> 0 | J15: =IF(J13<0,0%,-18%) -> -0.18 | ... P15: =IF(P13<0,0%,-18%) -> -0.18 | R15: =R16/R13 -> -0.18
B16: Income tax expenses | C16: =C15*C13 -> 0 | D16: =D15*D13 -> 0 | E16: =E15*E13 -> 0 | F16: =F15*F13 -> 0 | G16: =G15*G13 -> 0 | H16: =H15*H13 -> 0 | I16: =I15*I13 -> 0 | J16: =J15*J13 -> -1295.1461 | ... P16: =P15*P13 -> -31689.818 | R16: =SUM(L16:P16) -> -110649.88
B17: NOPAT (adjusted) | C17: =C13+C16 -> -97.695 | D17: =D13+D16 -> -620.221 | E17: =E13+E16 -> -2514.773 | F17: =F13+F16 -> -3228.485 | G17: =G13+G16 -> -4375.324 | H17: =H13+H16 -> -4869.4244 | I17: =I13+I16 -> -1304.063 | J17: =J13+J16 -> 5900.1098 | ... P17: =P13+P16 -> 144364.73 | R17: =SUM(L17:P17) -> 504071.69
B18: Depreciation & amortization | C18: =Model!F209+Model!F238 -> 20.018 | D18: =Model!G209+Model!G238 -> 68.931 | E18: =Model!H209+Model!H238 -> 279.937 | F18: =Model!I209+Model!I238 -> 281.061 | G18: =Model!J209+Model!J238 -> 143.61724 | H18: =Model!K209+Model!K238 -> 143.14779 | I18: =Model!L209+Model!L238 -> 48.242611 | J18: =Model!M209+Model!M238 -> 29.841016 | ... P18: =Model!S209+Model!S238 -> 55.781994 | R18: =SUM(L18:P18) -> 232.60341
B19: Change in working capital | C19: =SUM(Model!F255:F261) -> 9.893 | D19: =SUM(Model!G255:G261) -> -96.09 | E19: =SUM(Model!H255:H261) -> -0.026 | F19: =SUM(Model!I255:I261) -> 704.286 | G19: =SUM(Model!J255:J261) -> 1881.9336 | H19: =SUM(Model!K255:K261) -> 2300.1187 | I19: =SUM(Model!L255:L261) -> 2445.5425 | J19: =SUM(Model!M255:M261) -> 2289.5281 | ... P19: =SUM(Model!S255:S261) -> -19218.455 | R19: =SUM(L19:P19) -> -35526.462
B20: Capital expenditures | C20: =-Model!F190-Model!F219 -> -31.651 | D20: =-Model!G190-Model!G219 -> -508.569 | E20: =-Model!H190-Model!H219 -> -132.76 | F20: =-Model!I190-Model!I219 -> -23.088 | G20: =-Model!J190-Model!J219 -> -27.7056 | H20: =-Model!K190-Model!K219 -> -31.85508 | I20: =-Model!L190-Model!L219 -> -35.040588 | J20: =-Model!M190-Model!M219 -> -38.544647 | ... P20: =-Model!S190-Model!S219 -> -68.284193 | R20: =SUM(L20:P20) -> -284.7359
B21: Free cash flow | C21: =C17+C18+C19+C20 -> -99.435 | D21: =D17+D18+D19+D20 -> -1155.949 | E21: =E17+E18+E19+E20 -> -2367.622 | F21: =F17+F18+F19+F20 -> -2266.226 | G21: =G17+G18+G19+G20 -> -2377.4788 | H21: =H17+H18+H19+H20 -> -2458.013 | I21: =I17+I18+I19+I20 -> 1154.6815 | J21: =J17+J18+J19+J20 -> 8180.9342 | ... P21: =P17+P18+P19+P20 -> 125133.77 | R21: =SUM(L21:P21) -> 468493.1
B22: Free cash flow (with terminal value), 12% WACC | C22: =C21 -> -99.435 | D22: =D21 -> -1155.949 | E22: =E21 -> -2367.622 | F22: =F21 -> -2266.226 | G22: =G21 -> -2377.4788 | H22: =H21 -> -2458.013 | I22: =I21 -> 1154.6815 | J22: =J21 -> 8180.9342 | ... O22: =O21 -> 113426.96 | P22: =$P$21*(1+$C$48)*$C$50+$P$21 -> 1560461.6 | R22: =SUM(L22:P22) -> 1903820.9
B23: FCF margin | C23: =IF(C21<0,0,C21/C5) -> 0 | D23: =IF(D21<0,0,D21/D5) -> 0 | E23: =IF(E21<0,0,E21/E5) -> 0 | F23: =IF(F21<0,0,F21/F5) -> 0 | G23: =IF(G21<0,0,G21/G5) -> 0 | H23: =IF(H21<0,0,H21/H5) -> 0 | I23: =IF(I21<0,0,I21/I5) -> 0.019634311 | J23: =IF(J21<0,0,J21/J5) -> 0.067833249 | ... P23: =IF(P21<0,0,P21/P5) -> 0.18622097 | R23: =IF(R21<0,0,R21/R5) -> 0.17307991
B24: Discount factor | C24: =D24 -> 1 | D24: =E24 -> 1 | E24: =F24 -> 1 | F24: =G24 -> 1 | G24: =1/(1+$C$48)^(G4-$G$4) -> 1 | H24: =1/(1+$C$48)^(H4-$G$4) -> 0.8914245 | I24: =1/(1+$C$48)^(I4-$G$4) -> 0.79463763 | J24: =1/(1+$C$48)^(J4-$G$4) -> 0.70835945 | K24: =1/(1+$C$48)^(K4-$G$4) -> 0.63144897 | L24: =1/(1+$C$48)^(L4-$G$4) -> 0.56288908 | M24: =1/(1+$C$48)^(M4-$G$4) -> 0.50177311 | N24: =1/(1+$C$48)^(N4-$G$4) -> 0.44729284 | ... P24: =1/(1+$C$48)^(P4-$G$4) -> 0.35543573
B27: Firm value (discount to 2026E, Rmb mn) | C27: =NPV(C48,H22:P22) -> 731848.32
B28: Net cash (2026E) | C28: =Model!J169 -> 29767.347
B29: Equity valuation (discount to 2026E, Rmb mn) | C29: =C27+C28 -> 761615.67
B30: Equity valuation (discount to 2026E, HK$ mn) | C30: =C29/C52 -> 875420.31
B31: Terminal value as % of total | C31: =P22/(1+$C$48)^(P4-G4)/C29 -> 0.72824632
B33: Shares outstanding (mn) | C33: =Model!Z55 -> 465.62309
B34: Target Price (HK$) | C34: =ROUND(C30/C33,0) -> 1880
B36: WACC calculation | C36: High-end
B37: Equity component
B38: Equity market premium | C38: 0.07
B39: Risk free rate | C39: 0.035
B40: Beta | C40: 1.24
B41: Cost of equity | C41: =+C39+C38*C40 -> 0.1218
B43: Debt component
B44: Cost of debt | C44: 0.05
B45: Tax rate | C45: 0.15
B46: After-tax cost of debt | C46: =C44*(1-C45) -> 0.0425
B48: WACC | C48: =C41 -> 0.1218
B49: Terminal growth rate | C49: 0.024
B50: Implied exit FCF multiple | C50: =1/(C48-C49) -> 10.224949
B52: CNY/HKD | C52: 0.87
B55: Reverse DCF - bull case
B56: Revenue | C56: =C5 -> 57.409 | D56: =D5 -> 124.538 | E56: =E5 -> 312.414 | F56: =F5 -> 724.334 | G56: =G5 -> 6339.2276 | H56: =H5 -> 23724.729 | I56: =I68/(1-I66)+I64 -> 62626.764 | J56: =J68/(1-J66)+J64 -> 146182.83 | K56: =K68/(1-K66)+K64 -> 294251.51 | L56: =L68/(1-L66)+L64 -> 456723.58 | M56: =M68/(1-M66)+M64 -> 647302.2 | N56: =N68/(1-N66)+N64 -> 808694.22 | O56: =O68/(1-O66)+O64 -> 873582.6 | P56: =P68/(1-P66)+P64 -> 912110.64
B57: yoy % | G57: =G56/F56-1 -> 7.7518018 | H57: =H56/G56-1 -> 2.7425269 | I57: =I56/H56-1 -> 1.6397251 | J57: =J56/I56-1 -> 1.3341911 | K57: =K56/J56-1 -> 1.0129006 | L57: =L56/K56-1 -> 0.55215375 | M57: =M56/L56-1 -> 0.41727343 | N57: =N56/M56-1 -> 0.24933025 | ... P57: =P56/O56-1 -> 0.044103486
B58: Amongst which: open platform API revenue | G58: =G56*G62 -> 5248.44 | H58: =H56*H62 -> 21931 | I58: =I56*I62 -> 59787.849 | J58: =J56*J62 -> 141545.24 | K58: =K56*K62 -> 287171.69
B59: Implied % of market penetration | G59: =G58/G$3 -> 0.15107101 | H59: =H58/H$3 -> 0.20334209 | I59: =I58/I$3 -> 0.23570153 | J59: =J58/J$3 -> 0.28138947 | K59: =K58/K$3 -> 0.32659032
B60: Incremental market share gain | H60: =H59-G59 -> 0.052271081 | I60: =I59-H59 -> 0.032359439 | J60: =J59-I59 -> 0.045687935 | K60: =K59-J59 -> 0.045200856
B62: % of open platform API revenue | G62: =G7/G5 -> 0.82793052 | H62: =H7/H5 -> 0.9243941 | I62: =I7/I5 -> 0.95466931 | J62: =J7/J5 -> 0.96827538 | K62: =K7/K5 -> 0.97593955
B64: Fixed cost - training cost | C64: =-C11*C5 -> 0 | D64: =D11*D5 -> 311.746 | E64: =E11*E5 -> 1552.832 | F64: =F11*F5 -> 2249.5275 | G64: =G11*G5 -> 4049.1495 | H64: =H11*H5 -> 7693.3841 | I64: =I11*I5 -> 11532.383 | J64: =J11*J5 -> 18451.812 | K64: =K11*K5 -> 28600.309 | ... Q64: =Q11*Q5 -> 0
B65: Variable cost - all others
B66: Variable cost as % of revenue | G66: =(G5-G13-G64)/G5 -> 1.0514534 | H66: =(H5-H13-H64)/H5 -> 0.88096978 | I66: =(I5-I13-I64)/I5 -> 0.8260767 | J66: =(J5-J13-J64)/J5 -> 0.7873441 | K66: =(K5-K13-K64)/K5 -> 0.75780352 | L66: =(L5-L13-L64)/L5 -> 0.70375101 | M66: =(M5-M13-M64)/M5 -> 0.6935369 | N66: =(N5-N13-N64)/N5 -> 0.67725913 | O66: 0.65 | P66: 0.63
B68: Non-GAAP operating profit | G68: =G72-G71 -> -4375.324 | H68: =H72-H71 -> -4869.4244 | I68: =I72-I71 -> 8886.5035 | J68: =J72-J71 -> 27162.755 | K68: =K72-K71 -> 64339.785 | L68: =L72-L71 -> 123569.05 | M68: =M72-M71 -> 182963.22 | N68: =N72-N71 -> 241707.39 | ... P68: =P72-P71 -> 310129.92
B69: Non-GAAP operating margin % | G69: =G68/G56 -> -0.69019829 | H69: =H68/H56 -> -0.20524678 | I69: =I68/I56 -> 0.14189626 | J69: =J68/J56 -> 0.18581358 | K69: =K68/K56 -> 0.21865575 | L69: =L68/L56 -> 0.27055545 | M69: =M68/M56 -> 0.28265502 | N69: =N68/N56 -> 0.29888601 | ... P69: =P68/P56 -> 0.34001349
B70: Income tax rate % | G70: =IF(G72>0,-18%,0%) -> 0 | H70: =IF(H72>0,-18%,0%) -> 0 | I70: =IF(I72>0,-18%,0%) -> -0.18 | J70: =IF(J72>0,-18%,0%) -> -0.18 | K70: =IF(K72>0,-18%,0%) -> -0.18 | L70: =IF(L72>0,-18%,0%) -> -0.18 | M70: =IF(M72>0,-18%,0%) -> -0.18 | N70: =IF(N72>0,-18%,0%) -> -0.18 | ... P70: =IF(P72>0,-18%,0%) -> -0.18
B71: Income tax expenses/benefits | G71: =G70*G72 -> 0 | H71: =H70*H72 -> 0 | I71: =I70*I72 -> -1355.5683 | J71: =J70*J72 -> -4143.4712 | K71: =K70*K72 -> -9814.5435 | L71: =L70*L72 -> -18849.517 | M71: =M70*M72 -> -27909.644 | N71: =N70*N72 -> -36870.619 | ... P71: =P70*P72 -> -47307.954
B72: NOPAT (adjusted) | G72: =G76-SUM(G73:G75) -> -4375.324 | H72: =H76-SUM(H73:H75) -> -4869.4244 | I72: =I76-SUM(I73:I75) -> 7530.9351 | J72: =J76-SUM(J73:J75) -> 23019.284 | K72: =K76-SUM(K73:K75) -> 54525.242 | L72: =L76-SUM(L73:L75) -> 104719.54 | M72: =M76-SUM(M73:M75) -> 155053.58 | N72: =N76-SUM(N73:N75) -> 204836.77 | ... P72: =P76-SUM(P73:P75) -> 262821.97
B73: Depreciation & amortization | C73: =C18 -> 20.018 | D73: =D18 -> 68.931 | E73: =E18 -> 279.937 | F73: =F18 -> 281.061 | G73: =G18 -> 143.61724 | H73: =H18 -> 143.14779 | I73: =I18 -> 48.242611 | J73: =J18 -> 29.841016 | ... P73: =P18 -> 55.781994
B74: Change in working capital | C74: =C19 -> 9.893 | D74: =D19 -> -96.09 | E74: =E19 -> -0.026 | F74: =F19 -> 704.286 | G74: =G19 -> 1881.9336 | H74: =H19 -> 2300.1187 | I74: =I19 -> 2445.5425 | J74: =J19 -> 2289.5281 | ... P74: =P19 -> -19218.455
B75: Capital expenditures | C75: =C20 -> -31.651 | D75: =D20 -> -508.569 | E75: =E20 -> -132.76 | F75: =F20 -> -23.088 | G75: =G20 -> -27.7056 | H75: =H20 -> -31.85508 | I75: =I20 -> -35.040588 | J75: =J20 -> -38.544647 | ... P75: =P20 -> -68.284193
B76: Free cash flow - bull case | G76: =G77 -> -2377.4788 | H76: =H77 -> -2458.013 | I76: =I77 -> 9989.6796 | J76: =J77 -> 25300.109 | K76: =K77 -> 57004.3 | L76: =L77 -> 107864.65 | M76: =M77 -> 153523.49 | N76: =N77 -> 200441.93 | O76: =O77 -> 225475.05 | P76: =P77/((1+$C$49)*C50+1) -> 243591.01
B77: Free cash flow - bull case + terminal | G77: =G78+G81 -> -2377.4788 | H77: =H78+H81 -> -2458.013 | I77: =I78+I81 -> 9989.6796 | J77: =J78+J81 -> 25300.109 | K77: =K78+K81 -> 57004.3 | L77: =L78+L81 -> 107864.65 | M77: =M78+M81 -> 153523.49 | N77: =N78+N81 -> 200441.93 | ... P77: =P78+P81 -> 2794073.6
B78: Free cash flow - base case | C78: =C22 -> -99.435 | D78: =D22 -> -1155.949 | E78: =E22 -> -2367.622 | F78: =F22 -> -2266.226 | G78: =G22 -> -2377.4788 | H78: =H22 -> -2458.013 | I78: =I22 -> 1154.6815 | J78: =J22 -> 8180.9342 | ... P78: =P22 -> 1560461.6
B79: Weights | G79: 0 | H79: 0 | I79: 0.011 | J79: 0.019 | K79: 0.034 | L79: 0.048 | M79: 0.061 | N79: 0.07 | O79: 0.07 | P79: =1-SUM(G79:O79) -> 0.687
B80: Incremental present value by year | G80: =G79*$C$89 -> 0 | H80: =H79*$C$89 -> 0 | I80: =I79*$C$89 -> 7020.622 | J80: =J79*$C$89 -> 12126.529 | K80: =K79*$C$89 -> 21700.104 | L80: =L79*$C$89 -> 30635.442 | M80: =M79*$C$89 -> 38932.54 | N80: =N79*$C$89 -> 44676.686 | ... P80: =P79*$C$89 -> 438469.76
B81: Incremental FCF by year | G81: =G80/G24 -> 0 | H81: =H80/H24 -> 0 | I81: =I80/I24 -> 8834.9982 | J81: =J80/J24 -> 17119.174 | K81: =K80/K24 -> 34365.571 | L81: =L80/L24 -> 54425.362 | M81: =M80/M24 -> 77589.929 | N81: =N80/N24 -> 99882.407 | ... P81: =P80/P24 -> 1233611.9
B83: Firm value - bull case | C83: =C86-C85 -> 1370086.7
B85: Net cash (2026E) | C85: =C28 -> 29767.347
B86: Equity valuation - bull case | C86: ='Bull bear'!H16*7 -> 1399854
B88: Firm value - base case | C88: =C27 -> 731848.32
B89: Delta | C89: =C83-C88 -> 638238.37
B91: Reverse DCF - bear case
B92: Revenue | C92: =C5 -> 57.409 | D92: =D5 -> 124.538 | E92: =E5 -> 312.414 | F92: =F5 -> 724.334 | G92: =G5 -> 6339.2276 | H92: =H5 -> 23724.729 | I92: =I102/(1-I100)+I98 -> 51259.786 | J92: =J102/(1-J100)+J98 -> 94315.172 | K92: =K102/(1-K100)+K98 -> 159759.83 | L92: =L102/(1-L100)+L98 -> 197142.48 | M92: =M102/(1-M100)+M98 -> 258461.17 | N92: =N102/(1-N100)+N98 -> 309735.07 | O92: =O102/(1-O100)+O98 -> 332081.6 | P92: =P102/(1-P100)+P98 -> 338090.45
B93: yoy % | G93: =G92/F92-1 -> 7.7518018 | H93: =H92/G92-1 -> 2.7425269 | I93: =I92/H92-1 -> 1.1606057 | J93: =J92/I92-1 -> 0.83994472 | K93: =K92/J92-1 -> 0.69389323 | L93: =L92/K92-1 -> 0.23399278 | M93: =M92/L92-1 -> 0.31103742 | N93: =N92/M92-1 -> 0.19838147 | ... P93: =P92/O92-1 -> 0.018094477
B94: Amongst which: open platform API revenue | G94: =G92*G62 -> 5248.44 | H94: =H92*H62 -> 21931 | I94: =I92*I62 -> 48936.144 | J94: =J92*J62 -> 91323.059 | K94: =K92*K62 -> 155915.94
B95: Implied % of market penetration | G95: =G94/G$3 -> 0.15107101 | H95: =H94/H$3 -> 0.20334209 | I95: =I94/I$3 -> 0.19292087 | J95: =J94/J$3 -> 0.18154865 | K95: =K94/K$3 -> 0.17731775
B96: Incremental market share gain | H96: =H95-G95 -> 0.052271081 | I96: =I95-H95 -> -0.010421219 | J96: =J95-I95 -> -0.011372223 | K96: =K95-J95 -> -0.0042309034
B98: Fixed cost - training cost | C98: =C64 -> 0 | D98: =D64 -> 311.746 | E98: =E64 -> 1552.832 | F98: =F64 -> 2249.5275 | G98: =G64 -> 4049.1495 | H98: =H64 -> 7693.3841 | I98: =I64 -> 11532.383 | J98: =J64 -> 18451.812 | ... Q98: =Q64 -> 0
B99: Variable cost - all others
B100: Variable cost as % of revenue | G100: =(G5-G13-G98)/G5 -> 1.0514534 | H100: =(H5-H13-H98)/H5 -> 0.88096978 | I100: 1.25 | J100: 1.05 | K100: =(K5-K13-K98)/K5 -> 0.75780352 | L100: =(L5-L13-L98)/L5 -> 0.70375101 | M100: =(M5-M13-M98)/M5 -> 0.6935369 | N100: =(N5-N13-N98)/N5 -> 0.67725913 | O100: =(O5-O13-O98)/O5 -> 0.65226517 | P100: =(P5-P13-P98)/P5 -> 0.62799162
B102: Non-GAAP operating profit | G102: =G106-G105 -> -4375.324 | H102: =H106-H105 -> -4869.4244 | I102: =I106-I105 -> -9931.8508 | J102: =J106-J105 -> -3793.168 | K102: =K106-K105 -> 31766.374 | L102: =L106-L105 -> 46668.414 | M102: =M106-M105 -> 63797.79 | N102: =N106-N105 -> 80672.881 | ... P102: =P106-P105 -> 98273.002
B103: Non-GAAP operating margin % | G103: =G102/G92 -> -0.69019829 | H103: =H102/H92 -> -0.20524678 | I103: =I102/I92 -> -0.19375521 | J103: =J102/J92 -> -0.040218004 | K103: =K102/K92 -> 0.19883831 | L103: =L102/L92 -> 0.23672429 | M103: =M102/M92 -> 0.24683704 | N103: =N102/N92 -> 0.26045769 | ... P103: =P102/P92 -> 0.29067074
B104: Income tax rate % | G104: =IF(G106>0,-18%,0%) -> 0 | H104: =IF(H106>0,-18%,0%) -> 0 | I104: =IF(I106>0,-18%,0%) -> 0 | J104: =IF(J106>0,-18%,0%) -> 0 | K104: =IF(K106>0,-18%,0%) -> -0.18 | L104: =IF(L106>0,-18%,0%) -> -0.18 | M104: =IF(M106>0,-18%,0%) -> -0.18 | N104: =IF(N106>0,-18%,0%) -> -0.18 | ... P104: =IF(P106>0,-18%,0%) -> -0.18
B105: Income tax expenses/benefits | G105: =G104*G106 -> 0 | H105: =H104*H106 -> 0 | I105: =I104*I106 -> 0 | J105: =J104*J106 -> 0 | K105: =K104*K106 -> -4845.7181 | L105: =L104*L106 -> -7118.9106 | M105: =M104*M106 -> -9731.8663 | N105: =N104*N106 -> -12306.033 | ... P105: =P104*P106 -> -14990.797
B106: NOPAT (adjusted) | G106: =G110-SUM(G107:G109) -> -4375.324 | H106: =H110-SUM(H107:H109) -> -4869.4244 | I106: =I110-SUM(I107:I109) -> -9931.8508 | J106: =J110-SUM(J107:J109) -> -3793.168 | K106: =K110-SUM(K107:K109) -> 26920.656 | L106: =L110-SUM(L107:L109) -> 39549.503 | M106: =M110-SUM(M107:M109) -> 54065.924 | N106: =N110-SUM(N107:N109) -> 68366.848 | ... P106: =P110-SUM(P107:P109) -> 83282.205
B107: Depreciation & amortization | C107: =C18 -> 20.018 | D107: =D18 -> 68.931 | E107: =E18 -> 279.937 | F107: =F18 -> 281.061 | G107: =G18 -> 143.61724 | H107: =H18 -> 143.14779 | I107: =I18 -> 48.242611 | J107: =J18 -> 29.841016 | ... P107: =P18 -> 55.781994
B108: Change in working capital | C108: =C19 -> 9.893 | D108: =D19 -> -96.09 | E108: =E19 -> -0.026 | F108: =F19 -> 704.286 | G108: =G19 -> 1881.9336 | H108: =H19 -> 2300.1187 | I108: =I19 -> 2445.5425 | J108: =J19 -> 2289.5281 | ... P108: =P19 -> -19218.455
B109: Capital expenditures | C109: =C20 -> -31.651 | D109: =D20 -> -508.569 | E109: =E20 -> -132.76 | F109: =F20 -> -23.088 | G109: =G20 -> -27.7056 | H109: =H20 -> -31.85508 | I109: =I20 -> -35.040588 | J109: =J20 -> -38.544647 | ... P109: =P20 -> -68.284193
B110: Free cash flow - bear case | G110: =G111 -> -2377.4788 | H110: =H111 -> -2458.013 | I110: =I111 -> -7473.1063 | J110: =J111 -> -1512.3436 | K110: =K111 -> 29399.714 | L110: =L111 -> 42694.612 | M110: =M111 -> 52535.841 | N110: =N111 -> 63972.003 | O110: =O111 -> 64352.764 | P110: =P111/((1+$C$49)*C50+1) -> 64051.247
B111: Free cash flow - bear case + terminal | G111: =G112+G115 -> -2377.4788 | H111: =H112+H115 -> -2458.013 | I111: =I112+I115 -> -7473.1063 | J111: =J112+J115 -> -1512.3436 | K111: =K112+K115 -> 29399.714 | L111: =L112+L115 -> 42694.612 | M111: =M112+M115 -> 52535.841 | N111: =N112+N115 -> 63972.003 | ... P111: =P112+P115 -> 734690.08
B112: Free cash flow - base case | C112: =C22 -> -99.435 | D112: =D22 -> -1155.949 | E112: =E22 -> -2367.622 | F112: =F22 -> -2266.226 | G112: =G22 -> -2377.4788 | H112: =H22 -> -2458.013 | I112: 3.67 | J112: =J22 -> 8180.9342 | K112: =K22 -> 22638.728 | L112: =L22 -> 53439.284 | M112: =M22 -> 75933.564 | N112: =N22 -> 100559.52 | O112: =O22 -> 113426.96 | P112: =P22 -> 1560461.6
B113: Weights | G113: 0 | H113: 0 | I113: 0.0167 | J113: 0.0193 | K113: -0.012 | L113: 0.017 | M113: 0.033 | N113: 0.046 | O113: 0.055 | P113: =1-SUM(G113:O113) -> 0.825
B114: Incremental present value by year | G114: =G113*$C$122 -> 0 | H114: =H113*$C$122 -> 0 | I114: =I113*$C$122 -> -5941.3278 | J114: =J113*$C$122 -> -6866.3249 | K114: =K113*$C$122 -> 4269.2176 | L114: =L113*$C$122 -> -6048.0582 | M114: =M113*$C$122 -> -11740.348 | N114: =N113*$C$122 -> -16365.334 | ... P114: =P113*$C$122 -> -293508.71
B115: Incremental FCF by year | G115: =G114/G24 -> 0 | H115: =H114/H24 -> 0 | I115: =I114/I24 -> -7476.7763 | J115: =J114/J24 -> -9693.2778 | K115: =K114/K24 -> 6760.9859 | L115: =L114/L24 -> -10744.672 | M115: =M114/M24 -> -23397.723 | N115: =N114/N24 -> -36587.516 | ... P115: =P114/P24 -> -825771.54
B117: Firm value - bear case | C117: ='Bull bear'!D16*7 -> 376080.19
B121: Firm value - base case | C121: =C27 -> 731848.32
B122: Delta | C122: =C117-C121 -> -355768.13

Sheet Bull bear
B5: Scenarios for valuation | D5: Bear case | F5: Base case | H5: Bull case
D6: 2027E EV/Sales-based | F6: DCF-based | H6: DCF-based, mid-2028E ARR-implied
B7: Zhipu | D7: Applying 8X EV/Sales multiple to 27E open API platform revenue of Rmb22bn. Bear case valuation implies Zhipu’s revenue pool share declines from 20% to 18% from 2027 to 2030E on higher competition. | F7: Assuming Zhipu's revenue pool share to expand from 20% in 2027 to 24% by 2030E, and 26% EBIT margin (by 2035E). Applying 12% WACC and 2% terminal growth rate (consistent with our coverage). | H7: Bull case valuation assumes Zhipu’s revenue pool share to expand from 20% in 2027 to 33% by 2030E. Implies 28X mid-2028E ARR, discounting back using 12% p.a.
B9: Valuation per share (HK$) | D9: =D17/D18 -> 900 | F9: ='DCF+base-bull-bear'!C34 -> 1880 | H9: =H17/H18 -> 3350
B10: Valuation (US$bn) | D10: =D16/1000 -> 53.725741 | F10: ='DCF+base-bull-bear'!C30/7.8/1000*0.984 -> 110.43764 | H10: =H16/1000 -> 199.97915
B12: Upside/downside | D12: =D9/$D$21-1 -> -0.55708661 | F12: =F9/$D$21-1 -> -0.07480315 | H12: =H9/$D$21-1 -> 0.64862205
B14: ARR/Revenue (US$mn) | D14: =Revenue!K29/7 -> 3133 | H14: =Revenue!L29/7 -> 8020.5
B15: Multiple | D15: 7.6471096 | H15: 28.333524
B16: EV/equity value (US$ mn) | D16: =(D14*D15+D20) -> 53725.741 | H16: =H14*H15*(1-12%) -> 199979.15
B17: Equity value (HK$ mn) | D17: =D16*7.8 -> 419060.78 | H17: =H16*7.8 -> 1559837.4
B18: Share outstanding | D18: =H18 -> 465.62309 | H18: ='DCF+base-bull-bear'!C33 -> 465.62309
D19: =D17/D18 -> 900 | H19: =H17/H18 -> 3350
B20: Net cash | D20: ='DCF+base-bull-bear'!C85 -> 29767.347
B21: Current price | D21: 2032
